Workbook

Sheet Summary
B2: EUR | C2: Full Year | I2: YTD | O2: Full Year | S2: Total sales | AL2: Existing | AZ2: New
C3: 25A | D3: 25B | E3: 25F vs 25B | F3: 24A | G3: 25F vs 24A | I3: 25A | J3: 25B | K3: 25A vs 25B | L3: 24A | M3: 25A vs 24A | O3: 26B | P3: 25A | Q3: 26B vs 25F | S3: 46023 | T3: 46054 | U3: 46082 | V3: 46113 | W3: 46143 | X3: 46174 | Y3: 46204 | Z3: 46235 | AA3: 46266 | AB3: 46296 | AC3: 46327 | AD3: 46357 | AF3: Target: | AG3: Target NC | AH3: Growth | AI3: Comment | AL3: 46023 | AM3: 46054 | AN3: 46082 | AO3: 46113 | AP3: 46143 | AQ3: 46174 | AR3: 46204 | AS3: 46235 | AT3: 46266 | AU3: 46296 | AV3: 46327 | AW3: 46357 | AZ3: 46023 | BA3: 46054 | BB3: 46082 | BC3: 46113 | BD3: 46143 | BE3: 46174 | BF3: 46204 | BG3: 46235 | BH3: 46266 | BI3: 46296 | BJ3: 46327 | BK3: 46357
B4: North | C4: =North!Z28+North!Z35+North!Z41 -> 602834.42 | D4: =North!Y28+North!Y35+North!Y41 -> 757700 | E4: =IFERROR(C4/D4-1, "N/A") -> -0.20438905 | F4: =North!X28+North!X35+North!X41 -> 674868.99 | G4: =IFERROR(C4/F4-1, "N/A") -> -0.1067386 | I4: =North!P28+North!P35+North!P41 -> 602834.42 | J4: =North!Q28+North!Q35+North!Q41 -> 532111.49 | K4: =IFERROR(I4/J4-1, "N/A") -> 0.13290998 | L4: =North!O28+North!O35+North!O41 -> 601941.21 | M4: =IFERROR(I4/L4-1, "N/A") -> 0.0014838825 | O4: =North!AA28+North!AA35+North!AA41 -> 713889.64 | P4: =C4 -> 602834.42 | Q4: =IFERROR(O4/P4-1, "N/A") -> 0.18422176 | S4: =North!AG28+North!AG35+North!AG41 -> 45772.275 | T4: =North!AH28+North!AH35+North!AH41 -> 56311.171 | U4: =North!AI28+North!AI35+North!AI41 -> 70388.964 | V4: =North!AJ28+North!AJ35+North!AJ41 -> 60580.619 | W4: =North!AK28+North!AK35+North!AK41 -> 64850.068 | X4: =North!AL28+North!AL35+North!AL41 -> 58311.171 | Y4: =North!AM28+North!AM35+North!AM41 -> 56311.171 | Z4: =North!AN28+North!AN35+North!AN41 -> 44502.827 | ... AD4: =North!AR28+North!AR35+North!AR41 -> 50772.275 | AF4: =North!K28+North!K32 -> 653889.64 | AG4: 60000 | AH4: =AF4/P4-1 -> 0.084691944 | AJ4: =SUM(S4:AD4)-SUM(AF4:AG4) -> 0 | AL4: =North!AG28+North!AG35 -> 45772.275 | AM4: =North!AH28+North!AH35 -> 52311.171 | AN4: =North!AI28+North!AI35 -> 65388.964 | AO4: =North!AJ28+North!AJ35 -> 55580.619 | AP4: =North!AK28+North!AK35 -> 58850.068 | AQ4: =North!AL28+North!AL35 -> 52311.171 | AR4: =North!AM28+North!AM35 -> 52311.171 | AS4: =North!AN28+North!AN35 -> 42502.827 | ... AW4: =North!AR28+North!AR35 -> 45772.275 | AZ4: =S4-AL4 -> 0 | BA4: =T4-AM4 -> 4000 | BB4: =U4-AN4 -> 5000 | BC4: =V4-AO4 -> 5000 | BD4: =W4-AP4 -> 6000 | BE4: =X4-AQ4 -> 6000 | BF4: =Y4-AR4 -> 4000 | BG4: =Z4-AS4 -> 2000 | ... BK4: =AD4-AW4 -> 5000
B5: North East | C5: ='North East'!Z21+'North East'!Z28+'North East'!Z34 -> 375419.11 | D5: ='North East'!Y21+'North East'!Y28+'North East'!Y34 -> 329000 | E5: =IFERROR(C5/D5-1, "N/A") -> 0.14109152 | F5: ='North East'!X21+'North East'!X28+'North East'!X34 -> 304271.93 | G5: =IFERROR(C5/F5-1, "N/A") -> 0.23382762 | O5: ='North East'!AA21+'North East'!AA28+'North East'!AA34 -> 470452.64 | P5: =C5 -> 375419.11 | Q5: =IFERROR(O5/P5-1, "N/A") -> 0.25313983 | S5: ='North East'!AG21+'North East'!AG28+'North East'!AG34 -> 28381.685 | T5: ='North East'!AH21+'North East'!AH28+'North East'!AH34 -> 36436.211 | U5: ='North East'!AI21+'North East'!AI28+'North East'!AI34 -> 44545.264 | V5: ='North East'!AJ21+'North East'!AJ28+'North East'!AJ34 -> 38463.474 | W5: ='North East'!AK21+'North East'!AK28+'North East'!AK34 -> 40490.737 | X5: ='North East'!AL21+'North East'!AL28+'North East'!AL34 -> 37436.211 | Y5: ='North East'!AM21+'North East'!AM28+'North East'!AM34 -> 38436.211 | Z5: ='North East'!AN21+'North East'!AN28+'North East'!AN34 -> 29354.422 | ... AD5: ='North East'!AR21+'North East'!AR28+'North East'!AR34 -> 35381.685 | AF5: ='North East'!K21 -> 405452.64 | AG5: 65000 | AH5: =AF5/P5-1 -> 0.08 | AJ5: =SUM(S5:AD5)-SUM(AF5:AG5) -> 0 | AL5: ='North East'!AG21+'North East'!AG28 -> 28381.685 | AM5: ='North East'!AH21+'North East'!AH28 -> 32436.211 | AN5: ='North East'!AI21+'North East'!AI28 -> 40545.264 | AO5: ='North East'!AJ21+'North East'!AJ28 -> 34463.474 | AP5: ='North East'!AK21+'North East'!AK28 -> 36490.737 | AQ5: ='North East'!AL21+'North East'!AL28 -> 32436.211 | AR5: ='North East'!AM21+'North East'!AM28 -> 32436.211 | AS5: ='North East'!AN21+'North East'!AN28 -> 26354.422 | ... AW5: ='North East'!AR21+'North East'!AR28 -> 28381.685 | AZ5: =S5-AL5 -> 0 | BA5: =T5-AM5 -> 4000 | BB5: =U5-AN5 -> 4000 | BC5: =V5-AO5 -> 4000 | BD5: =W5-AP5 -> 4000 | BE5: =X5-AQ5 -> 5000 | BF5: =Y5-AR5 -> 6000 | BG5: =Z5-AS5 -> 3000 | ... BK5: =AD5-AW5 -> 7000
B6: NRW | C6: =C62 -> 685835.6 | D6: =D62 -> 711500 | E6: =IFERROR(C6/D6-1, "N/A") -> -0.036070836 | F6: =F62 -> 600179.62 | G6: =IFERROR(C6/F6-1, "N/A") -> 0.14271724 | I6: ='NRW Ulrike'!P23+'NRW Ulrike'!P31+'NRW Ulrike'!P37 -> 22367.95 | J6: ='NRW Ulrike'!Q23+'NRW Ulrike'!Q31+'NRW Ulrike'!Q37 -> 11250 | K6: =IFERROR(I6/J6-1, "N/A") -> 0.98826222 | L6: ='NRW Ulrike'!O23+'NRW Ulrike'!O31+'NRW Ulrike'!O37 -> 0 | M6: =IFERROR(I6/L6-1, "N/A") -> N/A | O6: =O62 -> 837067.21 | P6: =C6 -> 685835.6 | Q6: =IFERROR(O6/P6-1, "N/A") -> 0.22050708 | S6: =S62 -> 52644.705 | T6: =T62 -> 67165.377 | U6: =U62 -> 82206.721 | V6: =V62 -> 70925.713 | W6: =W62 -> 74686.049 | X6: =X62 -> 67165.377 | Y6: =Y62 -> 67165.377 | Z6: =Z62 -> 52884.369 | ... AD6: =AD62 -> 60644.705 | AF6: =AF62 -> 752067.21 | AG6: =AG62 -> 85000 | AH6: =AF6/P6-1 -> 0.096570677 | AJ6: =SUM(S6:AD6)-SUM(AF6:AG6) -> 0 | AL6: =AL62 -> 52644.705 | AM6: =AM62 -> 60165.377 | AN6: =AN62 -> 75206.721 | AO6: =AO62 -> 63925.713 | AP6: =AP62 -> 67686.049 | AQ6: =AQ62 -> 60165.377 | AR6: =AR62 -> 60165.377 | AS6: =AS62 -> 48884.369 | ... AW6: =AW62 -> 52644.705 | AZ6: =AZ62 -> 0 | BA6: =BA62 -> 7000 | BB6: =BB62 -> 7000 | BC6: =BC62 -> 7000 | BD6: =BD62 -> 7000 | BE6: =BE62 -> 7000 | BF6: =BF62 -> 7000 | BG6: =BG62 -> 4000 | ... BK6: =BK62 -> 8000
B7: South West | C7: ='South West'!Z63+'South West'!Z72+'South West'!Z78 -> 1740960.7 | D7: ='South West'!Y63+'South West'!Y72+'South West'!Y78 -> 1878000 | E7: =IFERROR(C7/D7-1, "N/A") -> -0.072970873 | F7: ='South West'!X63+'South West'!X72+'South West'!X78 -> 1772537.5 | G7: =IFERROR(C7/F7-1, "N/A") -> -0.017814466 | I7: ='South West'!P63+'South West'!P72+'South West'!P78 -> 1740960.7 | J7: ='South West'!Q63+'South West'!Q72+'South West'!Q78 -> 1360290 | K7: =IFERROR(I7/J7-1, "N/A") -> 0.27984525 | L7: ='South West'!O63+'South West'!O72+'South West'!O78 -> 1772537.5 | M7: =IFERROR(I7/L7-1, "N/A") -> -0.017814466 | O7: ='South West'!AA63+'South West'!AA72+'South West'!AA78 -> 1903818.2 | P7: =C7 -> 1740960.7 | Q7: =IFERROR(O7/P7-1, "N/A") -> 0.093544598 | S7: ='South West'!AG63+'South West'!AG72+'South West'!AG78 -> 129767.27 | T7: ='South West'!AH63+'South West'!AH72+'South West'!AH78 -> 152305.45 | U7: ='South West'!AI63+'South West'!AI72+'South West'!AI78 -> 189381.82 | V7: ='South West'!AJ63+'South West'!AJ72+'South West'!AJ78 -> 161574.54 | W7: ='South West'!AK63+'South West'!AK72+'South West'!AK78 -> 170843.64 | X7: ='South West'!AL63+'South West'!AL72+'South West'!AL78 -> 152305.45 | Y7: ='South West'!AM63+'South West'!AM72+'South West'!AM78 -> 152305.45 | Z7: ='South West'!AN63+'South West'!AN72+'South West'!AN78 -> 122498.18 | ... AD7: ='South West'!AR63+'South West'!AR72+'South West'!AR78 -> 134767.27 | AF7: ='South West'!K63+'South West'!K72 -> 1853818.2 | AG7: 50000 | AH7: =AF7/P7-1 -> 0.064824823 | AJ7: =SUM(S7:AD7)-SUM(AF7:AG7) -> 0 | AL7: ='South West'!AG63+'South West'!AG72 -> 129767.27 | AM7: ='South West'!AH63+'South West'!AH72 -> 148305.45 | AN7: ='South West'!AI63+'South West'!AI72 -> 185381.82 | AO7: ='South West'!AJ63+'South West'!AJ72 -> 157574.54 | AP7: ='South West'!AK63+'South West'!AK72 -> 166843.64 | AQ7: ='South West'!AL63+'South West'!AL72 -> 148305.45 | AR7: ='South West'!AM63+'South West'!AM72 -> 148305.45 | AS7: ='South West'!AN63+'South West'!AN72 -> 120498.18 | ... AW7: ='South West'!AR63+'South West'!AR72 -> 129767.27 | AZ7: =S7-AL7 -> 0 | BA7: =T7-AM7 -> 4000 | BB7: =U7-AN7 -> 4000 | BC7: =V7-AO7 -> 4000 | BD7: =W7-AP7 -> 4000 | BE7: =X7-AQ7 -> 4000 | BF7: =Y7-AR7 -> 4000 | BG7: =Z7-AS7 -> 2000 | ... BK7: =AD7-AW7 -> 5000
B8: Bayern | C8: =Bayern!Z30+Bayern!Z38+Bayern!Z44 -> 564796.81 | D8: =Bayern!Y30+Bayern!Y38+Bayern!Y44 -> 637000 | E8: =IFERROR(C8/D8-1, "N/A") -> -0.11334881 | F8: =Bayern!X30+Bayern!X38+Bayern!X44 -> 544865.42 | G8: =IFERROR(C8/F8-1, "N/A") -> 0.036580391 | I8: =Bayern!P30+Bayern!P38+Bayern!P44 -> 564796.81 | J8: =Bayern!Q30+Bayern!Q38+Bayern!Q44 -> 454360 | K8: =IFERROR(I8/J8-1, "N/A") -> 0.24306015 | L8: =Bayern!O30+Bayern!O38+Bayern!O44 -> 544865.42 | M8: =IFERROR(I8/L8-1, "N/A") -> 0.036580391 | O8: =Bayern!AA30+Bayern!AA38+Bayern!AA44 -> 669939.2 | P8: =C8 -> 564796.81 | Q8: =IFERROR(O8/P8-1, "N/A") -> 0.18615967 | S8: =Bayern!AG30+Bayern!AG38+Bayern!AG44 -> 43045.744 | T8: =Bayern!AH30+Bayern!AH38+Bayern!AH44 -> 53195.136 | U8: =Bayern!AI30+Bayern!AI38+Bayern!AI44 -> 65493.92 | V8: =Bayern!AJ30+Bayern!AJ38+Bayern!AJ44 -> 57269.832 | W8: =Bayern!AK30+Bayern!AK38+Bayern!AK44 -> 60344.528 | X8: =Bayern!AL30+Bayern!AL38+Bayern!AL44 -> 55195.136 | Y8: =Bayern!AM30+Bayern!AM38+Bayern!AM44 -> 54195.136 | Z8: =Bayern!AN30+Bayern!AN38+Bayern!AN44 -> 42971.048 | ... AD8: =Bayern!AR30+Bayern!AR38+Bayern!AR44 -> 48045.744 | AF8: =Bayern!K30+Bayern!K38 -> 614939.2 | AG8: 55000 | AH8: =AF8/P8-1 -> 0.088779513 | AJ8: =SUM(S8:AD8)-SUM(AF8:AG8) -> 0 | AL8: =Bayern!AG30+Bayern!AG38 -> 43045.744 | AM8: =Bayern!AH30+Bayern!AH38 -> 49195.136 | AN8: =Bayern!AI30+Bayern!AI38 -> 61493.92 | AO8: =Bayern!AJ30+Bayern!AJ38 -> 52269.832 | AP8: =Bayern!AK30+Bayern!AK38 -> 55344.528 | AQ8: =Bayern!AL30+Bayern!AL38 -> 49195.136 | AR8: =Bayern!AM30+Bayern!AM38 -> 49195.136 | AS8: =Bayern!AN30+Bayern!AN38 -> 39971.048 | ... AW8: =Bayern!AR30+Bayern!AR38 -> 43045.744 | AZ8: =S8-AL8 -> 0 | BA8: =T8-AM8 -> 4000 | BB8: =U8-AN8 -> 4000 | BC8: =V8-AO8 -> 5000 | BD8: =W8-AP8 -> 5000 | BE8: =X8-AQ8 -> 6000 | BF8: =Y8-AR8 -> 5000 | BG8: =Z8-AS8 -> 3000 | ... BK8: =AD8-AW8 -> 5000
B9: Retail | C9: =Retail!Z6 -> 197085.25 | D9: =Retail!Y6 -> 200000 | E9: =IFERROR(C9/D9-1, "N/A") -> -0.01457375 | F9: =Retail!X6 -> 76005.05 | G9: =IFERROR(C9/F9-1, "N/A") -> 1.5930547 | I9: =Retail!P6 -> 197085.25 | J9: =Retail!Q6 -> 146000 | K9: =IFERROR(I9/J9-1, "N/A") -> 0.34989897 | L9: =Retail!O6 -> 135005.05 | M9: =IFERROR(I9/L9-1, "N/A") -> 0.45983613 | O9: =Retail!AA6 -> 200000 | P9: =C9 -> 197085.25 | Q9: =IFERROR(O9/P9-1, "N/A") -> 0.014789285 | S9: =Retail!AG6 -> 14000 | T9: =Retail!AH6 -> 16000 | U9: =Retail!AI6 -> 20000 | V9: =Retail!AJ6 -> 17000 | W9: =Retail!AK6 -> 18000 | X9: =Retail!AL6 -> 16000 | Y9: =Retail!AM6 -> 16000 | Z9: =Retail!AN6 -> 13000 | ... AD9: =Retail!AR6 -> 14000 | AF9: 200000 | AH9: =AF9/P9-1 -> 0.014789285 | AJ9: =SUM(S9:AD9)-SUM(AF9:AG9) -> 0 | AL9: =Retail!AG6 -> 14000 | AM9: =Retail!AH6 -> 16000 | AN9: =Retail!AI6 -> 20000 | AO9: =Retail!AJ6 -> 17000 | AP9: =Retail!AK6 -> 18000 | AQ9: =Retail!AL6 -> 16000 | AR9: =Retail!AM6 -> 16000 | AS9: =Retail!AN6 -> 13000 | ... AW9: =Retail!AR6 -> 14000 | AZ9: =S9-AL9 -> 0 | BA9: =T9-AM9 -> 0 | BB9: =U9-AN9 -> 0 | BC9: =V9-AO9 -> 0 | BD9: =W9-AP9 -> 0 | BE9: =X9-AQ9 -> 0 | BF9: =Y9-AR9 -> 0 | BG9: =Z9-AS9 -> 0 | ... BK9: =AD9-AW9 -> 0
B10: DE Other | C10: ='Golden Girls DE'!Z58 -> 116209.75 | D10: ='Golden Girls DE'!Y58 -> 86500 | E10: =IFERROR(C10/D10-1, "N/A") -> 0.34346532 | F10: ='Golden Girls DE'!X58 -> 124718.59 | G10: =IFERROR(C10/F10-1, "N/A") -> -0.068224312 | I10: ='Golden Girls DE'!P58 -> 116209.75 | J10: ='Golden Girls DE'!Q58 -> 63145 | K10: =IFERROR(I10/J10-1, "N/A") -> 0.84036345 | L10: ='Golden Girls DE'!O58 -> 124718.59 | M10: =IFERROR(I10/L10-1, "N/A") -> -0.068224312 | O10: ='Golden Girls DE'!AA58 -> 116600 | P10: =C10 -> 116209.75 | Q10: =IFERROR(O10/P10-1, "N/A") -> 0.003358152 | S10: ='Golden Girls DE'!AG58 -> 8162 | T10: ='Golden Girls DE'!AH58 -> 9328 | U10: ='Golden Girls DE'!AI58 -> 11660 | V10: ='Golden Girls DE'!AJ58 -> 9911 | W10: ='Golden Girls DE'!AK58 -> 10494 | X10: ='Golden Girls DE'!AL58 -> 9328 | Y10: ='Golden Girls DE'!AM58 -> 9328 | Z10: ='Golden Girls DE'!AN58 -> 7579 | ... AD10: ='Golden Girls DE'!AR58 -> 8162 | AF10: ='Golden Girls DE'!K58 -> 116600 | AH10: =AF10/P10-1 -> 0.003358152 | AJ10: =SUM(S10:AD10)-SUM(AF10:AG10) -> 0 | AL10: ='Golden Girls DE'!AG58 -> 8162 | AM10: ='Golden Girls DE'!AH58 -> 9328 | AN10: ='Golden Girls DE'!AI58 -> 11660 | AO10: ='Golden Girls DE'!AJ58 -> 9911 | AP10: ='Golden Girls DE'!AK58 -> 10494 | AQ10: ='Golden Girls DE'!AL58 -> 9328 | AR10: ='Golden Girls DE'!AM58 -> 9328 | AS10: ='Golden Girls DE'!AN58 -> 7579 | ... AW10: ='Golden Girls DE'!AR58 -> 8162 | AZ10: =S10-AL10 -> 0 | BA10: =T10-AM10 -> 0 | BB10: =U10-AN10 -> 0 | BC10: =V10-AO10 -> 0 | BD10: =W10-AP10 -> 0 | BE10: =X10-AQ10 -> 0 | BF10: =Y10-AR10 -> 0 | BG10: =Z10-AS10 -> 0 | ... BK10: =AD10-AW10 -> 0
AJ11: =SUM(S11:AD11)-SUM(AF11:AG11) -> 0
B12: Germany | C12: =SUM(C4:C10) -> 4283141.6 | D12: =SUM(D4:D10) -> 4599700 | E12: =IFERROR(C12/D12-1, "N/A") -> -0.068821523 | F12: =SUM(F4:F10) -> 4097447.1 | G12: =IFERROR(C12/F12-1, "N/A") -> 0.045319567 | I12: =SUM(I4:I10) -> 3244254.9 | J12: =SUM(J4:J10) -> 2567156.5 | K12: =IFERROR(I12/J12-1, "N/A") -> 0.26375423 | L12: =SUM(L4:L10) -> 3179067.8 | M12: =IFERROR(I12/L12-1, "N/A") -> 0.020505099 | O12: =SUM(O4:O10) -> 4911766.9 | P12: =SUM(P4:P10) -> 4283141.6 | Q12: =IFERROR(O12/P12-1, "N/A") -> 0.14676732 | S12: =SUM(S4:S10) -> 321773.68 | T12: =SUM(T4:T10) -> 390741.35 | U12: =SUM(U4:U10) -> 483676.69 | V12: =SUM(V4:V10) -> 415725.18 | W12: =SUM(W4:W10) -> 439709.02 | X12: =SUM(X4:X10) -> 395741.35 | Y12: =SUM(Y4:Y10) -> 393741.35 | Z12: =SUM(Z4:Z10) -> 312789.85 | ... AD12: =SUM(AD4:AD10) -> 351773.68 | AF12: =SUM(AF4:AF10) -> 4596766.9 | AG12: =SUM(AG4:AG10) -> 315000 | AH12: =AF12/P12-1 -> 0.073223171 | AJ12: =SUM(S12:AD12)-SUM(AF12:AG12) -> 0 | AL12: =SUM(AL4:AL10) -> 321773.68 | AM12: =SUM(AM4:AM10) -> 367741.35 | AN12: =SUM(AN4:AN10) -> 459676.69 | AO12: =SUM(AO4:AO10) -> 390725.18 | AP12: =SUM(AP4:AP10) -> 413709.02 | AQ12: =SUM(AQ4:AQ10) -> 367741.35 | AR12: =SUM(AR4:AR10) -> 367741.35 | AS12: =SUM(AS4:AS10) -> 298789.85 | ... AW12: =SUM(AW4:AW10) -> 321773.68 | AZ12: =SUM(AZ4:AZ10) -> 0 | BA12: =SUM(BA4:BA10) -> 23000 | BB12: =SUM(BB4:BB10) -> 24000 | BC12: =SUM(BC4:BC10) -> 25000 | BD12: =SUM(BD4:BD10) -> 26000 | BE12: =SUM(BE4:BE10) -> 28000 | BF12: =SUM(BF4:BF10) -> 26000 | BG12: =SUM(BG4:BG10) -> 14000 | ... BK12: =SUM(BK4:BK10) -> 30000
AJ13: =SUM(S13:AD13)-SUM(AF13:AG13) -> 0
B14: NL Central | C14: ='NL Central'!Z40+'NL Central'!Z47+'NL Central'!Z53 -> 883520.61 | D14: ='NL Central'!Y40+'NL Central'!Y47+'NL Central'!Y53 -> 977000 | E14: =IFERROR(C14/D14-1, "N/A") -> -0.095680031 | F14: ='NL Central'!X40+'NL Central'!X47+'NL Central'!X53 -> 901478.03 | G14: =IFERROR(C14/F14-1, "N/A") -> -0.019919975 | I14: ='NL Central'!P40+'NL Central'!P47+'NL Central'!P53 -> 883520.61 | J14: ='NL Central'!Q40+'NL Central'!Q47+'NL Central'!Q53 -> 695460 | K14: =IFERROR(I14/J14-1, "N/A") -> 0.27041183 | L14: ='NL Central'!O40+'NL Central'!O47+'NL Central'!O53 -> 901478.03 | M14: =IFERROR(I14/L14-1, "N/A") -> -0.019919975 | O14: ='NL Central'!AA40+'NL Central'!AA47+'NL Central'!AA53 -> 1003873.2 | P14: =C14 -> 883520.61 | Q14: =IFERROR(O14/P14-1, "N/A") -> 0.13621935 | S14: ='NL Central'!AG40+'NL Central'!AG47+'NL Central'!AG53 -> 66771.125 | T14: ='NL Central'!AH40+'NL Central'!AH47+'NL Central'!AH53 -> 80309.857 | U14: ='NL Central'!AI40+'NL Central'!AI47+'NL Central'!AI53 -> 99387.321 | V14: ='NL Central'!AJ40+'NL Central'!AJ47+'NL Central'!AJ53 -> 85079.223 | W14: ='NL Central'!AK40+'NL Central'!AK47+'NL Central'!AK53 -> 89848.589 | X14: ='NL Central'!AL40+'NL Central'!AL47+'NL Central'!AL53 -> 80309.857 | Y14: ='NL Central'!AM40+'NL Central'!AM47+'NL Central'!AM53 -> 80309.857 | Z14: ='NL Central'!AN40+'NL Central'!AN47+'NL Central'!AN53 -> 64001.759 | ... AD14: ='NL Central'!AR40+'NL Central'!AR47+'NL Central'!AR53 -> 71771.125 | AF14: ='NL Central'!K40+'NL Central'!K47 -> 953873.21 | AG14: 50000 | AH14: =AF14/P14-1 -> 0.07962757 | AJ14: =SUM(S14:AD14)-SUM(AF14:AG14) -> 0 | AL14: ='NL Central'!AG40+'NL Central'!AG47 -> 66771.125 | AM14: ='NL Central'!AH40+'NL Central'!AH47 -> 76309.857 | AN14: ='NL Central'!AI40+'NL Central'!AI47 -> 95387.321 | AO14: ='NL Central'!AJ40+'NL Central'!AJ47 -> 81079.223 | AP14: ='NL Central'!AK40+'NL Central'!AK47 -> 85848.589 | AQ14: ='NL Central'!AL40+'NL Central'!AL47 -> 76309.857 | AR14: ='NL Central'!AM40+'NL Central'!AM47 -> 76309.857 | AS14: ='NL Central'!AN40+'NL Central'!AN47 -> 62001.759 | ... AW14: ='NL Central'!AR40+'NL Central'!AR47 -> 66771.125 | AZ14: =S14-AL14 -> 0 | BA14: =T14-AM14 -> 4000 | BB14: =U14-AN14 -> 4000 | BC14: =V14-AO14 -> 4000 | BD14: =W14-AP14 -> 4000 | BE14: =X14-AQ14 -> 4000 | BF14: =Y14-AR14 -> 4000 | BG14: =Z14-AS14 -> 2000 | ... BK14: =AD14-AW14 -> 5000
B15: NL Other + BL | C15: ='NL Other_Belgium'!Z37+'NL Other_Belgium'!Z49+'NL Other_Belgium'!Z55 -> 958120.43 | D15: ='NL Other_Belgium'!Y37+'NL Other_Belgium'!Y49+'NL Other_Belgium'!Y55 -> 1036500 | E15: =IFERROR(C15/D15-1, "N/A") -> -0.07561946 | F15: ='NL Other_Belgium'!X37+'NL Other_Belgium'!X49+'NL Other_Belgium'!X55 -> 898194.38 | G15: =IFERROR(C15/F15-1, "N/A") -> 0.066718353 | I15: ='NL Other_Belgium'!P37+'NL Other_Belgium'!P49+'NL Other_Belgium'!P55 -> 958120.43 | J15: ='NL Other_Belgium'!Q37+'NL Other_Belgium'!Q49+'NL Other_Belgium'!Q55 -> 800020 | K15: =IFERROR(I15/J15-1, "N/A") -> 0.1976206 | L15: ='NL Other_Belgium'!O37+'NL Other_Belgium'!O49+'NL Other_Belgium'!O55 -> 898194.38 | M15: =IFERROR(I15/L15-1, "N/A") -> 0.066718353 | O15: ='NL Other_Belgium'!AA37+'NL Other_Belgium'!AA49+'NL Other_Belgium'!AA55 -> 1074723.8 | P15: =C15 -> 958120.43 | Q15: =IFERROR(O15/P15-1, "N/A") -> 0.12170014 | S15: ='NL Other_Belgium'!AG37+'NL Other_Belgium'!AG49+'NL Other_Belgium'!AG55 -> 71730.667 | T15: ='NL Other_Belgium'!AH37+'NL Other_Belgium'!AH49+'NL Other_Belgium'!AH55 -> 85977.905 | U15: ='NL Other_Belgium'!AI37+'NL Other_Belgium'!AI49+'NL Other_Belgium'!AI55 -> 106472.38 | V15: ='NL Other_Belgium'!AJ37+'NL Other_Belgium'!AJ49+'NL Other_Belgium'!AJ55 -> 91101.524 | W15: ='NL Other_Belgium'!AK37+'NL Other_Belgium'!AK49+'NL Other_Belgium'!AK55 -> 96225.143 | X15: ='NL Other_Belgium'!AL37+'NL Other_Belgium'!AL49+'NL Other_Belgium'!AL55 -> 85977.905 | Y15: ='NL Other_Belgium'!AM37+'NL Other_Belgium'!AM49+'NL Other_Belgium'!AM55 -> 85977.905 | Z15: ='NL Other_Belgium'!AN37+'NL Other_Belgium'!AN49+'NL Other_Belgium'!AN55 -> 68607.048 | ... AD15: ='NL Other_Belgium'!AR37+'NL Other_Belgium'!AR49+'NL Other_Belgium'!AR55 -> 76730.667 | AF15: ='NL Other_Belgium'!K37+'NL Other_Belgium'!K49 -> 1024723.8 | AG15: 50000 | AH15: =AF15/P15-1 -> 0.069514629 | AJ15: =SUM(S15:AD15)-SUM(AF15:AG15) -> 0 | AL15: ='NL Other_Belgium'!AG37+'NL Other_Belgium'!AG49 -> 71730.667 | AM15: ='NL Other_Belgium'!AH37+'NL Other_Belgium'!AH49 -> 81977.905 | AN15: ='NL Other_Belgium'!AI37+'NL Other_Belgium'!AI49 -> 102472.38 | AO15: ='NL Other_Belgium'!AJ37+'NL Other_Belgium'!AJ49 -> 87101.524 | AP15: ='NL Other_Belgium'!AK37+'NL Other_Belgium'!AK49 -> 92225.143 | AQ15: ='NL Other_Belgium'!AL37+'NL Other_Belgium'!AL49 -> 81977.905 | AR15: ='NL Other_Belgium'!AM37+'NL Other_Belgium'!AM49 -> 81977.905 | AS15: ='NL Other_Belgium'!AN37+'NL Other_Belgium'!AN49 -> 66607.048 | ... AW15: ='NL Other_Belgium'!AR37+'NL Other_Belgium'!AR49 -> 71730.667 | AZ15: =S15-AL15 -> 0 | BA15: =T15-AM15 -> 4000 | BB15: =U15-AN15 -> 4000 | BC15: =V15-AO15 -> 4000 | BD15: =W15-AP15 -> 4000 | BE15: =X15-AQ15 -> 4000 | BF15: =Y15-AR15 -> 4000 | BG15: =Z15-AS15 -> 2000 | ... BK15: =AD15-AW15 -> 5000
B16: NL Other | C16: ='Golden Girls NL'!Z13 -> 10399.47 | D16: ='Golden Girls NL'!Y13 -> 27000 | E16: =IFERROR(C16/D16-1, "N/A") -> -0.61483444 | F16: ='Golden Girls NL'!X13 -> 28533.06 | G16: =IFERROR(C16/F16-1, "N/A") -> -0.6355291 | I16: ='Golden Girls NL'!P13 -> 10399.47 | J16: ='Golden Girls NL'!Q13 -> 19710 | K16: =IFERROR(I16/J16-1, "N/A") -> -0.47237595 | L16: ='Golden Girls NL'!O13 -> 28533.06 | M16: =IFERROR(I16/L16-1, "N/A") -> -0.6355291 | O16: ='Golden Girls NL'!AA13 -> 11000 | P16: =C16 -> 10399.47 | Q16: =IFERROR(O16/P16-1, "N/A") -> 0.057746212 | S16: ='Golden Girls NL'!AG13 -> 770 | T16: ='Golden Girls NL'!AH13 -> 880 | U16: ='Golden Girls NL'!AI13 -> 1100 | V16: ='Golden Girls NL'!AJ13 -> 935 | W16: ='Golden Girls NL'!AK13 -> 990 | X16: ='Golden Girls NL'!AL13 -> 880 | Y16: ='Golden Girls NL'!AM13 -> 880 | Z16: ='Golden Girls NL'!AN13 -> 715 | ... AD16: ='Golden Girls NL'!AR13 -> 770 | AF16: 28000 | AH16: =AF16/P16-1 -> 1.6924449 | AJ16: =SUM(S16:AD16)-SUM(AF16:AG16) -> -17000 | AL16: ='Golden Girls NL'!AG13 -> 770 | AM16: ='Golden Girls NL'!AH13 -> 880 | AN16: ='Golden Girls NL'!AI13 -> 1100 | AO16: ='Golden Girls NL'!AJ13 -> 935 | AP16: ='Golden Girls NL'!AK13 -> 990 | AQ16: ='Golden Girls NL'!AL13 -> 880 | AR16: ='Golden Girls NL'!AM13 -> 880 | AS16: ='Golden Girls NL'!AN13 -> 715 | ... AW16: ='Golden Girls NL'!AR13 -> 770 | AZ16: =S16-AL16 -> 0 | BA16: =T16-AM16 -> 0 | BB16: =U16-AN16 -> 0 | BC16: =V16-AO16 -> 0 | BD16: =W16-AP16 -> 0 | BE16: =X16-AQ16 -> 0 | BF16: =Y16-AR16 -> 0 | BG16: =Z16-AS16 -> 0 | ... BK16: =AD16-AW16 -> 0
AJ17: =SUM(S17:AD17)-SUM(AF17:AG17) -> 0
B18: Benelux | C18: =SUM(C14:C16) -> 1852040.5 | D18: =SUM(D14:D16) -> 2040500 | E18: =IFERROR(C18/D18-1, "N/A") -> -0.092359466 | F18: =SUM(F14:F16) -> 1828205.5 | G18: =IFERROR(C18/F18-1, "N/A") -> 0.013037397 | I18: =SUM(I14:I16) -> 1852040.5 | J18: =SUM(J14:J16) -> 1515190 | K18: =IFERROR(I18/J18-1, "N/A") -> 0.22231569 | L18: =SUM(L14:L16) -> 1828205.5 | M18: =IFERROR(I18/L18-1, "N/A") -> 0.013037397 | O18: =SUM(O14:O16) -> 2089597 | P18: =SUM(P14:P16) -> 1852040.5 | Q18: =IFERROR(O18/P18-1, "N/A") -> 0.12826745 | S18: =SUM(S14:S16) -> 139271.79 | T18: =SUM(T14:T16) -> 167167.76 | U18: =SUM(U14:U16) -> 206959.7 | V18: =SUM(V14:V16) -> 177115.75 | W18: =SUM(W14:W16) -> 187063.73 | X18: =SUM(X14:X16) -> 167167.76 | Y18: =SUM(Y14:Y16) -> 167167.76 | Z18: =SUM(Z14:Z16) -> 133323.81 | ... AD18: =SUM(AD14:AD16) -> 149271.79 | AF18: =SUM(AF14:AF16) -> 2006597 | AG18: =SUM(AG14:AG16) -> 100000 | AH18: =AF18/P18-1 -> 0.083452017 | AJ18: =SUM(S18:AD18)-SUM(AF18:AG18) -> -17000 | AL18: =SUM(AL14:AL16) -> 139271.79 | AM18: =SUM(AM14:AM16) -> 159167.76 | AN18: =SUM(AN14:AN16) -> 198959.7 | AO18: =SUM(AO14:AO16) -> 169115.75 | AP18: =SUM(AP14:AP16) -> 179063.73 | AQ18: =SUM(AQ14:AQ16) -> 159167.76 | AR18: =SUM(AR14:AR16) -> 159167.76 | AS18: =SUM(AS14:AS16) -> 129323.81 | ... AW18: =SUM(AW14:AW16) -> 139271.79 | AZ18: =SUM(AZ14:AZ16) -> 0 | BA18: =SUM(BA14:BA16) -> 8000 | BB18: =SUM(BB14:BB16) -> 8000 | BC18: =SUM(BC14:BC16) -> 8000 | BD18: =SUM(BD14:BD16) -> 8000 | BE18: =SUM(BE14:BE16) -> 8000 | BF18: =SUM(BF14:BF16) -> 8000 | BG18: =SUM(BG14:BG16) -> 4000 | ... BK18: =SUM(BK14:BK16) -> 10000
AJ19: =SUM(S19:AD19)-SUM(AF19:AG19) -> 0
B20: German Switzerland | C20: =C49*1.05 -> 607829.03 | D20: =D49*1.05 -> 786555 | E20: =IFERROR(C20/D20-1, "N/A") -> -0.22722628 | F20: =F49*1.05 -> 698312.76 | G20: =IFERROR(C20/F20-1, "N/A") -> -0.12957479 | I20: =I49*1.05 -> 607829.03 | J20: =J49*1.05 -> 566730.15 | K20: =IFERROR(I20/J20-1, "N/A") -> 0.07251931 | L20: =L49*1.05 -> 698312.76 | M20: =IFERROR(I20/L20-1, "N/A") -> -0.12957479 | O20: =O49*1.05 -> 759528.83 | P20: =C20 -> 607829.03 | Q20: =IFERROR(O20/P20-1, "N/A") -> 0.24957644 | S20: =S49*1.05 -> 49308.268 | T20: =T49*1.05 -> 60552.307 | U20: =U49*1.05 -> 74640.383 | V20: =V49*1.05 -> 65124.326 | W20: =W49*1.05 -> 67596.345 | X20: =X49*1.05 -> 62127.307 | Y20: =Y49*1.05 -> 60552.307 | Z20: =Z49*1.05 -> 47886.249 | ... AD20: =AD49*1.05 -> 54558.268 | AF20: =('Switzerland DE'!K51+'Switzerland DE'!K59)*1.05 -> 704403.83 | AG20: =50000*1.05 -> 52500 | AH20: =AF20/P20-1 -> 0.15888482 | AJ20: =SUM(S20:AD20)-SUM(AF20:AG20) -> 2625 | AL20: =AL49*1.05 -> 49308.268 | AM20: =AM49*1.05 -> 56352.307 | AN20: =AN49*1.05 -> 70440.383 | AO20: =AO49*1.05 -> 59874.326 | AP20: =AP49*1.05 -> 63396.345 | AQ20: =AQ49*1.05 -> 56352.307 | AR20: =AR49*1.05 -> 56352.307 | AS20: =AS49*1.05 -> 45786.249 | ... AW20: =AW49*1.05 -> 49308.268 | AZ20: =S20-AL20 -> 0 | BA20: =T20-AM20 -> 4200 | BB20: =U20-AN20 -> 4200 | BC20: =V20-AO20 -> 5250 | BD20: =W20-AP20 -> 4200 | BE20: =X20-AQ20 -> 5775 | BF20: =Y20-AR20 -> 4200 | BG20: =Z20-AS20 -> 2100 | ... BK20: =AD20-AW20 -> 5250
B21: French Switzerland | C21: =C50*1.05 -> 15500.405 | D21: =D50*1.05 -> 39900 | E21: =IFERROR(C21/D21-1, "N/A") -> -0.61151868 | F21: =F50*1.05 -> 17700.291 | G21: =IFERROR(C21/F21-1, "N/A") -> -0.12428533 | I21: =I50*1.05 -> 15500.405 | J21: =J50*1.05 -> 21672 | K21: =IFERROR(I21/J21-1, "N/A") -> -0.28477277 | L21: =L50*1.05 -> 17700.291 | M21: =IFERROR(I21/L21-1, "N/A") -> -0.12428533 | O21: =O50*1.05 -> 91875 | P21: =C21 -> 15500.405 | Q21: =IFERROR(O21/P21-1, "N/A") -> 4.9272647 | S21: =S50*1.05 -> 2572.5 | T21: =T50*1.05 -> 7140 | U21: =U50*1.05 -> 8925 | V21: =V50*1.05 -> 7323.75 | W21: =W50*1.05 -> 9082.5 | X21: =X50*1.05 -> 7140 | Y21: =Y50*1.05 -> 7140 | Z21: =Z50*1.05 -> 4488.75 | ... AD21: =AD50*1.05 -> 7822.5 | AF21: =('Switzerland FR'!AA8+'Switzerland FR'!AA14)*1.05 -> 36750 | AG21: =50000*1.05 -> 52500 | AH21: =AF21/P21-1 -> 1.3709059 | AJ21: =SUM(S21:AD21)-SUM(AF21:AG21) -> 2625 | AL21: =AL50*1.05 -> 2572.5 | AM21: =AM50*1.05 -> 2940 | AN21: =AN50*1.05 -> 3675 | AO21: =AO50*1.05 -> 3123.75 | AP21: =AP50*1.05 -> 3307.5 | AQ21: =AQ50*1.05 -> 2940 | AR21: =AR50*1.05 -> 2940 | AS21: =AS50*1.05 -> 2388.75 | ... AW21: =AW50*1.05 -> 2572.5 | AZ21: =S21-AL21 -> 0 | BA21: =T21-AM21 -> 4200 | BB21: =U21-AN21 -> 5250 | BC21: =V21-AO21 -> 4200 | BD21: =W21-AP21 -> 5775 | BE21: =X21-AQ21 -> 4200 | BF21: =Y21-AR21 -> 4200 | BG21: =Z21-AS21 -> 2100 | ... BK21: =AD21-AW21 -> 5250
B22: Other Switzerland | C22: =C51*1.05 -> 0 | D22: =D51*1.05 -> 0 | E22: =IFERROR(C22/D22-1, "N/A") -> N/A | F22: =F51*1.05 -> 0 | G22: =IFERROR(C22/F22-1, "N/A") -> N/A | I22: =I51*1.05 -> 0 | J22: =J51*1.05 -> 0 | K22: =IFERROR(I22/J22-1, "N/A") -> N/A | L22: =L51*1.05 -> 0 | M22: =IFERROR(I22/L22-1, "N/A") -> N/A | O22: =O51*1.05 -> 0 | P22: =C22 -> 0 | Q22: =IFERROR(O22/P22-1, "N/A") -> N/A | S22: =S51*1.05 -> 0 | T22: =T51*1.05 -> 0 | U22: =U51*1.05 -> 0 | V22: =V51*1.05 -> 0 | W22: =W51*1.05 -> 0 | X22: =X51*1.05 -> 0 | Y22: =Y51*1.05 -> 0 | Z22: =Z51*1.05 -> 0 | ... AD22: =AD51*1.05 -> 0 | AJ22: =SUM(S22:AD22)-SUM(AF22:AG22) -> 0 | AL22: =AL51*1.05 -> 0 | AM22: =AM51*1.05 -> 0 | AN22: =AN51*1.05 -> 0 | AO22: =AO51*1.05 -> 0 | AP22: =AP51*1.05 -> 0 | AQ22: =AQ51*1.05 -> 0 | AR22: =AR51*1.05 -> 0 | AS22: =AS51*1.05 -> 0 | ... AW22: =AW51*1.05 -> 0 | AZ22: =S22-AL22 -> 0 | BA22: =T22-AM22 -> 0 | BB22: =U22-AN22 -> 0 | BC22: =V22-AO22 -> 0 | BD22: =W22-AP22 -> 0 | BE22: =X22-AQ22 -> 0 | BF22: =Y22-AR22 -> 0 | BG22: =Z22-AS22 -> 0 | ... BK22: =AD22-AW22 -> 0
AJ23: =SUM(S23:AD23)-SUM(AF23:AG23) -> 0
B24: Switzerland | C24: =SUM(C20:C22) -> 623329.43 | D24: =SUM(D20:D22) -> 826455 | E24: =IFERROR(C24/D24-1, "N/A") -> -0.24577934 | F24: =SUM(F20:F22) -> 716013.05 | G24: =IFERROR(C24/F24-1, "N/A") -> -0.12944403 | I24: =SUM(I20:I22) -> 623329.43 | J24: =SUM(J20:J22) -> 588402.15 | K24: =IFERROR(I24/J24-1, "N/A") -> 0.059359545 | L24: =SUM(L20:L22) -> 716013.05 | M24: =IFERROR(I24/L24-1, "N/A") -> -0.12944403 | O24: =SUM(O20:O22) -> 851403.83 | P24: =SUM(P20:P22) -> 623329.43 | Q24: =IFERROR(O24/P24-1, "N/A") -> 0.36589705 | S24: =SUM(S20:S22) -> 51880.768 | T24: =SUM(T20:T22) -> 67692.307 | U24: =SUM(U20:U22) -> 83565.383 | V24: =SUM(V20:V22) -> 72448.076 | W24: =SUM(W20:W22) -> 76678.845 | X24: =SUM(X20:X22) -> 69267.307 | Y24: =SUM(Y20:Y22) -> 67692.307 | Z24: =SUM(Z20:Z22) -> 52374.999 | ... AD24: =SUM(AD20:AD22) -> 62380.768 | AF24: =SUM(AF20:AF22) -> 741153.83 | AG24: =SUM(AG20:AG22) -> 105000 | AH24: =AF24/P24-1 -> 0.18902428 | AJ24: =SUM(S24:AD24)-SUM(AF24:AG24) -> 5250 | AL24: =SUM(AL20:AL22) -> 51880.768 | AM24: =SUM(AM20:AM22) -> 59292.307 | AN24: =SUM(AN20:AN22) -> 74115.383 | AO24: =SUM(AO20:AO22) -> 62998.076 | AP24: =SUM(AP20:AP22) -> 66703.845 | AQ24: =SUM(AQ20:AQ22) -> 59292.307 | AR24: =SUM(AR20:AR22) -> 59292.307 | AS24: =SUM(AS20:AS22) -> 48174.999 | ... AW24: =SUM(AW20:AW22) -> 51880.768 | AZ24: =SUM(AZ20:AZ22) -> 0 | BA24: =SUM(BA20:BA22) -> 8400 | BB24: =SUM(BB20:BB22) -> 9450 | BC24: =SUM(BC20:BC22) -> 9450 | BD24: =SUM(BD20:BD22) -> 9975 | BE24: =SUM(BE20:BE22) -> 9975 | BF24: =SUM(BF20:BF22) -> 8400 | BG24: =SUM(BG20:BG22) -> 4200 | ... BK24: =SUM(BK20:BK22) -> 10500
AJ25: =SUM(S25:AD25)-SUM(AF25:AG25) -> 0
B26: Spain | C26: =Spain!Z14+Spain!Z22+Spain!Z28 -> 132779.43 | D26: =Spain!Y14+Spain!Y22+Spain!Y28 -> 200000 | E26: =IFERROR(C26/D26-1, "N/A") -> -0.33610285 | F26: =Spain!X14+Spain!X22+Spain!X28 -> 87682.84 | G26: =IFERROR(C26/F26-1, "N/A") -> 0.51431489 | I26: =Spain!P14+Spain!P22+Spain!P28 -> 132779.43 | J26: =Spain!Q14+Spain!Q22+Spain!Q28 -> 121150 | K26: =IFERROR(I26/J26-1, "N/A") -> 0.095991993 | L26: =Spain!O14+Spain!O22+Spain!O28 -> 87682.84 | M26: =IFERROR(I26/L26-1, "N/A") -> 0.51431489 | O26: =Spain!AA14+Spain!AA22+Spain!AA28 -> 225000 | P26: =C26 -> 132779.43 | Q26: =IFERROR(O26/P26-1, "N/A") -> 0.69453958 | S26: =Spain!AG14+Spain!AG22+Spain!AG28 -> 12250 | T26: =Spain!AH14+Spain!AH22+Spain!AH28 -> 18000 | U26: =Spain!AI14+Spain!AI22+Spain!AI28 -> 21500 | V26: =Spain!AJ14+Spain!AJ22+Spain!AJ28 -> 18875 | W26: =Spain!AK14+Spain!AK22+Spain!AK28 -> 19750 | X26: =Spain!AL14+Spain!AL22+Spain!AL28 -> 18000 | Y26: =Spain!AM14+Spain!AM22+Spain!AM28 -> 18000 | Z26: =Spain!AN14+Spain!AN22+Spain!AN28 -> 13375 | ... AD26: =Spain!AR14+Spain!AR22+Spain!AR28 -> 17250 | AF26: 225000 | AH26: =AF26/P26-1 -> 0.69453958 | AJ26: =SUM(S26:AD26)-SUM(AF26:AG26) -> 0 | AL26: =Spain!AG14+Spain!AG22 -> 12250 | AM26: =Spain!AH14+Spain!AH22 -> 14000 | AN26: =Spain!AI14+Spain!AI22 -> 17500 | AO26: =Spain!AJ14+Spain!AJ22 -> 14875 | AP26: =Spain!AK14+Spain!AK22 -> 15750 | AQ26: =Spain!AL14+Spain!AL22 -> 14000 | AR26: =Spain!AM14+Spain!AM22 -> 14000 | AS26: =Spain!AN14+Spain!AN22 -> 11375 | ... AW26: =Spain!AR14+Spain!AR22 -> 12250 | AZ26: =S26-AL26 -> 0 | BA26: =T26-AM26 -> 4000 | BB26: =U26-AN26 -> 4000 | BC26: =V26-AO26 -> 4000 | BD26: =W26-AP26 -> 4000 | BE26: =X26-AQ26 -> 4000 | BF26: =Y26-AR26 -> 4000 | BG26: =Z26-AS26 -> 2000 | ... BK26: =AD26-AW26 -> 5000
B27: France North | C27: ='France North'!Z6+'France North'!Z12+'France North'!Z18 -> 15631.42 | D27: ='France North'!Y6+'France North'!Y12+'France North'!Y18 -> 118500 | E27: =IFERROR(C27/D27-1, "N/A") -> -0.86808928 | F27: ='France North'!X6+'France North'!X12+'France North'!X18 -> 7914.88 | G27: =IFERROR(C27/F27-1, "N/A") -> 0.97494087 | I27: ='France North'!P6+'France North'!P12+'France North'!P18 -> 15631.42 | J27: ='France North'!Q6+'France North'!Q12+'France North'!Q18 -> 58105 | K27: =IFERROR(I27/J27-1, "N/A") -> -0.73097978 | L27: ='France North'!O6+'France North'!O12+'France North'!O18 -> 7914.88 | M27: =IFERROR(I27/L27-1, "N/A") -> 0.97494087 | O27: ='France North'!AA6+'France North'!AA12+'France North'!AA18 -> 80000 | P27: =C27 -> 15631.42 | Q27: =IFERROR(O27/P27-1, "N/A") -> 4.1178972 | S27: ='France North'!AG6+'France North'!AG12+'France North'!AG18 -> 1750 | T27: ='France North'!AH6+'France North'!AH12+'France North'!AH18 -> 6000 | U27: ='France North'!AI6+'France North'!AI12+'France North'!AI18 -> 7500 | V27: ='France North'!AJ6+'France North'!AJ12+'France North'!AJ18 -> 7125 | W27: ='France North'!AK6+'France North'!AK12+'France North'!AK18 -> 7250 | X27: ='France North'!AL6+'France North'!AL12+'France North'!AL18 -> 7000 | Y27: ='France North'!AM6+'France North'!AM12+'France North'!AM18 -> 7000 | Z27: ='France North'!AN6+'France North'!AN12+'France North'!AN18 -> 3625 | ... AD27: ='France North'!AR6+'France North'!AR12+'France North'!AR18 -> 6750 | AF27: 80000 | AH27: =AF27/P27-1 -> 4.1178972 | AJ27: =SUM(S27:AD27)-SUM(AF27:AG27) -> 0 | AL27: ='France North'!AG6+'France North'!AG12 -> 1750 | AM27: ='France North'!AH6+'France North'!AH12 -> 2000 | AN27: ='France North'!AI6+'France North'!AI12 -> 2500 | AO27: ='France North'!AJ6+'France North'!AJ12 -> 2125 | AP27: ='France North'!AK6+'France North'!AK12 -> 2250 | AQ27: ='France North'!AL6+'France North'!AL12 -> 2000 | AR27: ='France North'!AM6+'France North'!AM12 -> 2000 | AS27: ='France North'!AN6+'France North'!AN12 -> 1625 | ... AW27: ='France North'!AR6+'France North'!AR12 -> 1750 | AZ27: =S27-AL27 -> 0 | BA27: =T27-AM27 -> 4000 | BB27: =U27-AN27 -> 5000 | BC27: =V27-AO27 -> 5000 | BD27: =W27-AP27 -> 5000 | BE27: =X27-AQ27 -> 5000 | BF27: =Y27-AR27 -> 5000 | BG27: =Z27-AS27 -> 2000 | ... BK27: =AD27-AW27 -> 5000
B28: France South | C28: ='France South'!Z6+'France South'!Z14+'France South'!Z20 -> 32154.93 | D28: ='France South'!Y6+'France South'!Y14+'France South'!Y20 -> 132500 | E28: =IFERROR(C28/D28-1, "N/A") -> -0.75732128 | F28: ='France South'!X6+'France South'!X14+'France South'!X20 -> 25118.66 | G28: =IFERROR(C28/F28-1, "N/A") -> 0.28012123 | I28: ='France South'!P6+'France South'!P14+'France South'!P20 -> 32154.93 | J28: ='France South'!Q6+'France South'!Q14+'France South'!Q20 -> 68325 | K28: =IFERROR(I28/J28-1, "N/A") -> -0.52938266 | L28: ='France South'!O6+'France South'!O14+'France South'!O20 -> 25118.66 | M28: =IFERROR(I28/L28-1, "N/A") -> 0.28012123 | O28: ='France South'!AA6+'France South'!AA14+'France South'!AA20 -> 110000 | P28: =C28 -> 32154.93 | Q28: =IFERROR(O28/P28-1, "N/A") -> 2.4209373 | S28: ='France South'!AG6+'France South'!AG14+'France South'!AG20 -> 3500 | T28: ='France South'!AH6+'France South'!AH14+'France South'!AH20 -> 8000 | U28: ='France South'!AI6+'France South'!AI14+'France South'!AI20 -> 9000 | V28: ='France South'!AJ6+'France South'!AJ14+'France South'!AJ20 -> 8250 | W28: ='France South'!AK6+'France South'!AK14+'France South'!AK20 -> 11500 | X28: ='France South'!AL6+'France South'!AL14+'France South'!AL20 -> 11000 | Y28: ='France South'!AM6+'France South'!AM14+'France South'!AM20 -> 8000 | Z28: ='France South'!AN6+'France South'!AN14+'France South'!AN20 -> 5250 | ... AD28: ='France South'!AR6+'France South'!AR14+'France South'!AR20 -> 8500 | AF28: 100000 | AH28: =AF28/P28-1 -> 2.109943 | AJ28: =SUM(S28:AD28)-SUM(AF28:AG28) -> 10000 | AL28: ='France South'!AG6+'France South'!AG14 -> 3500 | AM28: ='France South'!AH6+'France South'!AH14 -> 4000 | AN28: ='France South'!AI6+'France South'!AI14 -> 5000 | AO28: ='France South'!AJ6+'France South'!AJ14 -> 4250 | AP28: ='France South'!AK6+'France South'!AK14 -> 4500 | AQ28: ='France South'!AL6+'France South'!AL14 -> 4000 | AR28: ='France South'!AM6+'France South'!AM14 -> 4000 | AS28: ='France South'!AN6+'France South'!AN14 -> 3250 | ... AW28: ='France South'!AR6+'France South'!AR14 -> 3500 | AZ28: =S28-AL28 -> 0 | BA28: =T28-AM28 -> 4000 | BB28: =U28-AN28 -> 4000 | BC28: =V28-AO28 -> 4000 | BD28: =W28-AP28 -> 7000 | BE28: =X28-AQ28 -> 7000 | BF28: =Y28-AR28 -> 4000 | BG28: =Z28-AS28 -> 2000 | ... BK28: =AD28-AW28 -> 5000
B29: Italy | C29: =SUM(Italy!Z5+Italy!Z11+Italy!Z17) -> 8199.18 | D29: =SUM(Italy!Y5+Italy!Y11+Italy!Y17) -> 0 | E29: =IFERROR(C29/D29-1, "N/A") -> N/A | F29: =SUM(Italy!X5+Italy!X11+Italy!X17) -> 0 | G29: =IFERROR(C29/F29-1, "N/A") -> N/A | I29: =SUM(Italy!P5+Italy!P11+Italy!P17) -> 8199.18 | J29: =SUM(Italy!Q5+Italy!Q11+Italy!Q17) -> 0 | K29: =IFERROR(I29/J29-1, "N/A") -> N/A | L29: =SUM(Italy!O5+Italy!O11+Italy!O17) -> 0 | M29: =IFERROR(I29/L29-1, "N/A") -> N/A | O29: =SUM(Italy!AA5+Italy!AA11+Italy!AA17) -> 75000 | P29: =C29 -> 8199.18 | Q29: =IFERROR(O29/P29-1, "N/A") -> 8.1472562 | S29: =SUM(Italy!AG5+Italy!AG11+Italy!AG17) -> 1050 | T29: =SUM(Italy!AH5+Italy!AH11+Italy!AH17) -> 5200 | U29: =SUM(Italy!AI5+Italy!AI11+Italy!AI17) -> 5500 | V29: =SUM(Italy!AJ5+Italy!AJ11+Italy!AJ17) -> 5275 | W29: =SUM(Italy!AK5+Italy!AK11+Italy!AK17) -> 10350 | X29: =SUM(Italy!AL5+Italy!AL11+Italy!AL17) -> 8200 | Y29: =SUM(Italy!AM5+Italy!AM11+Italy!AM17) -> 5200 | Z29: =SUM(Italy!AN5+Italy!AN11+Italy!AN17) -> 2975 | ... AD29: =SUM(Italy!AR5+Italy!AR11+Italy!AR17) -> 6050 | AF29: 75000 | AH29: =AF29/P29-1 -> 8.1472562 | AJ29: =SUM(S29:AD29)-SUM(AF29:AG29) -> 0 | AL29: =SUM(Italy!AG5+Italy!AG11) -> 1050 | AM29: =SUM(Italy!AH5+Italy!AH11) -> 1200 | AN29: =SUM(Italy!AI5+Italy!AI11) -> 1500 | AO29: =SUM(Italy!AJ5+Italy!AJ11) -> 1275 | AP29: =SUM(Italy!AK5+Italy!AK11) -> 1350 | AQ29: =SUM(Italy!AL5+Italy!AL11) -> 1200 | AR29: =SUM(Italy!AM5+Italy!AM11) -> 1200 | AS29: =SUM(Italy!AN5+Italy!AN11) -> 975 | ... AW29: =SUM(Italy!AR5+Italy!AR11) -> 1050 | AZ29: =S29-AL29 -> 0 | BA29: =T29-AM29 -> 4000 | BB29: =U29-AN29 -> 4000 | BC29: =V29-AO29 -> 4000 | BD29: =W29-AP29 -> 9000 | BE29: =X29-AQ29 -> 7000 | BF29: =Y29-AR29 -> 4000 | BG29: =Z29-AS29 -> 2000 | ... BK29: =AD29-AW29 -> 5000
AJ30: =SUM(S30:AD30)-SUM(AF30:AG30) -> 0
B31: Other EU | C31: =SUM(C26:C29) -> 188764.96 | D31: =SUM(D26:D29) -> 451000 | E31: =IFERROR(C31/D31-1, "N/A") -> -0.58145242 | F31: =SUM(F26:F29) -> 120716.38 | G31: =IFERROR(C31/F31-1, "N/A") -> 0.56370627 | I31: =SUM(I26:I29) -> 188764.96 | J31: =SUM(J26:J29) -> 247580 | K31: =IFERROR(I31/J31-1, "N/A") -> -0.23755974 | L31: =SUM(L26:L29) -> 120716.38 | M31: =IFERROR(I31/L31-1, "N/A") -> 0.56370627 | O31: =SUM(O26:O29) -> 490000 | P31: =SUM(P26:P29) -> 188764.96 | Q31: =IFERROR(O31/P31-1, "N/A") -> 1.5958207 | S31: =SUM(S26:S29) -> 18550 | T31: =SUM(T26:T29) -> 37200 | U31: =SUM(U26:U29) -> 43500 | V31: =SUM(V26:V29) -> 39525 | W31: =SUM(W26:W29) -> 48850 | X31: =SUM(X26:X29) -> 44200 | Y31: =SUM(Y26:Y29) -> 38200 | Z31: =SUM(Z26:Z29) -> 25225 | ... AD31: =SUM(AD26:AD29) -> 38550 | AF31: =SUM(AF26:AF29) -> 480000 | AG31: =SUM(AG26:AG29) -> 0 | AH31: =AF31/P31-1 -> 1.5428448 | AJ31: =SUM(S31:AD31)-SUM(AF31:AG31) -> 10000 | AL31: =SUM(AL26:AL29) -> 18550 | AM31: =SUM(AM26:AM29) -> 21200 | AN31: =SUM(AN26:AN29) -> 26500 | AO31: =SUM(AO26:AO29) -> 22525 | AP31: =SUM(AP26:AP29) -> 23850 | AQ31: =SUM(AQ26:AQ29) -> 21200 | AR31: =SUM(AR26:AR29) -> 21200 | AS31: =SUM(AS26:AS29) -> 17225 | ... AW31: =SUM(AW26:AW29) -> 18550 | AZ31: =SUM(AZ26:AZ29) -> 0 | BA31: =SUM(BA26:BA29) -> 16000 | BB31: =SUM(BB26:BB29) -> 17000 | BC31: =SUM(BC26:BC29) -> 17000 | BD31: =SUM(BD26:BD29) -> 25000 | BE31: =SUM(BE26:BE29) -> 23000 | BF31: =SUM(BF26:BF29) -> 17000 | BG31: =SUM(BG26:BG29) -> 8000 | ... BK31: =SUM(BK26:BK29) -> 20000
AF33: =SUM(AF31,AF24,AF18,AF12) -> 7824517.7 | AG33: =SUM(AG31,AG24,AG18,AG12) -> 520000
AF35: =SUM(AF33+AG33) -> 8344517.7
B36: Elena Summary
B37: EUR | C37: Full Year | I37: YTD | O37: Full Year
C38: 25A | D38: 25B | E38: 25F vs 25B | F38: 24A | G38: 25F vs 24A | I38: 25A | J38: 25B | K38: 25A vs 25B | L38: 24A | M38: 25A vs 24A | O38: 26B | P38: 25A | Q38: 26B vs 25F | S38: 46023 | T38: 46054 | U38: 46082 | V38: 46113 | W38: 46143 | X38: 46174 | Y38: 46204 | Z38: 46235 | AA38: 46266 | AB38: 46296 | AC38: 46327 | AD38: 46357 | AL38: 46023 | AM38: 46054 | AN38: 46082 | AO38: 46113 | AP38: 46143 | AQ38: 46174 | AR38: 46204 | AS38: 46235 | AT38: 46266 | AU38: 46296 | AV38: 46327 | AW38: 46357 | AZ38: 46023 | BA38: 46054 | BB38: 46082 | BC38: 46113 | BD38: 46143 | BE38: 46174 | BF38: 46204 | BG38: 46235 | BH38: 46266 | BI38: 46296 | BJ38: 46327 | BK38: 46357
B39: French Switzerland | C39: =C21 -> 15500.405 | D39: =D21 -> 39900 | E39: -1 | F39: =F21 -> 17700.291 | G39: -1 | I39: =I21 -> 15500.405 | J39: =J21 -> 21672 | K39: -0.62502539 | L39: =L21 -> 17700.291 | M39: -0.44078643 | O39: =O21 -> 91875 | P39: =P21 -> 15500.405 | Q39: N/A | S39: =S21 -> 2572.5 | T39: =T21 -> 7140 | U39: =U21 -> 8925 | V39: =V21 -> 7323.75 | W39: =W21 -> 9082.5 | X39: =X21 -> 7140 | Y39: =Y21 -> 7140 | Z39: =Z21 -> 4488.75 | ... AD39: =AD21 -> 7822.5 | AL39: =AL21 -> 2572.5 | AM39: =AM21 -> 2940 | AN39: =AN21 -> 3675 | AO39: =AO21 -> 3123.75 | AP39: =AP21 -> 3307.5 | AQ39: =AQ21 -> 2940 | AR39: =AR21 -> 2940 | AS39: =AS21 -> 2388.75 | ... AW39: =AW21 -> 2572.5 | AZ39: =AZ21 -> 0 | BA39: =BA21 -> 4200 | BB39: =BB21 -> 5250 | BC39: =BC21 -> 4200 | BD39: =BD21 -> 5775 | BE39: =BE21 -> 4200 | BF39: =BF21 -> 4200 | BG39: =BG21 -> 2100 | ... BK39: =BK21 -> 5250
B40: France North | C40: =C27 -> 15631.42 | D40: =D27 -> 118500 | E40: -1 | F40: =F27 -> 7914.88 | G40: -1 | I40: =I27 -> 15631.42 | J40: =J27 -> 58105 | K40: -0.93630434 | L40: =L27 -> 7914.88 | M40: -0.32964246 | O40: =O27 -> 80000 | P40: =P27 -> 15631.42 | Q40: N/A | S40: =S27 -> 1750 | T40: =T27 -> 6000 | U40: =U27 -> 7500 | V40: =V27 -> 7125 | W40: =W27 -> 7250 | X40: =X27 -> 7000 | Y40: =Y27 -> 7000 | Z40: =Z27 -> 3625 | ... AD40: =AD27 -> 6750 | AL40: =AL27 -> 1750 | AM40: =AM27 -> 2000 | AN40: =AN27 -> 2500 | AO40: =AO27 -> 2125 | AP40: =AP27 -> 2250 | AQ40: =AQ27 -> 2000 | AR40: =AR27 -> 2000 | AS40: =AS27 -> 1625 | ... AW40: =AW27 -> 1750 | AZ40: =AZ27 -> 0 | BA40: =BA27 -> 4000 | BB40: =BB27 -> 5000 | BC40: =BC27 -> 5000 | BD40: =BD27 -> 5000 | BE40: =BE27 -> 5000 | BF40: =BF27 -> 5000 | BG40: =BG27 -> 2000 | ... BK40: =BK27 -> 5000
B41: Italy | C41: =C29 -> 8199.18 | D41: =D29 -> 0 | E41: -1 | F41: =F29 -> 0 | G41: -1 | I41: =I29 -> 8199.18 | J41: =J29 -> 0 | K41: -0.93630434 | L41: =L29 -> 0 | M41: -0.32964246 | O41: =O29 -> 75000 | P41: =P29 -> 8199.18 | Q41: N/A | S41: =S29 -> 1050 | T41: =T29 -> 5200 | U41: =U29 -> 5500 | V41: =V29 -> 5275 | W41: =W29 -> 10350 | X41: =X29 -> 8200 | Y41: =Y29 -> 5200 | Z41: =Z29 -> 2975 | ... AD41: =AD29 -> 6050 | AL41: =AL29 -> 1050 | AM41: =AM29 -> 1200 | AN41: =AN29 -> 1500 | AO41: =AO29 -> 1275 | AP41: =AP29 -> 1350 | AQ41: =AQ29 -> 1200 | AR41: =AR29 -> 1200 | AS41: =AS29 -> 975 | ... AW41: =AW29 -> 1050 | AZ41: =AZ29 -> 0 | BA41: =BA29 -> 4000 | BB41: =BB29 -> 4000 | BC41: =BC29 -> 4000 | BD41: =BD29 -> 9000 | BE41: =BE29 -> 7000 | BF41: =BF29 -> 4000 | BG41: =BG29 -> 2000 | ... BK41: =BK29 -> 5000
B42: Total Elena | C42: =SUM(C39:C41) -> 39331.005 | D42: =SUM(D39:D41) -> 158400 | E42: -1 | F42: =SUM(F39:F41) -> 25615.171 | G42: -1 | I42: =SUM(I39:I41) -> 39331.005 | J42: =SUM(J39:J41) -> 79777 | K42: -0.93630434 | L42: =SUM(L39:L41) -> 25615.171 | M42: -0.32964246 | O42: =SUM(O39:O41) -> 246875 | P42: =SUM(P39:P41) -> 39331.005 | Q42: N/A | S42: =SUM(S39:S41) -> 5372.5 | T42: =SUM(T39:T41) -> 18340 | U42: =SUM(U39:U41) -> 21925 | V42: =SUM(V39:V41) -> 19723.75 | W42: =SUM(W39:W41) -> 26682.5 | X42: =SUM(X39:X41) -> 22340 | Y42: =SUM(Y39:Y41) -> 19340 | Z42: =SUM(Z39:Z41) -> 11088.75 | ... AD42: =SUM(AD39:AD41) -> 20622.5 | AL42: =SUM(AL39:AL41) -> 5372.5 | AM42: =SUM(AM39:AM41) -> 6140 | AN42: =SUM(AN39:AN41) -> 7675 | AO42: =SUM(AO39:AO41) -> 6523.75 | AP42: =SUM(AP39:AP41) -> 6907.5 | AQ42: =SUM(AQ39:AQ41) -> 6140 | AR42: =SUM(AR39:AR41) -> 6140 | AS42: =SUM(AS39:AS41) -> 4988.75 | ... AW42: =SUM(AW39:AW41) -> 5372.5 | AZ42: =SUM(AZ39:AZ41) -> 0 | BA42: =SUM(BA39:BA41) -> 12200 | BB42: =SUM(BB39:BB41) -> 14250 | BC42: =SUM(BC39:BC41) -> 13200 | BD42: =SUM(BD39:BD41) -> 19775 | BE42: =SUM(BE39:BE41) -> 16200 | BF42: =SUM(BF39:BF41) -> 13200 | BG42: =SUM(BG39:BG41) -> 6100 | ... BK42: =SUM(BK39:BK41) -> 15250
B46: These numbers below are in Swiss Francs, to be used for actual commission calculations for the Team
C47: Full Year | I47: YTD | O47: Full Year
B48: CHF | C48: 25A | D48: 25B | E48: 25F vs 25B | F48: 24A | G48: 25A vs 24A | I48: 25A | J48: 25B | K48: 25A vs 25B | L48: 24A | M48: 25A vs 24A | O48: 26B | P48: 25A | Q48: 26B vs 25F | S48: 46023 | T48: 46054 | U48: 46082 | V48: 46113 | W48: 46143 | X48: 46174 | Y48: 46204 | Z48: 46235 | AA48: 46266 | AB48: 46296 | AC48: 46327 | AD48: 46357 | AL48: 46023 | AM48: 46054 | AN48: 46082 | AO48: 46113 | AP48: 46143 | AQ48: 46174 | AR48: 46204 | AS48: 46235 | AT48: 46266 | AU48: 46296 | AV48: 46327 | AW48: 46357 | AZ48: 46023 | BA48: 46054 | BB48: 46082 | BC48: 46113 | BD48: 46143 | BE48: 46174 | BF48: 46204 | BG48: 46235 | BH48: 46266 | BI48: 46296 | BJ48: 46327 | BK48: 46357
B49: German Switzerland | C49: ='Switzerland DE'!Z51+'Switzerland DE'!Z59+'Switzerland DE'!Z65 -> 578884.79 | D49: ='Switzerland DE'!Y51+'Switzerland DE'!Y59+'Switzerland DE'!Y65 -> 749100 | E49: =IFERROR(C49/D49-1, "N/A") -> -0.22722628 | F49: ='Switzerland DE'!X51+'Switzerland DE'!X59+'Switzerland DE'!X65 -> 665059.77 | G49: =IFERROR(C49/F49-1, "N/A") -> -0.12957479 | I49: ='Switzerland DE'!P51+'Switzerland DE'!P59+'Switzerland DE'!P65 -> 578884.79 | J49: ='Switzerland DE'!Q51+'Switzerland DE'!Q59+'Switzerland DE'!Q65 -> 539743 | K49: =IFERROR(I49/J49-1, "N/A") -> 0.07251931 | L49: ='Switzerland DE'!O51+'Switzerland DE'!O59+'Switzerland DE'!O65 -> 665059.77 | M49: =IFERROR(I49/L49-1, "N/A") -> -0.12957479 | O49: ='Switzerland DE'!AA51+'Switzerland DE'!AA59+'Switzerland DE'!AA65 -> 723360.79 | P49: =C49 -> 578884.79 | Q49: =IFERROR(O49/P49-1, "N/A") -> 0.24957644 | S49: ='Switzerland DE'!AG51+'Switzerland DE'!AG59+'Switzerland DE'!AG65 -> 46960.256 | T49: ='Switzerland DE'!AH51+'Switzerland DE'!AH59+'Switzerland DE'!AH65 -> 57668.863 | U49: ='Switzerland DE'!AI51+'Switzerland DE'!AI59+'Switzerland DE'!AI65 -> 71086.079 | V49: ='Switzerland DE'!AJ51+'Switzerland DE'!AJ59+'Switzerland DE'!AJ65 -> 62023.167 | W49: ='Switzerland DE'!AK51+'Switzerland DE'!AK59+'Switzerland DE'!AK65 -> 64377.471 | X49: ='Switzerland DE'!AL51+'Switzerland DE'!AL59+'Switzerland DE'!AL65 -> 59168.863 | Y49: ='Switzerland DE'!AM51+'Switzerland DE'!AM59+'Switzerland DE'!AM65 -> 57668.863 | Z49: ='Switzerland DE'!AN51+'Switzerland DE'!AN59+'Switzerland DE'!AN65 -> 45605.952 | ... AD49: ='Switzerland DE'!AR51+'Switzerland DE'!AR59+'Switzerland DE'!AR65 -> 51960.256 | AL49: ='Switzerland DE'!AG51+'Switzerland DE'!AG59 -> 46960.256 | AM49: ='Switzerland DE'!AH51+'Switzerland DE'!AH59 -> 53668.863 | AN49: ='Switzerland DE'!AI51+'Switzerland DE'!AI59 -> 67086.079 | AO49: ='Switzerland DE'!AJ51+'Switzerland DE'!AJ59 -> 57023.167 | AP49: ='Switzerland DE'!AK51+'Switzerland DE'!AK59 -> 60377.471 | AQ49: ='Switzerland DE'!AL51+'Switzerland DE'!AL59 -> 53668.863 | AR49: ='Switzerland DE'!AM51+'Switzerland DE'!AM59 -> 53668.863 | AS49: ='Switzerland DE'!AN51+'Switzerland DE'!AN59 -> 43605.952 | ... AW49: ='Switzerland DE'!AR51+'Switzerland DE'!AR59 -> 46960.256 | AZ49: =S49-AL49 -> 0 | BA49: =T49-AM49 -> 4000 | BB49: =U49-AN49 -> 4000 | BC49: =V49-AO49 -> 5000 | BD49: =W49-AP49 -> 4000 | BE49: =X49-AQ49 -> 5500 | BF49: =Y49-AR49 -> 4000 | BG49: =Z49-AS49 -> 2000 | ... BK49: =AD49-AW49 -> 5000
B50: French Switzerland | C50: ='Switzerland FR'!Z8+'Switzerland FR'!Z14+'Switzerland FR'!Z20 -> 14762.29 | D50: ='Switzerland FR'!Y8+'Switzerland FR'!Y14+'Switzerland FR'!Y20 -> 38000 | E50: =IFERROR(C50/D50-1, "N/A") -> -0.61151868 | F50: ='Switzerland FR'!X8+'Switzerland FR'!X14+'Switzerland FR'!X20 -> 16857.42 | G50: =IFERROR(C50/F50-1, "N/A") -> -0.12428533 | I50: ='Switzerland FR'!P8+'Switzerland FR'!P14+'Switzerland FR'!P20 -> 14762.29 | J50: ='Switzerland FR'!Q8+'Switzerland FR'!Q14+'Switzerland FR'!Q20 -> 20640 | K50: =IFERROR(I50/J50-1, "N/A") -> -0.28477277 | L50: ='Switzerland FR'!O8+'Switzerland FR'!O14+'Switzerland FR'!O20 -> 16857.42 | M50: =IFERROR(I50/L50-1, "N/A") -> -0.12428533 | O50: ='Switzerland FR'!AA8+'Switzerland FR'!AA14+'Switzerland FR'!AA20 -> 87500 | P50: =C50 -> 14762.29 | Q50: =IFERROR(O50/P50-1, "N/A") -> 4.9272647 | S50: ='Switzerland FR'!AG8+'Switzerland FR'!AG14+'Switzerland FR'!AG20 -> 2450 | T50: ='Switzerland FR'!AH8+'Switzerland FR'!AH14+'Switzerland FR'!AH20 -> 6800 | U50: ='Switzerland FR'!AI8+'Switzerland FR'!AI14+'Switzerland FR'!AI20 -> 8500 | V50: ='Switzerland FR'!AJ8+'Switzerland FR'!AJ14+'Switzerland FR'!AJ20 -> 6975 | W50: ='Switzerland FR'!AK8+'Switzerland FR'!AK14+'Switzerland FR'!AK20 -> 8650 | X50: ='Switzerland FR'!AL8+'Switzerland FR'!AL14+'Switzerland FR'!AL20 -> 6800 | Y50: ='Switzerland FR'!AM8+'Switzerland FR'!AM14+'Switzerland FR'!AM20 -> 6800 | Z50: ='Switzerland FR'!AN8+'Switzerland FR'!AN14+'Switzerland FR'!AN20 -> 4275 | ... AD50: ='Switzerland FR'!AR8+'Switzerland FR'!AR14+'Switzerland FR'!AR20 -> 7450 | AL50: ='Switzerland FR'!AG8+'Switzerland FR'!AG14 -> 2450 | AM50: ='Switzerland FR'!AH8+'Switzerland FR'!AH14 -> 2800 | AN50: ='Switzerland FR'!AI8+'Switzerland FR'!AI14 -> 3500 | AO50: ='Switzerland FR'!AJ8+'Switzerland FR'!AJ14 -> 2975 | AP50: ='Switzerland FR'!AK8+'Switzerland FR'!AK14 -> 3150 | AQ50: ='Switzerland FR'!AL8+'Switzerland FR'!AL14 -> 2800 | AR50: ='Switzerland FR'!AM8+'Switzerland FR'!AM14 -> 2800 | AS50: ='Switzerland FR'!AN8+'Switzerland FR'!AN14 -> 2275 | ... AW50: ='Switzerland FR'!AR8+'Switzerland FR'!AR14 -> 2450 | AZ50: =S50-AL50 -> 0 | BA50: =T50-AM50 -> 4000 | BB50: =U50-AN50 -> 5000 | BC50: =V50-AO50 -> 4000 | BD50: =W50-AP50 -> 5500 | BE50: =X50-AQ50 -> 4000 | BF50: =Y50-AR50 -> 4000 | BG50: =Z50-AS50 -> 2000 | ... BK50: =AD50-AW50 -> 5000
B51: Other Switzerland | C51: ='Golden Girls CH'!Z16 -> 0 | D51: ='Golden Girls CH'!Y16 -> 0 | E51: =IFERROR(C51/D51-1, "N/A") -> N/A | F51: ='Golden Girls CH'!X16 -> 0 | G51: =IFERROR(C51/F51-1, "N/A") -> N/A | I51: ='Golden Girls CH'!P16 -> 0 | J51: ='Golden Girls CH'!Q16 -> 0 | K51: =IFERROR(I51/J51-1, "N/A") -> N/A | L51: ='Golden Girls CH'!O16 -> 0 | M51: =IFERROR(I51/L51-1, "N/A") -> N/A | O51: ='Golden Girls CH'!AA16 -> 0 | P51: ='Golden Girls CH'!AK16 -> 0 | Q51: =IFERROR(O51/P51-1, "N/A") -> N/A | S51: ='Golden Girls CH'!AG16 -> 0 | T51: ='Golden Girls CH'!AH16 -> 0 | U51: ='Golden Girls CH'!AI16 -> 0 | V51: ='Golden Girls CH'!AJ16 -> 0 | W51: ='Golden Girls CH'!AK16 -> 0 | X51: ='Golden Girls CH'!AL16 -> 0 | Y51: ='Golden Girls CH'!AM16 -> 0 | Z51: ='Golden Girls CH'!AN16 -> 0 | ... AD51: ='Golden Girls CH'!AR16 -> 0 | AL51: ='Golden Girls CH'!AG16 -> 0 | AM51: ='Golden Girls CH'!AH16 -> 0 | AN51: ='Golden Girls CH'!AI16 -> 0 | AO51: ='Golden Girls CH'!AJ16 -> 0 | AP51: ='Golden Girls CH'!AK16 -> 0 | AQ51: ='Golden Girls CH'!AL16 -> 0 | AR51: ='Golden Girls CH'!AM16 -> 0 | AS51: ='Golden Girls CH'!AN16 -> 0 | ... AW51: ='Golden Girls CH'!AR16 -> 0 | AZ51: =S51-AL51 -> 0 | BA51: =T51-AM51 -> 0 | BB51: =U51-AN51 -> 0 | BC51: =V51-AO51 -> 0 | BD51: =W51-AP51 -> 0 | BE51: =X51-AQ51 -> 0 | BF51: =Y51-AR51 -> 0 | BG51: =Z51-AS51 -> 0 | ... BK51: =AD51-AW51 -> 0
B53: Switzerland | C53: =SUM(C49:C51) -> 593647.08 | D53: =SUM(D49:D51) -> 787100 | E53: =IFERROR(C53/D53-1, "N/A") -> -0.24577934 | F53: =SUM(F49:F51) -> 681917.19 | G53: =IFERROR(C53/F53-1, "N/A") -> -0.12944403 | I53: =SUM(I49:I51) -> 593647.08 | J53: =SUM(J49:J51) -> 560383 | K53: =IFERROR(I53/J53-1, "N/A") -> 0.059359545 | L53: =SUM(L49:L51) -> 681917.19 | M53: =IFERROR(I53/L53-1, "N/A") -> -0.12944403 | O53: =SUM(O49:O51) -> 810860.79 | P53: =SUM(P49:P51) -> 593647.08 | Q53: =IFERROR(O53/P53-1, "N/A") -> 0.36589705 | S53: =SUM(S49:S51) -> 49410.256 | T53: =SUM(T49:T51) -> 64468.863 | U53: =SUM(U49:U51) -> 79586.079 | V53: =SUM(V49:V51) -> 68998.167 | W53: =SUM(W49:W51) -> 73027.471 | X53: =SUM(X49:X51) -> 65968.863 | Y53: =SUM(Y49:Y51) -> 64468.863 | Z53: =SUM(Z49:Z51) -> 49880.952 | ... AD53: =SUM(AD49:AD51) -> 59410.256 | AL53: =SUM(AL49:AL51) -> 49410.256 | AM53: =SUM(AM49:AM51) -> 56468.863 | AN53: =SUM(AN49:AN51) -> 70586.079 | AO53: =SUM(AO49:AO51) -> 59998.167 | AP53: =SUM(AP49:AP51) -> 63527.471 | AQ53: =SUM(AQ49:AQ51) -> 56468.863 | AR53: =SUM(AR49:AR51) -> 56468.863 | AS53: =SUM(AS49:AS51) -> 45880.952 | ... AW53: =SUM(AW49:AW51) -> 49410.256 | AZ53: =SUM(AZ49:AZ51) -> 0 | BA53: =SUM(BA49:BA51) -> 8000 | BB53: =SUM(BB49:BB51) -> 9000 | BC53: =SUM(BC49:BC51) -> 9000 | BD53: =SUM(BD49:BD51) -> 9500 | BE53: =SUM(BE49:BE51) -> 9500 | BF53: =SUM(BF49:BF51) -> 8000 | BG53: =SUM(BG49:BG51) -> 4000 | ... BK53: =SUM(BK49:BK51) -> 10000
B57: NRW Summary | C57: Full Year | I57: YTD | O57: Full Year
C58: 25A | D58: 25B | E58: 25F vs 25B | F58: 24A | G58: 25F vs 24A | I58: 25A | J58: 25B | K58: 25A vs 25B | L58: 24A | M58: 25A vs 24A | O58: 26B | P58: 25A | Q58: 26B vs 25F | S58: 46023 | T58: 46054 | U58: 46082 | V58: 46113 | W58: 46143 | X58: 46174 | Y58: 46204 | Z58: 46235 | AA58: 46266 | AB58: 46296 | AC58: 46327 | AD58: 46357 | AF58: Target: | AG58: Target NC | AH58: Growth | AI58: Comment | AL58: 46023 | AM58: 46054 | AN58: 46082 | AO58: 46113 | AP58: 46143 | AQ58: 46174 | AR58: 46204 | AS58: 46235 | AT58: 46266 | AU58: 46296 | AV58: 46327 | AW58: 46357 | AZ58: 46023 | BA58: 46054 | BB58: 46082 | BC58: 46113 | BD58: 46143 | BE58: 46174 | BF58: 46204 | BG58: 46235 | BH58: 46266 | BI58: 46296 | BJ58: 46327 | BK58: 46357
B59: Marina | C59: ='NRW Marina'!Z21+'NRW Marina'!Z33+'NRW Marina'!Z39 -> 557416.49 | D59: ='NRW Marina'!Y21+'NRW Marina'!Y33+'NRW Marina'!Y39 -> 526500 | E59: =IFERROR(C59/D59-1, "N/A") -> 0.058720779 | F59: ='NRW Marina'!X21+'NRW Marina'!X33+'NRW Marina'!X39 -> 456058.65 | G59: =IFERROR(C59/F59-1, "N/A") -> 0.22224738 | I59: ='Switzerland DE'!P61+'Switzerland DE'!P69+'Switzerland DE'!P75 -> 0 | J59: ='Switzerland DE'!Q61+'Switzerland DE'!Q69+'Switzerland DE'!Q75 -> 0 | K59: =IFERROR(I59/J59-1, "N/A") -> N/A | L59: ='Switzerland DE'!O61+'Switzerland DE'!O69+'Switzerland DE'!O75 -> 0 | M59: =IFERROR(I59/L59-1, "N/A") -> N/A | O59: ='NRW Marina'!AA21+'NRW Marina'!AA33+'NRW Marina'!AA39 -> 644137.21 | P59: =C59 -> 557416.49 | Q59: =IFERROR(O59/P59-1, "N/A") -> 0.15557617 | S59: ='NRW Marina'!AG21+'NRW Marina'!AG33+'NRW Marina'!AG39 -> 41589.605 | T59: ='NRW Marina'!AH21+'NRW Marina'!AH33+'NRW Marina'!AH39 -> 51530.977 | U59: ='NRW Marina'!AI21+'NRW Marina'!AI33+'NRW Marina'!AI39 -> 63413.721 | V59: ='NRW Marina'!AJ21+'NRW Marina'!AJ33+'NRW Marina'!AJ39 -> 54501.663 | W59: ='NRW Marina'!AK21+'NRW Marina'!AK33+'NRW Marina'!AK39 -> 57472.349 | X59: ='NRW Marina'!AL21+'NRW Marina'!AL33+'NRW Marina'!AL39 -> 51530.977 | Y59: ='NRW Marina'!AM21+'NRW Marina'!AM33+'NRW Marina'!AM39 -> 51530.977 | Z59: ='NRW Marina'!AN21+'NRW Marina'!AN33+'NRW Marina'!AN39 -> 40618.919 | ... AD59: ='NRW Marina'!AR21+'NRW Marina'!AR33+'NRW Marina'!AR39 -> 46589.605 | AF59: ='NRW Marina'!AA21+'NRW Marina'!AA33 -> 594137.21 | AG59: =+'NRW Marina'!AA39 -> 50000 | AL59: ='NRW Marina'!AG21+'NRW Marina'!AG33 -> 41589.605 | AM59: ='NRW Marina'!AH21+'NRW Marina'!AH33 -> 47530.977 | AN59: ='NRW Marina'!AI21+'NRW Marina'!AI33 -> 59413.721 | AO59: ='NRW Marina'!AJ21+'NRW Marina'!AJ33 -> 50501.663 | AP59: ='NRW Marina'!AK21+'NRW Marina'!AK33 -> 53472.349 | AQ59: ='NRW Marina'!AL21+'NRW Marina'!AL33 -> 47530.977 | AR59: ='NRW Marina'!AM21+'NRW Marina'!AM33 -> 47530.977 | AS59: ='NRW Marina'!AN21+'NRW Marina'!AN33 -> 38618.919 | ... AW59: ='NRW Marina'!AR21+'NRW Marina'!AR33 -> 41589.605 | AZ59: =S59-AL59 -> 0 | BA59: =T59-AM59 -> 4000 | BB59: =U59-AN59 -> 4000 | BC59: =V59-AO59 -> 4000 | BD59: =W59-AP59 -> 4000 | BE59: =X59-AQ59 -> 4000 | BF59: =Y59-AR59 -> 4000 | BG59: =Z59-AS59 -> 2000 | ... BK59: =AD59-AW59 -> 5000
B60: Ulrike | C60: ='NRW Ulrike'!Z23+'NRW Ulrike'!Z31+'NRW Ulrike'!Z37 -> 128419.11 | D60: ='NRW Ulrike'!Y23+'NRW Ulrike'!Y31+'NRW Ulrike'!Y37 -> 185000 | E60: =IFERROR(C60/D60-1, "N/A") -> -0.30584265 | F60: ='NRW Ulrike'!X23+'NRW Ulrike'!X31+'NRW Ulrike'!X37 -> 144120.97 | G60: =IFERROR(C60/F60-1, "N/A") -> -0.10894917 | I60: ='Switzerland FR'!P18+'Switzerland FR'!P24+'Switzerland FR'!P30 -> 0 | J60: ='Switzerland FR'!Q18+'Switzerland FR'!Q24+'Switzerland FR'!Q30 -> 0 | K60: =IFERROR(I60/J60-1, "N/A") -> N/A | L60: ='Switzerland FR'!O18+'Switzerland FR'!O24+'Switzerland FR'!O30 -> 0 | M60: =IFERROR(I60/L60-1, "N/A") -> N/A | O60: ='NRW Ulrike'!AA23+'NRW Ulrike'!AA31+'NRW Ulrike'!AA37 -> 192929.99 | P60: =C60 -> 128419.11 | Q60: =IFERROR(O60/P60-1, "N/A") -> 0.50234645 | S60: ='NRW Ulrike'!AG23+'NRW Ulrike'!AG31+'NRW Ulrike'!AG37 -> 11055.1 | T60: ='NRW Ulrike'!AH23+'NRW Ulrike'!AH31+'NRW Ulrike'!AH37 -> 15634.4 | U60: ='NRW Ulrike'!AI23+'NRW Ulrike'!AI31+'NRW Ulrike'!AI37 -> 18792.999 | V60: ='NRW Ulrike'!AJ23+'NRW Ulrike'!AJ31+'NRW Ulrike'!AJ37 -> 16424.05 | W60: ='NRW Ulrike'!AK23+'NRW Ulrike'!AK31+'NRW Ulrike'!AK37 -> 17213.699 | X60: ='NRW Ulrike'!AL23+'NRW Ulrike'!AL31+'NRW Ulrike'!AL37 -> 15634.4 | Y60: ='NRW Ulrike'!AM23+'NRW Ulrike'!AM31+'NRW Ulrike'!AM37 -> 15634.4 | Z60: ='NRW Ulrike'!AN23+'NRW Ulrike'!AN31+'NRW Ulrike'!AN37 -> 12265.45 | ... AD60: ='NRW Ulrike'!AR23+'NRW Ulrike'!AR31+'NRW Ulrike'!AR37 -> 14055.1 | AF60: ='NRW Ulrike'!AA23+'NRW Ulrike'!AA31 -> 157929.99 | AG60: =+'NRW Ulrike'!AA37 -> 35000 | AL60: ='NRW Ulrike'!AG23+'NRW Ulrike'!AG31 -> 11055.1 | AM60: ='NRW Ulrike'!AH23+'NRW Ulrike'!AH31 -> 12634.4 | AN60: ='NRW Ulrike'!AI23+'NRW Ulrike'!AI31 -> 15792.999 | AO60: ='NRW Ulrike'!AJ23+'NRW Ulrike'!AJ31 -> 13424.05 | AP60: ='NRW Ulrike'!AK23+'NRW Ulrike'!AK31 -> 14213.699 | AQ60: ='NRW Ulrike'!AL23+'NRW Ulrike'!AL31 -> 12634.4 | AR60: ='NRW Ulrike'!AM23+'NRW Ulrike'!AM31 -> 12634.4 | AS60: ='NRW Ulrike'!AN23+'NRW Ulrike'!AN31 -> 10265.45 | ... AW60: ='NRW Ulrike'!AR23+'NRW Ulrike'!AR31 -> 11055.1 | AZ60: =S60-AL60 -> 0 | BA60: =T60-AM60 -> 3000 | BB60: =U60-AN60 -> 3000 | BC60: =V60-AO60 -> 3000 | BD60: =W60-AP60 -> 3000 | BE60: =X60-AQ60 -> 3000 | BF60: =Y60-AR60 -> 3000 | BG60: =Z60-AS60 -> 2000 | ... BK60: =AD60-AW60 -> 3000
B62: Total | C62: =SUM(C58:C60) -> 685835.6 | D62: =SUM(D58:D60) -> 711500 | E62: =IFERROR(C62/D62-1, "N/A") -> -0.036070836 | F62: =SUM(F58:F60) -> 600179.62 | G62: =IFERROR(C62/F62-1, "N/A") -> 0.14271724 | I62: =SUM(I58:I60) -> 0 | J62: =SUM(J58:J60) -> 0 | K62: =IFERROR(I62/J62-1, "N/A") -> N/A | L62: =SUM(L58:L60) -> 0 | M62: =IFERROR(I62/L62-1, "N/A") -> N/A | O62: =SUM(O58:O60) -> 837067.21 | P62: =SUM(P58:P60) -> 685835.6 | Q62: =IFERROR(O62/P62-1, "N/A") -> 0.22050708 | S62: =SUM(S59:S60) -> 52644.705 | T62: =SUM(T59:T60) -> 67165.377 | U62: =SUM(U59:U60) -> 82206.721 | V62: =SUM(V59:V60) -> 70925.713 | W62: =SUM(W59:W60) -> 74686.049 | X62: =SUM(X59:X60) -> 67165.377 | Y62: =SUM(Y59:Y60) -> 67165.377 | Z62: =SUM(Z59:Z60) -> 52884.369 | ... AD62: =SUM(AD59:AD60) -> 60644.705 | AF62: =SUM(AF58:AF60) -> 752067.21 | AG62: =SUM(AG58:AG60) -> 85000 | AL62: =SUM(AL59:AL60) -> 52644.705 | AM62: =SUM(AM59:AM60) -> 60165.377 | AN62: =SUM(AN59:AN60) -> 75206.721 | AO62: =SUM(AO59:AO60) -> 63925.713 | AP62: =SUM(AP59:AP60) -> 67686.049 | AQ62: =SUM(AQ59:AQ60) -> 60165.377 | AR62: =SUM(AR59:AR60) -> 60165.377 | AS62: =SUM(AS59:AS60) -> 48884.369 | ... AW62: =SUM(AW59:AW60) -> 52644.705 | AZ62: =SUM(AZ59:AZ60) -> 0 | BA62: =SUM(BA59:BA60) -> 7000 | BB62: =SUM(BB59:BB60) -> 7000 | BC62: =SUM(BC59:BC60) -> 7000 | BD62: =SUM(BD59:BD60) -> 7000 | BE62: =SUM(BE59:BE60) -> 7000 | BF62: =SUM(BF59:BF60) -> 7000 | BG62: =SUM(BG59:BG60) -> 4000 | ... BK62: =SUM(BK59:BK60) -> 8000

Sheet Region review
C1: 2025
C2: Old region | D2: New region | F2: Commission earned | G2: Commission % | I2: "Lost" sales | J2: Commission % used | K2: Lost Commission | L2: Monthly uplift | N2: Commission under old scheme | O2: Commission under new scheme | P2: Benefit of new scheme on 2025 sales
B3: Kerstin | C3: 721212.06 | D3: =Summary!C4 -> 602834.42 | F3: 19711.32 | G3: =F3/C3 -> 0.027330824 | I3: =C3-D3 -> 118377.64 | J3: 0.03 | K3: =I3*J3 -> 3551.3292 | L3: =MROUND(K3/12, 100) -> 300 | N3: =F3 -> 19711.32 | O3: =SUM(D23:O23,D31:O31,Q31) -> 27498.357 | P3: =O3-N3 -> 7787.0367
B4: Ara | C4: 719983.41 | D4: =Summary!C5 -> 375419.11 | F4: 28357.29 | G4: =F4/C4 -> 0.039386033 | I4: =C4-D4 -> 344564.3 | J4: 0.04 | K4: =I4*J4 -> 13782.572 | L4: =MROUND(K4/12, 100) -> 1100 | N4: =F4 -> 28357.29 | O4: =SUM(D46:O46,D54:O54,Q54) -> 38024.733 | P4: =O4-N4 -> 9667.443
B17: Kerstin:
B18: 2025 | D18: 45658 | E18: 45689 | F18: 45717 | G18: 45748 | H18: 45778 | I18: 45809 | J18: 45839 | K18: 45870 | L18: 45901 | M18: 45931 | N18: 45962 | O18: 45992
B19: Existing sales | D19: =D33-D27 -> 47163.19 | E19: =E33-E27 -> 38296.67 | F19: =F33-F27 -> 52596.8 | G19: =G33-G27 -> 61308.56 | H19: =H33-H27 -> 61413.83 | I19: =I33-I27 -> 39368.89 | J19: =J33-J27 -> 66298.71 | K19: =K33-K27 -> 59196.87 | ... O19: =O33-O27 -> 49560.6
B20: Existing budget | D20: =D34-D28 -> 51005.5 | E20: =E34-E28 -> 62776 | F20: =F34-F28 -> 82393.5 | G20: =G34-G28 -> 70623 | H20: =H34-H28 -> 70623 | I20: =I34-I28 -> 62776 | J20: =J34-J28 -> 62776 | K20: =K34-K28 -> 39235 | ... O20: =O34-O28 -> 54929
B21: % achieved | D21: =D19/D20 -> 0.92466871 | E21: =E19/E20 -> 0.61005273 | F21: =F19/F20 -> 0.63836104 | G21: =G19/G20 -> 0.86811039 | H21: =H19/H20 -> 0.86960098 | I21: =I19/I20 -> 0.62713282 | J21: =J19/J20 -> 1.0561156 | K21: =K19/K20 -> 1.5087771 | ... O21: =O19/O20 -> 0.90226656
B22: Commission % applied | D22: =IF(D21<0.9, 0, IF(D21<1, 0.03, IF(D21>1, "Multiple"))) -> 0.03 | E22: =IF(E21<0.9, 0, IF(E21<1, 0.03, IF(E21>1, "Multiple"))) -> 0 | F22: =IF(F21<0.9, 0, IF(F21<1, 0.03, IF(F21>1, "Multiple"))) -> 0 | G22: =IF(G21<0.9, 0, IF(G21<1, 0.03, IF(G21>1, "Multiple"))) -> 0 | H22: =IF(H21<0.9, 0, IF(H21<1, 0.03, IF(H21>1, "Multiple"))) -> 0 | I22: =IF(I21<0.9, 0, IF(I21<1, 0.03, IF(I21>1, "Multiple"))) -> 0 | J22: =IF(J21<0.9, 0, IF(J21<1, 0.03, IF(J21>1, "Multiple"))) -> Multiple | K22: =IF(K21<0.9, 0, IF(K21<1, 0.03, IF(K21>1, "Multiple"))) -> Multiple | ... O22: =IF(O21<0.9, 0, IF(O21<1, 0.03, IF(O21>1, "Multiple"))) -> 0.03
B23: Commission | D23: =IF(D22="Multiple", D20*6%+(D19-D20)*10%, D19*D22) -> 1414.8957 | E23: =IF(E22="Multiple", E20*6%+(E19-E20)*10%, E19*E22) -> 0 | F23: =IF(F22="Multiple", F20*6%+(F19-F20)*10%, F19*F22) -> 0 | G23: =IF(G22="Multiple", G20*6%+(G19-G20)*10%, G19*G22) -> 0 | H23: =IF(H22="Multiple", H20*6%+(H19-H20)*10%, H19*H22) -> 0 | I23: =IF(I22="Multiple", I20*6%+(I19-I20)*10%, I19*I22) -> 0 | J23: =IF(J22="Multiple", J20*6%+(J19-J20)*10%, J19*J22) -> 4118.831 | K23: =IF(K22="Multiple", K20*6%+(K19-K20)*10%, K19*K22) -> 4350.287 | ... O23: =IF(O22="Multiple", O20*6%+(O19-O20)*10%, O19*O22) -> 1486.818
B25: New door sales (first 3 months) | D25: 0 | E25: 0 | F25: 0 | G25: 0 | H25: 11459.17 | I25: 0 | J25: 13774.14 | K25: 0 | L25: 0 | M25: 0 | N25: 0 | O25: 0 | Q25: Full year check
B26: New door sales (reorder) | D26: 0 | E26: 0 | F26: 0 | G26: 0 | H26: 0 | I26: 0 | J26: 0 | K26: 0 | L26: 13576.99 | M26: 10724.19 | N26: -27.73 | O26: 0
B27: Total new door sales | D27: 0 | E27: 0 | F27: 0 | G27: 0 | H27: 11459.17 | I27: 0 | J27: 13774.14 | K27: 0 | L27: 13576.99 | M27: 10724.19 | N27: -27.73 | O27: 0 | Q27: =SUM(D27:O27) -> 49506.76
B28: New door budget | D28: 0 | E28: 750 | F28: 1500 | G28: 1500 | H28: 2250 | I28: 2250 | J28: 3000 | K28: 2250 | L28: 4500 | M28: 4500 | N28: 4500 | O28: 3000 | Q28: =SUM(D28:O28) -> 30000
B29: % achieved | D29: =IFERROR(D27/D28, 0) -> 0 | E29: =IFERROR(E27/E28, 0) -> 0 | F29: =IFERROR(F27/F28, 0) -> 0 | G29: =IFERROR(G27/G28, 0) -> 0 | H29: =IFERROR(H27/H28, 0) -> 5.0929644 | I29: =IFERROR(I27/I28, 0) -> 0 | J29: =IFERROR(J27/J28, 0) -> 4.59138 | K29: =IFERROR(K27/K28, 0) -> 0 | ... O29: =IFERROR(O27/O28, 0) -> 0 | Q29: =IFERROR(Q27/Q28, 0) -> 1.6502253
B30: Commission % applied | D30: =IF(D29<0.8, 0, IF(D29<0.9, 5%, 10%)) -> 0 | E30: =IF(E29<0.8, 0, IF(E29<0.9, 5%, 10%)) -> 0 | F30: =IF(F29<0.8, 0, IF(F29<0.9, 5%, 10%)) -> 0 | G30: =IF(G29<0.8, 0, IF(G29<0.9, 5%, 10%)) -> 0 | H30: =IF(H29<0.8, 0, IF(H29<0.9, 5%, 10%)) -> 0.1 | I30: =IF(I29<0.8, 0, IF(I29<0.9, 5%, 10%)) -> 0 | J30: =IF(J29<0.8, 0, IF(J29<0.9, 5%, 10%)) -> 0.1 | K30: =IF(K29<0.8, 0, IF(K29<0.9, 5%, 10%)) -> 0 | ... O30: =IF(O29<0.8, 0, IF(O29<0.9, 5%, 10%)) -> 0 | Q30: N/A
B31: Commission | D31: =D25*10%+D30*D26 -> 0 | E31: =E25*10%+E30*E26 -> 0 | F31: =F25*10%+F30*F26 -> 0 | G31: =G25*10%+G30*G26 -> 0 | H31: =H25*10%+H30*H26 -> 1145.917 | I31: =I25*10%+I30*I26 -> 0 | J31: =J25*10%+J30*J26 -> 1377.414 | K31: =K25*10%+K30*K26 -> 0 | ... O31: =O25*10%+O30*O26 -> 0 | Q31: =IF(Q29>1, 5000, 0) -> 5000
B33: Total Sales | D33: 47163.19 | E33: 38296.67 | F33: 52596.8 | G33: 61308.56 | H33: 72873 | I33: 39368.89 | J33: 80072.85 | K33: 59196.87 | L33: 66780.44 | M33: 64031.96 | N33: 89962.23 | O33: 49560.6
B34: Total Budget | D34: 51005.5 | E34: 63526 | F34: 83893.5 | G34: 72123 | H34: 72873 | I34: 65026 | J34: 65776 | K34: 41485 | L34: 75123 | M34: 90817 | N34: 75123 | O34: 57929
B40: Ara:
B41: 2025 | D41: 45658 | E41: 45689 | F41: 45717 | G41: 45748 | H41: 45778 | I41: 45809 | J41: 45839 | K41: 45870 | L41: 45901 | M41: 45931 | N41: 45962 | O41: 45992
B42: Existing sales | D42: =D56-D48 -> 40604.13 | E42: =E56-E48 -> 45367.29 | F42: =F56-F48 -> 52810.52 | G42: =G56-G48 -> 81802.45 | H42: =H56-H48 -> 67677.67 | I42: =I56-I48 -> 20634.6 | J42: =J56-J48 -> 64676.87 | K42: =K56-K48 -> 40795.76 | ... O42: =O56-O48 -> 64703.47
B43: Existing budget | D43: =D57-D51 -> 47710 | E43: =E57-E51 -> 58720 | F43: =F57-F51 -> 77070 | G43: =G57-G51 -> 66060 | H43: =H57-H51 -> 66060 | I43: =I57-I51 -> 58720 | J43: =J57-J51 -> 58720 | K43: =K57-K51 -> 36700 | ... O43: =O57-O51 -> 51380
B44: % achieved | D44: =D42/D43 -> 0.8510612 | E44: =E42/E43 -> 0.77260371 | F44: =F42/F43 -> 0.68522797 | G44: =G42/G43 -> 1.2383053 | H44: =H42/H43 -> 1.0244879 | I44: =I42/I43 -> 0.35140668 | J44: =J42/J43 -> 1.1014453 | K44: =K42/K43 -> 1.1116011 | ... O44: =O42/O43 -> 1.2593124
B45: Commission % applied | D45: =IF(D44<0.9, 0, IF(D44<1, 0.03, IF(D44>1, "Multiple"))) -> 0 | E45: =IF(E44<0.9, 0, IF(E44<1, 0.03, IF(E44>1, "Multiple"))) -> 0 | F45: =IF(F44<0.9, 0, IF(F44<1, 0.03, IF(F44>1, "Multiple"))) -> 0 | G45: =IF(G44<0.9, 0, IF(G44<1, 0.03, IF(G44>1, "Multiple"))) -> Multiple | H45: =IF(H44<0.9, 0, IF(H44<1, 0.03, IF(H44>1, "Multiple"))) -> Multiple | I45: =IF(I44<0.9, 0, IF(I44<1, 0.03, IF(I44>1, "Multiple"))) -> 0 | J45: =IF(J44<0.9, 0, IF(J44<1, 0.03, IF(J44>1, "Multiple"))) -> Multiple | K45: =IF(K44<0.9, 0, IF(K44<1, 0.03, IF(K44>1, "Multiple"))) -> Multiple | ... O45: =IF(O44<0.9, 0, IF(O44<1, 0.03, IF(O44>1, "Multiple"))) -> Multiple
B46: Commission | D46: =IF(D45="Multiple", D43*6%+(D42-D43)*10%, D42*D45) -> 0 | E46: =IF(E45="Multiple", E43*6%+(E42-E43)*10%, E42*E45) -> 0 | F46: =IF(F45="Multiple", F43*6%+(F42-F43)*10%, F42*F45) -> 0 | G46: =IF(G45="Multiple", G43*6%+(G42-G43)*10%, G42*G45) -> 5537.845 | H46: =IF(H45="Multiple", H43*6%+(H42-H43)*10%, H42*H45) -> 4125.367 | I46: =IF(I45="Multiple", I43*6%+(I42-I43)*10%, I42*I45) -> 0 | J46: =IF(J45="Multiple", J43*6%+(J42-J43)*10%, J42*J45) -> 4118.887 | K46: =IF(K45="Multiple", K43*6%+(K42-K43)*10%, K42*K45) -> 2611.576 | ... O46: =IF(O45="Multiple", O43*6%+(O42-O43)*10%, O42*O45) -> 4415.147
B48: New door sales (first 3 months) | D48: 11352.24 | E48: 690.25 | F48: 561.63 | G48: 0 | H48: 0 | I48: 5372.19 | J48: 4407.18 | K48: 0 | L48: 985.15 | M48: 1453.72 | N48: 0 | O48: 0 | Q48: Full year check
B49: New door sales (reorder) | D49: =D50-D48 -> 0 | E49: =E50-E48 -> 0 | F49: =F50-F48 -> 0 | G49: =G50-G48 -> 0 | H49: =H50-H48 -> 0 | I49: =I50-I48 -> 0 | J49: =J50-J48 -> 0 | K49: =K50-K48 -> 1770.87 | ... O49: =O50-O48 -> 2444.34
B50: Total new door sales | D50: 11352.24 | E50: 690.25 | F50: 561.63 | G50: 0 | H50: 0 | I50: 5372.19 | J50: 4407.18 | K50: 1770.87 | L50: 2083.3 | M50: 1865.24 | N50: 5835.91 | O50: 2444.34 | Q50: =SUM(D50:O50) -> 36383.15
B51: New door budget | D51: 0 | E51: 750 | F51: 1500 | G51: 1500 | H51: 2250 | I51: 2250 | J51: 3000 | K51: 2250 | L51: 4500 | M51: 4500 | N51: 4500 | O51: 3000 | Q51: =SUM(D51:O51) -> 30000
B52: % achieved | D52: =IFERROR(D50/D51, 0) -> 0 | E52: =IFERROR(E50/E51, 0) -> 0.92033333 | F52: =IFERROR(F50/F51, 0) -> 0.37442 | G52: =IFERROR(G50/G51, 0) -> 0 | H52: =IFERROR(H50/H51, 0) -> 0 | I52: =IFERROR(I50/I51, 0) -> 2.38764 | J52: =IFERROR(J50/J51, 0) -> 1.46906 | K52: =IFERROR(K50/K51, 0) -> 0.78705333 | ... O52: =IFERROR(O50/O51, 0) -> 0.81478 | Q52: =IFERROR(Q50/Q51, 0) -> 1.2127717
B53: Commission % applied | D53: =IF(D52<0.8, 0, IF(D52<0.9, 5%, 10%)) -> 0 | E53: =IF(E52<0.8, 0, IF(E52<0.9, 5%, 10%)) -> 0.1 | F53: =IF(F52<0.8, 0, IF(F52<0.9, 5%, 10%)) -> 0 | G53: =IF(G52<0.8, 0, IF(G52<0.9, 5%, 10%)) -> 0 | H53: =IF(H52<0.8, 0, IF(H52<0.9, 5%, 10%)) -> 0 | I53: =IF(I52<0.8, 0, IF(I52<0.9, 5%, 10%)) -> 0.1 | J53: =IF(J52<0.8, 0, IF(J52<0.9, 5%, 10%)) -> 0.1 | K53: =IF(K52<0.8, 0, IF(K52<0.9, 5%, 10%)) -> 0 | ... O53: =IF(O52<0.8, 0, IF(O52<0.9, 5%, 10%)) -> 0.05 | Q53: N/A
B54: Commission | D54: =D48*10%+D53*D49 -> 1135.224 | E54: =E48*10%+E53*E49 -> 69.025 | F54: =F48*10%+F53*F49 -> 56.163 | G54: =G48*10%+G53*G49 -> 0 | H54: =H48*10%+H53*H49 -> 0 | I54: =I48*10%+I53*I49 -> 537.219 | J54: =J48*10%+J53*J49 -> 440.718 | K54: =K48*10%+K53*K49 -> 0 | ... O54: =O48*10%+O53*O49 -> 122.217 | Q54: =IF(Q52>1, 5000, 0) -> 5000
B56: Total Sales | D56: 51956.37 | E56: 46057.54 | F56: 53372.15 | G56: 81802.45 | H56: 67677.67 | I56: 26006.79 | J56: 69084.05 | K56: 40795.76 | L56: 48596.55 | M56: 83213.45 | N56: 67238.94 | O56: 64703.47
B57: Total Budget | D57: 47710 | E57: 59470 | F57: 78570 | G57: 67560 | H57: 68310 | I57: 60970 | J57: 61720 | K57: 38950 | L57: 70560 | M57: 85240 | N57: 70560 | O57: 54380

Sheet NRW Marina
O1: Year to date | P1: Year to date | Q1: Year to date | S1: Year to date | T1: Year to date | V1: Full year | W1: Full year | X1: Full year | Y1: Full year | Z1: Full year | AA1: Full year | AC1: Full year | AD1: Full year | AE1: Full year | AG1: 0.07 | AH1: 0.08 | AI1: 0.1 | AJ1: 0.085 | AK1: 0.09 | AL1: 0.08 | AM1: 0.08 | AN1: 0.065 | AO1: 0.095 | AP1: 0.1 | AQ1: 0.085 | AR1: 0.07
B2: Customer Code | C2: Customer Name | D2: Country | E2: Region | F2: Customer Map | G2: New door year | H2: Active? | I2: 2025 Cluster | J2: 2025A | K2: 2026B | L2: Size indicator | M2: Customer Growth Class | O2: 2024 YTD | P2: 2025 YTD | Q2: 2025B YTD | S2: 25 vs 24 % | T2: 25 vs 25B % | V2: 2022 | W2: 2023 | X2: 2024 | Y2: 2025B | Z2: 2025A | AA2: 2026B | AC2: 25 vs 24 % | AD2: 25 vs 25B % | AE2: 26B vs 25F % | AG2: 46023 | AH2: 46054 | AI2: 46082 | AJ2: 46113 | AK2: 46143 | AL2: 46174 | AM2: 46204 | AN2: 46235 | AO2: 46266 | AP2: 46296 | AQ2: 46327 | AR2: 46357
A3: Marina | B3: 20018 | C3: Susanne Gollmer | D3: =VLOOKUP($B3, 'Performance Data'!$B:$K, 3, 0) -> Germany | E3: =VLOOKUP($B3, 'Performance Data'!$B:$K, 4, 0) -> NRW | F3: =VLOOKUP($B3, 'Performance Data'!$B:$K, 6, 0) -> Institutes / Clinic | G3: =VLOOKUP($B3, 'Performance Data'!$B:$K, 10, 0) -> Pre-2022 | H3: Yes | I3: =VLOOKUP($B3, 'Performance Data'!$B:$K, 7, 0) -> AA | J3: =P3 -> 45228.2 | K3: =J3*1.07-500 -> 47894.174 | M3: Grow | O3: =SUMIF('Performance Data'!$B:$B, $B3,'Performance Data'!N:N) -> 33166.95 | P3: =SUMIF('Performance Data'!$B:$B, $B3,'Performance Data'!O:O) -> 45228.2 | Q3: =SUMIF('Performance Data'!$B:$B, $B3,'Performance Data'!P:P) -> 25550 | S3: =$P3/O3-1 -> 0.36365267 | T3: =P3/Q3-1 -> 0.77018395 | V3: =SUMIF('Performance Data'!$B:$B, $B3,'Performance Data'!AC:AC) -> 34150.32 | W3: =SUMIF('Performance Data'!$B:$B, $B3,'Performance Data'!AD:AD) -> 37681.89 | X3: =SUMIF('Performance Data'!$B:$B, $B3,'Performance Data'!AE:AE) -> 33166.95 | Y3: =SUMIF('Performance Data'!$B:$B, $B3,'Performance Data'!AG:AG) -> 35000 | Z3: =P3 -> 45228.2 | AA3: =K3 -> 47894.174 | AC3: =Z3/X3-1 -> 0.36365267 | AD3: =Z3/Y3-1 -> 0.29223429 | AE3: =AA3/Z3-1 -> 0.05894495 | AG3: =$AA3*AG$1 -> 3352.5922 | AH3: =$AA3*AH$1 -> 3831.5339 | AI3: =$AA3*AI$1 -> 4789.4174 | AJ3: =$AA3*AJ$1 -> 4071.0048 | AK3: =$AA3*AK$1 -> 4310.4757 | AL3: =$AA3*AL$1 -> 3831.5339 | AM3: =$AA3*AM$1 -> 3831.5339 | AN3: =$AA3*AN$1 -> 3113.1213 | ... AR3: =$AA3*AR$1 -> 3352.5922
B4: 20395 | C4: Top Parfümerie Manegold | D4: =VLOOKUP($B4, 'Performance Data'!$B:$K, 3, 0) -> Germany | E4: =VLOOKUP($B4, 'Performance Data'!$B:$K, 4, 0) -> NRW | F4: =VLOOKUP($B4, 'Performance Data'!$B:$K, 6, 0) -> Institutes / Clinic | G4: =VLOOKUP($B4, 'Performance Data'!$B:$K, 10, 0) -> Pre-2022 | H4: Yes | I4: =VLOOKUP($B4, 'Performance Data'!$B:$K, 7, 0) -> AA | J4: =P4 -> 38545.42 | K4: =J4*1.07-500 -> 40743.599 | M4: Grow | O4: =SUMIF('Performance Data'!$B:$B, $B4,'Performance Data'!N:N) -> 24902.71 | P4: =SUMIF('Performance Data'!$B:$B, $B4,'Performance Data'!O:O) -> 38545.42 | Q4: =SUMIF('Performance Data'!$B:$B, $B4,'Performance Data'!P:P) -> 19345 | S4: =$P4/O4-1 -> 0.54784038 | T4: =P4/Q4-1 -> 0.99252623 | V4: =SUMIF('Performance Data'!$B:$B, $B4,'Performance Data'!AC:AC) -> 20225.52 | W4: =SUMIF('Performance Data'!$B:$B, $B4,'Performance Data'!AD:AD) -> 22701.68 | X4: =SUMIF('Performance Data'!$B:$B, $B4,'Performance Data'!AE:AE) -> 24902.71 | Y4: =SUMIF('Performance Data'!$B:$B, $B4,'Performance Data'!AG:AG) -> 26500 | Z4: =P4 -> 38545.42 | AA4: =K4 -> 40743.599 | AC4: =Z4/X4-1 -> 0.54784038 | AD4: =Z4/Y4-1 -> 0.45454415 | AE4: =AA4/Z4-1 -> 0.05702829 | AG4: =$AA4*AG$1 -> 2852.052 | AH4: =$AA4*AH$1 -> 3259.488 | AI4: =$AA4*AI$1 -> 4074.3599 | AJ4: =$AA4*AJ$1 -> 3463.2059 | AK4: =$AA4*AK$1 -> 3666.9239 | AL4: =$AA4*AL$1 -> 3259.488 | AM4: =$AA4*AM$1 -> 3259.488 | AN4: =$AA4*AN$1 -> 2648.334 | ... AR4: =$AA4*AR$1 -> 2852.052
B5: 20519 | C5: Besime Celik | D5: =VLOOKUP($B5, 'Performance Data'!$B:$K, 3, 0) -> Germany | E5: =VLOOKUP($B5, 'Performance Data'!$B:$K, 4, 0) -> NRW | F5: =VLOOKUP($B5, 'Performance Data'!$B:$K, 6, 0) -> 0 | G5: =VLOOKUP($B5, 'Performance Data'!$B:$K, 10, 0) -> Pre-2022 | H5: Yes | I5: =VLOOKUP($B5, 'Performance Data'!$B:$K, 7, 0) -> AA | J5: =P5 -> 19654.56 | K5: =J5*1.07-500 -> 20530.379 | M5: Maintain | O5: =SUMIF('Performance Data'!$B:$B, $B5,'Performance Data'!N:N) -> 20150.65 | P5: =SUMIF('Performance Data'!$B:$B, $B5,'Performance Data'!O:O) -> 19654.56 | Q5: =SUMIF('Performance Data'!$B:$B, $B5,'Performance Data'!P:P) -> 17520 | S5: =$P5/O5-1 -> -0.024619057 | T5: =P5/Q5-1 -> 0.12183562 | V5: =SUMIF('Performance Data'!$B:$B, $B5,'Performance Data'!AC:AC) -> 10659.14 | W5: =SUMIF('Performance Data'!$B:$B, $B5,'Performance Data'!AD:AD) -> 14136.59 | X5: =SUMIF('Performance Data'!$B:$B, $B5,'Performance Data'!AE:AE) -> 20150.65 | Y5: =SUMIF('Performance Data'!$B:$B, $B5,'Performance Data'!AG:AG) -> 24000 | Z5: =P5 -> 19654.56 | AA5: =K5 -> 20530.379 | AC5: =Z5/X5-1 -> -0.024619057 | AD5: =Z5/Y5-1 -> -0.18106 | AE5: =AA5/Z5-1 -> 0.044560611 | AG5: =$AA5*AG$1 -> 1437.1265 | AH5: =$AA5*AH$1 -> 1642.4303 | AI5: =$AA5*AI$1 -> 2053.0379 | AJ5: =$AA5*AJ$1 -> 1745.0822 | AK5: =$AA5*AK$1 -> 1847.7341 | AL5: =$AA5*AL$1 -> 1642.4303 | AM5: =$AA5*AM$1 -> 1642.4303 | AN5: =$AA5*AN$1 -> 1334.4746 | ... AR5: =$AA5*AR$1 -> 1437.1265
B6: 20772 | C6: SK Kosmetik; Sebastian Klitsch | D6: =VLOOKUP($B6, 'Performance Data'!$B:$K, 3, 0) -> Germany | E6: =VLOOKUP($B6, 'Performance Data'!$B:$K, 4, 0) -> NRW | F6: =VLOOKUP($B6, 'Performance Data'!$B:$K, 6, 0) -> Hotel Spa | G6: =VLOOKUP($B6, 'Performance Data'!$B:$K, 10, 0) -> Pre-2022 | H6: Yes | I6: =VLOOKUP($B6, 'Performance Data'!$B:$K, 7, 0) -> AA | J6: =P6 -> 143991.41 | K6: =J6*1.07-500 -> 153570.81 | M6: Grow | O6: =SUMIF('Performance Data'!$B:$B, $B6,'Performance Data'!N:N) -> 131126.56 | P6: =SUMIF('Performance Data'!$B:$B, $B6,'Performance Data'!O:O) -> 143991.41 | Q6: =SUMIF('Performance Data'!$B:$B, $B6,'Performance Data'!P:P) -> 102200 | S6: =$P6/O6-1 -> 0.098110177 | T6: =P6/Q6-1 -> 0.40891791 | V6: =SUMIF('Performance Data'!$B:$B, $B6,'Performance Data'!AC:AC) -> 173169.82 | W6: =SUMIF('Performance Data'!$B:$B, $B6,'Performance Data'!AD:AD) -> 101481.39 | X6: =SUMIF('Performance Data'!$B:$B, $B6,'Performance Data'!AE:AE) -> 131126.56 | Y6: =SUMIF('Performance Data'!$B:$B, $B6,'Performance Data'!AG:AG) -> 140000 | Z6: =P6 -> 143991.41 | AA6: =K6 -> 153570.81 | AC6: =Z6/X6-1 -> 0.098110177 | AD6: =Z6/Y6-1 -> 0.028510071 | AE6: =AA6/Z6-1 -> 0.066527571 | AG6: =$AA6*AG$1 -> 10749.957 | AH6: =$AA6*AH$1 -> 12285.665 | AI6: =$AA6*AI$1 -> 15357.081 | AJ6: =$AA6*AJ$1 -> 13053.519 | AK6: =$AA6*AK$1 -> 13821.373 | AL6: =$AA6*AL$1 -> 12285.665 | AM6: =$AA6*AM$1 -> 12285.665 | AN6: =$AA6*AN$1 -> 9982.1026 | ... AR6: =$AA6*AR$1 -> 10749.957
B7: 20881 | C7: kosmetikfuchs, Schnitzler | D7: =VLOOKUP($B7, 'Performance Data'!$B:$K, 3, 0) -> Germany | E7: =VLOOKUP($B7, 'Performance Data'!$B:$K, 4, 0) -> NRW | F7: =VLOOKUP($B7, 'Performance Data'!$B:$K, 6, 0) -> 0 | G7: =VLOOKUP($B7, 'Performance Data'!$B:$K, 10, 0) -> Pre-2022 | H7: Yes | I7: =VLOOKUP($B7, 'Performance Data'!$B:$K, 7, 0) -> AA | J7: =P7 -> 16613.58 | K7: =J7*1.07-500 -> 17276.531 | M7: Maintain | O7: =SUMIF('Performance Data'!$B:$B, $B7,'Performance Data'!N:N) -> 22901.43 | P7: =SUMIF('Performance Data'!$B:$B, $B7,'Performance Data'!O:O) -> 16613.58 | Q7: =SUMIF('Performance Data'!$B:$B, $B7,'Performance Data'!P:P) -> 18250 | S7: =$P7/O7-1 -> -0.27456146 | T7: =P7/Q7-1 -> -0.089666849 | V7: =SUMIF('Performance Data'!$B:$B, $B7,'Performance Data'!AC:AC) -> 43016.14 | W7: =SUMIF('Performance Data'!$B:$B, $B7,'Performance Data'!AD:AD) -> 52186.61 | X7: =SUMIF('Performance Data'!$B:$B, $B7,'Performance Data'!AE:AE) -> 22901.43 | Y7: =SUMIF('Performance Data'!$B:$B, $B7,'Performance Data'!AG:AG) -> 25000 | Z7: =P7 -> 16613.58 | AA7: =K7 -> 17276.531 | AC7: =Z7/X7-1 -> -0.27456146 | AD7: =Z7/Y7-1 -> -0.3354568 | AE7: =AA7/Z7-1 -> 0.039904139 | AG7: =$AA7*AG$1 -> 1209.3571 | AH7: =$AA7*AH$1 -> 1382.1224 | AI7: =$AA7*AI$1 -> 1727.6531 | AJ7: =$AA7*AJ$1 -> 1468.5051 | AK7: =$AA7*AK$1 -> 1554.8878 | AL7: =$AA7*AL$1 -> 1382.1224 | AM7: =$AA7*AM$1 -> 1382.1224 | AN7: =$AA7*AN$1 -> 1122.9745 | ... AR7: =$AA7*AR$1 -> 1209.3571
B8: 20985 | C8: Kalyana-by-K;Kerstin Leonard;Interessent | D8: =VLOOKUP($B8, 'Performance Data'!$B:$K, 3, 0) -> Germany | E8: =VLOOKUP($B8, 'Performance Data'!$B:$K, 4, 0) -> NRW | F8: =VLOOKUP($B8, 'Performance Data'!$B:$K, 6, 0) -> Institutes / Clinic | G8: =VLOOKUP($B8, 'Performance Data'!$B:$K, 10, 0) -> 2023 | H8: Yes | I8: =VLOOKUP($B8, 'Performance Data'!$B:$K, 7, 0) -> AA | J8: =P8 -> 17987.62 | K8: =J8*1.07-500 -> 18746.753 | M8: Maintain | O8: =SUMIF('Performance Data'!$B:$B, $B8,'Performance Data'!N:N) -> 24748.07 | P8: =SUMIF('Performance Data'!$B:$B, $B8,'Performance Data'!O:O) -> 17987.62 | Q8: =SUMIF('Performance Data'!$B:$B, $B8,'Performance Data'!P:P) -> 18250 | S8: =$P8/O8-1 -> -0.2731708 | T8: =P8/Q8-1 -> -0.014376986 | V8: =SUMIF('Performance Data'!$B:$B, $B8,'Performance Data'!AC:AC) -> 0 | W8: =SUMIF('Performance Data'!$B:$B, $B8,'Performance Data'!AD:AD) -> 25245.06 | X8: =SUMIF('Performance Data'!$B:$B, $B8,'Performance Data'!AE:AE) -> 24748.07 | Y8: =SUMIF('Performance Data'!$B:$B, $B8,'Performance Data'!AG:AG) -> 25000 | Z8: =P8 -> 17987.62 | AA8: =K8 -> 18746.753 | AC8: =Z8/X8-1 -> -0.2731708 | AD8: =Z8/Y8-1 -> -0.2804952 | AE8: =AA8/Z8-1 -> 0.042203104 | AG8: =$AA8*AG$1 -> 1312.2727 | AH8: =$AA8*AH$1 -> 1499.7403 | AI8: =$AA8*AI$1 -> 1874.6753 | AJ8: =$AA8*AJ$1 -> 1593.474 | AK8: =$AA8*AK$1 -> 1687.2078 | AL8: =$AA8*AL$1 -> 1499.7403 | AM8: =$AA8*AM$1 -> 1499.7403 | AN8: =$AA8*AN$1 -> 1218.539 | ... AR8: =$AA8*AR$1 -> 1312.2727
B9: 20445 | C9: Agnes Peltzer | D9: =VLOOKUP($B9, 'Performance Data'!$B:$K, 3, 0) -> Germany | E9: =VLOOKUP($B9, 'Performance Data'!$B:$K, 4, 0) -> NRW | F9: =VLOOKUP($B9, 'Performance Data'!$B:$K, 6, 0) -> Institutes / Clinic | G9: =VLOOKUP($B9, 'Performance Data'!$B:$K, 10, 0) -> Pre-2022 | H9: Yes | I9: =VLOOKUP($B9, 'Performance Data'!$B:$K, 7, 0) -> AC | J9: =P9 -> 36159.64 | K9: =J9*1.07-500 -> 38190.815 | M9: Grow | O9: =SUMIF('Performance Data'!$B:$B, $B9,'Performance Data'!N:N) -> 33797.24 | P9: =SUMIF('Performance Data'!$B:$B, $B9,'Performance Data'!O:O) -> 36159.64 | Q9: =SUMIF('Performance Data'!$B:$B, $B9,'Performance Data'!P:P) -> 25915 | S9: =$P9/O9-1 -> 0.069899199 | T9: =P9/Q9-1 -> 0.395317 | V9: =SUMIF('Performance Data'!$B:$B, $B9,'Performance Data'!AC:AC) -> 20470.03 | W9: =SUMIF('Performance Data'!$B:$B, $B9,'Performance Data'!AD:AD) -> 30382.74 | X9: =SUMIF('Performance Data'!$B:$B, $B9,'Performance Data'!AE:AE) -> 33797.24 | Y9: =SUMIF('Performance Data'!$B:$B, $B9,'Performance Data'!AG:AG) -> 35500 | Z9: =P9 -> 36159.64 | AA9: =K9 -> 38190.815 | AC9: =Z9/X9-1 -> 0.069899199 | AD9: =Z9/Y9-1 -> 0.018581408 | AE9: =AA9/Z9-1 -> 0.056172429 | AG9: =$AA9*AG$1 -> 2673.357 | AH9: =$AA9*AH$1 -> 3055.2652 | AI9: =$AA9*AI$1 -> 3819.0815 | AJ9: =$AA9*AJ$1 -> 3246.2193 | AK9: =$AA9*AK$1 -> 3437.1733 | AL9: =$AA9*AL$1 -> 3055.2652 | AM9: =$AA9*AM$1 -> 3055.2652 | AN9: =$AA9*AN$1 -> 2482.403 | ... AR9: =$AA9*AR$1 -> 2673.357
B10: 20765 | C10: Svetlana Grießner | D10: =VLOOKUP($B10, 'Performance Data'!$B:$K, 3, 0) -> Germany | E10: =VLOOKUP($B10, 'Performance Data'!$B:$K, 4, 0) -> NRW | F10: =VLOOKUP($B10, 'Performance Data'!$B:$K, 6, 0) -> Institutes / Clinic | G10: =VLOOKUP($B10, 'Performance Data'!$B:$K, 10, 0) -> Pre-2022 | H10: Yes | I10: =VLOOKUP($B10, 'Performance Data'!$B:$K, 7, 0) -> BA | J10: =P10 -> 16460.67 | K10: =J10*1.07-500 -> 17112.917 | M10: Grow | O10: =SUMIF('Performance Data'!$B:$B, $B10,'Performance Data'!N:N) -> 14168 | P10: =SUMIF('Performance Data'!$B:$B, $B10,'Performance Data'!O:O) -> 16460.67 | Q10: =SUMIF('Performance Data'!$B:$B, $B10,'Performance Data'!P:P) -> 10220 | S10: =$P10/O10-1 -> 0.1618203 | T10: =P10/Q10-1 -> 0.61063307 | V10: =SUMIF('Performance Data'!$B:$B, $B10,'Performance Data'!AC:AC) -> 19476.97 | W10: =SUMIF('Performance Data'!$B:$B, $B10,'Performance Data'!AD:AD) -> 15402 | X10: =SUMIF('Performance Data'!$B:$B, $B10,'Performance Data'!AE:AE) -> 14168 | Y10: =SUMIF('Performance Data'!$B:$B, $B10,'Performance Data'!AG:AG) -> 14000 | Z10: =P10 -> 16460.67 | AA10: =K10 -> 17112.917 | AC10: =Z10/X10-1 -> 0.1618203 | AD10: =Z10/Y10-1 -> 0.17576214 | AE10: =AA10/Z10-1 -> 0.039624566 | AG10: =$AA10*AG$1 -> 1197.9042 | AH10: =$AA10*AH$1 -> 1369.0334 | AI10: =$AA10*AI$1 -> 1711.2917 | AJ10: =$AA10*AJ$1 -> 1454.5979 | AK10: =$AA10*AK$1 -> 1540.1625 | AL10: =$AA10*AL$1 -> 1369.0334 | AM10: =$AA10*AM$1 -> 1369.0334 | AN10: =$AA10*AN$1 -> 1112.3396 | ... AR10: =$AA10*AR$1 -> 1197.9042
B11: 20778 | C11: Ursula Feinbier | D11: =VLOOKUP($B11, 'Performance Data'!$B:$K, 3, 0) -> Germany | E11: =VLOOKUP($B11, 'Performance Data'!$B:$K, 4, 0) -> NRW | F11: =VLOOKUP($B11, 'Performance Data'!$B:$K, 6, 0) -> Institutes / Clinic | G11: =VLOOKUP($B11, 'Performance Data'!$B:$K, 10, 0) -> Pre-2022 | H11: Yes | I11: =VLOOKUP($B11, 'Performance Data'!$B:$K, 7, 0) -> BA | J11: =P11 -> 27597.46 | K11: =J11*1.07-500 -> 29029.282 | M11: Grow | O11: =SUMIF('Performance Data'!$B:$B, $B11,'Performance Data'!N:N) -> 19945.33 | P11: =SUMIF('Performance Data'!$B:$B, $B11,'Performance Data'!O:O) -> 27597.46 | Q11: =SUMIF('Performance Data'!$B:$B, $B11,'Performance Data'!P:P) -> 16060 | S11: =$P11/O11-1 -> 0.38365522 | T11: =P11/Q11-1 -> 0.71839726 | V11: =SUMIF('Performance Data'!$B:$B, $B11,'Performance Data'!AC:AC) -> 6330.76 | W11: =SUMIF('Performance Data'!$B:$B, $B11,'Performance Data'!AD:AD) -> 12872.51 | X11: =SUMIF('Performance Data'!$B:$B, $B11,'Performance Data'!AE:AE) -> 19945.33 | Y11: =SUMIF('Performance Data'!$B:$B, $B11,'Performance Data'!AG:AG) -> 22000 | Z11: =P11 -> 27597.46 | AA11: =K11 -> 29029.282 | AC11: =Z11/X11-1 -> 0.38365522 | AD11: =Z11/Y11-1 -> 0.25443 | AE11: =AA11/Z11-1 -> 0.051882391 | AG11: =$AA11*AG$1 -> 2032.0498 | AH11: =$AA11*AH$1 -> 2322.3426 | AI11: =$AA11*AI$1 -> 2902.9282 | AJ11: =$AA11*AJ$1 -> 2467.489 | AK11: =$AA11*AK$1 -> 2612.6354 | AL11: =$AA11*AL$1 -> 2322.3426 | AM11: =$AA11*AM$1 -> 2322.3426 | AN11: =$AA11*AN$1 -> 1886.9033 | ... AR11: =$AA11*AR$1 -> 2032.0498
B12: 20590 | C12: Alexandra Eßer | D12: =VLOOKUP($B12, 'Performance Data'!$B:$K, 3, 0) -> Germany | E12: =VLOOKUP($B12, 'Performance Data'!$B:$K, 4, 0) -> NRW | F12: =VLOOKUP($B12, 'Performance Data'!$B:$K, 6, 0) -> Institutes / Clinic | G12: =VLOOKUP($B12, 'Performance Data'!$B:$K, 10, 0) -> Pre-2022 | H12: Yes | I12: =VLOOKUP($B12, 'Performance Data'!$B:$K, 7, 0) -> BB | J12: =P12 -> 12495.17 | K12: =J12*1.07-500 -> 12869.832 | M12: Maintain | O12: =SUMIF('Performance Data'!$B:$B, $B12,'Performance Data'!N:N) -> 11293.56 | P12: =SUMIF('Performance Data'!$B:$B, $B12,'Performance Data'!O:O) -> 12495.17 | Q12: =SUMIF('Performance Data'!$B:$B, $B12,'Performance Data'!P:P) -> 8030 | S12: =$P12/O12-1 -> 0.10639781 | T12: =P12/Q12-1 -> 0.55606102 | V12: =SUMIF('Performance Data'!$B:$B, $B12,'Performance Data'!AC:AC) -> 12576.88 | W12: =SUMIF('Performance Data'!$B:$B, $B12,'Performance Data'!AD:AD) -> 14491.51 | X12: =SUMIF('Performance Data'!$B:$B, $B12,'Performance Data'!AE:AE) -> 11293.56 | Y12: =SUMIF('Performance Data'!$B:$B, $B12,'Performance Data'!AG:AG) -> 11000 | Z12: =P12 -> 12495.17 | AA12: =K12 -> 12869.832 | AC12: =Z12/X12-1 -> 0.10639781 | AD12: =Z12/Y12-1 -> 0.13592455 | AE12: =AA12/Z12-1 -> 0.029984538 | AG12: =$AA12*AG$1 -> 900.88823 | AH12: =$AA12*AH$1 -> 1029.5866 | AI12: =$AA12*AI$1 -> 1286.9832 | AJ12: =$AA12*AJ$1 -> 1093.9357 | AK12: =$AA12*AK$1 -> 1158.2849 | AL12: =$AA12*AL$1 -> 1029.5866 | AM12: =$AA12*AM$1 -> 1029.5866 | AN12: =$AA12*AN$1 -> 836.53907 | ... AR12: =$AA12*AR$1 -> 900.88823
B13: 20645 | C13: Parfümerie Figge OHG | D13: =VLOOKUP($B13, 'Performance Data'!$B:$K, 3, 0) -> Germany | E13: =VLOOKUP($B13, 'Performance Data'!$B:$K, 4, 0) -> NRW | F13: =VLOOKUP($B13, 'Performance Data'!$B:$K, 6, 0) -> Institutes / Clinic | G13: =VLOOKUP($B13, 'Performance Data'!$B:$K, 10, 0) -> Pre-2022 | H13: Yes | I13: =VLOOKUP($B13, 'Performance Data'!$B:$K, 7, 0) -> BB | J13: =P13 -> 6654.15 | K13: =J13*1.07-500 -> 6619.9405 | M13: Maintain | O13: =SUMIF('Performance Data'!$B:$B, $B13,'Performance Data'!N:N) -> 6739.31 | P13: =SUMIF('Performance Data'!$B:$B, $B13,'Performance Data'!O:O) -> 6654.15 | Q13: =SUMIF('Performance Data'!$B:$B, $B13,'Performance Data'!P:P) -> 5110 | S13: =$P13/O13-1 -> -0.012636308 | T13: =P13/Q13-1 -> 0.302182 | V13: =SUMIF('Performance Data'!$B:$B, $B13,'Performance Data'!AC:AC) -> 6885.83 | W13: =SUMIF('Performance Data'!$B:$B, $B13,'Performance Data'!AD:AD) -> 7525.28 | X13: =SUMIF('Performance Data'!$B:$B, $B13,'Performance Data'!AE:AE) -> 6739.31 | Y13: =SUMIF('Performance Data'!$B:$B, $B13,'Performance Data'!AG:AG) -> 7000 | Z13: =P13 -> 6654.15 | AA13: =K13 -> 6619.9405 | AC13: =Z13/X13-1 -> -0.012636308 | AD13: =Z13/Y13-1 -> -0.049407143 | AE13: =AA13/Z13-1 -> -0.0051410774 | AG13: =$AA13*AG$1 -> 463.39584 | AH13: =$AA13*AH$1 -> 529.59524 | AI13: =$AA13*AI$1 -> 661.99405 | AJ13: =$AA13*AJ$1 -> 562.69494 | AK13: =$AA13*AK$1 -> 595.79464 | AL13: =$AA13*AL$1 -> 529.59524 | AM13: =$AA13*AM$1 -> 529.59524 | AN13: =$AA13*AN$1 -> 430.29613 | ... AR13: =$AA13*AR$1 -> 463.39584
B14: 20725 | C14: Fadime Avci | D14: =VLOOKUP($B14, 'Performance Data'!$B:$K, 3, 0) -> Germany | E14: =VLOOKUP($B14, 'Performance Data'!$B:$K, 4, 0) -> NRW | F14: =VLOOKUP($B14, 'Performance Data'!$B:$K, 6, 0) -> Institutes / Clinic | G14: =VLOOKUP($B14, 'Performance Data'!$B:$K, 10, 0) -> Pre-2022 | H14: Yes | I14: =VLOOKUP($B14, 'Performance Data'!$B:$K, 7, 0) -> BB | J14: =P14 -> 15279.57 | K14: =J14*1.07-500 -> 15849.14 | M14: Maintain | O14: =SUMIF('Performance Data'!$B:$B, $B14,'Performance Data'!N:N) -> 17017.07 | P14: =SUMIF('Performance Data'!$B:$B, $B14,'Performance Data'!O:O) -> 15279.57 | Q14: =SUMIF('Performance Data'!$B:$B, $B14,'Performance Data'!P:P) -> 13870 | S14: =$P14/O14-1 -> -0.10210336 | T14: =P14/Q14-1 -> 0.10162725 | V14: =SUMIF('Performance Data'!$B:$B, $B14,'Performance Data'!AC:AC) -> 10118.17 | W14: =SUMIF('Performance Data'!$B:$B, $B14,'Performance Data'!AD:AD) -> 9905.56 | X14: =SUMIF('Performance Data'!$B:$B, $B14,'Performance Data'!AE:AE) -> 17017.07 | Y14: =SUMIF('Performance Data'!$B:$B, $B14,'Performance Data'!AG:AG) -> 19000 | Z14: =P14 -> 15279.57 | AA14: =K14 -> 15849.14 | AC14: =Z14/X14-1 -> -0.10210336 | AD14: =Z14/Y14-1 -> -0.19581211 | AE14: =AA14/Z14-1 -> 0.037276566 | AG14: =$AA14*AG$1 -> 1109.4398 | AH14: =$AA14*AH$1 -> 1267.9312 | AI14: =$AA14*AI$1 -> 1584.914 | AJ14: =$AA14*AJ$1 -> 1347.1769 | AK14: =$AA14*AK$1 -> 1426.4226 | AL14: =$AA14*AL$1 -> 1267.9312 | AM14: =$AA14*AM$1 -> 1267.9312 | AN14: =$AA14*AN$1 -> 1030.1941 | ... AR14: =$AA14*AR$1 -> 1109.4398
B15: 20744 | C15: Yvonne Gloris | D15: =VLOOKUP($B15, 'Performance Data'!$B:$K, 3, 0) -> Germany | E15: =VLOOKUP($B15, 'Performance Data'!$B:$K, 4, 0) -> NRW | F15: =VLOOKUP($B15, 'Performance Data'!$B:$K, 6, 0) -> Institutes / Clinic | G15: =VLOOKUP($B15, 'Performance Data'!$B:$K, 10, 0) -> Pre-2022 | H15: Yes | I15: =VLOOKUP($B15, 'Performance Data'!$B:$K, 7, 0) -> BB | J15: =P15 -> 12366.11 | K15: =J15*1.07-500 -> 12731.738 | M15: Maintain | O15: =SUMIF('Performance Data'!$B:$B, $B15,'Performance Data'!N:N) -> 17651.5 | P15: =SUMIF('Performance Data'!$B:$B, $B15,'Performance Data'!O:O) -> 12366.11 | Q15: =SUMIF('Performance Data'!$B:$B, $B15,'Performance Data'!P:P) -> 13140 | S15: =$P15/O15-1 -> -0.29943008 | T15: =P15/Q15-1 -> -0.058895738 | V15: =SUMIF('Performance Data'!$B:$B, $B15,'Performance Data'!AC:AC) -> 13794.23 | W15: =SUMIF('Performance Data'!$B:$B, $B15,'Performance Data'!AD:AD) -> 16755.46 | X15: =SUMIF('Performance Data'!$B:$B, $B15,'Performance Data'!AE:AE) -> 17651.5 | Y15: =SUMIF('Performance Data'!$B:$B, $B15,'Performance Data'!AG:AG) -> 18000 | Z15: =P15 -> 12366.11 | AA15: =K15 -> 12731.738 | AC15: =Z15/X15-1 -> -0.29943008 | AD15: =Z15/Y15-1 -> -0.31299389 | AE15: =AA15/Z15-1 -> 0.029566913 | AG15: =$AA15*AG$1 -> 891.22164 | AH15: =$AA15*AH$1 -> 1018.539 | AI15: =$AA15*AI$1 -> 1273.1738 | AJ15: =$AA15*AJ$1 -> 1082.1977 | AK15: =$AA15*AK$1 -> 1145.8564 | AL15: =$AA15*AL$1 -> 1018.539 | AM15: =$AA15*AM$1 -> 1018.539 | AN15: =$AA15*AN$1 -> 827.56295 | ... AR15: =$AA15*AR$1 -> 891.22164
... B20: 29017 | C20: SeCos-Kosmetik; Sevgi Cosguner | D20: =VLOOKUP($B20, 'Performance Data'!$B:$K, 3, 0) -> Germany | E20: =VLOOKUP($B20, 'Performance Data'!$B:$K, 4, 0) -> NRW | F20: =VLOOKUP($B20, 'Performance Data'!$B:$K, 6, 0) -> Institutes / Clinic | G20: =VLOOKUP($B20, 'Performance Data'!$B:$K, 10, 0) -> 2024 | H20: Yes | I20: =VLOOKUP($B20, 'Performance Data'!$B:$K, 7, 0) -> NKD24 | J20: =P20 -> 24175.67 | K20: =J20*1.07-500 -> 25367.967 | M20: Grow | O20: =SUMIF('Performance Data'!$B:$B, $B20,'Performance Data'!N:N) -> 7799.29 | P20: =SUMIF('Performance Data'!$B:$B, $B20,'Performance Data'!O:O) -> 24175.67 | Q20: =SUMIF('Performance Data'!$B:$B, $B20,'Performance Data'!P:P) -> 7300 | S20: =$P20/O20-1 -> 2.099727 | T20: =P20/Q20-1 -> 2.3117356 | V20: =SUMIF('Performance Data'!$B:$B, $B20,'Performance Data'!AC:AC) -> 0 | W20: =SUMIF('Performance Data'!$B:$B, $B20,'Performance Data'!AD:AD) -> 0 | X20: =SUMIF('Performance Data'!$B:$B, $B20,'Performance Data'!AE:AE) -> 7799.29 | Y20: =SUMIF('Performance Data'!$B:$B, $B20,'Performance Data'!AG:AG) -> 10000 | Z20: =P20 -> 24175.67 | AA20: =K20 -> 25367.967 | AC20: =Z20/X20-1 -> 2.099727 | AD20: =Z20/Y20-1 -> 1.417567 | AE20: =AA20/Z20-1 -> 0.04931805 | AG20: =$AA20*AG$1 -> 1775.7577 | AH20: =$AA20*AH$1 -> 2029.4374 | AI20: =$AA20*AI$1 -> 2536.7967 | AJ20: =$AA20*AJ$1 -> 2156.2772 | AK20: =$AA20*AK$1 -> 2283.117 | AL20: =$AA20*AL$1 -> 2029.4374 | AM20: =$AA20*AM$1 -> 2029.4374 | AN20: =$AA20*AN$1 -> 1648.9178 | ... AR20: =$AA20*AR$1 -> 1775.7577
B21: Total Active Existing Doors | H21: =COUNTIF(H3:H20, "Yes") -> 18 | J21: =SUM(J3:J20) -> 510030.49 | K21: =SUM(K3:K20) -> 536732.62 | O21: =SUM(O3:O20) -> 455770.68 | P21: =SUM(P3:P20) -> 510030.49 | Q21: =SUM(Q3:Q20) -> 362445 | S21: =$P21/O21-1 -> 0.11905068 | T21: =P21/Q21-1 -> 0.40719417 | V21: =SUM(V3:V20) -> 382877.32 | W21: =SUM(W3:W20) -> 385284.18 | X21: =SUM(X3:X20) -> 455770.68 | Y21: =SUM(Y3:Y20) -> 496500 | Z21: =SUM(Z3:Z20) -> 510030.49 | AA21: =SUM(AA3:AA20) -> 536732.62 | AC21: =Z21/X21-1 -> 0.11905068 | AD21: =Z21/Y21-1 -> 0.027251742 | AE21: =AA21/Z21-1 -> 0.052353996 | AG21: =SUM(AG3:AG20) -> 37571.284 | AH21: =SUM(AH3:AH20) -> 42938.61 | AI21: =SUM(AI3:AI20) -> 53673.262 | AJ21: =SUM(AJ3:AJ20) -> 45622.273 | AK21: =SUM(AK3:AK20) -> 48305.936 | AL21: =SUM(AL3:AL20) -> 42938.61 | AM21: =SUM(AM3:AM20) -> 42938.61 | AN21: =SUM(AN3:AN20) -> 34887.621 | ... AR21: =SUM(AR3:AR20) -> 37571.284
B25: 29004 | C25: Bunter Garten Eva Schmitz | D25: =VLOOKUP($B25, 'Performance Data'!$B:$K, 3, 0) -> Germany | E25: =VLOOKUP($B25, 'Performance Data'!$B:$K, 4, 0) -> NRW | F25: =VLOOKUP($B25, 'Performance Data'!$B:$K, 6, 0) -> Institutes / Clinic | G25: =VLOOKUP($B25, 'Performance Data'!$B:$K, 10, 0) -> 2025 | H25: Yes | I25: =VLOOKUP($B25, 'Performance Data'!$B:$K, 7, 0) -> NKD25 | J25: =P25 -> 7861.75 | K25: =J25*1.07 -> 8412.0725 | M25: Grow | O25: =SUMIF('Performance Data'!$B:$B, $B25,'Performance Data'!N:N) -> 287.97 | P25: =SUMIF('Performance Data'!$B:$B, $B25,'Performance Data'!O:O) -> 7861.75 | Q25: =SUMIF('Performance Data'!$B:$B, $B25,'Performance Data'!P:P) -> 0 | S25: =$P25/O25-1 -> 26.300587 | T25: =P25/Q25-1 -> #DIV/0! | V25: =SUMIF('Performance Data'!$B:$B, $B25,'Performance Data'!AC:AC) -> 0 | W25: =SUMIF('Performance Data'!$B:$B, $B25,'Performance Data'!AD:AD) -> 0 | X25: =SUMIF('Performance Data'!$B:$B, $B25,'Performance Data'!AE:AE) -> 287.97 | Y25: =SUMIF('Performance Data'!$B:$B, $B25,'Performance Data'!AG:AG) -> 0 | Z25: =P25 -> 7861.75 | AA25: =K25 -> 8412.0725 | AC25: =Z25/X25-1 -> 26.300587 | AD25: =Z25/Y25-1 -> #DIV/0! | AE25: =AA25/Z25-1 -> 0.07 | AG25: =$AA25*AG$1 -> 588.84508 | AH25: =$AA25*AH$1 -> 672.9658 | AI25: =$AA25*AI$1 -> 841.20725 | AJ25: =$AA25*AJ$1 -> 715.02616 | AK25: =$AA25*AK$1 -> 757.08652 | AL25: =$AA25*AL$1 -> 672.9658 | AM25: =$AA25*AM$1 -> 672.9658 | AN25: =$AA25*AN$1 -> 546.78471 | ... AR25: =$AA25*AR$1 -> 588.84508
B26: 20983 | C26: Heistermann | D26: Germany | E26: NRW | F26: Institutes / Clinic | G26: 2025 | H26: yes | I26: NKD25 | J26: =P26 -> 1017.4 | M26: Grow | O26: =SUMIF('Performance Data'!$B:$B, $B26,'Performance Data'!N:N) -> 0 | P26: =SUMIF('Performance Data'!$B:$B, $B26,'Performance Data'!O:O) -> 1017.4 | Q26: =SUMIF('Performance Data'!$B:$B, $B26,'Performance Data'!P:P) -> 0 | S26: =$P26/O26-1 -> #DIV/0! | T26: =P26/Q26-1 -> #DIV/0! | V26: =SUMIF('Performance Data'!$B:$B, $B26,'Performance Data'!AC:AC) -> 0 | W26: =SUMIF('Performance Data'!$B:$B, $B26,'Performance Data'!AD:AD) -> 387.57 | X26: =SUMIF('Performance Data'!$B:$B, $B26,'Performance Data'!AE:AE) -> 0 | Y26: =SUMIF('Performance Data'!$B:$B, $B26,'Performance Data'!AG:AG) -> 0 | Z26: =P26 -> 1017.4 | AA26: =K26 -> 0 | AC26: =Z26/X26-1 -> #DIV/0! | AD26: =Z26/Y26-1 -> #DIV/0! | AE26: =AA26/Z26-1 -> -1 | AG26: =$AA26*AG$1 -> 0 | AH26: =$AA26*AH$1 -> 0 | AI26: =$AA26*AI$1 -> 0 | AJ26: =$AA26*AJ$1 -> 0 | AK26: =$AA26*AK$1 -> 0 | AL26: =$AA26*AL$1 -> 0 | AM26: =$AA26*AM$1 -> 0 | AN26: =$AA26*AN$1 -> 0 | ... AR26: =$AA26*AR$1 -> 0
B27: 29022 | C27: Anja-Maria Fischedick; Gladbeck | D27: =VLOOKUP($B27, 'Performance Data'!$B:$K, 3, 0) -> Germany | E27: =VLOOKUP($B27, 'Performance Data'!$B:$K, 4, 0) -> NRW | F27: =VLOOKUP($B27, 'Performance Data'!$B:$K, 6, 0) -> Institutes / Clinic | G27: =VLOOKUP($B27, 'Performance Data'!$B:$K, 10, 0) -> 2025 | H27: Yes | I27: =VLOOKUP($B27, 'Performance Data'!$B:$K, 7, 0) -> NKD25 | J27: =P27 -> 18622.98 | K27: =J27*1.07 -> 19926.589 | M27: Grow | O27: =SUMIF('Performance Data'!$B:$B, $B27,'Performance Data'!N:N) -> 0 | P27: =SUMIF('Performance Data'!$B:$B, $B27,'Performance Data'!O:O) -> 18622.98 | Q27: =SUMIF('Performance Data'!$B:$B, $B27,'Performance Data'!P:P) -> 0 | S27: =$P27/O27-1 -> #DIV/0! | T27: =P27/Q27-1 -> #DIV/0! | V27: =SUMIF('Performance Data'!$B:$B, $B27,'Performance Data'!AC:AC) -> 0 | W27: =SUMIF('Performance Data'!$B:$B, $B27,'Performance Data'!AD:AD) -> 0 | X27: =SUMIF('Performance Data'!$B:$B, $B27,'Performance Data'!AE:AE) -> 0 | Y27: =SUMIF('Performance Data'!$B:$B, $B27,'Performance Data'!AG:AG) -> 0 | Z27: =P27 -> 18622.98 | AA27: =K27 -> 19926.589 | AC27: =Z27/X27-1 -> #DIV/0! | AD27: =Z27/Y27-1 -> #DIV/0! | AE27: =AA27/Z27-1 -> 0.07 | AG27: =$AA27*AG$1 -> 1394.8612 | AH27: =$AA27*AH$1 -> 1594.1271 | AI27: =$AA27*AI$1 -> 1992.6589 | AJ27: =$AA27*AJ$1 -> 1693.76 | AK27: =$AA27*AK$1 -> 1793.393 | AL27: =$AA27*AL$1 -> 1594.1271 | AM27: =$AA27*AM$1 -> 1594.1271 | AN27: =$AA27*AN$1 -> 1295.2283 | ... AR27: =$AA27*AR$1 -> 1394.8612
B28: 29026 | C28: By Natalia; Natalia Ivica | D28: =VLOOKUP($B28, 'Performance Data'!$B:$K, 3, 0) -> Germany | E28: =VLOOKUP($B28, 'Performance Data'!$B:$K, 4, 0) -> NRW | F28: =VLOOKUP($B28, 'Performance Data'!$B:$K, 6, 0) -> Institutes / Clinic | G28: =VLOOKUP($B28, 'Performance Data'!$B:$K, 10, 0) -> 2025 | H28: Yes | I28: =VLOOKUP($B28, 'Performance Data'!$B:$K, 7, 0) -> NKD25 | J28: =P28 -> 9407.41 | K28: =J28*1.07 -> 10065.929 | M28: Grow | O28: =SUMIF('Performance Data'!$B:$B, $B28,'Performance Data'!N:N) -> 0 | P28: =SUMIF('Performance Data'!$B:$B, $B28,'Performance Data'!O:O) -> 9407.41 | Q28: =SUMIF('Performance Data'!$B:$B, $B28,'Performance Data'!P:P) -> 0 | S28: =$P28/O28-1 -> #DIV/0! | T28: =P28/Q28-1 -> #DIV/0! | V28: =SUMIF('Performance Data'!$B:$B, $B28,'Performance Data'!AC:AC) -> 0 | W28: =SUMIF('Performance Data'!$B:$B, $B28,'Performance Data'!AD:AD) -> 0 | X28: =SUMIF('Performance Data'!$B:$B, $B28,'Performance Data'!AE:AE) -> 0 | Y28: =SUMIF('Performance Data'!$B:$B, $B28,'Performance Data'!AG:AG) -> 0 | Z28: =P28 -> 9407.41 | AA28: =K28 -> 10065.929 | AC28: =Z28/X28-1 -> #DIV/0! | AD28: =Z28/Y28-1 -> #DIV/0! | AE28: =AA28/Z28-1 -> 0.07 | AG28: =$AA28*AG$1 -> 704.61501 | AH28: =$AA28*AH$1 -> 805.2743 | AI28: =$AA28*AI$1 -> 1006.5929 | AJ28: =$AA28*AJ$1 -> 855.60394 | AK28: =$AA28*AK$1 -> 905.93358 | AL28: =$AA28*AL$1 -> 805.2743 | AM28: =$AA28*AM$1 -> 805.2743 | AN28: =$AA28*AN$1 -> 654.28537 | ... AR28: =$AA28*AR$1 -> 704.61501
B29: 29031 | C29: de Medici Moment & Spa Club; Regina Lörke | D29: =VLOOKUP($B29, 'Performance Data'!$B:$K, 3, 0) -> Germany | E29: =VLOOKUP($B29, 'Performance Data'!$B:$K, 4, 0) -> NRW | F29: =VLOOKUP($B29, 'Performance Data'!$B:$K, 6, 0) -> Institutes / Clinic | G29: =VLOOKUP($B29, 'Performance Data'!$B:$K, 10, 0) -> 2025 | I29: =VLOOKUP($B29, 'Performance Data'!$B:$K, 7, 0) -> NKD25 | J29: =P29 -> 5566.09 | K29: 10000 | M29: Grow | O29: =SUMIF('Performance Data'!$B:$B, $B29,'Performance Data'!N:N) -> 0 | P29: =SUMIF('Performance Data'!$B:$B, $B29,'Performance Data'!O:O) -> 5566.09 | Q29: =SUMIF('Performance Data'!$B:$B, $B29,'Performance Data'!P:P) -> 0 | S29: =$P29/O29-1 -> #DIV/0! | T29: =P29/Q29-1 -> #DIV/0! | V29: =SUMIF('Performance Data'!$B:$B, $B29,'Performance Data'!AC:AC) -> 0 | W29: =SUMIF('Performance Data'!$B:$B, $B29,'Performance Data'!AD:AD) -> 0 | X29: =SUMIF('Performance Data'!$B:$B, $B29,'Performance Data'!AE:AE) -> 0 | Y29: =SUMIF('Performance Data'!$B:$B, $B29,'Performance Data'!AG:AG) -> 0 | Z29: =P29 -> 5566.09 | AA29: =K29 -> 10000 | AC29: =Z29/X29-1 -> #DIV/0! | AD29: =Z29/Y29-1 -> #DIV/0! | AG29: =$AA29*AG$1 -> 700 | AH29: =$AA29*AH$1 -> 800 | AI29: =$AA29*AI$1 -> 1000 | AJ29: =$AA29*AJ$1 -> 850 | AK29: =$AA29*AK$1 -> 900 | AL29: =$AA29*AL$1 -> 800 | AM29: =$AA29*AM$1 -> 800 | AN29: =$AA29*AN$1 -> 650 | ... AR29: =$AA29*AR$1 -> 700
B30: 29033 | C30: Angelo stile italiano; Paderborn | D30: =VLOOKUP($B30, 'Performance Data'!$B:$K, 3, 0) -> Germany | E30: =VLOOKUP($B30, 'Performance Data'!$B:$K, 4, 0) -> NRW | F30: =VLOOKUP($B30, 'Performance Data'!$B:$K, 6, 0) -> Institutes / Clinic | G30: =VLOOKUP($B30, 'Performance Data'!$B:$K, 10, 0) -> 2025 | I30: =VLOOKUP($B30, 'Performance Data'!$B:$K, 7, 0) -> NKD25 | J30: =P30 -> 4910.37 | K30: 9000 | M30: Grow | O30: =SUMIF('Performance Data'!$B:$B, $B30,'Performance Data'!N:N) -> 0 | P30: =SUMIF('Performance Data'!$B:$B, $B30,'Performance Data'!O:O) -> 4910.37 | Q30: =SUMIF('Performance Data'!$B:$B, $B30,'Performance Data'!P:P) -> 0 | S30: =$P30/O30-1 -> #DIV/0! | T30: =P30/Q30-1 -> #DIV/0! | V30: =SUMIF('Performance Data'!$B:$B, $B30,'Performance Data'!AC:AC) -> 0 | W30: =SUMIF('Performance Data'!$B:$B, $B30,'Performance Data'!AD:AD) -> 0 | X30: =SUMIF('Performance Data'!$B:$B, $B30,'Performance Data'!AE:AE) -> 0 | Y30: =SUMIF('Performance Data'!$B:$B, $B30,'Performance Data'!AG:AG) -> 0 | Z30: =P30 -> 4910.37 | AA30: =K30 -> 9000 | AC30: =Z30/X30-1 -> #DIV/0! | AD30: =Z30/Y30-1 -> #DIV/0! | AG30: =$AA30*AG$1 -> 630 | AH30: =$AA30*AH$1 -> 720 | AI30: =$AA30*AI$1 -> 900 | AJ30: =$AA30*AJ$1 -> 765 | AK30: =$AA30*AK$1 -> 810 | AL30: =$AA30*AL$1 -> 720 | AM30: =$AA30*AM$1 -> 720 | AN30: =$AA30*AN$1 -> 585 | ... AR30: =$AA30*AR$1 -> 630
B31: NKD25_MP | C31: New doors 2025 | D31: Germany | E31: NRW | G31: 2025 | H31: 0 | I31: NKD25 | J31: 0 | K31: 0 | O31: 0 | P31: 0 | Q31: =SUMIF('Combined Budget 2025 EUR'!$B:$B, $B31,'Combined Budget 2025 EUR'!$AL:$AL) -> 11250 | S31: =$P31/O31-1 -> #DIV/0! | T31: =P31/Q31-1 -> -1 | V31: 0 | W31: 0 | X31: 0 | Y31: =SUMIF('Combined Budget 2025 EUR'!$B:$B, $B31,'Combined Budget 2025 EUR'!$AQ:$AQ) -> 30000 | Z31: =J31 -> 0 | AA31: =K31 -> 0 | AC31: =Z31/X31-1 -> #DIV/0! | AD31: =Z31/Y31-1 -> -1 | AE31: =AA31/Z31-1 -> #DIV/0! | AG31: =$AA31*AG$1 -> 0 | AH31: =$AA31*AH$1 -> 0 | AI31: =$AA31*AI$1 -> 0 | AJ31: =$AA31*AJ$1 -> 0 | AK31: =$AA31*AK$1 -> 0 | AL31: =$AA31*AL$1 -> 0 | AM31: =$AA31*AM$1 -> 0 | AN31: =$AA31*AN$1 -> 0 | ... AR31: =$AA31*AR$1 -> 0
B33: Total New Doors 2025 | H33: =COUNTIF(H25:H28, "Yes")+H31 -> 4 | J33: =SUM(J25:J31) -> 47386 | K33: =SUM(K25:K31) -> 57404.59 | O33: =SUM(O25:O31) -> 287.97 | P33: =SUM(P25:P31) -> 47386 | Q33: =SUM(Q25:Q31) -> 11250 | S33: =$P33/O33-1 -> 163.55186 | T33: =P33/Q33-1 -> 3.2120889 | V33: =SUM(V25:V31) -> 0 | W33: =SUM(W25:W31) -> 387.57 | X33: =SUM(X25:X31) -> 287.97 | Y33: =SUM(Y25:Y31) -> 30000 | Z33: =SUM(Z25:Z31) -> 47386 | AA33: =SUM(AA25:AA31) -> 57404.59 | AC33: =Z33/X33-1 -> 163.55186 | AD33: =Z33/Y33-1 -> 0.57953333 | AE33: =AA33/Z33-1 -> 0.2114251 | AG33: =SUM(AG25:AG31) -> 4018.3213 | AH33: =SUM(AH25:AH31) -> 4592.3672 | AI33: =SUM(AI25:AI31) -> 5740.459 | AJ33: =SUM(AJ25:AJ31) -> 4879.3901 | AK33: =SUM(AK25:AK31) -> 5166.4131 | AL33: =SUM(AL25:AL31) -> 4592.3672 | AM33: =SUM(AM25:AM31) -> 4592.3672 | AN33: =SUM(AN25:AN31) -> 3731.2983 | ... AR33: =SUM(AR25:AR31) -> 4018.3213
B35: Global Target existing and new doors 2025 | AG35: {=AG21:AR21+AG33:AR33} -> 41589.605 | AH35: 47530.977 | AI35: 59413.721 | AJ35: 50501.663 | AK35: 53472.349 | AL35: 47530.977 | AM35: 47530.977 | AN35: 38618.919 | AO35: 56443.035 | AP35: 59413.721 | AQ35: 50501.663 | AR35: 41589.605
AY36: =AV37 -> 1 | AZ36: =AW37 -> 0 | BA36: =AX37+AV37 -> 2 | BB36: =AY37+AW37 -> 0 | BC36: =AZ37+AX37+AV37 -> 2 | BD36: =BA37+AY37+AW37 -> 1 | BE36: =BB37+AZ37+AX37+AV37 -> 2 | BF36: =BC37+BA37+AY37+AW37 -> 2
B37: NKD26_MP | C37: New doors 2026 | D37: Germany | E37: NRW | G37: 2026 | H37: 5 | I37: NKD26 | K37: 50000 | O37: 0 | P37: 0 | Q37: 0 | S37: =$P37/O37-1 -> #DIV/0! | T37: =P37/Q37-1 -> #DIV/0! | V37: 0 | W37: 0 | X37: 0 | Y37: 0 | Z37: =J37 -> 0 | AA37: =K37 -> 50000 | AC37: =Z37/X37-1 -> #DIV/0! | AD37: =Z37/Y37-1 -> #DIV/0! | AE37: =AA37/Z37-1 -> #DIV/0! | AG37: =AU37*4000+AU36*3000 -> 0 | AH37: =AV37*4000+AV36*3000 -> 4000 | AI37: 4000 | AJ37: =AX37*4000+AX36*3000 -> 4000 | AK37: 4000 | AL37: 4000 | AM37: 4000 | AN37: 2000 | AO37: 6000 | AP37: 5000 | AQ37: 8000 | AR37: 5000 | AV37: 1 | AX37: 1 | BA37: 1 | BC37: 1 | BE37: 1
B39: Total New Doors 2026 | H39: =COUNTIF(H36:H36, "Yes")+H37 -> 5 | J39: =SUM(J36:J37) -> 0 | K39: =SUM(K36:K37) -> 50000 | O39: =SUM(O36:O37) -> 0 | P39: =SUM(P36:P37) -> 0 | Q39: =SUM(Q36:Q37) -> 0 | S39: =$P39/O39-1 -> #DIV/0! | T39: =P39/Q39-1 -> #DIV/0! | V39: =SUM(V36:V37) -> 0 | W39: =SUM(W36:W37) -> 0 | X39: =SUM(X36:X37) -> 0 | Y39: =SUM(Y36:Y37) -> 0 | Z39: =SUM(Z36:Z37) -> 0 | AA39: =SUM(AA36:AA37) -> 50000 | AC39: =Z39/X39-1 -> #DIV/0! | AD39: =Z39/Y39-1 -> #DIV/0! | AE39: =AA39/Z39-1 -> #DIV/0! | AG39: =SUM(AG36:AG37) -> 0 | AH39: =SUM(AH36:AH37) -> 4000 | AI39: =SUM(AI36:AI37) -> 4000 | AJ39: =SUM(AJ36:AJ37) -> 4000 | AK39: =SUM(AK36:AK37) -> 4000 | AL39: =SUM(AL36:AL37) -> 4000 | AM39: =SUM(AM36:AM37) -> 4000 | AN39: =SUM(AN36:AN37) -> 2000 | ... AR39: =SUM(AR36:AR37) -> 5000

Sheet NRW Ulrike
O1: Year to date | P1: Year to date | Q1: Year to date | S1: Year to date | T1: Year to date | V1: Full year | W1: Full year | X1: Full year | Y1: Full year | Z1: Full year | AA1: Full year | AC1: Full year | AD1: Full year | AE1: Full year | AG1: 0.07 | AH1: 0.08 | AI1: 0.1 | AJ1: 0.085 | AK1: 0.09 | AL1: 0.08 | AM1: 0.08 | AN1: 0.065 | AO1: 0.095 | AP1: 0.1 | AQ1: 0.085 | AR1: 0.07
B2: Customer Code | C2: Customer Name | D2: Country | E2: Region | F2: Customer Map | G2: New door year | H2: Active? | I2: 2025 Cluster | J2: 2025A | K2: 2026B | L2: Size indicator | M2: Customer Growth Class | O2: 2024 YTD | P2: 2025 YTD | Q2: 2025B YTD | S2: 25 vs 24 % | T2: 25 vs 25B % | V2: 2022 | W2: 2023 | X2: 2024 | Y2: 2025B | Z2: 2025A | AA2: 2026B | AC2: 25 vs 24 % | AD2: 25 vs 25B % | AE2: 26B vs 25F % | AG2: 46023 | AH2: 46054 | AI2: 46082 | AJ2: 46113 | AK2: 46143 | AL2: 46174 | AM2: 46204 | AN2: 46235 | AO2: 46266 | AP2: 46296 | AQ2: 46327 | AR2: 46357
B3: 20169 | C3: Monika Sebetzky | D3: =VLOOKUP($B3, 'Performance Data'!$B:$K, 3, 0) -> Germany | E3: =VLOOKUP($B3, 'Performance Data'!$B:$K, 4, 0) -> NRW | F3: =VLOOKUP($B3, 'Performance Data'!$B:$K, 6, 0) -> Institutes / Clinic | G3: =VLOOKUP($B3, 'Performance Data'!$B:$K, 10, 0) -> Pre-2022 | H3: Yes | I3: =VLOOKUP($B3, 'Performance Data'!$B:$K, 7, 0) -> BB | J3: =P3 -> 16030.89 | K3: =J3*1.08 -> 17313.361 | M3: Maintain | O3: =SUMIF('Performance Data'!$B:$B, $B3,'Performance Data'!N:N) -> 18311.16 | P3: =SUMIF('Performance Data'!$B:$B, $B3,'Performance Data'!O:O) -> 16030.89 | Q3: =SUMIF('Performance Data'!$B:$B, $B3,'Performance Data'!P:P) -> 14600 | S3: =$P3/O3-1 -> -0.12452898 | T3: =P3/Q3-1 -> 0.098006164 | V3: =SUMIF('Performance Data'!$B:$B, $B3,'Performance Data'!AC:AC) -> 18997.41 | W3: =SUMIF('Performance Data'!$B:$B, $B3,'Performance Data'!AD:AD) -> 21900.88 | X3: =SUMIF('Performance Data'!$B:$B, $B3,'Performance Data'!AE:AE) -> 18311.16 | Y3: =SUMIF('Performance Data'!$B:$B, $B3,'Performance Data'!AG:AG) -> 20000 | Z3: =P3 -> 16030.89 | AA3: =K3 -> 17313.361 | AC3: =Z3/X3-1 -> -0.12452898 | AD3: =Z3/Y3-1 -> -0.1984555 | AE3: =AA3/Z3-1 -> 0.08 | AG3: =$AA3*AG$1 -> 1211.9353 | AH3: =$AA3*AH$1 -> 1385.0689 | AI3: =$AA3*AI$1 -> 1731.3361 | AJ3: =$AA3*AJ$1 -> 1471.6357 | AK3: =$AA3*AK$1 -> 1558.2025 | AL3: =$AA3*AL$1 -> 1385.0689 | AM3: =$AA3*AM$1 -> 1385.0689 | AN3: =$AA3*AN$1 -> 1125.3685 | ... AR3: =$AA3*AR$1 -> 1211.9353
B4: 20746 | C4: Martina Born | D4: =VLOOKUP($B4, 'Performance Data'!$B:$K, 3, 0) -> Germany | E4: =VLOOKUP($B4, 'Performance Data'!$B:$K, 4, 0) -> NRW | F4: =VLOOKUP($B4, 'Performance Data'!$B:$K, 6, 0) -> Institutes / Clinic | G4: =VLOOKUP($B4, 'Performance Data'!$B:$K, 10, 0) -> Pre-2022 | H4: Yes | I4: =VLOOKUP($B4, 'Performance Data'!$B:$K, 7, 0) -> BB | J4: =P4 -> 9327.05 | K4: =J4*1.08 -> 10073.214 | M4: Maintain | O4: =SUMIF('Performance Data'!$B:$B, $B4,'Performance Data'!N:N) -> 6272.17 | P4: =SUMIF('Performance Data'!$B:$B, $B4,'Performance Data'!O:O) -> 9327.05 | Q4: =SUMIF('Performance Data'!$B:$B, $B4,'Performance Data'!P:P) -> 4380 | S4: =$P4/O4-1 -> 0.48705313 | T4: =P4/Q4-1 -> 1.1294635 | V4: =SUMIF('Performance Data'!$B:$B, $B4,'Performance Data'!AC:AC) -> 6054.33 | W4: =SUMIF('Performance Data'!$B:$B, $B4,'Performance Data'!AD:AD) -> 6702.24 | X4: =SUMIF('Performance Data'!$B:$B, $B4,'Performance Data'!AE:AE) -> 6272.17 | Y4: =SUMIF('Performance Data'!$B:$B, $B4,'Performance Data'!AG:AG) -> 6000 | Z4: =P4 -> 9327.05 | AA4: =K4 -> 10073.214 | AC4: =Z4/X4-1 -> 0.48705313 | AD4: =Z4/Y4-1 -> 0.55450833 | AE4: =AA4/Z4-1 -> 0.08 | AG4: =$AA4*AG$1 -> 705.12498 | AH4: =$AA4*AH$1 -> 805.85712 | AI4: =$AA4*AI$1 -> 1007.3214 | AJ4: =$AA4*AJ$1 -> 856.22319 | AK4: =$AA4*AK$1 -> 906.58926 | AL4: =$AA4*AL$1 -> 805.85712 | AM4: =$AA4*AM$1 -> 805.85712 | AN4: =$AA4*AN$1 -> 654.75891 | ... AR4: =$AA4*AR$1 -> 705.12498
B5: 29019 | C5: PM Kinga; Kinga Mathey | D5: =VLOOKUP($B5, 'Performance Data'!$B:$K, 3, 0) -> Germany | E5: North | F5: =VLOOKUP($B5, 'Performance Data'!$B:$K, 6, 0) -> Institutes / Clinic | G5: =VLOOKUP($B5, 'Performance Data'!$B:$K, 10, 0) -> 2025 | H5: Yes | I5: =VLOOKUP($B5, 'Performance Data'!$B:$K, 7, 0) -> NKD25 | J5: =P5 -> 4205.28 | K5: 10000 | M5: Grow | O5: =SUMIF('Performance Data'!$B:$B, $B5,'Performance Data'!N:N) -> 0 | P5: =SUMIF('Performance Data'!$B:$B, $B5,'Performance Data'!O:O) -> 4205.28 | Q5: =SUMIF('Performance Data'!$B:$B, $B5,'Performance Data'!P:P) -> 0 | S5: =$P5/O5-1 -> #DIV/0! | T5: =P5/Q5-1 -> #DIV/0! | V5: =SUMIF('Performance Data'!$B:$B, $B5,'Performance Data'!AC:AC) -> 0 | W5: =SUMIF('Performance Data'!$B:$B, $B5,'Performance Data'!AD:AD) -> 0 | X5: =SUMIF('Performance Data'!$B:$B, $B5,'Performance Data'!AE:AE) -> 0 | Y5: =SUMIF('Performance Data'!$B:$B, $B5,'Performance Data'!AG:AG) -> 0 | Z5: =P5 -> 4205.28 | AA5: =K5 -> 10000 | AC5: =Z5/X5-1 -> #DIV/0! | AD5: =Z5/Y5-1 -> #DIV/0! | AE5: =AA5/Z5-1 -> 1.3779629 | AG5: =$AA5*AG$1 -> 700 | AH5: =$AA5*AH$1 -> 800 | AI5: =$AA5*AI$1 -> 1000 | AJ5: =$AA5*AJ$1 -> 850 | AK5: =$AA5*AK$1 -> 900 | AL5: =$AA5*AL$1 -> 800 | AM5: =$AA5*AM$1 -> 800 | AN5: =$AA5*AN$1 -> 650 | ... AR5: =$AA5*AR$1 -> 700
B6: 29020 | C6: Sandra Duratovic; Osnabrück | D6: =VLOOKUP($B6, 'Performance Data'!$B:$K, 3, 0) -> Germany | E6: North | F6: =VLOOKUP($B6, 'Performance Data'!$B:$K, 6, 0) -> Institutes / Clinic | G6: =VLOOKUP($B6, 'Performance Data'!$B:$K, 10, 0) -> 2025 | H6: Yes | I6: =VLOOKUP($B6, 'Performance Data'!$B:$K, 7, 0) -> NKD25 | J6: =P6 -> 4763.47 | K6: 10000 | M6: Grow | O6: =SUMIF('Performance Data'!$B:$B, $B6,'Performance Data'!N:N) -> 0 | P6: =SUMIF('Performance Data'!$B:$B, $B6,'Performance Data'!O:O) -> 4763.47 | Q6: =SUMIF('Performance Data'!$B:$B, $B6,'Performance Data'!P:P) -> 0 | S6: =$P6/O6-1 -> #DIV/0! | T6: =P6/Q6-1 -> #DIV/0! | V6: =SUMIF('Performance Data'!$B:$B, $B6,'Performance Data'!AC:AC) -> 0 | W6: =SUMIF('Performance Data'!$B:$B, $B6,'Performance Data'!AD:AD) -> 0 | X6: =SUMIF('Performance Data'!$B:$B, $B6,'Performance Data'!AE:AE) -> 0 | Y6: =SUMIF('Performance Data'!$B:$B, $B6,'Performance Data'!AG:AG) -> 0 | Z6: =P6 -> 4763.47 | AA6: =K6 -> 10000 | AC6: =Z6/X6-1 -> #DIV/0! | AD6: =Z6/Y6-1 -> #DIV/0! | AE6: =AA6/Z6-1 -> 1.09931 | AG6: =$AA6*AG$1 -> 700 | AH6: =$AA6*AH$1 -> 800 | AI6: =$AA6*AI$1 -> 1000 | AJ6: =$AA6*AJ$1 -> 850 | AK6: =$AA6*AK$1 -> 900 | AL6: =$AA6*AL$1 -> 800 | AM6: =$AA6*AM$1 -> 800 | AN6: =$AA6*AN$1 -> 650 | ... AR6: =$AA6*AR$1 -> 700
B7: 20984 | C7: Kosmetik am Park, Meike Ewens | D7: =VLOOKUP($B7, 'Performance Data'!$B:$K, 3, 0) -> Germany | E7: =VLOOKUP($B7, 'Performance Data'!$B:$K, 4, 0) -> NRW | F7: =VLOOKUP($B7, 'Performance Data'!$B:$K, 6, 0) -> Institutes / Clinic | G7: =VLOOKUP($B7, 'Performance Data'!$B:$K, 10, 0) -> 2023 | H7: Yes | I7: =VLOOKUP($B7, 'Performance Data'!$B:$K, 7, 0) -> BC | J7: =P7 -> 8780.43 | K7: =J7*1.08 -> 9482.8644 | M7: Maintain | O7: =SUMIF('Performance Data'!$B:$B, $B7,'Performance Data'!N:N) -> 8905.66 | P7: =SUMIF('Performance Data'!$B:$B, $B7,'Performance Data'!O:O) -> 8780.43 | Q7: =SUMIF('Performance Data'!$B:$B, $B7,'Performance Data'!P:P) -> 6570 | S7: =$P7/O7-1 -> -0.014061844 | T7: =P7/Q7-1 -> 0.33644292 | V7: =SUMIF('Performance Data'!$B:$B, $B7,'Performance Data'!AC:AC) -> 0 | W7: =SUMIF('Performance Data'!$B:$B, $B7,'Performance Data'!AD:AD) -> 6604.56 | X7: =SUMIF('Performance Data'!$B:$B, $B7,'Performance Data'!AE:AE) -> 8905.66 | Y7: =SUMIF('Performance Data'!$B:$B, $B7,'Performance Data'!AG:AG) -> 9000 | Z7: =P7 -> 8780.43 | AA7: =K7 -> 9482.8644 | AC7: =Z7/X7-1 -> -0.014061844 | AD7: =Z7/Y7-1 -> -0.024396667 | AE7: =AA7/Z7-1 -> 0.08 | AG7: =$AA7*AG$1 -> 663.80051 | AH7: =$AA7*AH$1 -> 758.62915 | AI7: =$AA7*AI$1 -> 948.28644 | AJ7: =$AA7*AJ$1 -> 806.04347 | AK7: =$AA7*AK$1 -> 853.4578 | AL7: =$AA7*AL$1 -> 758.62915 | AM7: =$AA7*AM$1 -> 758.62915 | AN7: =$AA7*AN$1 -> 616.38619 | ... AR7: =$AA7*AR$1 -> 663.80051
B8: 20872 | C8: Mirsada Hülsemann | D8: =VLOOKUP($B8, 'Performance Data'!$B:$K, 3, 0) -> Germany | E8: =VLOOKUP($B8, 'Performance Data'!$B:$K, 4, 0) -> NRW | F8: =VLOOKUP($B8, 'Performance Data'!$B:$K, 6, 0) -> Institutes / Clinic | G8: =VLOOKUP($B8, 'Performance Data'!$B:$K, 10, 0) -> Pre-2022 | H8: Yes | I8: =VLOOKUP($B8, 'Performance Data'!$B:$K, 7, 0) -> BC | J8: =P8 -> 7496.83 | K8: =J8*1.08 -> 8096.5764 | M8: Maintain | O8: =SUMIF('Performance Data'!$B:$B, $B8,'Performance Data'!N:N) -> 8820.25 | P8: =SUMIF('Performance Data'!$B:$B, $B8,'Performance Data'!O:O) -> 7496.83 | Q8: =SUMIF('Performance Data'!$B:$B, $B8,'Performance Data'!P:P) -> 5840 | S8: =$P8/O8-1 -> -0.15004337 | T8: =P8/Q8-1 -> 0.28370377 | V8: =SUMIF('Performance Data'!$B:$B, $B8,'Performance Data'!AC:AC) -> 28989.56 | W8: =SUMIF('Performance Data'!$B:$B, $B8,'Performance Data'!AD:AD) -> 19051.54 | X8: =SUMIF('Performance Data'!$B:$B, $B8,'Performance Data'!AE:AE) -> 8820.25 | Y8: =SUMIF('Performance Data'!$B:$B, $B8,'Performance Data'!AG:AG) -> 8000 | Z8: =P8 -> 7496.83 | AA8: =K8 -> 8096.5764 | AC8: =Z8/X8-1 -> -0.15004337 | AD8: =Z8/Y8-1 -> -0.06289625 | AE8: =AA8/Z8-1 -> 0.08 | AG8: =$AA8*AG$1 -> 566.76035 | AH8: =$AA8*AH$1 -> 647.72611 | AI8: =$AA8*AI$1 -> 809.65764 | AJ8: =$AA8*AJ$1 -> 688.20899 | AK8: =$AA8*AK$1 -> 728.69188 | AL8: =$AA8*AL$1 -> 647.72611 | AM8: =$AA8*AM$1 -> 647.72611 | AN8: =$AA8*AN$1 -> 526.27747 | ... AR8: =$AA8*AR$1 -> 566.76035
B9: 20251 | C9: Esther Wohlfahrt-Maley | D9: =VLOOKUP($B9, 'Performance Data'!$B:$K, 3, 0) -> Germany | E9: =VLOOKUP($B9, 'Performance Data'!$B:$K, 4, 0) -> NRW | F9: =VLOOKUP($B9, 'Performance Data'!$B:$K, 6, 0) -> Institutes / Clinic | G9: =VLOOKUP($B9, 'Performance Data'!$B:$K, 10, 0) -> Pre-2022 | H9: Yes | I9: =VLOOKUP($B9, 'Performance Data'!$B:$K, 7, 0) -> BB | J9: =P9 -> 7149.45 | K9: =J9*1.08 -> 7721.406 | M9: Maintain | O9: =SUMIF('Performance Data'!$B:$B, $B9,'Performance Data'!N:N) -> 8846.71 | P9: =SUMIF('Performance Data'!$B:$B, $B9,'Performance Data'!O:O) -> 7149.45 | Q9: =SUMIF('Performance Data'!$B:$B, $B9,'Performance Data'!P:P) -> 6205 | S9: =$P9/O9-1 -> -0.19185211 | T9: =P9/Q9-1 -> 0.1522079 | V9: =SUMIF('Performance Data'!$B:$B, $B9,'Performance Data'!AC:AC) -> 7958.06 | W9: =SUMIF('Performance Data'!$B:$B, $B9,'Performance Data'!AD:AD) -> 10240.88 | X9: =SUMIF('Performance Data'!$B:$B, $B9,'Performance Data'!AE:AE) -> 8846.71 | Y9: =SUMIF('Performance Data'!$B:$B, $B9,'Performance Data'!AG:AG) -> 8500 | Z9: =P9 -> 7149.45 | AA9: =K9 -> 7721.406 | AC9: =Z9/X9-1 -> -0.19185211 | AD9: =Z9/Y9-1 -> -0.15888824 | AE9: =AA9/Z9-1 -> 0.08 | AG9: =$AA9*AG$1 -> 540.49842 | AH9: =$AA9*AH$1 -> 617.71248 | AI9: =$AA9*AI$1 -> 772.1406 | AJ9: =$AA9*AJ$1 -> 656.31951 | AK9: =$AA9*AK$1 -> 694.92654 | AL9: =$AA9*AL$1 -> 617.71248 | AM9: =$AA9*AM$1 -> 617.71248 | AN9: =$AA9*AN$1 -> 501.89139 | ... AR9: =$AA9*AR$1 -> 540.49842
B10: 20270 | C10: Susanne Schwidden | D10: =VLOOKUP($B10, 'Performance Data'!$B:$K, 3, 0) -> Germany | E10: =VLOOKUP($B10, 'Performance Data'!$B:$K, 4, 0) -> NRW | F10: =VLOOKUP($B10, 'Performance Data'!$B:$K, 6, 0) -> Perfumery | G10: =VLOOKUP($B10, 'Performance Data'!$B:$K, 10, 0) -> Pre-2022 | H10: Yes | I10: =VLOOKUP($B10, 'Performance Data'!$B:$K, 7, 0) -> BC | J10: =P10 -> 6984.31 | K10: =J10*1.08 -> 7543.0548 | M10: Maintain | O10: =SUMIF('Performance Data'!$B:$B, $B10,'Performance Data'!N:N) -> 5756.81 | P10: =SUMIF('Performance Data'!$B:$B, $B10,'Performance Data'!O:O) -> 6984.31 | Q10: =SUMIF('Performance Data'!$B:$B, $B10,'Performance Data'!P:P) -> 3650 | S10: =$P10/O10-1 -> 0.21322573 | T10: =P10/Q10-1 -> 0.91350959 | V10: =SUMIF('Performance Data'!$B:$B, $B10,'Performance Data'!AC:AC) -> 4142.39 | W10: =SUMIF('Performance Data'!$B:$B, $B10,'Performance Data'!AD:AD) -> 5240.07 | X10: =SUMIF('Performance Data'!$B:$B, $B10,'Performance Data'!AE:AE) -> 5756.81 | Y10: =SUMIF('Performance Data'!$B:$B, $B10,'Performance Data'!AG:AG) -> 5000 | Z10: =P10 -> 6984.31 | AA10: =K10 -> 7543.0548 | AC10: =Z10/X10-1 -> 0.21322573 | AD10: =Z10/Y10-1 -> 0.396862 | AE10: =AA10/Z10-1 -> 0.08 | AG10: =$AA10*AG$1 -> 528.01384 | AH10: =$AA10*AH$1 -> 603.44438 | AI10: =$AA10*AI$1 -> 754.30548 | AJ10: =$AA10*AJ$1 -> 641.15966 | AK10: =$AA10*AK$1 -> 678.87493 | AL10: =$AA10*AL$1 -> 603.44438 | AM10: =$AA10*AM$1 -> 603.44438 | AN10: =$AA10*AN$1 -> 490.29856 | ... AR10: =$AA10*AR$1 -> 528.01384
B11: 20533 | C11: Wir-Für-Sie Parfümerie Wigger | D11: =VLOOKUP($B11, 'Performance Data'!$B:$K, 3, 0) -> Germany | E11: =VLOOKUP($B11, 'Performance Data'!$B:$K, 4, 0) -> NRW | F11: =VLOOKUP($B11, 'Performance Data'!$B:$K, 6, 0) -> Institutes / Clinic | G11: =VLOOKUP($B11, 'Performance Data'!$B:$K, 10, 0) -> Pre-2022 | H11: Yes | I11: =VLOOKUP($B11, 'Performance Data'!$B:$K, 7, 0) -> BA | J11: =P11 -> 6522.1 | K11: =J11*1.08 -> 7043.868 | M11: Maintain | O11: =SUMIF('Performance Data'!$B:$B, $B11,'Performance Data'!N:N) -> 14012.47 | P11: =SUMIF('Performance Data'!$B:$B, $B11,'Performance Data'!O:O) -> 6522.1 | Q11: =SUMIF('Performance Data'!$B:$B, $B11,'Performance Data'!P:P) -> 10950 | S11: =$P11/O11-1 -> -0.5345503 | T11: =P11/Q11-1 -> -0.40437443 | V11: =SUMIF('Performance Data'!$B:$B, $B11,'Performance Data'!AC:AC) -> 319.67 | W11: =SUMIF('Performance Data'!$B:$B, $B11,'Performance Data'!AD:AD) -> 13225.26 | X11: =SUMIF('Performance Data'!$B:$B, $B11,'Performance Data'!AE:AE) -> 14012.47 | Y11: =SUMIF('Performance Data'!$B:$B, $B11,'Performance Data'!AG:AG) -> 15000 | Z11: =P11 -> 6522.1 | AA11: =K11 -> 7043.868 | AC11: =Z11/X11-1 -> -0.5345503 | AD11: =Z11/Y11-1 -> -0.56519333 | AE11: =AA11/Z11-1 -> 0.08 | AG11: =$AA11*AG$1 -> 493.07076 | AH11: =$AA11*AH$1 -> 563.50944 | AI11: =$AA11*AI$1 -> 704.3868 | AJ11: =$AA11*AJ$1 -> 598.72878 | AK11: =$AA11*AK$1 -> 633.94812 | AL11: =$AA11*AL$1 -> 563.50944 | AM11: =$AA11*AM$1 -> 563.50944 | AN11: =$AA11*AN$1 -> 457.85142 | ... AR11: =$AA11*AR$1 -> 493.07076
B12: 20981 | C12: Maleko Kosmetik; Maria Lebeth | D12: =VLOOKUP($B12, 'Performance Data'!$B:$K, 3, 0) -> Germany | E12: =VLOOKUP($B12, 'Performance Data'!$B:$K, 4, 0) -> NRW | F12: =VLOOKUP($B12, 'Performance Data'!$B:$K, 6, 0) -> Institutes / Clinic | G12: =VLOOKUP($B12, 'Performance Data'!$B:$K, 10, 0) -> 2023 | H12: Yes | I12: =VLOOKUP($B12, 'Performance Data'!$B:$K, 7, 0) -> BB | J12: =P12 -> 5898.42 | K12: =J12*1.08 -> 6370.2936 | M12: Maintain | O12: =SUMIF('Performance Data'!$B:$B, $B12,'Performance Data'!N:N) -> 12688.78 | P12: =SUMIF('Performance Data'!$B:$B, $B12,'Performance Data'!O:O) -> 5898.42 | Q12: =SUMIF('Performance Data'!$B:$B, $B12,'Performance Data'!P:P) -> 9490 | S12: =$P12/O12-1 -> -0.5351468 | T12: =P12/Q12-1 -> -0.37845943 | V12: =SUMIF('Performance Data'!$B:$B, $B12,'Performance Data'!AC:AC) -> 0 | W12: =SUMIF('Performance Data'!$B:$B, $B12,'Performance Data'!AD:AD) -> 11979.05 | X12: =SUMIF('Performance Data'!$B:$B, $B12,'Performance Data'!AE:AE) -> 12688.78 | Y12: =SUMIF('Performance Data'!$B:$B, $B12,'Performance Data'!AG:AG) -> 13000 | Z12: =P12 -> 5898.42 | AA12: =K12 -> 6370.2936 | AC12: =Z12/X12-1 -> -0.5351468 | AD12: =Z12/Y12-1 -> -0.54627538 | AE12: =AA12/Z12-1 -> 0.08 | AG12: =$AA12*AG$1 -> 445.92055 | AH12: =$AA12*AH$1 -> 509.62349 | AI12: =$AA12*AI$1 -> 637.02936 | AJ12: =$AA12*AJ$1 -> 541.47496 | AK12: =$AA12*AK$1 -> 573.32642 | AL12: =$AA12*AL$1 -> 509.62349 | AM12: =$AA12*AM$1 -> 509.62349 | AN12: =$AA12*AN$1 -> 414.06908 | ... AR12: =$AA12*AR$1 -> 445.92055
B13: 20724 | C13: Farida Zaman | D13: =VLOOKUP($B13, 'Performance Data'!$B:$K, 3, 0) -> Germany | E13: =VLOOKUP($B13, 'Performance Data'!$B:$K, 4, 0) -> NRW | F13: =VLOOKUP($B13, 'Performance Data'!$B:$K, 6, 0) -> Hotel Spa | G13: =VLOOKUP($B13, 'Performance Data'!$B:$K, 10, 0) -> Pre-2022 | H13: Yes | I13: =VLOOKUP($B13, 'Performance Data'!$B:$K, 7, 0) -> BC | J13: =P13 -> 5614.67 | K13: =J13*1.08 -> 6063.8436 | M13: Maintain | O13: =SUMIF('Performance Data'!$B:$B, $B13,'Performance Data'!N:N) -> 7352.53 | P13: =SUMIF('Performance Data'!$B:$B, $B13,'Performance Data'!O:O) -> 5614.67 | Q13: =SUMIF('Performance Data'!$B:$B, $B13,'Performance Data'!P:P) -> 5840 | S13: =$P13/O13-1 -> -0.23636218 | T13: =P13/Q13-1 -> -0.038583904 | V13: =SUMIF('Performance Data'!$B:$B, $B13,'Performance Data'!AC:AC) -> 5352.67 | W13: =SUMIF('Performance Data'!$B:$B, $B13,'Performance Data'!AD:AD) -> 4836.92 | X13: =SUMIF('Performance Data'!$B:$B, $B13,'Performance Data'!AE:AE) -> 7352.53 | Y13: =SUMIF('Performance Data'!$B:$B, $B13,'Performance Data'!AG:AG) -> 8000 | Z13: =P13 -> 5614.67 | AA13: =K13 -> 6063.8436 | AC13: =Z13/X13-1 -> -0.23636218 | AD13: =Z13/Y13-1 -> -0.29816625 | AE13: =AA13/Z13-1 -> 0.08 | AG13: =$AA13*AG$1 -> 424.46905 | AH13: =$AA13*AH$1 -> 485.10749 | AI13: =$AA13*AI$1 -> 606.38436 | AJ13: =$AA13*AJ$1 -> 515.42671 | AK13: =$AA13*AK$1 -> 545.74592 | AL13: =$AA13*AL$1 -> 485.10749 | AM13: =$AA13*AM$1 -> 485.10749 | AN13: =$AA13*AN$1 -> 394.14983 | ... AR13: =$AA13*AR$1 -> 424.46905
B14: 20910 | C14: Isabella Faßbender | D14: =VLOOKUP($B14, 'Performance Data'!$B:$K, 3, 0) -> Germany | E14: =VLOOKUP($B14, 'Performance Data'!$B:$K, 4, 0) -> NRW | F14: =VLOOKUP($B14, 'Performance Data'!$B:$K, 6, 0) -> Institutes / Clinic | G14: =VLOOKUP($B14, 'Performance Data'!$B:$K, 10, 0) -> Pre-2022 | H14: Yes | I14: =VLOOKUP($B14, 'Performance Data'!$B:$K, 7, 0) -> BC | J14: =P14 -> 4154.15 | K14: =J14*1.08 -> 4486.482 | M14: Maintain | O14: =SUMIF('Performance Data'!$B:$B, $B14,'Performance Data'!N:N) -> 7249.22 | P14: =SUMIF('Performance Data'!$B:$B, $B14,'Performance Data'!O:O) -> 4154.15 | Q14: =SUMIF('Performance Data'!$B:$B, $B14,'Performance Data'!P:P) -> 5110 | S14: =$P14/O14-1 -> -0.42695214 | T14: =P14/Q14-1 -> -0.18705479 | V14: =SUMIF('Performance Data'!$B:$B, $B14,'Performance Data'!AC:AC) -> 10836.72 | W14: =SUMIF('Performance Data'!$B:$B, $B14,'Performance Data'!AD:AD) -> 7803.28 | X14: =SUMIF('Performance Data'!$B:$B, $B14,'Performance Data'!AE:AE) -> 7249.22 | Y14: =SUMIF('Performance Data'!$B:$B, $B14,'Performance Data'!AG:AG) -> 7000 | Z14: =P14 -> 4154.15 | AA14: =K14 -> 4486.482 | AC14: =Z14/X14-1 -> -0.42695214 | AD14: =Z14/Y14-1 -> -0.40655 | AE14: =AA14/Z14-1 -> 0.08 | AG14: =$AA14*AG$1 -> 314.05374 | AH14: =$AA14*AH$1 -> 358.91856 | AI14: =$AA14*AI$1 -> 448.6482 | AJ14: =$AA14*AJ$1 -> 381.35097 | AK14: =$AA14*AK$1 -> 403.78338 | AL14: =$AA14*AL$1 -> 358.91856 | AM14: =$AA14*AM$1 -> 358.91856 | AN14: =$AA14*AN$1 -> 291.62133 | ... AR14: =$AA14*AR$1 -> 314.05374
B15: 29003 | C15: Malorne Cosmetics; Tessa | D15: =VLOOKUP($B15, 'Performance Data'!$B:$K, 3, 0) -> Germany | E15: =VLOOKUP($B15, 'Performance Data'!$B:$K, 4, 0) -> NRW | F15: =VLOOKUP($B15, 'Performance Data'!$B:$K, 6, 0) -> Institutes / Clinic | G15: =VLOOKUP($B15, 'Performance Data'!$B:$K, 10, 0) -> 2023 | H15: Yes | I15: =VLOOKUP($B15, 'Performance Data'!$B:$K, 7, 0) -> BC | J15: =P15 -> 3321.32 | K15: 4000 | M15: Maintain | O15: =SUMIF('Performance Data'!$B:$B, $B15,'Performance Data'!N:N) -> 6267.38 | P15: =SUMIF('Performance Data'!$B:$B, $B15,'Performance Data'!O:O) -> 3321.32 | Q15: =SUMIF('Performance Data'!$B:$B, $B15,'Performance Data'!P:P) -> 4380 | S15: =$P15/O15-1 -> -0.47006245 | T15: =P15/Q15-1 -> -0.24170776 | V15: =SUMIF('Performance Data'!$B:$B, $B15,'Performance Data'!AC:AC) -> 0 | W15: =SUMIF('Performance Data'!$B:$B, $B15,'Performance Data'!AD:AD) -> 2431.59 | X15: =SUMIF('Performance Data'!$B:$B, $B15,'Performance Data'!AE:AE) -> 6267.38 | Y15: =SUMIF('Performance Data'!$B:$B, $B15,'Performance Data'!AG:AG) -> 6000 | Z15: =P15 -> 3321.32 | AA15: =K15 -> 4000 | AC15: =Z15/X15-1 -> -0.47006245 | AD15: =Z15/Y15-1 -> -0.44644667 | AE15: =AA15/Z15-1 -> 0.20434044 | AG15: =$AA15*AG$1 -> 280 | AH15: =$AA15*AH$1 -> 320 | AI15: =$AA15*AI$1 -> 400 | AJ15: =$AA15*AJ$1 -> 340 | AK15: =$AA15*AK$1 -> 360 | AL15: =$AA15*AL$1 -> 320 | AM15: =$AA15*AM$1 -> 320 | AN15: =$AA15*AN$1 -> 260 | ... AR15: =$AA15*AR$1 -> 280
B16: 29014 | C16: GA Laserstudio, Celal Altintas; Wuppertal | D16: =VLOOKUP($B16, 'Performance Data'!$B:$K, 3, 0) -> Germany | E16: =VLOOKUP($B16, 'Performance Data'!$B:$K, 4, 0) -> NRW | F16: =VLOOKUP($B16, 'Performance Data'!$B:$K, 6, 0) -> Institutes / Clinic | G16: =VLOOKUP($B16, 'Performance Data'!$B:$K, 10, 0) -> 2024 | H16: Yes | I16: =VLOOKUP($B16, 'Performance Data'!$B:$K, 7, 0) -> NKD24 | J16: =P16 -> 3204.16 | K16: 4000 | M16: Maintain | O16: =SUMIF('Performance Data'!$B:$B, $B16,'Performance Data'!N:N) -> 9263.29 | P16: =SUMIF('Performance Data'!$B:$B, $B16,'Performance Data'!O:O) -> 3204.16 | Q16: =SUMIF('Performance Data'!$B:$B, $B16,'Performance Data'!P:P) -> 9855 | S16: =$P16/O16-1 -> -0.6541013 | T16: =P16/Q16-1 -> -0.67486961 | V16: =SUMIF('Performance Data'!$B:$B, $B16,'Performance Data'!AC:AC) -> 0 | W16: =SUMIF('Performance Data'!$B:$B, $B16,'Performance Data'!AD:AD) -> 0 | X16: =SUMIF('Performance Data'!$B:$B, $B16,'Performance Data'!AE:AE) -> 9263.29 | Y16: =SUMIF('Performance Data'!$B:$B, $B16,'Performance Data'!AG:AG) -> 13500 | Z16: =P16 -> 3204.16 | AA16: =K16 -> 4000 | AC16: =Z16/X16-1 -> -0.6541013 | AD16: =Z16/Y16-1 -> -0.76265481 | AE16: =AA16/Z16-1 -> 0.24837711 | AG16: =$AA16*AG$1 -> 280 | AH16: =$AA16*AH$1 -> 320 | AI16: =$AA16*AI$1 -> 400 | AJ16: =$AA16*AJ$1 -> 340 | AK16: =$AA16*AK$1 -> 360 | AL16: =$AA16*AL$1 -> 320 | AM16: =$AA16*AM$1 -> 320 | AN16: =$AA16*AN$1 -> 260 | ... AR16: =$AA16*AR$1 -> 280
B17: 20982 | C17: Suyas Beauty; Melissa Arisoy | D17: =VLOOKUP($B17, 'Performance Data'!$B:$K, 3, 0) -> Germany | E17: =VLOOKUP($B17, 'Performance Data'!$B:$K, 4, 0) -> NRW | F17: =VLOOKUP($B17, 'Performance Data'!$B:$K, 6, 0) -> Institutes / Clinic | G17: =VLOOKUP($B17, 'Performance Data'!$B:$K, 10, 0) -> 2023 | H17: Yes | I17: =VLOOKUP($B17, 'Performance Data'!$B:$K, 7, 0) -> CC | J17: =P17 -> 3065.56 | K17: 4000 | M17: Maintain | O17: =SUMIF('Performance Data'!$B:$B, $B17,'Performance Data'!N:N) -> 4962.17 | P17: =SUMIF('Performance Data'!$B:$B, $B17,'Performance Data'!O:O) -> 3065.56 | Q17: =SUMIF('Performance Data'!$B:$B, $B17,'Performance Data'!P:P) -> 3650 | S17: =$P17/O17-1 -> -0.38221383 | T17: =P17/Q17-1 -> -0.16012055 | V17: =SUMIF('Performance Data'!$B:$B, $B17,'Performance Data'!AC:AC) -> 0 | W17: =SUMIF('Performance Data'!$B:$B, $B17,'Performance Data'!AD:AD) -> 6363.03 | X17: =SUMIF('Performance Data'!$B:$B, $B17,'Performance Data'!AE:AE) -> 4962.17 | Y17: =SUMIF('Performance Data'!$B:$B, $B17,'Performance Data'!AG:AG) -> 5000 | Z17: =P17 -> 3065.56 | AA17: =K17 -> 4000 | AC17: =Z17/X17-1 -> -0.38221383 | AD17: =Z17/Y17-1 -> -0.386888 | AE17: =AA17/Z17-1 -> 0.3048187 | AG17: =$AA17*AG$1 -> 280 | AH17: =$AA17*AH$1 -> 320 | AI17: =$AA17*AI$1 -> 400 | AJ17: =$AA17*AJ$1 -> 340 | AK17: =$AA17*AK$1 -> 360 | AL17: =$AA17*AL$1 -> 320 | AM17: =$AA17*AM$1 -> 320 | AN17: =$AA17*AN$1 -> 260 | ... AR17: =$AA17*AR$1 -> 280
B18: 20517 | C18: Marita Hess | D18: =VLOOKUP($B18, 'Performance Data'!$B:$K, 3, 0) -> Germany | E18: =VLOOKUP($B18, 'Performance Data'!$B:$K, 4, 0) -> NRW | F18: =VLOOKUP($B18, 'Performance Data'!$B:$K, 6, 0) -> Institutes / Clinic | G18: =VLOOKUP($B18, 'Performance Data'!$B:$K, 10, 0) -> Pre-2022 | H18: Yes | I18: =VLOOKUP($B18, 'Performance Data'!$B:$K, 7, 0) -> BC | J18: =P18 -> 2992.04 | K18: 4000 | M18: Lose | O18: =SUMIF('Performance Data'!$B:$B, $B18,'Performance Data'!N:N) -> 5244.15 | P18: =SUMIF('Performance Data'!$B:$B, $B18,'Performance Data'!O:O) -> 2992.04 | Q18: =SUMIF('Performance Data'!$B:$B, $B18,'Performance Data'!P:P) -> 4380 | S18: =$P18/O18-1 -> -0.42945187 | T18: =P18/Q18-1 -> -0.31688584 | V18: =SUMIF('Performance Data'!$B:$B, $B18,'Performance Data'!AC:AC) -> 3666.64 | W18: =SUMIF('Performance Data'!$B:$B, $B18,'Performance Data'!AD:AD) -> 4654.11 | X18: =SUMIF('Performance Data'!$B:$B, $B18,'Performance Data'!AE:AE) -> 5244.15 | Y18: =SUMIF('Performance Data'!$B:$B, $B18,'Performance Data'!AG:AG) -> 6000 | Z18: =P18 -> 2992.04 | AA18: =K18 -> 4000 | AC18: =Z18/X18-1 -> -0.42945187 | AD18: =Z18/Y18-1 -> -0.50132667 | AE18: =AA18/Z18-1 -> 0.33688052 | AG18: =$AA18*AG$1 -> 280 | AH18: =$AA18*AH$1 -> 320 | AI18: =$AA18*AI$1 -> 400 | AJ18: =$AA18*AJ$1 -> 340 | AK18: =$AA18*AK$1 -> 360 | AL18: =$AA18*AL$1 -> 320 | AM18: =$AA18*AM$1 -> 320 | AN18: =$AA18*AN$1 -> 260 | ... AR18: =$AA18*AR$1 -> 280
B19: 20007 | C19: Birgit Kraft | D19: =VLOOKUP($B19, 'Performance Data'!$B:$K, 3, 0) -> Germany | E19: =VLOOKUP($B19, 'Performance Data'!$B:$K, 4, 0) -> NRW | F19: =VLOOKUP($B19, 'Performance Data'!$B:$K, 6, 0) -> Perfumery | G19: =VLOOKUP($B19, 'Performance Data'!$B:$K, 10, 0) -> Pre-2022 | H19: Yes | I19: =VLOOKUP($B19, 'Performance Data'!$B:$K, 7, 0) -> CC | J19: =P19 -> 2965.71 | K19: 4000 | M19: Lose | O19: =SUMIF('Performance Data'!$B:$B, $B19,'Performance Data'!N:N) -> 4504.97 | P19: =SUMIF('Performance Data'!$B:$B, $B19,'Performance Data'!O:O) -> 2965.71 | Q19: =SUMIF('Performance Data'!$B:$B, $B19,'Performance Data'!P:P) -> 3650 | S19: =$P19/O19-1 -> -0.34168041 | T19: =P19/Q19-1 -> -0.18747671 | V19: =SUMIF('Performance Data'!$B:$B, $B19,'Performance Data'!AC:AC) -> 2938.51 | W19: =SUMIF('Performance Data'!$B:$B, $B19,'Performance Data'!AD:AD) -> 4350.81 | X19: =SUMIF('Performance Data'!$B:$B, $B19,'Performance Data'!AE:AE) -> 4504.97 | Y19: =SUMIF('Performance Data'!$B:$B, $B19,'Performance Data'!AG:AG) -> 5000 | Z19: =P19 -> 2965.71 | AA19: =K19 -> 4000 | AC19: =Z19/X19-1 -> -0.34168041 | AD19: =Z19/Y19-1 -> -0.406858 | AE19: =AA19/Z19-1 -> 0.34874954 | AG19: =$AA19*AG$1 -> 280 | AH19: =$AA19*AH$1 -> 320 | AI19: =$AA19*AI$1 -> 400 | AJ19: =$AA19*AJ$1 -> 340 | AK19: =$AA19*AK$1 -> 360 | AL19: =$AA19*AL$1 -> 320 | AM19: =$AA19*AM$1 -> 320 | AN19: =$AA19*AN$1 -> 260 | ... AR19: =$AA19*AR$1 -> 280
B20: 29016 | C20: Bellessa-Academy, Elke Single | D20: =VLOOKUP($B20, 'Performance Data'!$B:$K, 3, 0) -> Germany | E20: North | F20: =VLOOKUP($B20, 'Performance Data'!$B:$K, 6, 0) -> Institutes / Clinic | G20: =VLOOKUP($B20, 'Performance Data'!$B:$K, 10, 0) -> 2024 | H20: Yes | I20: =VLOOKUP($B20, 'Performance Data'!$B:$K, 7, 0) -> NKD24 | J20: =P20 -> 1483.61 | K20: 3000 | M20: Maintain | O20: =SUMIF('Performance Data'!$B:$B, $B20,'Performance Data'!N:N) -> 8910.89 | P20: =SUMIF('Performance Data'!$B:$B, $B20,'Performance Data'!O:O) -> 1483.61 | Q20: =SUMIF('Performance Data'!$B:$B, $B20,'Performance Data'!P:P) -> 9490 | S20: =$P20/O20-1 -> -0.83350597 | T20: =P20/Q20-1 -> -0.84366596 | V20: =SUMIF('Performance Data'!$B:$B, $B20,'Performance Data'!AC:AC) -> 0 | W20: =SUMIF('Performance Data'!$B:$B, $B20,'Performance Data'!AD:AD) -> 0 | X20: =SUMIF('Performance Data'!$B:$B, $B20,'Performance Data'!AE:AE) -> 8910.89 | Y20: =SUMIF('Performance Data'!$B:$B, $B20,'Performance Data'!AG:AG) -> 13000 | Z20: =P20 -> 1483.61 | AA20: =K20 -> 3000 | AC20: =Z20/X20-1 -> -0.83350597 | AD20: =Z20/Y20-1 -> -0.88587615 | AE20: =AA20/Z20-1 -> 1.0220948 | AG20: =$AA20*AG$1 -> 210 | AH20: =$AA20*AH$1 -> 240 | AI20: =$AA20*AI$1 -> 300 | AJ20: =$AA20*AJ$1 -> 255 | AK20: =$AA20*AK$1 -> 270 | AL20: =$AA20*AL$1 -> 240 | AM20: =$AA20*AM$1 -> 240 | AN20: =$AA20*AN$1 -> 195 | ... AR20: =$AA20*AR$1 -> 210
B21: 20934 | C21: Ästhetik Lounge; Alexandra Holmstoel-Müller | D21: =VLOOKUP($B21, 'Performance Data'!$B:$K, 3, 0) -> Germany | E21: =VLOOKUP($B21, 'Performance Data'!$B:$K, 4, 0) -> NRW | F21: =VLOOKUP($B21, 'Performance Data'!$B:$K, 6, 0) -> 0 | G21: =VLOOKUP($B21, 'Performance Data'!$B:$K, 10, 0) -> Pre-2022 | H21: Yes | I21: =VLOOKUP($B21, 'Performance Data'!$B:$K, 7, 0) -> CB | J21: =P21 -> 665.66 | K21: 1500 | M21: Lose | O21: =SUMIF('Performance Data'!$B:$B, $B21,'Performance Data'!N:N) -> 2996.91 | P21: =SUMIF('Performance Data'!$B:$B, $B21,'Performance Data'!O:O) -> 665.66 | Q21: =SUMIF('Performance Data'!$B:$B, $B21,'Performance Data'!P:P) -> 2190 | S21: =$P21/O21-1 -> -0.77788455 | T21: =P21/Q21-1 -> -0.69604566 | V21: =SUMIF('Performance Data'!$B:$B, $B21,'Performance Data'!AC:AC) -> 12205.03 | W21: =SUMIF('Performance Data'!$B:$B, $B21,'Performance Data'!AD:AD) -> 16139.25 | X21: =SUMIF('Performance Data'!$B:$B, $B21,'Performance Data'!AE:AE) -> 2996.91 | Y21: =SUMIF('Performance Data'!$B:$B, $B21,'Performance Data'!AG:AG) -> 3000 | Z21: =P21 -> 665.66 | AA21: =K21 -> 1500 | AC21: =Z21/X21-1 -> -0.77788455 | AD21: =Z21/Y21-1 -> -0.77811333 | AE21: =AA21/Z21-1 -> 1.2534026 | AG21: =$AA21*AG$1 -> 105 | AH21: =$AA21*AH$1 -> 120 | AI21: =$AA21*AI$1 -> 150 | AJ21: =$AA21*AJ$1 -> 127.5 | AK21: =$AA21*AK$1 -> 135 | AL21: =$AA21*AL$1 -> 120 | AM21: =$AA21*AM$1 -> 120 | AN21: =$AA21*AN$1 -> 97.5 | ... AR21: =$AA21*AR$1 -> 105
B22: 20845 | C22: Cornelia Wielgosch | D22: =VLOOKUP($B22, 'Performance Data'!$B:$K, 3, 0) -> Germany | E22: =VLOOKUP($B22, 'Performance Data'!$B:$K, 4, 0) -> NRW | F22: =VLOOKUP($B22, 'Performance Data'!$B:$K, 6, 0) -> Institutes / Clinic | G22: =VLOOKUP($B22, 'Performance Data'!$B:$K, 10, 0) -> Pre-2022 | H22: Yes | I22: =VLOOKUP($B22, 'Performance Data'!$B:$K, 7, 0) -> CC | J22: =P22 -> 1426.05 | K22: 3000 | M22: Lose | O22: =SUMIF('Performance Data'!$B:$B, $B22,'Performance Data'!N:N) -> 3755.45 | P22: =SUMIF('Performance Data'!$B:$B, $B22,'Performance Data'!O:O) -> 1426.05 | Q22: =SUMIF('Performance Data'!$B:$B, $B22,'Performance Data'!P:P) -> 2920 | S22: =$P22/O22-1 -> -0.62027187 | T22: =P22/Q22-1 -> -0.51162671 | V22: =SUMIF('Performance Data'!$B:$B, $B22,'Performance Data'!AC:AC) -> 7100.18 | W22: =SUMIF('Performance Data'!$B:$B, $B22,'Performance Data'!AD:AD) -> 4493.3 | X22: =SUMIF('Performance Data'!$B:$B, $B22,'Performance Data'!AE:AE) -> 3755.45 | Y22: =SUMIF('Performance Data'!$B:$B, $B22,'Performance Data'!AG:AG) -> 4000 | Z22: =P22 -> 1426.05 | AA22: =K22 -> 3000 | AC22: =Z22/X22-1 -> -0.62027187 | AD22: =Z22/Y22-1 -> -0.6434875 | AE22: =AA22/Z22-1 -> 1.1037131 | AG22: =$AA22*AG$1 -> 210 | AH22: =$AA22*AH$1 -> 240 | AI22: =$AA22*AI$1 -> 300 | AJ22: =$AA22*AJ$1 -> 255 | AK22: =$AA22*AK$1 -> 270 | AL22: =$AA22*AL$1 -> 240 | AM22: =$AA22*AM$1 -> 240 | AN22: =$AA22*AN$1 -> 195 | ... AR22: =$AA22*AR$1 -> 210
B23: Total Active Existing Doors | J23: =SUM(J3:J22) -> 106051.16 | K23: =SUM(K3:K22) -> 131694.96 | O23: =SUMIF('Performance Data'!$B:$B, $B23,'Performance Data'!N:N) -> 0 | P23: =SUMIF('Performance Data'!$B:$B, $B23,'Performance Data'!O:O) -> 0 | Q23: =SUMIF('Performance Data'!$B:$B, $B23,'Performance Data'!P:P) -> 0 | S23: =$P23/O23-1 -> #DIV/0! | T23: =P23/Q23-1 -> #DIV/0! | V23: =SUM(V3:V22) -> 108561.17 | W23: =SUM(W3:W22) -> 146016.77 | X23: =SUM(X3:X22) -> 144120.97 | Y23: =SUM(Y3:Y22) -> 155000 | Z23: =SUM(Z3:Z22) -> 106051.16 | AA23: =SUM(AA3:AA22) -> 131694.96 | AC23: =Z23/X23-1 -> -0.26415177 | AD23: =Z23/Y23-1 -> -0.31579897 | AE23: =AA23/Z23-1 -> 0.24180597 | AG23: =SUM(AG3:AG22) -> 9218.6475 | AH23: =SUM(AH3:AH22) -> 10535.597 | AI23: =SUM(AI3:AI22) -> 13169.496 | AJ23: =SUM(AJ3:AJ22) -> 11194.072 | AK23: =SUM(AK3:AK22) -> 11852.547 | AL23: =SUM(AL3:AL22) -> 10535.597 | AM23: =SUM(AM3:AM22) -> 10535.597 | AN23: =SUM(AN3:AN22) -> 8560.1727 | ... AR23: =SUM(AR3:AR22) -> 9218.6475
B27: 20668 | C27: Gregor von Wirth | D27: =VLOOKUP($B27, 'Performance Data'!$B:$K, 3, 0) -> Germany | E27: =VLOOKUP($B27, 'Performance Data'!$B:$K, 4, 0) -> NRW | F27: =VLOOKUP($B27, 'Performance Data'!$B:$K, 6, 0) -> eTailer | G27: =VLOOKUP($B27, 'Performance Data'!$B:$K, 10, 0) -> 2025 | I27: =VLOOKUP($B27, 'Performance Data'!$B:$K, 7, 0) -> NKD25 | J27: =P27 -> 21976.88 | K27: =J27*1.08 -> 23735.03 | M27: Grow | O27: =SUMIF('Performance Data'!$B:$B, $B27,'Performance Data'!N:N) -> 0 | P27: =SUMIF('Performance Data'!$B:$B, $B27,'Performance Data'!O:O) -> 21976.88 | Q27: =SUMIF('Performance Data'!$B:$B, $B27,'Performance Data'!P:P) -> 0 | S27: =$P27/O27-1 -> #DIV/0! | T27: =P27/Q27-1 -> #DIV/0! | V27: =SUMIF('Performance Data'!$B:$B, $B27,'Performance Data'!AC:AC) -> 0 | W27: =SUMIF('Performance Data'!$B:$B, $B27,'Performance Data'!AD:AD) -> 0 | X27: =SUMIF('Performance Data'!$B:$B, $B27,'Performance Data'!AE:AE) -> 0 | Y27: =SUMIF('Performance Data'!$B:$B, $B27,'Performance Data'!AG:AG) -> 0 | Z27: =P27 -> 21976.88 | AA27: =K27 -> 23735.03 | AC27: =Z27/X27-1 -> #DIV/0! | AD27: =Z27/Y27-1 -> #DIV/0! | AE27: =AA27/Z27-1 -> 0.08 | AG27: =$AA27*AG$1 -> 1661.4521 | AH27: =$AA27*AH$1 -> 1898.8024 | AI27: =$AA27*AI$1 -> 2373.503 | AJ27: =$AA27*AJ$1 -> 2017.4776 | AK27: =$AA27*AK$1 -> 2136.1527 | AL27: =$AA27*AL$1 -> 1898.8024 | AM27: =$AA27*AM$1 -> 1898.8024 | AN27: =$AA27*AN$1 -> 1542.777 | ... AR27: =$AA27*AR$1 -> 1661.4521
B28: 29029 | C28: Beauty Space; Shareen Idu | D28: =VLOOKUP($B28, 'Performance Data'!$B:$K, 3, 0) -> Germany | E28: =VLOOKUP($B28, 'Performance Data'!$B:$K, 4, 0) -> NRW | F28: =VLOOKUP($B28, 'Performance Data'!$B:$K, 6, 0) -> Institutes / Clinic | G28: =VLOOKUP($B28, 'Performance Data'!$B:$K, 10, 0) -> 2025 | I28: =VLOOKUP($B28, 'Performance Data'!$B:$K, 7, 0) -> NKD25 | J28: =P28 -> 391.07 | K28: 2500 | M28: Grow | O28: =SUMIF('Performance Data'!$B:$B, $B28,'Performance Data'!N:N) -> 0 | P28: =SUMIF('Performance Data'!$B:$B, $B28,'Performance Data'!O:O) -> 391.07 | Q28: =SUMIF('Performance Data'!$B:$B, $B28,'Performance Data'!P:P) -> 0 | S28: =$P28/O28-1 -> #DIV/0! | T28: =P28/Q28-1 -> #DIV/0! | V28: =SUMIF('Performance Data'!$B:$B, $B28,'Performance Data'!AC:AC) -> 0 | W28: =SUMIF('Performance Data'!$B:$B, $B28,'Performance Data'!AD:AD) -> 0 | X28: =SUMIF('Performance Data'!$B:$B, $B28,'Performance Data'!AE:AE) -> 0 | Y28: =SUMIF('Performance Data'!$B:$B, $B28,'Performance Data'!AG:AG) -> 0 | Z28: =P28 -> 391.07 | AA28: =K28 -> 2500 | AC28: =Z28/X28-1 -> #DIV/0! | AD28: =Z28/Y28-1 -> #DIV/0! | AE28: =AA28/Z28-1 -> 5.3927174 | AG28: =$AA28*AG$1 -> 175 | AH28: =$AA28*AH$1 -> 200 | AI28: =$AA28*AI$1 -> 250 | AJ28: =$AA28*AJ$1 -> 212.5 | AK28: =$AA28*AK$1 -> 225 | AL28: =$AA28*AL$1 -> 200 | AM28: =$AA28*AM$1 -> 200 | AN28: =$AA28*AN$1 -> 162.5 | ... AR28: =$AA28*AR$1 -> 175
B29: NKD25_MP | C29: New doors 2025 | D29: Germany | E29: NRW | G29: 2025 | H29: 0 | I29: NKD25 | J29: 0 | K29: 0 | O29: 0 | P29: 0 | Q29: =SUMIF('Combined Budget 2025 EUR'!$B:$B, $B29,'Combined Budget 2025 EUR'!$AL:$AL) -> 11250 | S29: =$P29/O29-1 -> #DIV/0! | T29: =P29/Q29-1 -> -1 | V29: 0 | W29: 0 | X29: 0 | Y29: =SUMIF('Combined Budget 2025 EUR'!$B:$B, $B29,'Combined Budget 2025 EUR'!$AQ:$AQ) -> 30000 | Z29: =J29 -> 0 | AA29: =K29 -> 0 | AC29: =Z29/X29-1 -> #DIV/0! | AD29: =Z29/Y29-1 -> -1 | AE29: =AA29/Z29-1 -> #DIV/0! | AG29: =$AA29*AG$1 -> 0 | AH29: =$AA29*AH$1 -> 0 | AI29: =$AA29*AI$1 -> 0 | AJ29: =$AA29*AJ$1 -> 0 | AK29: =$AA29*AK$1 -> 0 | AL29: =$AA29*AL$1 -> 0 | AM29: =$AA29*AM$1 -> 0 | AN29: =$AA29*AN$1 -> 0 | ... AR29: =$AA29*AR$1 -> 0
B31: Total New Doors 2025 | H31: =COUNTIF(H27:H28, "Yes")+H29 -> 0 | J31: =SUM(J27:J29) -> 22367.95 | K31: =SUM(K27:K29) -> 26235.03 | O31: =SUM(O27:O29) -> 0 | P31: =SUM(P27:P29) -> 22367.95 | Q31: =SUM(Q27:Q29) -> 11250 | S31: =$P31/O31-1 -> #DIV/0! | T31: =P31/Q31-1 -> 0.98826222 | V31: =SUM(V27:V29) -> 0 | W31: =SUM(W27:W29) -> 0 | X31: =SUM(X27:X29) -> 0 | Y31: =SUM(Y27:Y29) -> 30000 | Z31: =SUM(Z27:Z29) -> 22367.95 | AA31: =SUM(AA27:AA29) -> 26235.03 | AC31: =Z31/X31-1 -> #DIV/0! | AD31: =Z31/Y31-1 -> -0.25440167 | AE31: =AA31/Z31-1 -> 0.17288488 | AG31: =SUM(AG27:AG29) -> 1836.4521 | AH31: =SUM(AH27:AH29) -> 2098.8024 | AI31: =SUM(AI27:AI29) -> 2623.503 | AJ31: =SUM(AJ27:AJ29) -> 2229.9776 | AK31: =SUM(AK27:AK29) -> 2361.1527 | AL31: =SUM(AL27:AL29) -> 2098.8024 | AM31: =SUM(AM27:AM29) -> 2098.8024 | AN31: =SUM(AN27:AN29) -> 1705.277 | ... AR31: =SUM(AR27:AR29) -> 1836.4521
B33: Global Target existing and new doors 2025 | AG33: {=AG23:AR23+AG31:AR31} -> 11055.1 | AH33: 12634.4 | AI33: 15792.999 | AJ33: 13424.05 | AK33: 14213.699 | AL33: 12634.4 | AM33: 12634.4 | AN33: 10265.45 | AO33: 15003.349 | AP33: 15792.999 | AQ33: 13424.05 | AR33: 11055.1
AY34: =AV35 -> 1 | AZ34: =AW35 -> 0 | BA34: =AX35+AV35 -> 2 | BB34: =AY35+AW35 -> 0 | BC34: =AZ35+AX35+AV35 -> 2 | BD34: =BA35+AY35+AW35 -> 1 | BE34: =BB35+AZ35+AX35+AV35 -> 2 | BF34: =BC35+BA35+AY35+AW35 -> 2
B35: NKD26_MP | C35: New doors 2026 | D35: Germany | E35: NRW | G35: 2026 | H35: 5 | I35: NKD26 | K35: 35000 | O35: 0 | P35: 0 | Q35: 0 | S35: =$P35/O35-1 -> #DIV/0! | T35: =P35/Q35-1 -> #DIV/0! | V35: 0 | W35: 0 | X35: 0 | Y35: 0 | Z35: =J35 -> 0 | AA35: =K35 -> 35000 | AC35: =Z35/X35-1 -> #DIV/0! | AD35: =Z35/Y35-1 -> #DIV/0! | AE35: =AA35/Z35-1 -> #DIV/0! | AG35: =AU35*4000+AU34*3000 -> 0 | AH35: 3000 | AI35: 3000 | AJ35: 3000 | AK35: 3000 | AL35: 3000 | AM35: 3000 | AN35: 2000 | AO35: 4000 | AP35: 4000 | AQ35: 4000 | AR35: 3000 | AV35: 1 | AX35: 1 | BA35: 1 | BC35: 1 | BE35: 1
B37: Total New Doors 2026 | H37: =COUNTIF(H34:H34, "Yes")+H35 -> 5 | J37: =SUM(J34:J35) -> 0 | K37: =SUM(K34:K35) -> 35000 | O37: =SUM(O34:O35) -> 0 | P37: =SUM(P34:P35) -> 0 | Q37: =SUM(Q34:Q35) -> 0 | S37: =$P37/O37-1 -> #DIV/0! | T37: =P37/Q37-1 -> #DIV/0! | V37: =SUM(V34:V35) -> 0 | W37: =SUM(W34:W35) -> 0 | X37: =SUM(X34:X35) -> 0 | Y37: =SUM(Y34:Y35) -> 0 | Z37: =SUM(Z34:Z35) -> 0 | AA37: =SUM(AA34:AA35) -> 35000 | AC37: =Z37/X37-1 -> #DIV/0! | AD37: =Z37/Y37-1 -> #DIV/0! | AE37: =AA37/Z37-1 -> #DIV/0! | AG37: =SUM(AG34:AG35) -> 0 | AH37: =SUM(AH34:AH35) -> 3000 | AI37: =SUM(AI34:AI35) -> 3000 | AJ37: =SUM(AJ34:AJ35) -> 3000 | AK37: =SUM(AK34:AK35) -> 3000 | AL37: =SUM(AL34:AL35) -> 3000 | AM37: =SUM(AM34:AM35) -> 3000 | AN37: =SUM(AN34:AN35) -> 2000 | ... AR37: =SUM(AR34:AR35) -> 3000

Sheet North
O1: Year to date | P1: Year to date | Q1: Year to date | S1: Year to date | T1: Year to date | V1: Full year | W1: Full year | X1: Full year | Y1: Full year | Z1: Full year | AA1: Full year | AC1: Full year | AD1: Full year | AE1: Full year | AG1: 0.07 | AH1: 0.08 | AI1: 0.1 | AJ1: 0.085 | AK1: 0.09 | AL1: 0.08 | AM1: 0.08 | AN1: 0.065 | AO1: 0.095 | AP1: 0.1 | AQ1: 0.085 | AR1: 0.07
B2: Customer Code | C2: Customer Name | D2: Country | E2: Region | F2: Customer Map | G2: New door year | H2: Active? | I2: 2025 Cluster | J2: 2025A | K2: 2026B | L2: Size indicator | M2: Customer Growth Class | O2: 2024 YTD | P2: 2025 YTD | Q2: 2025B YTD | S2: 25 vs 24 % | T2: 25 vs 25B % | V2: 2022 | W2: 2023 | X2: 2024 | Y2: 2025B | Z2: 2025A | AA2: 2026B | AC2: 25 vs 24 % | AD2: 25 vs 25B % | AE2: 26B vs 25F % | AG2: 46023 | AH2: 46054 | AI2: 46082 | AJ2: 46113 | AK2: 46143 | AL2: 46174 | AM2: 46204 | AN2: 46235 | AO2: 46266 | AP2: 46296 | AQ2: 46327 | AR2: 46357 | AU2: 46023 | AV2: 46054 | AW2: 46082 | AX2: 46113 | AY2: 46143 | AZ2: 46174 | BA2: 46204 | BB2: 46235 | BC2: 46266 | BD2: 46296 | BE2: 46327 | BF2: 46357
B3: 20097 | C3: Heidi Sönksen | D3: =VLOOKUP($B3, 'Performance Data'!$B:$K, 3, 0) -> Germany | E3: North | F3: =VLOOKUP($B3, 'Performance Data'!$B:$K, 6, 0) -> Institutes / Clinic | G3: =VLOOKUP($B3, 'Performance Data'!$B:$K, 10, 0) -> Pre-2022 | I3: =VLOOKUP($B3, 'Performance Data'!$B:$K, 7, 0) -> AA | J3: =Z3 -> 27253.64 | K3: =J3*1.07 -> 29161.395 | M3: Maintain | O3: =SUMIF('Performance Data'!$B:$B, $B3,'Performance Data'!N:N) -> 40302.77 | P3: =SUMIF('Performance Data'!$B:$B, $B3,'Performance Data'!O:O) -> 27253.64 | Q3: =SUMIF('Performance Data'!$B:$B, $B3,'Performance Data'!P:P) -> 31390 | S3: =$P3/O3-1 -> -0.3237775 | T3: =P3/Q3-1 -> -0.13177318 | V3: =SUMIF('Performance Data'!$B:$B, $B3,'Performance Data'!AC:AC) -> 19794.82 | W3: =SUMIF('Performance Data'!$B:$B, $B3,'Performance Data'!AD:AD) -> 27422.97 | X3: =SUMIF('Performance Data'!$B:$B, $B3,'Performance Data'!AE:AE) -> 40302.77 | Y3: =SUMIF('Performance Data'!$B:$B, $B3,'Performance Data'!AG:AG) -> 43000 | Z3: =P3 -> 27253.64 | AA3: =K3 -> 29161.395 | AC3: =Z3/X3-1 -> -0.3237775 | AD3: =Z3/Y3-1 -> -0.36619442 | AE3: =AA3/Z3-1 -> 0.07 | AG3: =$AA3*AG$1 -> 2041.2976 | AH3: =$AA3*AH$1 -> 2332.9116 | AI3: =$AA3*AI$1 -> 2916.1395 | AJ3: =$AA3*AJ$1 -> 2478.7186 | AK3: =$AA3*AK$1 -> 2624.5255 | AL3: =$AA3*AL$1 -> 2332.9116 | AM3: =$AA3*AM$1 -> 2332.9116 | AN3: =$AA3*AN$1 -> 1895.4907 | ... AR3: =$AA3*AR$1 -> 2041.2976
B4: 20263 | C4: Brigitte Preikschat | D4: =VLOOKUP($B4, 'Performance Data'!$B:$K, 3, 0) -> Germany | E4: North | F4: =VLOOKUP($B4, 'Performance Data'!$B:$K, 6, 0) -> Institutes / Clinic | G4: =VLOOKUP($B4, 'Performance Data'!$B:$K, 10, 0) -> Pre-2022 | I4: =VLOOKUP($B4, 'Performance Data'!$B:$K, 7, 0) -> AA | J4: =Z4 -> 40802.74 | K4: =J4*1.07 -> 43658.932 | M4: Grow | O4: =SUMIF('Performance Data'!$B:$B, $B4,'Performance Data'!N:N) -> 33641.2 | P4: =SUMIF('Performance Data'!$B:$B, $B4,'Performance Data'!O:O) -> 40802.74 | Q4: =SUMIF('Performance Data'!$B:$B, $B4,'Performance Data'!P:P) -> 26280 | S4: =$P4/O4-1 -> 0.21288004 | T4: =P4/Q4-1 -> 0.55261568 | V4: =SUMIF('Performance Data'!$B:$B, $B4,'Performance Data'!AC:AC) -> 26648.24 | W4: =SUMIF('Performance Data'!$B:$B, $B4,'Performance Data'!AD:AD) -> 29316.99 | X4: =SUMIF('Performance Data'!$B:$B, $B4,'Performance Data'!AE:AE) -> 33641.2 | Y4: =SUMIF('Performance Data'!$B:$B, $B4,'Performance Data'!AG:AG) -> 36000 | Z4: =P4 -> 40802.74 | AA4: =K4 -> 43658.932 | AC4: =Z4/X4-1 -> 0.21288004 | AD4: =Z4/Y4-1 -> 0.13340944 | AE4: =AA4/Z4-1 -> 0.07 | AG4: =$AA4*AG$1 -> 3056.1252 | AH4: =$AA4*AH$1 -> 3492.7145 | AI4: =$AA4*AI$1 -> 4365.8932 | AJ4: =$AA4*AJ$1 -> 3711.0092 | AK4: =$AA4*AK$1 -> 3929.3039 | AL4: =$AA4*AL$1 -> 3492.7145 | AM4: =$AA4*AM$1 -> 3492.7145 | AN4: =$AA4*AN$1 -> 2837.8306 | ... AR4: =$AA4*AR$1 -> 3056.1252
B5: 20266 | C5: Frauke Hinz | D5: =VLOOKUP($B5, 'Performance Data'!$B:$K, 3, 0) -> Germany | E5: North | F5: =VLOOKUP($B5, 'Performance Data'!$B:$K, 6, 0) -> Institutes / Clinic | G5: =VLOOKUP($B5, 'Performance Data'!$B:$K, 10, 0) -> Pre-2022 | I5: =VLOOKUP($B5, 'Performance Data'!$B:$K, 7, 0) -> AA | J5: =Z5 -> 61046.21 | K5: =J5*1.07 -> 65319.445 | M5: Maintain | O5: =SUMIF('Performance Data'!$B:$B, $B5,'Performance Data'!N:N) -> 60289.61 | P5: =SUMIF('Performance Data'!$B:$B, $B5,'Performance Data'!O:O) -> 61046.21 | Q5: =SUMIF('Performance Data'!$B:$B, $B5,'Performance Data'!P:P) -> 46720 | S5: =$P5/O5-1 -> 0.012549426 | T5: =P5/Q5-1 -> 0.30663977 | V5: =SUMIF('Performance Data'!$B:$B, $B5,'Performance Data'!AC:AC) -> 36178.74 | W5: =SUMIF('Performance Data'!$B:$B, $B5,'Performance Data'!AD:AD) -> 46826.3 | X5: =SUMIF('Performance Data'!$B:$B, $B5,'Performance Data'!AE:AE) -> 60289.61 | Y5: =SUMIF('Performance Data'!$B:$B, $B5,'Performance Data'!AG:AG) -> 64000 | Z5: =P5 -> 61046.21 | AA5: =K5 -> 65319.445 | AC5: =Z5/X5-1 -> 0.012549426 | AD5: =Z5/Y5-1 -> -0.046152969 | AE5: =AA5/Z5-1 -> 0.07 | AG5: =$AA5*AG$1 -> 4572.3611 | AH5: =$AA5*AH$1 -> 5225.5556 | AI5: =$AA5*AI$1 -> 6531.9445 | AJ5: =$AA5*AJ$1 -> 5552.1528 | AK5: =$AA5*AK$1 -> 5878.75 | AL5: =$AA5*AL$1 -> 5225.5556 | AM5: =$AA5*AM$1 -> 5225.5556 | AN5: =$AA5*AN$1 -> 4245.7639 | ... AR5: =$AA5*AR$1 -> 4572.3611
B6: 20598 | C6: Parfümerie Schuback GmbH | D6: =VLOOKUP($B6, 'Performance Data'!$B:$K, 3, 0) -> Germany | E6: North | F6: =VLOOKUP($B6, 'Performance Data'!$B:$K, 6, 0) -> Institutes / Clinic | G6: =VLOOKUP($B6, 'Performance Data'!$B:$K, 10, 0) -> Pre-2022 | I6: =VLOOKUP($B6, 'Performance Data'!$B:$K, 7, 0) -> AA | J6: =Z6 -> 70864.57 | K6: =J6*1.07 -> 75825.09 | M6: Maintain | O6: =SUMIF('Performance Data'!$B:$B, $B6,'Performance Data'!N:N) -> 71215.66 | P6: =SUMIF('Performance Data'!$B:$B, $B6,'Performance Data'!O:O) -> 70864.57 | Q6: =SUMIF('Performance Data'!$B:$B, $B6,'Performance Data'!P:P) -> 51100 | S6: =$P6/O6-1 -> -0.004929955 | T6: =P6/Q6-1 -> 0.38678219 | V6: =SUMIF('Performance Data'!$B:$B, $B6,'Performance Data'!AC:AC) -> 53357.93 | W6: =SUMIF('Performance Data'!$B:$B, $B6,'Performance Data'!AD:AD) -> 58398.78 | X6: =SUMIF('Performance Data'!$B:$B, $B6,'Performance Data'!AE:AE) -> 71215.66 | Y6: =SUMIF('Performance Data'!$B:$B, $B6,'Performance Data'!AG:AG) -> 70000 | Z6: =P6 -> 70864.57 | AA6: =K6 -> 75825.09 | AC6: =Z6/X6-1 -> -0.004929955 | AD6: =Z6/Y6-1 -> 0.012351 | AE6: =AA6/Z6-1 -> 0.07 | AG6: =$AA6*AG$1 -> 5307.7563 | AH6: =$AA6*AH$1 -> 6066.0072 | AI6: =$AA6*AI$1 -> 7582.509 | AJ6: =$AA6*AJ$1 -> 6445.1326 | AK6: =$AA6*AK$1 -> 6824.2581 | AL6: =$AA6*AL$1 -> 6066.0072 | AM6: =$AA6*AM$1 -> 6066.0072 | AN6: =$AA6*AN$1 -> 4928.6308 | ... AR6: =$AA6*AR$1 -> 5307.7563
B7: 20674 | C7: Sonja Schreyer | D7: =VLOOKUP($B7, 'Performance Data'!$B:$K, 3, 0) -> Germany | E7: North | F7: =VLOOKUP($B7, 'Performance Data'!$B:$K, 6, 0) -> 0 | G7: =VLOOKUP($B7, 'Performance Data'!$B:$K, 10, 0) -> Pre-2022 | I7: =VLOOKUP($B7, 'Performance Data'!$B:$K, 7, 0) -> AA | J7: =Z7 -> 92430.47 | K7: =J7*1.05 -> 97051.994 | M7: Maintain | O7: =SUMIF('Performance Data'!$B:$B, $B7,'Performance Data'!N:N) -> 131844.97 | P7: =SUMIF('Performance Data'!$B:$B, $B7,'Performance Data'!O:O) -> 92430.47 | Q7: =SUMIF('Performance Data'!$B:$B, $B7,'Performance Data'!P:P) -> 102200 | S7: =$P7/O7-1 -> -0.2989458 | T7: =P7/Q7-1 -> -0.09559227 | V7: =SUMIF('Performance Data'!$B:$B, $B7,'Performance Data'!AC:AC) -> 133976.27 | W7: =SUMIF('Performance Data'!$B:$B, $B7,'Performance Data'!AD:AD) -> 134434.73 | X7: =SUMIF('Performance Data'!$B:$B, $B7,'Performance Data'!AE:AE) -> 131844.97 | Y7: =SUMIF('Performance Data'!$B:$B, $B7,'Performance Data'!AG:AG) -> 140000 | Z7: =P7 -> 92430.47 | AA7: =K7 -> 97051.994 | AC7: =Z7/X7-1 -> -0.2989458 | AD7: =Z7/Y7-1 -> -0.33978236 | AE7: =AA7/Z7-1 -> 0.05 | AG7: =$AA7*AG$1 -> 6793.6395 | AH7: =$AA7*AH$1 -> 7764.1595 | AI7: =$AA7*AI$1 -> 9705.1994 | AJ7: =$AA7*AJ$1 -> 8249.4194 | AK7: =$AA7*AK$1 -> 8734.6794 | AL7: =$AA7*AL$1 -> 7764.1595 | AM7: =$AA7*AM$1 -> 7764.1595 | AN7: =$AA7*AN$1 -> 6308.3796 | ... AR7: =$AA7*AR$1 -> 6793.6395
B8: 20933 | C8: Beautywelt; Pascal Zieglmeier | D8: =VLOOKUP($B8, 'Performance Data'!$B:$K, 3, 0) -> Germany | E8: North | F8: =VLOOKUP($B8, 'Performance Data'!$B:$K, 6, 0) -> Perfumery | G8: =VLOOKUP($B8, 'Performance Data'!$B:$K, 10, 0) -> Pre-2022 | I8: =VLOOKUP($B8, 'Performance Data'!$B:$K, 7, 0) -> AA | J8: =Z8 -> 28202.06 | K8: =J8*1.4 -> 39482.884 | M8: Maintain | O8: =SUMIF('Performance Data'!$B:$B, $B8,'Performance Data'!N:N) -> 100288.01 | P8: =SUMIF('Performance Data'!$B:$B, $B8,'Performance Data'!O:O) -> 28202.06 | Q8: =SUMIF('Performance Data'!$B:$B, $B8,'Performance Data'!P:P) -> 80300 | S8: =$P8/O8-1 -> -0.71878931 | T8: =P8/Q8-1 -> -0.64879128 | V8: =SUMIF('Performance Data'!$B:$B, $B8,'Performance Data'!AC:AC) -> 53437.85 | W8: =SUMIF('Performance Data'!$B:$B, $B8,'Performance Data'!AD:AD) -> 79726.2 | X8: =SUMIF('Performance Data'!$B:$B, $B8,'Performance Data'!AE:AE) -> 100288.01 | Y8: =SUMIF('Performance Data'!$B:$B, $B8,'Performance Data'!AG:AG) -> 110000 | Z8: =P8 -> 28202.06 | AA8: =K8 -> 39482.884 | AC8: =Z8/X8-1 -> -0.71878931 | AD8: =Z8/Y8-1 -> -0.74361764 | AE8: =AA8/Z8-1 -> 0.4 | AG8: =$AA8*AG$1 -> 2763.8019 | AH8: =$AA8*AH$1 -> 3158.6307 | AI8: =$AA8*AI$1 -> 3948.2884 | AJ8: =$AA8*AJ$1 -> 3356.0451 | AK8: =$AA8*AK$1 -> 3553.4596 | AL8: =$AA8*AL$1 -> 3158.6307 | AM8: =$AA8*AM$1 -> 3158.6307 | AN8: =$AA8*AN$1 -> 2566.3875 | ... AR8: =$AA8*AR$1 -> 2763.8019
B9: 20147 | C9: Ursula Heidemann | D9: Germany | E9: North | F9: Institutes / Clinic | G9: Pre-2022 | I9: AA | J9: 47806.3 | K9: =J9*1.07 -> 51152.741 | M9: Grow | O9: 15388.37 | P9: =SUMIF('Performance Data'!$B:$B, $B9,'Performance Data'!O:O) -> 47806.3 | Q9: 30941.22 | R9: 35000 | S9: 47806.3 | T9: 50000 | V9: =SUMIF('Performance Data'!$B:$B, $B9,'Performance Data'!AC:AC) -> 15388.37 | W9: =SUMIF('Performance Data'!$B:$B, $B9,'Performance Data'!AD:AD) -> 25299.61 | X9: =SUMIF('Performance Data'!$B:$B, $B9,'Performance Data'!AE:AE) -> 30941.22 | Y9: =SUMIF('Performance Data'!$B:$B, $B9,'Performance Data'!AG:AG) -> 35000 | Z9: =P9 -> 47806.3 | AA9: =K9 -> 51152.741 | AC9: =Z9/X9-1 -> 0.54506836 | AD9: =Z9/Y9-1 -> 0.36589429 | AE9: =AA9/Z9-1 -> 0.07 | AG9: =$AA9*AG$1 -> 3580.6919 | AH9: =$AA9*AH$1 -> 4092.2193 | AI9: =$AA9*AI$1 -> 5115.2741 | AJ9: =$AA9*AJ$1 -> 4347.983 | AK9: =$AA9*AK$1 -> 4603.7467 | AL9: =$AA9*AL$1 -> 4092.2193 | AM9: =$AA9*AM$1 -> 4092.2193 | AN9: =$AA9*AN$1 -> 3324.9282 | ... AR9: =$AA9*AR$1 -> 3580.6919
B10: 20172 | C10: Charlotte Eggers | D10: =VLOOKUP($B10, 'Performance Data'!$B:$K, 3, 0) -> Germany | E10: North | F10: =VLOOKUP($B10, 'Performance Data'!$B:$K, 6, 0) -> Perfumery | G10: =VLOOKUP($B10, 'Performance Data'!$B:$K, 10, 0) -> Pre-2022 | I10: =VLOOKUP($B10, 'Performance Data'!$B:$K, 7, 0) -> AB | J10: =Z10 -> 19157.53 | K10: =J10*1.07 -> 20498.557 | M10: Maintain | O10: =SUMIF('Performance Data'!$B:$B, $B10,'Performance Data'!N:N) -> 23517.07 | P10: =SUMIF('Performance Data'!$B:$B, $B10,'Performance Data'!O:O) -> 19157.53 | Q10: =SUMIF('Performance Data'!$B:$B, $B10,'Performance Data'!P:P) -> 18250 | S10: =$P10/O10-1 -> -0.18537769 | T10: =P10/Q10-1 -> 0.049727671 | V10: =SUMIF('Performance Data'!$B:$B, $B10,'Performance Data'!AC:AC) -> 16386.62 | W10: =SUMIF('Performance Data'!$B:$B, $B10,'Performance Data'!AD:AD) -> 21111.44 | X10: =SUMIF('Performance Data'!$B:$B, $B10,'Performance Data'!AE:AE) -> 23517.07 | Y10: =SUMIF('Performance Data'!$B:$B, $B10,'Performance Data'!AG:AG) -> 25000 | Z10: =P10 -> 19157.53 | AA10: =K10 -> 20498.557 | AC10: =Z10/X10-1 -> -0.18537769 | AD10: =Z10/Y10-1 -> -0.2336988 | AE10: =AA10/Z10-1 -> 0.07 | AG10: =$AA10*AG$1 -> 1434.899 | AH10: =$AA10*AH$1 -> 1639.8846 | AI10: =$AA10*AI$1 -> 2049.8557 | AJ10: =$AA10*AJ$1 -> 1742.3774 | AK10: =$AA10*AK$1 -> 1844.8701 | AL10: =$AA10*AL$1 -> 1639.8846 | AM10: =$AA10*AM$1 -> 1639.8846 | AN10: =$AA10*AN$1 -> 1332.4062 | ... AR10: =$AA10*AR$1 -> 1434.899
B11: 20781 | C11: Claudia Brodersen | D11: =VLOOKUP($B11, 'Performance Data'!$B:$K, 3, 0) -> Germany | E11: North | F11: =VLOOKUP($B11, 'Performance Data'!$B:$K, 6, 0) -> Institutes / Clinic | G11: =VLOOKUP($B11, 'Performance Data'!$B:$K, 10, 0) -> Pre-2022 | I11: =VLOOKUP($B11, 'Performance Data'!$B:$K, 7, 0) -> BA | J11: =Z11 -> 8738.66 | K11: =J11*1.07 -> 9350.3662 | M11: Maintain | O11: =SUMIF('Performance Data'!$B:$B, $B11,'Performance Data'!N:N) -> 10344.6 | P11: =SUMIF('Performance Data'!$B:$B, $B11,'Performance Data'!O:O) -> 8738.66 | Q11: =SUMIF('Performance Data'!$B:$B, $B11,'Performance Data'!P:P) -> 8030 | S11: =$P11/O11-1 -> -0.15524428 | T11: =P11/Q11-1 -> 0.088251557 | V11: =SUMIF('Performance Data'!$B:$B, $B11,'Performance Data'!AC:AC) -> 11028.51 | W11: =SUMIF('Performance Data'!$B:$B, $B11,'Performance Data'!AD:AD) -> 12645.51 | X11: =SUMIF('Performance Data'!$B:$B, $B11,'Performance Data'!AE:AE) -> 10344.6 | Y11: =SUMIF('Performance Data'!$B:$B, $B11,'Performance Data'!AG:AG) -> 11000 | Z11: =P11 -> 8738.66 | AA11: =K11 -> 9350.3662 | AC11: =Z11/X11-1 -> -0.15524428 | AD11: =Z11/Y11-1 -> -0.20557636 | AE11: =AA11/Z11-1 -> 0.07 | AG11: =$AA11*AG$1 -> 654.52563 | AH11: =$AA11*AH$1 -> 748.0293 | AI11: =$AA11*AI$1 -> 935.03662 | AJ11: =$AA11*AJ$1 -> 794.78113 | AK11: =$AA11*AK$1 -> 841.53296 | AL11: =$AA11*AL$1 -> 748.0293 | AM11: =$AA11*AM$1 -> 748.0293 | AN11: =$AA11*AN$1 -> 607.7738 | ... AR11: =$AA11*AR$1 -> 654.52563
B12: 20877 | C12: Sandra Koschny | D12: =VLOOKUP($B12, 'Performance Data'!$B:$K, 3, 0) -> Germany | E12: North | F12: =VLOOKUP($B12, 'Performance Data'!$B:$K, 6, 0) -> Institutes / Clinic | G12: =VLOOKUP($B12, 'Performance Data'!$B:$K, 10, 0) -> Pre-2022 | I12: =VLOOKUP($B12, 'Performance Data'!$B:$K, 7, 0) -> BA | J12: =Z12 -> 31511.68 | K12: =J12*1.07 -> 33717.498 | M12: Grow | O12: =SUMIF('Performance Data'!$B:$B, $B12,'Performance Data'!N:N) -> 17282.91 | P12: =SUMIF('Performance Data'!$B:$B, $B12,'Performance Data'!O:O) -> 31511.68 | Q12: =SUMIF('Performance Data'!$B:$B, $B12,'Performance Data'!P:P) -> 13505 | S12: =$P12/O12-1 -> 0.82328555 | T12: =P12/Q12-1 -> 1.3333343 | V12: =SUMIF('Performance Data'!$B:$B, $B12,'Performance Data'!AC:AC) -> 9064.38 | W12: =SUMIF('Performance Data'!$B:$B, $B12,'Performance Data'!AD:AD) -> 9489.28 | X12: =SUMIF('Performance Data'!$B:$B, $B12,'Performance Data'!AE:AE) -> 17282.91 | Y12: =SUMIF('Performance Data'!$B:$B, $B12,'Performance Data'!AG:AG) -> 18500 | Z12: =P12 -> 31511.68 | AA12: =K12 -> 33717.498 | AC12: =Z12/X12-1 -> 0.82328555 | AD12: =Z12/Y12-1 -> 0.70333405 | AE12: =AA12/Z12-1 -> 0.07 | AG12: =$AA12*AG$1 -> 2360.2248 | AH12: =$AA12*AH$1 -> 2697.3998 | AI12: =$AA12*AI$1 -> 3371.7498 | AJ12: =$AA12*AJ$1 -> 2865.9873 | AK12: =$AA12*AK$1 -> 3034.5748 | AL12: =$AA12*AL$1 -> 2697.3998 | AM12: =$AA12*AM$1 -> 2697.3998 | AN12: =$AA12*AN$1 -> 2191.6373 | ... AR12: =$AA12*AR$1 -> 2360.2248
B13: 20507 | C13: Heidi Sprafke | D13: Germany | E13: North | F13: Institutes / Clinic | G13: Pre-2022 | I13: BA | J13: 13721.99 | K13: =J13*1.08 -> 14819.749 | M13: Grow | O13: 6074.57 | P13: =SUMIF('Performance Data'!$B:$B, $B13,'Performance Data'!O:O) -> 13721.99 | Q13: 12008.94 | R13: 13000 | S13: 13721.99 | T13: 15000 | V13: =SUMIF('Performance Data'!$B:$B, $B13,'Performance Data'!AC:AC) -> 6074.57 | W13: =SUMIF('Performance Data'!$B:$B, $B13,'Performance Data'!AD:AD) -> 9349.36 | X13: =SUMIF('Performance Data'!$B:$B, $B13,'Performance Data'!AE:AE) -> 12008.94 | Y13: =SUMIF('Performance Data'!$B:$B, $B13,'Performance Data'!AG:AG) -> 13000 | Z13: =P13 -> 13721.99 | AA13: =K13 -> 14819.749 | AC13: =Z13/X13-1 -> 0.14264789 | AD13: =Z13/Y13-1 -> 0.055537692 | AE13: =AA13/Z13-1 -> 0.08 | AG13: =$AA13*AG$1 -> 1037.3824 | AH13: =$AA13*AH$1 -> 1185.5799 | AI13: =$AA13*AI$1 -> 1481.9749 | AJ13: =$AA13*AJ$1 -> 1259.6787 | AK13: =$AA13*AK$1 -> 1333.7774 | AL13: =$AA13*AL$1 -> 1185.5799 | AM13: =$AA13*AM$1 -> 1185.5799 | AN13: =$AA13*AN$1 -> 963.2837 | ... AR13: =$AA13*AR$1 -> 1037.3824
B14: 20340 | C14: Parfümerie W. Liebe GmbH & Co KG | D14: =VLOOKUP($B14, 'Performance Data'!$B:$K, 3, 0) -> Germany | E14: North | F14: =VLOOKUP($B14, 'Performance Data'!$B:$K, 6, 0) -> Perfumery | G14: =VLOOKUP($B14, 'Performance Data'!$B:$K, 10, 0) -> Pre-2022 | I14: =VLOOKUP($B14, 'Performance Data'!$B:$K, 7, 0) -> BB | J14: =Z14 -> 15732.83 | K14: =J14*1.07 -> 16834.128 | M14: Maintain | O14: =SUMIF('Performance Data'!$B:$B, $B14,'Performance Data'!N:N) -> 18522.89 | P14: =SUMIF('Performance Data'!$B:$B, $B14,'Performance Data'!O:O) -> 15732.83 | Q14: =SUMIF('Performance Data'!$B:$B, $B14,'Performance Data'!P:P) -> 14600 | S14: =$P14/O14-1 -> -0.15062768 | T14: =P14/Q14-1 -> 0.077591096 | V14: =SUMIF('Performance Data'!$B:$B, $B14,'Performance Data'!AC:AC) -> 8671.67 | W14: =SUMIF('Performance Data'!$B:$B, $B14,'Performance Data'!AD:AD) -> 16654.3 | X14: =SUMIF('Performance Data'!$B:$B, $B14,'Performance Data'!AE:AE) -> 18522.89 | Y14: =SUMIF('Performance Data'!$B:$B, $B14,'Performance Data'!AG:AG) -> 20000 | Z14: =P14 -> 15732.83 | AA14: =K14 -> 16834.128 | AC14: =Z14/X14-1 -> -0.15062768 | AD14: =Z14/Y14-1 -> -0.2133585 | AE14: =AA14/Z14-1 -> 0.07 | AG14: =$AA14*AG$1 -> 1178.389 | AH14: =$AA14*AH$1 -> 1346.7302 | AI14: =$AA14*AI$1 -> 1683.4128 | AJ14: =$AA14*AJ$1 -> 1430.9009 | AK14: =$AA14*AK$1 -> 1515.0715 | AL14: =$AA14*AL$1 -> 1346.7302 | AM14: =$AA14*AM$1 -> 1346.7302 | AN14: =$AA14*AN$1 -> 1094.2183 | ... AR14: =$AA14*AR$1 -> 1178.389
B15: 20920 | C15: von Carben Cosmetics;Bettina von Carben | D15: =VLOOKUP($B15, 'Performance Data'!$B:$K, 3, 0) -> Germany | E15: North | F15: =VLOOKUP($B15, 'Performance Data'!$B:$K, 6, 0) -> Institutes / Clinic | G15: =VLOOKUP($B15, 'Performance Data'!$B:$K, 10, 0) -> Pre-2022 | I15: =VLOOKUP($B15, 'Performance Data'!$B:$K, 7, 0) -> BB | J15: =Z15 -> 11103.29 | K15: =J15*1.09 -> 12102.586 | M15: Maintain | O15: =SUMIF('Performance Data'!$B:$B, $B15,'Performance Data'!N:N) -> 12690.58 | P15: =SUMIF('Performance Data'!$B:$B, $B15,'Performance Data'!O:O) -> 11103.29 | Q15: =SUMIF('Performance Data'!$B:$B, $B15,'Performance Data'!P:P) -> 9636 | S15: =$P15/O15-1 -> -0.12507624 | T15: =P15/Q15-1 -> 0.15227169 | V15: =SUMIF('Performance Data'!$B:$B, $B15,'Performance Data'!AC:AC) -> 10407.53 | W15: =SUMIF('Performance Data'!$B:$B, $B15,'Performance Data'!AD:AD) -> 11533.54 | X15: =SUMIF('Performance Data'!$B:$B, $B15,'Performance Data'!AE:AE) -> 12690.58 | Y15: =SUMIF('Performance Data'!$B:$B, $B15,'Performance Data'!AG:AG) -> 13200 | Z15: =P15 -> 11103.29 | AA15: =K15 -> 12102.586 | AC15: =Z15/X15-1 -> -0.12507624 | AD15: =Z15/Y15-1 -> -0.15884167 | AE15: =AA15/Z15-1 -> 0.09 | AG15: =$AA15*AG$1 -> 847.18103 | AH15: =$AA15*AH$1 -> 968.20689 | AI15: =$AA15*AI$1 -> 1210.2586 | AJ15: =$AA15*AJ$1 -> 1028.7198 | AK15: =$AA15*AK$1 -> 1089.2327 | AL15: =$AA15*AL$1 -> 968.20689 | AM15: =$AA15*AM$1 -> 968.20689 | AN15: =$AA15*AN$1 -> 786.6681 | ... AR15: =$AA15*AR$1 -> 847.18103
B16: 20347 | C16: Frauke Beierle-Wittern | D16: =VLOOKUP($B16, 'Performance Data'!$B:$K, 3, 0) -> Germany | E16: North | F16: =VLOOKUP($B16, 'Performance Data'!$B:$K, 6, 0) -> Institutes / Clinic | G16: =VLOOKUP($B16, 'Performance Data'!$B:$K, 10, 0) -> Pre-2022 | I16: =VLOOKUP($B16, 'Performance Data'!$B:$K, 7, 0) -> BC | J16: =Z16 -> 7668.22 | K16: =J16*1.08 -> 8281.6776 | M16: Maintain | O16: =SUMIF('Performance Data'!$B:$B, $B16,'Performance Data'!N:N) -> 9567.4 | P16: =SUMIF('Performance Data'!$B:$B, $B16,'Performance Data'!O:O) -> 7668.22 | Q16: =SUMIF('Performance Data'!$B:$B, $B16,'Performance Data'!P:P) -> 6935 | S16: =$P16/O16-1 -> -0.19850534 | T16: =P16/Q16-1 -> 0.10572747 | V16: =SUMIF('Performance Data'!$B:$B, $B16,'Performance Data'!AC:AC) -> 6265.02 | W16: =SUMIF('Performance Data'!$B:$B, $B16,'Performance Data'!AD:AD) -> 10587.74 | X16: =SUMIF('Performance Data'!$B:$B, $B16,'Performance Data'!AE:AE) -> 9567.4 | Y16: =SUMIF('Performance Data'!$B:$B, $B16,'Performance Data'!AG:AG) -> 9500 | Z16: =P16 -> 7668.22 | AA16: =K16 -> 8281.6776 | AC16: =Z16/X16-1 -> -0.19850534 | AD16: =Z16/Y16-1 -> -0.19281895 | AE16: =AA16/Z16-1 -> 0.08 | AG16: =$AA16*AG$1 -> 579.71743 | AH16: =$AA16*AH$1 -> 662.53421 | AI16: =$AA16*AI$1 -> 828.16776 | AJ16: =$AA16*AJ$1 -> 703.9426 | AK16: =$AA16*AK$1 -> 745.35098 | AL16: =$AA16*AL$1 -> 662.53421 | AM16: =$AA16*AM$1 -> 662.53421 | AN16: =$AA16*AN$1 -> 538.30904 | ... AR16: =$AA16*AR$1 -> 579.71743
B17: 20441 | C17: Ursula Hohagen | D17: =VLOOKUP($B17, 'Performance Data'!$B:$K, 3, 0) -> Germany | E17: North | F17: =VLOOKUP($B17, 'Performance Data'!$B:$K, 6, 0) -> 0 | G17: =VLOOKUP($B17, 'Performance Data'!$B:$K, 10, 0) -> Pre-2022 | I17: =VLOOKUP($B17, 'Performance Data'!$B:$K, 7, 0) -> BC | J17: =Z17 -> 7290.92 | K17: =J17*1.08 -> 7874.1936 | M17: Maintain | O17: =SUMIF('Performance Data'!$B:$B, $B17,'Performance Data'!N:N) -> 6947.2 | P17: =SUMIF('Performance Data'!$B:$B, $B17,'Performance Data'!O:O) -> 7290.92 | Q17: =SUMIF('Performance Data'!$B:$B, $B17,'Performance Data'!P:P) -> 5475 | S17: =$P17/O17-1 -> 0.049476048 | T17: =P17/Q17-1 -> 0.33167489 | V17: =SUMIF('Performance Data'!$B:$B, $B17,'Performance Data'!AC:AC) -> 7292.99 | W17: =SUMIF('Performance Data'!$B:$B, $B17,'Performance Data'!AD:AD) -> 6617.5 | X17: =SUMIF('Performance Data'!$B:$B, $B17,'Performance Data'!AE:AE) -> 6947.2 | Y17: =SUMIF('Performance Data'!$B:$B, $B17,'Performance Data'!AG:AG) -> 7500 | Z17: =P17 -> 7290.92 | AA17: =K17 -> 7874.1936 | AC17: =Z17/X17-1 -> 0.049476048 | AD17: =Z17/Y17-1 -> -0.027877333 | AE17: =AA17/Z17-1 -> 0.08 | AG17: =$AA17*AG$1 -> 551.19355 | AH17: =$AA17*AH$1 -> 629.93549 | AI17: =$AA17*AI$1 -> 787.41936 | AJ17: =$AA17*AJ$1 -> 669.30646 | AK17: =$AA17*AK$1 -> 708.67742 | AL17: =$AA17*AL$1 -> 629.93549 | AM17: =$AA17*AM$1 -> 629.93549 | AN17: =$AA17*AN$1 -> 511.82258 | ... AR17: =$AA17*AR$1 -> 551.19355
B18: 20511 | C18: Jana Jungblut | D18: =VLOOKUP($B18, 'Performance Data'!$B:$K, 3, 0) -> Germany | E18: North | F18: =VLOOKUP($B18, 'Performance Data'!$B:$K, 6, 0) -> Institutes / Clinic | G18: =VLOOKUP($B18, 'Performance Data'!$B:$K, 10, 0) -> Pre-2022 | I18: =VLOOKUP($B18, 'Performance Data'!$B:$K, 7, 0) -> BC | J18: =Z18 -> 4860.32 | K18: =J18*1.08 -> 5249.1456 | M18: Maintain | O18: =SUMIF('Performance Data'!$B:$B, $B18,'Performance Data'!N:N) -> 5255.26 | P18: =SUMIF('Performance Data'!$B:$B, $B18,'Performance Data'!O:O) -> 4860.32 | Q18: =SUMIF('Performance Data'!$B:$B, $B18,'Performance Data'!P:P) -> 4015 | S18: =$P18/O18-1 -> -0.075151372 | T18: =P18/Q18-1 -> 0.21054047 | V18: =SUMIF('Performance Data'!$B:$B, $B18,'Performance Data'!AC:AC) -> 6999.47 | W18: =SUMIF('Performance Data'!$B:$B, $B18,'Performance Data'!AD:AD) -> 6964.86 | X18: =SUMIF('Performance Data'!$B:$B, $B18,'Performance Data'!AE:AE) -> 5255.26 | Y18: =SUMIF('Performance Data'!$B:$B, $B18,'Performance Data'!AG:AG) -> 5500 | Z18: =P18 -> 4860.32 | AA18: =K18 -> 5249.1456 | AC18: =Z18/X18-1 -> -0.075151372 | AD18: =Z18/Y18-1 -> -0.11630545 | AE18: =AA18/Z18-1 -> 0.08 | AG18: =$AA18*AG$1 -> 367.44019 | AH18: =$AA18*AH$1 -> 419.93165 | AI18: =$AA18*AI$1 -> 524.91456 | AJ18: =$AA18*AJ$1 -> 446.17738 | AK18: =$AA18*AK$1 -> 472.4231 | AL18: =$AA18*AL$1 -> 419.93165 | AM18: =$AA18*AM$1 -> 419.93165 | AN18: =$AA18*AN$1 -> 341.19446 | ... AR18: =$AA18*AR$1 -> 367.44019
B19: 20576 | C19: Susanne Große | D19: =VLOOKUP($B19, 'Performance Data'!$B:$K, 3, 0) -> Germany | E19: North | F19: =VLOOKUP($B19, 'Performance Data'!$B:$K, 6, 0) -> 0 | G19: =VLOOKUP($B19, 'Performance Data'!$B:$K, 10, 0) -> Pre-2022 | I19: =VLOOKUP($B19, 'Performance Data'!$B:$K, 7, 0) -> BC | J19: =Z19 -> 11619.81 | K19: =J19*1.07 -> 12433.197 | M19: Grow | O19: =SUMIF('Performance Data'!$B:$B, $B19,'Performance Data'!N:N) -> 7533.77 | P19: =SUMIF('Performance Data'!$B:$B, $B19,'Performance Data'!O:O) -> 11619.81 | Q19: =SUMIF('Performance Data'!$B:$B, $B19,'Performance Data'!P:P) -> 5840 | S19: =$P19/O19-1 -> 0.54236325 | T19: =P19/Q19-1 -> 0.98969349 | V19: =SUMIF('Performance Data'!$B:$B, $B19,'Performance Data'!AC:AC) -> 8784.47 | W19: =SUMIF('Performance Data'!$B:$B, $B19,'Performance Data'!AD:AD) -> 7679.85 | X19: =SUMIF('Performance Data'!$B:$B, $B19,'Performance Data'!AE:AE) -> 7533.77 | Y19: =SUMIF('Performance Data'!$B:$B, $B19,'Performance Data'!AG:AG) -> 8000 | Z19: =P19 -> 11619.81 | AA19: =K19 -> 12433.197 | AC19: =Z19/X19-1 -> 0.54236325 | AD19: =Z19/Y19-1 -> 0.45247625 | AE19: =AA19/Z19-1 -> 0.07 | AG19: =$AA19*AG$1 -> 870.32377 | AH19: =$AA19*AH$1 -> 994.65574 | AI19: =$AA19*AI$1 -> 1243.3197 | AJ19: =$AA19*AJ$1 -> 1056.8217 | AK19: =$AA19*AK$1 -> 1118.9877 | AL19: =$AA19*AL$1 -> 994.65574 | AM19: =$AA19*AM$1 -> 994.65574 | AN19: =$AA19*AN$1 -> 808.15779 | ... AR19: =$AA19*AR$1 -> 870.32377
B20: 20857 | C20: Kerstin Vollmer | D20: Germany | E20: North | F20: 0 | G20: Pre-2022 | I20: BC | J20: 10185.89 | K20: =J20*1.07 -> 10898.902 | M20: Maintain | O20: 10056.92 | P20: =SUMIF('Performance Data'!$B:$B, $B20,'Performance Data'!O:O) -> 10185.89 | Q20: 10214.55 | R20: 11000 | S20: 10185.89 | T20: 10500 | V20: =SUMIF('Performance Data'!$B:$B, $B20,'Performance Data'!AC:AC) -> 10056.92 | W20: =SUMIF('Performance Data'!$B:$B, $B20,'Performance Data'!AD:AD) -> 9524.87 | X20: =SUMIF('Performance Data'!$B:$B, $B20,'Performance Data'!AE:AE) -> 10214.55 | Y20: =SUMIF('Performance Data'!$B:$B, $B20,'Performance Data'!AG:AG) -> 11000 | Z20: =P20 -> 10185.89 | AA20: =K20 -> 10898.902 | AC20: =Z20/X20-1 -> -0.0028058015 | AD20: =Z20/Y20-1 -> -0.07401 | AE20: =AA20/Z20-1 -> 0.07 | AG20: =$AA20*AG$1 -> 762.92316 | AH20: =$AA20*AH$1 -> 871.91218 | AI20: =$AA20*AI$1 -> 1089.8902 | AJ20: =$AA20*AJ$1 -> 926.4067 | AK20: =$AA20*AK$1 -> 980.90121 | AL20: =$AA20*AL$1 -> 871.91218 | AM20: =$AA20*AM$1 -> 871.91218 | AN20: =$AA20*AN$1 -> 708.42865 | ... AR20: =$AA20*AR$1 -> 762.92316
B21: 20475 | C21: Jürgen Kappei | D21: =VLOOKUP($B21, 'Performance Data'!$B:$K, 3, 0) -> Germany | E21: North | F21: =VLOOKUP($B21, 'Performance Data'!$B:$K, 6, 0) -> Perfumery | G21: =VLOOKUP($B21, 'Performance Data'!$B:$K, 10, 0) -> Pre-2022 | I21: =VLOOKUP($B21, 'Performance Data'!$B:$K, 7, 0) -> CB | J21: =Z21 -> 522.1 | K21: =J21*1.07 -> 558.647 | M21: Lose | O21: =SUMIF('Performance Data'!$B:$B, $B21,'Performance Data'!N:N) -> 3334.44 | P21: =SUMIF('Performance Data'!$B:$B, $B21,'Performance Data'!O:O) -> 522.1 | Q21: =SUMIF('Performance Data'!$B:$B, $B21,'Performance Data'!P:P) -> 2555 | S21: =$P21/O21-1 -> -0.84342198 | T21: =P21/Q21-1 -> -0.79565558 | V21: =SUMIF('Performance Data'!$B:$B, $B21,'Performance Data'!AC:AC) -> 4701.13 | W21: =SUMIF('Performance Data'!$B:$B, $B21,'Performance Data'!AD:AD) -> 6704.59 | X21: =SUMIF('Performance Data'!$B:$B, $B21,'Performance Data'!AE:AE) -> 3334.44 | Y21: =SUMIF('Performance Data'!$B:$B, $B21,'Performance Data'!AG:AG) -> 3500 | Z21: =P21 -> 522.1 | AA21: =K21 -> 558.647 | AC21: =Z21/X21-1 -> -0.84342198 | AD21: =Z21/Y21-1 -> -0.85082857 | AE21: =AA21/Z21-1 -> 0.07 | AG21: =$AA21*AG$1 -> 39.10529 | AH21: =$AA21*AH$1 -> 44.69176 | AI21: =$AA21*AI$1 -> 55.8647 | AJ21: =$AA21*AJ$1 -> 47.484995 | AK21: =$AA21*AK$1 -> 50.27823 | AL21: =$AA21*AL$1 -> 44.69176 | AM21: =$AA21*AM$1 -> 44.69176 | AN21: =$AA21*AN$1 -> 36.312055 | ... AR21: =$AA21*AR$1 -> 39.10529
B22: 20093 | C22: Susanne Thomsen | D22: =VLOOKUP($B22, 'Performance Data'!$B:$K, 3, 0) -> Germany | E22: North | F22: =VLOOKUP($B22, 'Performance Data'!$B:$K, 6, 0) -> eTailer | G22: =VLOOKUP($B22, 'Performance Data'!$B:$K, 10, 0) -> Pre-2022 | I22: =VLOOKUP($B22, 'Performance Data'!$B:$K, 7, 0) -> CC | J22: =Z22 -> 5859.89 | K22: =J22*1.08 -> 6328.6812 | M22: Maintain | O22: =SUMIF('Performance Data'!$B:$B, $B22,'Performance Data'!N:N) -> 4934.03 | P22: =SUMIF('Performance Data'!$B:$B, $B22,'Performance Data'!O:O) -> 5859.89 | Q22: =SUMIF('Performance Data'!$B:$B, $B22,'Performance Data'!P:P) -> 4380 | S22: =$P22/O22-1 -> 0.18764783 | T22: =P22/Q22-1 -> 0.33787443 | V22: =SUMIF('Performance Data'!$B:$B, $B22,'Performance Data'!AC:AC) -> 3416.86 | W22: =SUMIF('Performance Data'!$B:$B, $B22,'Performance Data'!AD:AD) -> 3814.8 | X22: =SUMIF('Performance Data'!$B:$B, $B22,'Performance Data'!AE:AE) -> 4934.03 | Y22: =SUMIF('Performance Data'!$B:$B, $B22,'Performance Data'!AG:AG) -> 6000 | Z22: =P22 -> 5859.89 | AA22: =K22 -> 6328.6812 | AC22: =Z22/X22-1 -> 0.18764783 | AD22: =Z22/Y22-1 -> -0.023351667 | AE22: =AA22/Z22-1 -> 0.08 | AG22: =$AA22*AG$1 -> 443.00768 | AH22: =$AA22*AH$1 -> 506.2945 | AI22: =$AA22*AI$1 -> 632.86812 | AJ22: =$AA22*AJ$1 -> 537.9379 | AK22: =$AA22*AK$1 -> 569.58131 | AL22: =$AA22*AL$1 -> 506.2945 | AM22: =$AA22*AM$1 -> 506.2945 | AN22: =$AA22*AN$1 -> 411.36428 | ... AR22: =$AA22*AR$1 -> 443.00768
B23: 20995 | C23: Long Time Liner; Annett Roeder; Interessent | D23: =VLOOKUP($B23, 'Performance Data'!$B:$K, 3, 0) -> Germany | E23: North | F23: =VLOOKUP($B23, 'Performance Data'!$B:$K, 6, 0) -> Institutes / Clinic | G23: =VLOOKUP($B23, 'Performance Data'!$B:$K, 10, 0) -> 2023 | I23: =VLOOKUP($B23, 'Performance Data'!$B:$K, 7, 0) -> CC | J23: =Z23 -> 2076.89 | K23: 3500 | M23: Maintain | O23: =SUMIF('Performance Data'!$B:$B, $B23,'Performance Data'!N:N) -> 3227.74 | P23: =SUMIF('Performance Data'!$B:$B, $B23,'Performance Data'!O:O) -> 2076.89 | Q23: =SUMIF('Performance Data'!$B:$B, $B23,'Performance Data'!P:P) -> 7300 | S23: =$P23/O23-1 -> -0.35654978 | T23: =P23/Q23-1 -> -0.71549452 | V23: =SUMIF('Performance Data'!$B:$B, $B23,'Performance Data'!AC:AC) -> 0 | W23: =SUMIF('Performance Data'!$B:$B, $B23,'Performance Data'!AD:AD) -> 4015.37 | X23: =SUMIF('Performance Data'!$B:$B, $B23,'Performance Data'!AE:AE) -> 3227.74 | Y23: =SUMIF('Performance Data'!$B:$B, $B23,'Performance Data'!AG:AG) -> 10000 | Z23: =P23 -> 2076.89 | AA23: =K23 -> 3500 | AC23: =Z23/X23-1 -> -0.35654978 | AD23: =Z23/Y23-1 -> -0.792311 | AE23: =AA23/Z23-1 -> 0.68521202 | AG23: =$AA23*AG$1 -> 245 | AH23: =$AA23*AH$1 -> 280 | AI23: =$AA23*AI$1 -> 350 | AJ23: =$AA23*AJ$1 -> 297.5 | AK23: =$AA23*AK$1 -> 315 | AL23: =$AA23*AL$1 -> 280 | AM23: =$AA23*AM$1 -> 280 | AN23: =$AA23*AN$1 -> 227.5 | ... AR23: =$AA23*AR$1 -> 245
B24: 29015 | C24: Auszeit, Maria Schomaker, Lingen | D24: Germany | E24: North | F24: Institutes / Clinic | G24: 2024 | I24: NKD24 | J24: 3667.15 | K24: =J24*1.07 -> 3923.8505 | M24: Maintain | O24: 0 | P24: =SUMIF('Performance Data'!$B:$B, $B24,'Performance Data'!O:O) -> 3667.15 | Q24: 21155.78 | R24: 25000 | S24: 3667.15 | T24: 3500 | V24: =SUMIF('Performance Data'!$B:$B, $B24,'Performance Data'!AC:AC) -> 0 | W24: =SUMIF('Performance Data'!$B:$B, $B24,'Performance Data'!AD:AD) -> 0 | X24: =SUMIF('Performance Data'!$B:$B, $B24,'Performance Data'!AE:AE) -> 21155.78 | Y24: =SUMIF('Performance Data'!$B:$B, $B24,'Performance Data'!AG:AG) -> 25000 | Z24: =P24 -> 3667.15 | AA24: =K24 -> 3923.8505 | AC24: =Z24/X24-1 -> -0.82665966 | AD24: =Z24/Y24-1 -> -0.853314 | AE24: =AA24/Z24-1 -> 0.07 | AG24: =$AA24*AG$1 -> 274.66954 | AH24: =$AA24*AH$1 -> 313.90804 | AI24: =$AA24*AI$1 -> 392.38505 | AJ24: =$AA24*AJ$1 -> 333.52729 | AK24: =$AA24*AK$1 -> 353.14655 | AL24: =$AA24*AL$1 -> 313.90804 | AM24: =$AA24*AM$1 -> 313.90804 | AN24: =$AA24*AN$1 -> 255.05028 | ... AR24: =$AA24*AR$1 -> 274.66954
B25: 20693 | C25: Susanne Barke | D25: =VLOOKUP($B25, 'Performance Data'!$B:$K, 3, 0) -> Germany | E25: North | F25: =VLOOKUP($B25, 'Performance Data'!$B:$K, 6, 0) -> Institutes / Clinic | G25: =VLOOKUP($B25, 'Performance Data'!$B:$K, 10, 0) -> Pre-2022 | H25: Yes | I25: =VLOOKUP($B25, 'Performance Data'!$B:$K, 7, 0) -> BA | J25: =P25 -> 7100.77 | K25: =J25*1.07 -> 7597.8239 | M25: Maintain | O25: =SUMIF('Performance Data'!$B:$B, $B25,'Performance Data'!N:N) -> 9681.24 | P25: =SUMIF('Performance Data'!$B:$B, $B25,'Performance Data'!O:O) -> 7100.77 | Q25: =SUMIF('Performance Data'!$B:$B, $B25,'Performance Data'!P:P) -> 8030 | S25: =$P25/O25-1 -> -0.26654334 | T25: =P25/Q25-1 -> -0.1157198 | V25: =SUMIF('Performance Data'!$B:$B, $B25,'Performance Data'!AC:AC) -> 5112.28 | W25: =SUMIF('Performance Data'!$B:$B, $B25,'Performance Data'!AD:AD) -> 6599.3 | X25: =SUMIF('Performance Data'!$B:$B, $B25,'Performance Data'!AE:AE) -> 9681.24 | Y25: =SUMIF('Performance Data'!$B:$B, $B25,'Performance Data'!AG:AG) -> 11000 | Z25: =P25 -> 7100.77 | AA25: =K25 -> 7597.8239 | AC25: =Z25/X25-1 -> -0.26654334 | AD25: =Z25/Y25-1 -> -0.35447545 | AE25: =AA25/Z25-1 -> 0.07 | AG25: =$AA25*AG$1 -> 531.84767 | AH25: =$AA25*AH$1 -> 607.82591 | AI25: =$AA25*AI$1 -> 759.78239 | AJ25: =$AA25*AJ$1 -> 645.81503 | AK25: =$AA25*AK$1 -> 683.80415 | AL25: =$AA25*AL$1 -> 607.82591 | AM25: =$AA25*AM$1 -> 607.82591 | AN25: =$AA25*AN$1 -> 493.85855 | ... AR25: =$AA25*AR$1 -> 531.84767
B26: 20108 | C26: Petra Pott | D26: =VLOOKUP($B26, 'Performance Data'!$B:$K, 3, 0) -> Germany | E26: North | F26: =VLOOKUP($B26, 'Performance Data'!$B:$K, 6, 0) -> Institutes / Clinic | G26: =VLOOKUP($B26, 'Performance Data'!$B:$K, 10, 0) -> Pre-2022 | H26: Yes | I26: =VLOOKUP($B26, 'Performance Data'!$B:$K, 7, 0) -> BB | J26: =P26 -> 11942.99 | K26: =J26*1.07 -> 12778.999 | M26: Maintain | O26: =SUMIF('Performance Data'!$B:$B, $B26,'Performance Data'!N:N) -> 19485.78 | P26: =SUMIF('Performance Data'!$B:$B, $B26,'Performance Data'!O:O) -> 11942.99 | Q26: =SUMIF('Performance Data'!$B:$B, $B26,'Performance Data'!P:P) -> 14600 | S26: =$P26/O26-1 -> -0.38709202 | T26: =P26/Q26-1 -> -0.18198699 | V26: =SUMIF('Performance Data'!$B:$B, $B26,'Performance Data'!AC:AC) -> 16091.17 | W26: =SUMIF('Performance Data'!$B:$B, $B26,'Performance Data'!AD:AD) -> 16180.14 | X26: =SUMIF('Performance Data'!$B:$B, $B26,'Performance Data'!AE:AE) -> 19485.78 | Y26: =SUMIF('Performance Data'!$B:$B, $B26,'Performance Data'!AG:AG) -> 20000 | Z26: =P26 -> 11942.99 | AA26: =K26 -> 12778.999 | AC26: =Z26/X26-1 -> -0.38709202 | AD26: =Z26/Y26-1 -> -0.4028505 | AE26: =AA26/Z26-1 -> 0.07 | AG26: =$AA26*AG$1 -> 894.52995 | AH26: =$AA26*AH$1 -> 1022.3199 | AI26: =$AA26*AI$1 -> 1277.8999 | AJ26: =$AA26*AJ$1 -> 1086.2149 | AK26: =$AA26*AK$1 -> 1150.1099 | AL26: =$AA26*AL$1 -> 1022.3199 | AM26: =$AA26*AM$1 -> 1022.3199 | AN26: =$AA26*AN$1 -> 830.63495 | ... AR26: =$AA26*AR$1 -> 894.52995
B27: 20349 | C27: Simone Maschmeyer | D27: =VLOOKUP($B27, 'Performance Data'!$B:$K, 3, 0) -> Germany | E27: North | F27: =VLOOKUP($B27, 'Performance Data'!$B:$K, 6, 0) -> Institutes / Clinic | G27: =VLOOKUP($B27, 'Performance Data'!$B:$K, 10, 0) -> Pre-2022 | H27: Yes | I27: =VLOOKUP($B27, 'Performance Data'!$B:$K, 7, 0) -> BC | J27: =P27 -> 12160.74 | K27: =J27*1.07 -> 13011.992 | M27: Grow | O27: =SUMIF('Performance Data'!$B:$B, $B27,'Performance Data'!N:N) -> 10641.37 | P27: =SUMIF('Performance Data'!$B:$B, $B27,'Performance Data'!O:O) -> 12160.74 | Q27: =SUMIF('Performance Data'!$B:$B, $B27,'Performance Data'!P:P) -> 8760 | S27: =$P27/O27-1 -> 0.14277955 | T27: =P27/Q27-1 -> 0.38821233 | V27: =SUMIF('Performance Data'!$B:$B, $B27,'Performance Data'!AC:AC) -> 6565.04 | W27: =SUMIF('Performance Data'!$B:$B, $B27,'Performance Data'!AD:AD) -> 9673.68 | X27: =SUMIF('Performance Data'!$B:$B, $B27,'Performance Data'!AE:AE) -> 10641.37 | Y27: =SUMIF('Performance Data'!$B:$B, $B27,'Performance Data'!AG:AG) -> 12000 | Z27: =P27 -> 12160.74 | AA27: =K27 -> 13011.992 | AC27: =Z27/X27-1 -> 0.14277955 | AD27: =Z27/Y27-1 -> 0.013395 | AE27: =AA27/Z27-1 -> 0.07 | AG27: =$AA27*AG$1 -> 910.83943 | AH27: =$AA27*AH$1 -> 1040.9593 | AI27: =$AA27*AI$1 -> 1301.1992 | AJ27: =$AA27*AJ$1 -> 1106.0193 | AK27: =$AA27*AK$1 -> 1171.0793 | AL27: =$AA27*AL$1 -> 1040.9593 | AM27: =$AA27*AM$1 -> 1040.9593 | AN27: =$AA27*AN$1 -> 845.77947 | ... AR27: =$AA27*AR$1 -> 910.83943
B28: Total Active Existing Doors | H28: =COUNTIF(H3:H27, "Yes") -> 3 | J28: =SUM(J3:J27) -> 553327.66 | K28: =SUM(K3:K27) -> 601412.47 | O28: =SUM(O3:O25) -> 601941.21 | P28: =SUM(P3:P27) -> 553327.66 | Q28: =SUM(Q3:Q25) -> 520861.49 | S28: =$P28/O28-1 -> -0.080761292 | T28: =P28/Q28-1 -> 0.062331677 | V28: =SUM(V3:V27) -> 475700.85 | W28: =SUM(W3:W27) -> 570571.71 | X28: =SUM(X3:X27) -> 674868.99 | Y28: =SUM(Y3:Y27) -> 727700 | Z28: =SUM(Z3:Z27) -> 553327.66 | AA28: =SUM(AA3:AA27) -> 601412.47 | AC28: =Z28/X28-1 -> -0.18009618 | AD28: =Z28/Y28-1 -> -0.23962119 | AE28: =AA28/Z28-1 -> 0.086901156 | AG28: =SUM(AG3:AG27) -> 42098.873 | AH28: =SUM(AH3:AH27) -> 48112.998 | AI28: =SUM(AI3:AI27) -> 60141.247 | AJ28: =SUM(AJ3:AJ27) -> 51120.06 | AK28: =SUM(AK3:AK27) -> 54127.123 | AL28: =SUM(AL3:AL27) -> 48112.998 | AM28: =SUM(AM3:AM27) -> 48112.998 | AN28: =SUM(AN3:AN27) -> 39091.811 | ... AR28: =SUM(AR3:AR27) -> 42098.873
B32: 29024 | C32: Parfümerie Pieper, Herne | D32: =VLOOKUP($B32, 'Performance Data'!$B:$K, 3, 0) -> Germany | E32: =VLOOKUP($B32, 'Performance Data'!$B:$K, 4, 0) -> North | F32: =VLOOKUP($B32, 'Performance Data'!$B:$K, 6, 0) -> Institutes / Clinic | G32: =VLOOKUP($B32, 'Performance Data'!$B:$K, 10, 0) -> 2025 | I32: =VLOOKUP($B32, 'Performance Data'!$B:$K, 7, 0) -> NKD25 | J32: =Z32 -> 49506.76 | K32: =J32*1.06 -> 52477.166 | M32: Maintain | O32: =SUMIF('Performance Data'!$B:$B, $B32,'Performance Data'!N:N) -> 0 | P32: =SUMIF('Performance Data'!$B:$B, $B32,'Performance Data'!O:O) -> 49506.76 | Q32: =SUMIF('Performance Data'!$B:$B, $B32,'Performance Data'!P:P) -> 0 | S32: =$P32/O32-1 -> #DIV/0! | T32: =P32/Q32-1 -> #DIV/0! | V32: =SUMIF('Performance Data'!$B:$B, $B32,'Performance Data'!AC:AC) -> 0 | W32: =SUMIF('Performance Data'!$B:$B, $B32,'Performance Data'!AD:AD) -> 0 | X32: =SUMIF('Performance Data'!$B:$B, $B32,'Performance Data'!AE:AE) -> 0 | Y32: =SUMIF('Performance Data'!$B:$B, $B32,'Performance Data'!AG:AG) -> 0 | Z32: =P32 -> 49506.76 | AA32: =K32 -> 52477.166 | AC32: =Z32/X32-1 -> #DIV/0! | AD32: =Z32/Y32-1 -> #DIV/0! | AE32: =AA32/Z32-1 -> 0.06 | AG32: =$AA32*AG$1 -> 3673.4016 | AH32: =$AA32*AH$1 -> 4198.1732 | AI32: =$AA32*AI$1 -> 5247.7166 | AJ32: =$AA32*AJ$1 -> 4460.5591 | AK32: =$AA32*AK$1 -> 4722.9449 | AL32: =$AA32*AL$1 -> 4198.1732 | AM32: =$AA32*AM$1 -> 4198.1732 | AN32: =$AA32*AN$1 -> 3411.0158 | ... AR32: =$AA32*AR$1 -> 3673.4016
B33: NKD25_KB | C33: New doors 2025 | D33: Germany | E33: North | G33: 2025 | I33: NKD25 | O33: 0 | P33: 0 | Q33: =SUMIF('Combined Budget 2025 EUR'!$B:$B, $B33,'Combined Budget 2025 EUR'!$AL:$AL) -> 11250 | S33: =$P33/O33-1 -> #DIV/0! | T33: =P33/Q33-1 -> -1 | V33: 0 | W33: 0 | X33: 0 | Y33: =SUMIF('Combined Budget 2025 EUR'!$B:$B, $B33,'Combined Budget 2025 EUR'!$AQ:$AQ) -> 30000 | Z33: =P33 -> 0 | AA33: =K33 -> 0 | AC33: =Z33/X33-1 -> #DIV/0! | AD33: =Z33/Y33-1 -> -1 | AE33: =AA33/Z33-1 -> #DIV/0!
B35: Total New Doors 2025 | H35: =COUNTIF(H32:H32, "Yes")+H33 -> 0 | J35: =SUM(J32:J33) -> 49506.76 | K35: =SUM(K32:K33) -> 52477.166 | O35: =SUM(O32:O33) -> 0 | P35: =SUM(P32:P33) -> 49506.76 | Q35: =SUM(Q32:Q33) -> 11250 | S35: =$P35/O35-1 -> #DIV/0! | T35: =P35/Q35-1 -> 3.4006009 | V35: =SUM(V32:V33) -> 0 | W35: =SUM(W32:W33) -> 0 | X35: =SUM(X32:X33) -> 0 | Y35: =SUM(Y32:Y33) -> 30000 | Z35: =SUM(Z32:Z33) -> 49506.76 | AA35: =SUM(AA32:AA33) -> 52477.166 | AC35: =Z35/X35-1 -> #DIV/0! | AD35: =Z35/Y35-1 -> 0.65022533 | AE35: =AA35/Z35-1 -> 0.06 | AG35: =SUM(AG32:AG33) -> 3673.4016 | AH35: =SUM(AH32:AH33) -> 4198.1732 | AI35: =SUM(AI32:AI33) -> 5247.7166 | AJ35: =SUM(AJ32:AJ33) -> 4460.5591 | AK35: =SUM(AK32:AK33) -> 4722.9449 | AL35: =SUM(AL32:AL33) -> 4198.1732 | AM35: =SUM(AM32:AM33) -> 4198.1732 | AN35: =SUM(AN32:AN33) -> 3411.0158 | ... AR35: =SUM(AR32:AR33) -> 3673.4016
B37: Global Target existing and new doors 2025 | AG37: {=AG28:AR28+AG35:AR35} -> 45772.275 | AH37: 52311.171 | AI37: 65388.964 | AJ37: 55580.619 | AK37: 58850.068 | AL37: 52311.171 | AM37: 52311.171 | AN37: 42502.827 | AO37: 62119.516 | AP37: 65388.964 | AQ37: 55580.619 | AR37: 45772.275
AY38: =AV39 -> 1 | AZ38: =AW39 -> 0 | BA38: =AX39+AV39 -> 2 | BB38: =AY39+AW39 -> 0 | BC38: =AZ39+AX39+AV39 -> 3 | BD38: =BA39+AY39+AW39 -> 1 | BE38: =BB39+AZ39+AX39+AV39 -> 3 | BF38: =BC39+BA39+AY39+AW39 -> 2
B39: NKD26_KB | C39: New doors 2026 | D39: Germany | E39: North | G39: 2026 | H39: 6 | I39: NKD26 | K39: 60000 | O39: 0 | P39: 0 | Q39: 0 | S39: =$P39/O39-1 -> #DIV/0! | T39: =P39/Q39-1 -> #DIV/0! | V39: 0 | W39: 0 | X39: 0 | Y39: 0 | Z39: =J39 -> 0 | AA39: =K39 -> 60000 | AC39: =Z39/X39-1 -> #DIV/0! | AD39: =Z39/Y39-1 -> #DIV/0! | AE39: =AA39/Z39-1 -> #DIV/0! | AG39: =AU39*4000+AU38*3000 -> 0 | AH39: =AV39*4000+AV38*3000 -> 4000 | AI39: 5000 | AJ39: 5000 | AK39: 6000 | AL39: 6000 | AM39: 4000 | AN39: 2000 | AO39: 8000 | AP39: 7000 | AQ39: 8000 | AR39: 5000 | AV39: 1 | AX39: 1 | AZ39: 1 | BA39: 1 | BC39: 1 | BE39: 1
B41: Total New Doors 2026 | H41: =COUNTIF(H38:H38, "Yes")+H39 -> 6 | J41: =SUM(J38:J39) -> 0 | K41: =SUM(K38:K39) -> 60000 | O41: =SUM(O38:O39) -> 0 | P41: =SUM(P38:P39) -> 0 | Q41: =SUM(Q38:Q39) -> 0 | S41: =$P41/O41-1 -> #DIV/0! | T41: =P41/Q41-1 -> #DIV/0! | V41: =SUM(V38:V39) -> 0 | W41: =SUM(W38:W39) -> 0 | X41: =SUM(X38:X39) -> 0 | Y41: =SUM(Y38:Y39) -> 0 | Z41: =SUM(Z38:Z39) -> 0 | AA41: =SUM(AA38:AA39) -> 60000 | AC41: =Z41/X41-1 -> #DIV/0! | AD41: =Z41/Y41-1 -> #DIV/0! | AE41: =AA41/Z41-1 -> #DIV/0! | AG41: =SUM(AG38:AG39) -> 0 | AH41: =SUM(AH38:AH39) -> 4000 | AI41: =SUM(AI38:AI39) -> 5000 | AJ41: =SUM(AJ38:AJ39) -> 5000 | AK41: =SUM(AK38:AK39) -> 6000 | AL41: =SUM(AL38:AL39) -> 6000 | AM41: =SUM(AM38:AM39) -> 4000 | AN41: =SUM(AN38:AN39) -> 2000 | ... AR41: =SUM(AR38:AR39) -> 5000

Sheet North East
O1: Year to date | P1: Year to date | Q1: Year to date | S1: Year to date | T1: Year to date | V1: Full year | W1: Full year | X1: Full year | Y1: Full year | Z1: Full year | AA1: Full year | AC1: Full year | AD1: Full year | AE1: Full year | AG1: 0.07 | AH1: 0.08 | AI1: 0.1 | AJ1: 0.085 | AK1: 0.09 | AL1: 0.08 | AM1: 0.08 | AN1: 0.065 | AO1: 0.095 | AP1: 0.1 | AQ1: 0.085 | AR1: 0.07
B2: Customer Code | C2: Customer Name | D2: Country | E2: Region | F2: Customer Map | G2: New door year | H2: Active? | I2: 2025 Cluster | J2: 2025A | K2: 2026B | L2: Size indicator | M2: Customer Growth Class | O2: 2024 YTD | P2: 2025 YTD | Q2: 2025B YTD | S2: 25 vs 24 % | T2: 25 vs 25B % | V2: 2022 | W2: 2023 | X2: 2024 | Y2: 2025B | Z2: 2025A | AA2: 2026B | AC2: 25 vs 24 % | AD2: 25 vs 25B % | AE2: 26B vs 25F % | AG2: 46023 | AH2: 46054 | AI2: 46082 | AJ2: 46113 | AK2: 46143 | AL2: 46174 | AM2: 46204 | AN2: 46235 | AO2: 46266 | AP2: 46296 | AQ2: 46327 | AR2: 46357
B3: 20106 | C3: Susanne Alltschekow | D3: =VLOOKUP($B3, 'Performance Data'!$B:$K, 3, 0) -> Germany | E3: North East | F3: =VLOOKUP($B3, 'Performance Data'!$B:$K, 6, 0) -> Institutes / Clinic | G3: =VLOOKUP($B3, 'Performance Data'!$B:$K, 10, 0) -> Pre-2022 | I3: =VLOOKUP($B3, 'Performance Data'!$B:$K, 7, 0) -> AA | J3: =Z3 -> 19012.77 | K3: =J3*1.08 -> 20533.792 | M3: Maintain | O3: =SUMIF('Performance Data'!$B:$B, $B3,'Performance Data'!N:N) -> 25750.07 | P3: =SUMIF('Performance Data'!$B:$B, $B3,'Performance Data'!O:O) -> 19012.77 | Q3: =SUMIF('Performance Data'!$B:$B, $B3,'Performance Data'!P:P) -> 19710 | S3: =$P3/O3-1 -> -0.26164201 | T3: =P3/Q3-1 -> -0.035374429 | V3: =SUMIF('Performance Data'!$B:$B, $B3,'Performance Data'!AC:AC) -> 21034.84 | W3: =SUMIF('Performance Data'!$B:$B, $B3,'Performance Data'!AD:AD) -> 23256.36 | X3: =SUMIF('Performance Data'!$B:$B, $B3,'Performance Data'!AE:AE) -> 25750.07 | Y3: =SUMIF('Performance Data'!$B:$B, $B3,'Performance Data'!AG:AG) -> 27000 | Z3: =P3 -> 19012.77 | AA3: =K3 -> 20533.792 | AC3: =Z3/X3-1 -> -0.26164201 | AD3: =Z3/Y3-1 -> -0.29582333 | AE3: =AA3/Z3-1 -> 0.08 | AG3: =$AA3*AG$1 -> 1437.3654 | AH3: =$AA3*AH$1 -> 1642.7033 | AI3: =$AA3*AI$1 -> 2053.3792 | AJ3: =$AA3*AJ$1 -> 1745.3723 | AK3: =$AA3*AK$1 -> 1848.0412 | AL3: =$AA3*AL$1 -> 1642.7033 | AM3: =$AA3*AM$1 -> 1642.7033 | AN3: =$AA3*AN$1 -> 1334.6965 | ... AR3: =$AA3*AR$1 -> 1437.3654
B4: 20255 | C4: Gregor Wiese, Le Visage | D4: =VLOOKUP($B4, 'Performance Data'!$B:$K, 3, 0) -> Germany | E4: North East | F4: =VLOOKUP($B4, 'Performance Data'!$B:$K, 6, 0) -> Institutes / Clinic | G4: =VLOOKUP($B4, 'Performance Data'!$B:$K, 10, 0) -> Pre-2022 | I4: =VLOOKUP($B4, 'Performance Data'!$B:$K, 7, 0) -> AA | J4: =Z4 -> 26100.01 | K4: =J4*1.08 -> 28188.011 | M4: Maintain | O4: =SUMIF('Performance Data'!$B:$B, $B4,'Performance Data'!N:N) -> 28221.5 | P4: =SUMIF('Performance Data'!$B:$B, $B4,'Performance Data'!O:O) -> 26100.01 | Q4: =SUMIF('Performance Data'!$B:$B, $B4,'Performance Data'!P:P) -> 21900 | S4: =$P4/O4-1 -> -0.075172829 | T4: =P4/Q4-1 -> 0.19178128 | V4: =SUMIF('Performance Data'!$B:$B, $B4,'Performance Data'!AC:AC) -> 20821.62 | W4: =SUMIF('Performance Data'!$B:$B, $B4,'Performance Data'!AD:AD) -> 23499.33 | X4: =SUMIF('Performance Data'!$B:$B, $B4,'Performance Data'!AE:AE) -> 28221.5 | Y4: =SUMIF('Performance Data'!$B:$B, $B4,'Performance Data'!AG:AG) -> 30000 | Z4: =P4 -> 26100.01 | AA4: =K4 -> 28188.011 | AC4: =Z4/X4-1 -> -0.075172829 | AD4: =Z4/Y4-1 -> -0.12999967 | AE4: =AA4/Z4-1 -> 0.08 | AG4: =$AA4*AG$1 -> 1973.1608 | AH4: =$AA4*AH$1 -> 2255.0409 | AI4: =$AA4*AI$1 -> 2818.8011 | AJ4: =$AA4*AJ$1 -> 2395.9809 | AK4: =$AA4*AK$1 -> 2536.921 | AL4: =$AA4*AL$1 -> 2255.0409 | AM4: =$AA4*AM$1 -> 2255.0409 | AN4: =$AA4*AN$1 -> 1832.2207 | ... AR4: =$AA4*AR$1 -> 1973.1608
B5: 20370 | C5: Birgit Henning | D5: =VLOOKUP($B5, 'Performance Data'!$B:$K, 3, 0) -> Germany | E5: North East | F5: =VLOOKUP($B5, 'Performance Data'!$B:$K, 6, 0) -> Institutes / Clinic | G5: =VLOOKUP($B5, 'Performance Data'!$B:$K, 10, 0) -> Pre-2022 | I5: =VLOOKUP($B5, 'Performance Data'!$B:$K, 7, 0) -> AA | J5: =Z5 -> 30646.91 | K5: =J5*1.08 -> 33098.663 | M5: Grow | O5: =SUMIF('Performance Data'!$B:$B, $B5,'Performance Data'!N:N) -> 20271.78 | P5: =SUMIF('Performance Data'!$B:$B, $B5,'Performance Data'!O:O) -> 30646.91 | Q5: =SUMIF('Performance Data'!$B:$B, $B5,'Performance Data'!P:P) -> 16060 | S5: =$P5/O5-1 -> 0.51180163 | T5: =P5/Q5-1 -> 0.90827584 | V5: =SUMIF('Performance Data'!$B:$B, $B5,'Performance Data'!AC:AC) -> 13827.77 | W5: =SUMIF('Performance Data'!$B:$B, $B5,'Performance Data'!AD:AD) -> 21676.88 | X5: =SUMIF('Performance Data'!$B:$B, $B5,'Performance Data'!AE:AE) -> 20271.78 | Y5: =SUMIF('Performance Data'!$B:$B, $B5,'Performance Data'!AG:AG) -> 22000 | Z5: =P5 -> 30646.91 | AA5: =K5 -> 33098.663 | AC5: =Z5/X5-1 -> 0.51180163 | AD5: =Z5/Y5-1 -> 0.39304136 | AE5: =AA5/Z5-1 -> 0.08 | AG5: =$AA5*AG$1 -> 2316.9064 | AH5: =$AA5*AH$1 -> 2647.893 | AI5: =$AA5*AI$1 -> 3309.8663 | AJ5: =$AA5*AJ$1 -> 2813.3863 | AK5: =$AA5*AK$1 -> 2978.8797 | AL5: =$AA5*AL$1 -> 2647.893 | AM5: =$AA5*AM$1 -> 2647.893 | AN5: =$AA5*AN$1 -> 2151.4131 | ... AR5: =$AA5*AR$1 -> 2316.9064
B6: 20986 | C6: Beletage; Nora Medyan | D6: =VLOOKUP($B6, 'Performance Data'!$B:$K, 3, 0) -> Germany | E6: North East | F6: =VLOOKUP($B6, 'Performance Data'!$B:$K, 6, 0) -> Institutes / Clinic | G6: =VLOOKUP($B6, 'Performance Data'!$B:$K, 10, 0) -> 2023 | H6: Yes | I6: =VLOOKUP($B6, 'Performance Data'!$B:$K, 7, 0) -> BA | J6: =P6 -> 21087.72 | K6: =J6*1.08 -> 22774.738 | M6: Grow | O6: =SUMIF('Performance Data'!$B:$B, $B6,'Performance Data'!N:N) -> 11766.74 | P6: =SUMIF('Performance Data'!$B:$B, $B6,'Performance Data'!O:O) -> 21087.72 | Q6: =SUMIF('Performance Data'!$B:$B, $B6,'Performance Data'!P:P) -> 12045 | S6: =$P6/O6-1 -> 0.79214634 | T6: =P6/Q6-1 -> 0.75074471 | V6: =SUMIF('Performance Data'!$B:$B, $B6,'Performance Data'!AC:AC) -> 0 | W6: =SUMIF('Performance Data'!$B:$B, $B6,'Performance Data'!AD:AD) -> 5962.11 | X6: =SUMIF('Performance Data'!$B:$B, $B6,'Performance Data'!AE:AE) -> 11766.74 | Y6: =SUMIF('Performance Data'!$B:$B, $B6,'Performance Data'!AG:AG) -> 16500 | Z6: =P6 -> 21087.72 | AA6: =K6 -> 22774.738 | AC6: =Z6/X6-1 -> 0.79214634 | AD6: =Z6/Y6-1 -> 0.27804364 | AE6: =AA6/Z6-1 -> 0.08 | AG6: =$AA6*AG$1 -> 1594.2316 | AH6: =$AA6*AH$1 -> 1821.979 | AI6: =$AA6*AI$1 -> 2277.4738 | AJ6: =$AA6*AJ$1 -> 1935.8527 | AK6: =$AA6*AK$1 -> 2049.7264 | AL6: =$AA6*AL$1 -> 1821.979 | AM6: =$AA6*AM$1 -> 1821.979 | AN6: =$AA6*AN$1 -> 1480.3579 | ... AR6: =$AA6*AR$1 -> 1594.2316
B7: 20005 | C7: Heike Kreutzburg | D7: =VLOOKUP($B7, 'Performance Data'!$B:$K, 3, 0) -> Germany | E7: North East | F7: =VLOOKUP($B7, 'Performance Data'!$B:$K, 6, 0) -> Institutes / Clinic | G7: =VLOOKUP($B7, 'Performance Data'!$B:$K, 10, 0) -> Pre-2022 | H7: Yes | I7: =VLOOKUP($B7, 'Performance Data'!$B:$K, 7, 0) -> BB | J7: =P7 -> 17312.06 | K7: =J7*1.08 -> 18697.025 | M7: Grow | O7: =SUMIF('Performance Data'!$B:$B, $B7,'Performance Data'!N:N) -> 15727.2 | P7: =SUMIF('Performance Data'!$B:$B, $B7,'Performance Data'!O:O) -> 17312.06 | Q7: =SUMIF('Performance Data'!$B:$B, $B7,'Performance Data'!P:P) -> 12045 | S7: =$P7/O7-1 -> 0.10077191 | T7: =P7/Q7-1 -> 0.43728186 | V7: =SUMIF('Performance Data'!$B:$B, $B7,'Performance Data'!AC:AC) -> 12843.43 | W7: =SUMIF('Performance Data'!$B:$B, $B7,'Performance Data'!AD:AD) -> 14745.16 | X7: =SUMIF('Performance Data'!$B:$B, $B7,'Performance Data'!AE:AE) -> 15727.2 | Y7: =SUMIF('Performance Data'!$B:$B, $B7,'Performance Data'!AG:AG) -> 16500 | Z7: =P7 -> 17312.06 | AA7: =K7 -> 18697.025 | AC7: =Z7/X7-1 -> 0.10077191 | AD7: =Z7/Y7-1 -> 0.049215758 | AE7: =AA7/Z7-1 -> 0.08 | AG7: =$AA7*AG$1 -> 1308.7917 | AH7: =$AA7*AH$1 -> 1495.762 | AI7: =$AA7*AI$1 -> 1869.7025 | AJ7: =$AA7*AJ$1 -> 1589.2471 | AK7: =$AA7*AK$1 -> 1682.7322 | AL7: =$AA7*AL$1 -> 1495.762 | AM7: =$AA7*AM$1 -> 1495.762 | AN7: =$AA7*AN$1 -> 1215.3066 | ... AR7: =$AA7*AR$1 -> 1308.7917
B8: 20768 | C8: Ariane Dumke (ehem.Stüwe) | D8: =VLOOKUP($B8, 'Performance Data'!$B:$K, 3, 0) -> Germany | E8: North East | F8: =VLOOKUP($B8, 'Performance Data'!$B:$K, 6, 0) -> Hotel Spa | G8: =VLOOKUP($B8, 'Performance Data'!$B:$K, 10, 0) -> Pre-2022 | I8: =VLOOKUP($B8, 'Performance Data'!$B:$K, 7, 0) -> AA | J8: =Z8 -> 32377.18 | K8: =J8*1.08 -> 34967.354 | M8: Maintain | O8: =SUMIF('Performance Data'!$B:$B, $B8,'Performance Data'!N:N) -> 34917.56 | P8: =SUMIF('Performance Data'!$B:$B, $B8,'Performance Data'!O:O) -> 32377.18 | Q8: =SUMIF('Performance Data'!$B:$B, $B8,'Performance Data'!P:P) -> 27740 | S8: =$P8/O8-1 -> -0.072753652 | T8: =P8/Q8-1 -> 0.16716583 | V8: =SUMIF('Performance Data'!$B:$B, $B8,'Performance Data'!AC:AC) -> 33029.46 | W8: =SUMIF('Performance Data'!$B:$B, $B8,'Performance Data'!AD:AD) -> 30364.57 | X8: =SUMIF('Performance Data'!$B:$B, $B8,'Performance Data'!AE:AE) -> 34917.56 | Y8: =SUMIF('Performance Data'!$B:$B, $B8,'Performance Data'!AG:AG) -> 38000 | Z8: =P8 -> 32377.18 | AA8: =K8 -> 34967.354 | AC8: =Z8/X8-1 -> -0.072753652 | AD8: =Z8/Y8-1 -> -0.14796895 | AE8: =AA8/Z8-1 -> 0.08 | AG8: =$AA8*AG$1 -> 2447.7148 | AH8: =$AA8*AH$1 -> 2797.3884 | AI8: =$AA8*AI$1 -> 3496.7354 | AJ8: =$AA8*AJ$1 -> 2972.2251 | AK8: =$AA8*AK$1 -> 3147.0619 | AL8: =$AA8*AL$1 -> 2797.3884 | AM8: =$AA8*AM$1 -> 2797.3884 | AN8: =$AA8*AN$1 -> 2272.878 | ... AR8: =$AA8*AR$1 -> 2447.7148
B9: 20334 | C9: Marion Schlereth | D9: =VLOOKUP($B9, 'Performance Data'!$B:$K, 3, 0) -> Germany | E9: North East | F9: =VLOOKUP($B9, 'Performance Data'!$B:$K, 6, 0) -> Institutes / Clinic | G9: =VLOOKUP($B9, 'Performance Data'!$B:$K, 10, 0) -> Pre-2022 | H9: Yes | I9: =VLOOKUP($B9, 'Performance Data'!$B:$K, 7, 0) -> AA | J9: =P9 -> 33226.21 | K9: =J9*1.08 -> 35884.307 | M9: Maintain | O9: =SUMIF('Performance Data'!$B:$B, $B9,'Performance Data'!N:N) -> 30003.7 | P9: =SUMIF('Performance Data'!$B:$B, $B9,'Performance Data'!O:O) -> 33226.21 | Q9: =SUMIF('Performance Data'!$B:$B, $B9,'Performance Data'!P:P) -> 24090 | S9: =$P9/O9-1 -> 0.10740375 | T9: =P9/Q9-1 -> 0.37925322 | V9: =SUMIF('Performance Data'!$B:$B, $B9,'Performance Data'!AC:AC) -> 23409.82 | W9: =SUMIF('Performance Data'!$B:$B, $B9,'Performance Data'!AD:AD) -> 27161.15 | X9: =SUMIF('Performance Data'!$B:$B, $B9,'Performance Data'!AE:AE) -> 30003.7 | Y9: =SUMIF('Performance Data'!$B:$B, $B9,'Performance Data'!AG:AG) -> 33000 | Z9: =P9 -> 33226.21 | AA9: =K9 -> 35884.307 | AC9: =Z9/X9-1 -> 0.10740375 | AD9: =Z9/Y9-1 -> 0.0068548485 | AE9: =AA9/Z9-1 -> 0.08 | AG9: =$AA9*AG$1 -> 2511.9015 | AH9: =$AA9*AH$1 -> 2870.7445 | AI9: =$AA9*AI$1 -> 3588.4307 | AJ9: =$AA9*AJ$1 -> 3050.1661 | AK9: =$AA9*AK$1 -> 3229.5876 | AL9: =$AA9*AL$1 -> 2870.7445 | AM9: =$AA9*AM$1 -> 2870.7445 | AN9: =$AA9*AN$1 -> 2332.4799 | ... AR9: =$AA9*AR$1 -> 2511.9015
B10: 20697 | C10: Sonja Zgrabic | D10: =VLOOKUP($B10, 'Performance Data'!$B:$K, 3, 0) -> Germany | E10: North East | F10: =VLOOKUP($B10, 'Performance Data'!$B:$K, 6, 0) -> Institutes / Clinic | G10: =VLOOKUP($B10, 'Performance Data'!$B:$K, 10, 0) -> 2025 | I10: =VLOOKUP($B10, 'Performance Data'!$B:$K, 7, 0) -> NKD25 | J10: =P10 -> 12706.38 | K10: =J10*1.08 -> 13722.89 | M10: Grow | O10: =SUMIF('Performance Data'!$B:$B, $B10,'Performance Data'!N:N) -> 0 | P10: =SUMIF('Performance Data'!$B:$B, $B10,'Performance Data'!O:O) -> 12706.38 | Q10: =SUMIF('Performance Data'!$B:$B, $B10,'Performance Data'!P:P) -> 0 | S10: =$P10/O10-1 -> #DIV/0! | T10: =P10/Q10-1 -> #DIV/0! | V10: =SUMIF('Performance Data'!$B:$B, $B10,'Performance Data'!AC:AC) -> 1866.36 | W10: =SUMIF('Performance Data'!$B:$B, $B10,'Performance Data'!AD:AD) -> 0 | X10: =SUMIF('Performance Data'!$B:$B, $B10,'Performance Data'!AE:AE) -> 0 | Y10: =SUMIF('Performance Data'!$B:$B, $B10,'Performance Data'!AG:AG) -> 0 | Z10: =P10 -> 12706.38 | AA10: =K10 -> 13722.89 | AC10: =Z10/X10-1 -> #DIV/0! | AD10: =Z10/Y10-1 -> #DIV/0! | AE10: =AA10/Z10-1 -> 0.08 | AG10: =$AA10*AG$1 -> 960.60233 | AH10: =$AA10*AH$1 -> 1097.8312 | AI10: =$AA10*AI$1 -> 1372.289 | AJ10: =$AA10*AJ$1 -> 1166.4457 | AK10: =$AA10*AK$1 -> 1235.0601 | AL10: =$AA10*AL$1 -> 1097.8312 | AM10: =$AA10*AM$1 -> 1097.8312 | AN10: =$AA10*AN$1 -> 891.98788 | ... AR10: =$AA10*AR$1 -> 960.60233
B11: 20024 | C11: Gudrun Möderl | D11: =VLOOKUP($B11, 'Performance Data'!$B:$K, 3, 0) -> Germany | E11: North East | F11: =VLOOKUP($B11, 'Performance Data'!$B:$K, 6, 0) -> Perfumery | G11: =VLOOKUP($B11, 'Performance Data'!$B:$K, 10, 0) -> Pre-2022 | H11: Yes | I11: =VLOOKUP($B11, 'Performance Data'!$B:$K, 7, 0) -> AB | J11: =P11 -> 26726.42 | K11: =J11*1.08 -> 28864.534 | M11: Maintain | O11: =SUMIF('Performance Data'!$B:$B, $B11,'Performance Data'!N:N) -> 26706.73 | P11: =SUMIF('Performance Data'!$B:$B, $B11,'Performance Data'!O:O) -> 26726.42 | Q11: =SUMIF('Performance Data'!$B:$B, $B11,'Performance Data'!P:P) -> 20440 | S11: =$P11/O11-1 -> 0.00073726735 | T11: =P11/Q11-1 -> 0.30755479 | V11: =SUMIF('Performance Data'!$B:$B, $B11,'Performance Data'!AC:AC) -> 21974.44 | W11: =SUMIF('Performance Data'!$B:$B, $B11,'Performance Data'!AD:AD) -> 23292.94 | X11: =SUMIF('Performance Data'!$B:$B, $B11,'Performance Data'!AE:AE) -> 26706.73 | Y11: =SUMIF('Performance Data'!$B:$B, $B11,'Performance Data'!AG:AG) -> 28000 | Z11: =P11 -> 26726.42 | AA11: =K11 -> 28864.534 | AC11: =Z11/X11-1 -> 0.00073726735 | AD11: =Z11/Y11-1 -> -0.045485 | AE11: =AA11/Z11-1 -> 0.08 | AG11: =$AA11*AG$1 -> 2020.5174 | AH11: =$AA11*AH$1 -> 2309.1627 | AI11: =$AA11*AI$1 -> 2886.4534 | AJ11: =$AA11*AJ$1 -> 2453.4854 | AK11: =$AA11*AK$1 -> 2597.808 | AL11: =$AA11*AL$1 -> 2309.1627 | AM11: =$AA11*AM$1 -> 2309.1627 | AN11: =$AA11*AN$1 -> 1876.1947 | ... AR11: =$AA11*AR$1 -> 2020.5174
B12: 20948 | C12: MP Cosmetic; Milita Pernawas | D12: =VLOOKUP($B12, 'Performance Data'!$B:$K, 3, 0) -> Germany | E12: North East | F12: =VLOOKUP($B12, 'Performance Data'!$B:$K, 6, 0) -> Institutes / Clinic | G12: =VLOOKUP($B12, 'Performance Data'!$B:$K, 10, 0) -> 2022 | I12: =VLOOKUP($B12, 'Performance Data'!$B:$K, 7, 0) -> AA | J12: =Z12 -> 39367.54 | K12: =J12*1.08 -> 42516.943 | M12: Grow | O12: =SUMIF('Performance Data'!$B:$B, $B12,'Performance Data'!N:N) -> 21467.58 | P12: =SUMIF('Performance Data'!$B:$B, $B12,'Performance Data'!O:O) -> 39367.54 | Q12: =SUMIF('Performance Data'!$B:$B, $B12,'Performance Data'!P:P) -> 16790 | S12: =$P12/O12-1 -> 0.83381359 | T12: =P12/Q12-1 -> 1.3447016 | V12: =SUMIF('Performance Data'!$B:$B, $B12,'Performance Data'!AC:AC) -> 12147.47 | W12: =SUMIF('Performance Data'!$B:$B, $B12,'Performance Data'!AD:AD) -> 25271.08 | X12: =SUMIF('Performance Data'!$B:$B, $B12,'Performance Data'!AE:AE) -> 21467.58 | Y12: =SUMIF('Performance Data'!$B:$B, $B12,'Performance Data'!AG:AG) -> 23000 | Z12: =P12 -> 39367.54 | AA12: =K12 -> 42516.943 | AC12: =Z12/X12-1 -> 0.83381359 | AD12: =Z12/Y12-1 -> 0.71163217 | AE12: =AA12/Z12-1 -> 0.08 | AG12: =$AA12*AG$1 -> 2976.186 | AH12: =$AA12*AH$1 -> 3401.3555 | AI12: =$AA12*AI$1 -> 4251.6943 | AJ12: =$AA12*AJ$1 -> 3613.9402 | AK12: =$AA12*AK$1 -> 3826.5249 | AL12: =$AA12*AL$1 -> 3401.3555 | AM12: =$AA12*AM$1 -> 3401.3555 | AN12: =$AA12*AN$1 -> 2763.6013 | ... AR12: =$AA12*AR$1 -> 2976.186
B13: 20923 | C13: No.1 Cosmetics GmbH; Dirk Brüggemann | D13: =VLOOKUP($B13, 'Performance Data'!$B:$K, 3, 0) -> Germany | E13: North East | F13: =VLOOKUP($B13, 'Performance Data'!$B:$K, 6, 0) -> Institutes / Clinic | G13: =VLOOKUP($B13, 'Performance Data'!$B:$K, 10, 0) -> 2022 | I13: =VLOOKUP($B13, 'Performance Data'!$B:$K, 7, 0) -> BA | J13: =Z13 -> 14797.27 | K13: =J13*1.08 -> 15981.052 | M13: Lose | O13: =SUMIF('Performance Data'!$B:$B, $B13,'Performance Data'!N:N) -> 12455.11 | P13: =SUMIF('Performance Data'!$B:$B, $B13,'Performance Data'!O:O) -> 14797.27 | Q13: =SUMIF('Performance Data'!$B:$B, $B13,'Performance Data'!P:P) -> 7300 | S13: =$P13/O13-1 -> 0.18804812 | T13: =P13/Q13-1 -> 1.0270233 | V13: =SUMIF('Performance Data'!$B:$B, $B13,'Performance Data'!AC:AC) -> 20982.53 | W13: =SUMIF('Performance Data'!$B:$B, $B13,'Performance Data'!AD:AD) -> 18043.48 | X13: =SUMIF('Performance Data'!$B:$B, $B13,'Performance Data'!AE:AE) -> 12455.11 | Y13: =SUMIF('Performance Data'!$B:$B, $B13,'Performance Data'!AG:AG) -> 10000 | Z13: =P13 -> 14797.27 | AA13: =K13 -> 15981.052 | AC13: =Z13/X13-1 -> 0.18804812 | AD13: =Z13/Y13-1 -> 0.479727 | AE13: =AA13/Z13-1 -> 0.08 | AG13: =$AA13*AG$1 -> 1118.6736 | AH13: =$AA13*AH$1 -> 1278.4841 | AI13: =$AA13*AI$1 -> 1598.1052 | AJ13: =$AA13*AJ$1 -> 1358.3894 | AK13: =$AA13*AK$1 -> 1438.2946 | AL13: =$AA13*AL$1 -> 1278.4841 | AM13: =$AA13*AM$1 -> 1278.4841 | AN13: =$AA13*AN$1 -> 1038.7684 | ... AR13: =$AA13*AR$1 -> 1118.6736
