Workbook

Sheet Trackers >>

Sheet Initiative Log - Detailed
B1: Date: | C1: =TODAY() -> 46044 | D1: =MONTH(C1)&RIGHT(YEAR(C1), 2) -> 126
B3: Initiative | C3: Description | D3: Segment | E3: Responsible Director | F3: Responsible Consultant | G3: 2026B Sales Incremental (kEUR) | H3: 2028B Sales Incremental (kEUR) | I3: 2028 Potential Sales (kEUR) | J3: 2026B EBITDA (kEUR) | K3: 2028B EBITDA (kEUR) | L3: 2028 Potential EBITDA (kEUR) | M3: Upfront Cost (Cost prior to revenue) | N3: Size of the prize | O3: Impact on Business Valuation | P3: Level of QMS Control / Influence | Q3: Mgmt Action | R3: Start Date | S3: Review Date | T3: Current status | U3: Updates since last reporting | V3: Key activities until next reporting | W3: Expected long-term developments | X3: Notes | Y3: Sales Planned to date (kEUR) | Z3: Sales achieved to date (kEUR) | AA3: Costs planned to date (kEUR) | AB3: Costs incurred to date (kEUR) | AC3: Costs committed to date (kEUR)
B4: 1.1 Core Market Visibility | C4: Attend more Trade Shows | D4: Core Markets | E4: Giovanni Russo | F4: N/A | G4: ='Initiatives Summary'!$C45*2/3 -> 179.72605 | H4: ='Initiatives Summary'!$AQ45*50% -> 560.63216 | I4: ='1.1 Core Markets Visibility'!$E7*40% -> 640.72247 | J4: =G4*'1.1 Core Markets Visibility'!$K$17+'1.1 Core Markets Visibility'!K20+'1.1 Core Markets Visibility'!K26+'1.1 Core Markets Visibility'!K25 -> -0.9890255 | K4: =H4*'1.1 Core Markets Visibility'!$M$17+'1.1 Core Markets Visibility'!M20+'1.1 Core Markets Visibility'!M26+'1.1 Core Markets Visibility'!M25 -> 194.58878 | L4: =I4*'1.1 Core Markets Visibility'!$E$17+'1.1 Core Markets Visibility'!E20+'1.1 Core Markets Visibility'!E26+'1.1 Core Markets Visibility'!E25 -> 211.8082 | M4: ='1.1 Core Markets Visibility'!K20 -> -120 | N4: =IF(OR(I4>1000,L4>500),"High",IF(OR(I4>500,L4>250),"Medium","Low")) -> Medium | O4: Low | P4: High | Q4: Proceed | R4: 46023 | S4: =R4+6*30 -> 46203 | T4: Not yet started | Y4: =INDEX('1.1 Core Markets Visibility'!$AG$6:$AT$15, 1, MATCH( $D$1, '1.1 Core Markets Visibility'!$AG$4:$AT$4, 0)) -> 0 | AA4: =INDEX('1.1 Core Markets Visibility'!$AG$6:$AT$15, 9, MATCH( $D$1, '1.1 Core Markets Visibility'!$AG$4:$AT$4, 0)) -> 0
C5: Specific PR and Merchandising Support | D5: Core Markets | E5: Giovanni Russo | F5: N/A | G5: ='Initiatives Summary'!$C45*1/3 -> 89.863025 | H5: ='Initiatives Summary'!$AQ45*50% -> 560.63216 | I5: ='1.1 Core Markets Visibility'!$E7*60% -> 961.08371 | J5: ='Initiatives Summary'!$C68-J4 -> -467.41506 | K5: ='Initiatives Summary'!$AQ68-K4 -> -199.99379 | L5: ='1.1 Core Markets Visibility'!E28-L4 -> 126.37422 | M5: ='Initiatives Summary'!$C77-M4 -> -325.74 | N5: =IF(OR(I5>1000,L5>500),"High",IF(OR(I5>500,L5>250),"Medium","Low")) -> Medium | O5: Low | P5: Medium | Q5: Proceed | R5: 46023 | S5: =R5+6*30 -> 46203 | T5: Not yet started | U5: Committed to Platinum Sponsorship at SpaInside (€6k) | W5: SpaInside event planned for Jun-26 | Y5: =INDEX('1.1 Core Markets Visibility'!$AG$6:$AT$15, 2, MATCH( $D$1, '1.1 Core Markets Visibility'!$AG$4:$AT$4, 0)) -> 0 | AA5: =INDEX('1.1 Core Markets Visibility'!$AG$6:$AT$15, 10, MATCH( $D$1, '1.1 Core Markets Visibility'!$AG$4:$AT$4, 0)) -> 0 | AC5: 6
B6: 1.2 Core Markets Team | C6: Additional Team Members (+2 FTE) | D6: Core Markets | E6: Giovanni Russo | F6: N/A | G6: ='Initiatives Summary'!$D45 -> 84 | H6: ='Initiatives Summary'!$AR45 -> 644 | I6: ='1.2 Core Markets Team expansion'!$E7 -> 920 | J6: ='Initiatives Summary'!$D68 -> -72.84 | K6: ='Initiatives Summary'!$AR68 -> 293.26 | L6: ='1.2 Core Markets Team expansion'!$E28 -> 490.6 | M6: ='Initiatives Summary'!$D77 -> -71.7 | N6: =IF(OR(I6>1000,L6>500),"High",IF(OR(I6>500,L6>250),"Medium","Low")) -> Medium | O6: Medium | P6: High | Q6: Proceed | R6: 46113 | S6: =R6+6*30 -> 46293 | T6: Not yet started | Y6: =INDEX('1.2 Core Markets Team expansion'!$AH$7:$AU$11, 1, MATCH($D$1, '1.2 Core Markets Team expansion'!$AH$4:$AU$4, 0)) -> 0 | AA6: =INDEX('1.2 Core Markets Team expansion'!$AH$7:$AU$11, 5, MATCH($D$1, '1.2 Core Markets Team expansion'!$AH$4:$AU$4, 0)) -> 0
B7: 2.1 Mark Wuttke | C7: Spa Chains - Tosca | D7: USA B2B | E7: Melissa Blamey | F7: Mark Wuttke | G7: ='2.1 Mark Wuttke Contact Book'!C46*20% -> 200 | H7: ='2.1 Mark Wuttke Contact Book'!E46*20% -> 400 | I7: ='2.1 Mark Wuttke Contact Book'!E46 -> 2000 | J7: =G7*'2.1 Mark Wuttke Contact Book'!K$29 -> 101.28397 | K7: =H7*'2.1 Mark Wuttke Contact Book'!M$29 -> 217.09177 | L7: =I7*'2.1 Mark Wuttke Contact Book'!E$29 -> 1181.1174 | M7: ='Initiatives Summary'!$E77 -> -95.121506 | N7: =IF(OR(I7>1000,L7>500),"High",IF(OR(I7>500,L7>250),"Medium","Low")) -> High | O7: High | P7: Low | Q7: Performance Review | R7: 45839 | S7: 46174 | T7: Under Review | Y7: =INDEX('2.1 Mark Wuttke Contact Book'!$AH$6:$AU$21,1,MATCH($D$1,'2.1 Mark Wuttke Contact Book'!$AH$4:$AU$4,0)) -> 0 | AA7: =INDEX('2.1 Mark Wuttke Contact Book'!$AH$6:$AU$21,16,MATCH($D$1,'2.1 Mark Wuttke Contact Book'!$AH$4:$AU$4,0)) -> 43
C8: Spa Chains - Woodhouse | D8: USA B2B | E8: Melissa Blamey | F8: Mark Wuttke | G8: ='2.1 Mark Wuttke Contact Book'!C47*40% -> 600 | H8: ='2.1 Mark Wuttke Contact Book'!E47*36%+30 -> 2370 | I8: ='2.1 Mark Wuttke Contact Book'!E47 -> 6500 | J8: =G8*'2.1 Mark Wuttke Contact Book'!K$29 -> 303.85191 | K8: =H8*'2.1 Mark Wuttke Contact Book'!M$29 -> 1286.2687 | L8: =I8*'2.1 Mark Wuttke Contact Book'!E$29 -> 3838.6315 | N8: =IF(OR(I8>1000,L8>500),"High",IF(OR(I8>500,L8>250),"Medium","Low")) -> High | O8: High | P8: Low | Q8: Monitor | R8: 45839 | S8: 46082 | T8: Ongoing | Y8: =INDEX('2.1 Mark Wuttke Contact Book'!$AH$6:$AU$21,2,MATCH($D$1,'2.1 Mark Wuttke Contact Book'!$AH$4:$AU$4,0)) -> 0
C9: Spa Chains - Trilogy | D9: USA B2B | E9: Melissa Blamey | F9: Mark Wuttke | G9: ='2.1 Mark Wuttke Contact Book'!C48*40% -> 400 | H9: ='2.1 Mark Wuttke Contact Book'!E48*40% -> 800 | I9: ='2.1 Mark Wuttke Contact Book'!E48 -> 2000 | J9: =G9*'2.1 Mark Wuttke Contact Book'!K$29 -> 202.56794 | K9: =H9*'2.1 Mark Wuttke Contact Book'!M$29 -> 434.18353 | L9: =I9*'2.1 Mark Wuttke Contact Book'!E$29 -> 1181.1174 | N9: =IF(OR(I9>1000,L9>500),"High",IF(OR(I9>500,L9>250),"Medium","Low")) -> High | O9: High | P9: Low | Q9: Monitor | R9: 45839 | S9: 46082 | T9: Ongoing | Y9: =INDEX('2.1 Mark Wuttke Contact Book'!$AH$6:$AU$21,3,MATCH($D$1,'2.1 Mark Wuttke Contact Book'!$AH$4:$AU$4,0)) -> 0
C10: Spa Chains - Other | D10: USA B2B | E10: Melissa Blamey | F10: Mark Wuttke | G10: ='2.1 Mark Wuttke Contact Book'!C49*20% -> 100 | H10: ='2.1 Mark Wuttke Contact Book'!E49*20% -> 200 | I10: ='2.1 Mark Wuttke Contact Book'!E49 -> 1000 | J10: =G10*'2.1 Mark Wuttke Contact Book'!K$29 -> 50.641985 | K10: =H10*'2.1 Mark Wuttke Contact Book'!M$29 -> 108.54588 | L10: =I10*'2.1 Mark Wuttke Contact Book'!E$29 -> 590.5587 | N10: =IF(OR(I10>1000,L10>500),"High",IF(OR(I10>500,L10>250),"Medium","Low")) -> High | O10: Medium | P10: Low | Q10: Monitor | R10: 45839 | S10: 46082 | T10: Initiated | Y10: =INDEX('2.1 Mark Wuttke Contact Book'!$AH$6:$AU$21,4,MATCH($D$1,'2.1 Mark Wuttke Contact Book'!$AH$4:$AU$4,0)) -> 0
C11: Key Account Openings | D11: USA B2B | E11: Melissa Blamey | F11: Mark Wuttke | G11: ='2.1 Mark Wuttke Contact Book'!C51*30*(1+'2.1 Mark Wuttke Contact Book'!$H$7) -> 19.8 | H11: =('2.1 Mark Wuttke Contact Book'!E51*30+'2.1 Mark Wuttke Contact Book'!D51*50+'2.1 Mark Wuttke Contact Book'!C51*55)*(1+'2.1 Mark Wuttke Contact Book'!$H$7) -> 89.1 | I11: =('2.1 Mark Wuttke Contact Book'!E51*30+'2.1 Mark Wuttke Contact Book'!D51*50+'2.1 Mark Wuttke Contact Book'!C51*55) -> 270 | J11: =G11*'2.1 Mark Wuttke Contact Book'!K$29 -> 10.027113 | K11: =H11*'2.1 Mark Wuttke Contact Book'!M$29 -> 48.357191 | L11: =I11*'2.1 Mark Wuttke Contact Book'!E$29 -> 159.45085 | N11: =IF(OR(I11>1000,L11>500),"High",IF(OR(I11>500,L11>250),"Medium","Low")) -> Low | O11: Medium | P11: Medium | Q11: Monitor | R11: 45839 | S11: 46082 | T11: Initiated | Y11: =INDEX('2.1 Mark Wuttke Contact Book'!$AH$6:$AU$21,5,MATCH($D$1,'2.1 Mark Wuttke Contact Book'!$AH$4:$AU$4,0)) -> 0
C12: Team Improvements / Coaching | D12: USA B2B | E12: Melissa Blamey | F12: Mark Wuttke | G12: ='2.1 Mark Wuttke Contact Book'!K7-SUM('Initiative Log - Detailed'!G7:G11) -> 29.734096 | H12: ='2.1 Mark Wuttke Contact Book'!M7-SUM('Initiative Log - Detailed'!H7:H11) -> 40.185189 | I12: ='2.1 Mark Wuttke Contact Book'!E7-SUM(I7:I11) -> 46.015726 | J12: =G12*'2.1 Mark Wuttke Contact Book'!K$29 -> 15.057936 | K12: =H12*'2.1 Mark Wuttke Contact Book'!M$29 -> 21.809684 | L12: =I12*'2.1 Mark Wuttke Contact Book'!E$29 -> 27.174987 | N12: =IF(OR(I12>1000,L12>500),"High",IF(OR(I12>500,L12>250),"Medium","Low")) -> Low | O12: Low | P12: High | Q12: Monitor | R12: 45839 | S12: 46082 | T12: Ongoing | Y12: =INDEX('2.1 Mark Wuttke Contact Book'!$AH$6:$AU$21,6,MATCH($D$1,'2.1 Mark Wuttke Contact Book'!$AH$4:$AU$4,0)) -> 0
B13: 2.2 Jaime Castle | C13: Med Spas | D13: USA B2B | E13: Melissa Blamey | F13: Jaime Castle | G13: ='2.2 Jaime Contact Book'!C46*(1+'2.2 Jaime Contact Book'!$H$7) -> 510 | H13: ='2.2 Jaime Contact Book'!E46*(1+'2.2 Jaime Contact Book'!$H$7) -> 900 | I13: ='2.2 Jaime Contact Book'!E46 -> 1500 | J13: =G13*'2.2 Jaime Contact Book'!K$29 -> 244.78748 | K13: =H13*'2.2 Jaime Contact Book'!M$29 -> 467.91785 | L13: =I13*'2.2 Jaime Contact Book'!E$29 -> 814.36442 | M13: ='Initiatives Summary'!$F77 -> -166.79623 | N13: =IF(OR(I13>1000,L13>500),"High",IF(OR(I13>500,L13>250),"Medium","Low")) -> High | O13: High | P13: Medium | Q13: Monitor | R13: 45839 | S13: 46082 | T13: Ongoing | Y13: =INDEX('2.2 Jaime Contact Book'!$AH$6:$AU$20, 1, MATCH($D$1, '2.2 Jaime Contact Book'!$AH$4:$AU$4, 0)) -> 0 | AA13: =INDEX('2.2 Jaime Contact Book'!$AH$6:$AU$20, 15, MATCH($D$1, '2.2 Jaime Contact Book'!$AH$4:$AU$4, 0)) -> 24
C14: Extended Salesforce (1099er / MeyerSpa) | D14: USA B2B | E14: Melissa Blamey | F14: Jaime Castle | G14: ='2.2 Jaime Contact Book'!C47*(1+'2.2 Jaime Contact Book'!$H$7) -> 300 | H14: ='2.2 Jaime Contact Book'!E47*(1+'2.2 Jaime Contact Book'!$H$7) -> 1200 | I14: ='2.2 Jaime Contact Book'!E47 -> 2000 | J14: =G14*'2.2 Jaime Contact Book'!K$29 -> 143.99263 | K14: =H14*'2.2 Jaime Contact Book'!M$29 -> 623.89046 | L14: =I14*'2.2 Jaime Contact Book'!E$29 -> 1085.8192 | N14: =IF(OR(I14>1000,L14>500),"High",IF(OR(I14>500,L14>250),"Medium","Low")) -> High | O14: High | P14: Medium | Q14: Monitor | R14: 45839 | S14: 46082 | T14: Ongoing | Y14: =INDEX('2.2 Jaime Contact Book'!$AH$6:$AU$20, 2, MATCH($D$1, '2.2 Jaime Contact Book'!$AH$4:$AU$4, 0)) -> 0
C15: Cruise Ships | D15: USA B2B | E15: Melissa Blamey | F15: Jaime Castle | G15: ='2.2 Jaime Contact Book'!C48*(1+'2.2 Jaime Contact Book'!$H$7) -> 3 | H15: ='2.2 Jaime Contact Book'!E48*(1+'2.2 Jaime Contact Book'!$H$7) -> 450 | I15: ='2.2 Jaime Contact Book'!E48 -> 750 | J15: =G15*'2.2 Jaime Contact Book'!K$29 -> 1.4399263 | K15: =H15*'2.2 Jaime Contact Book'!M$29 -> 233.95892 | L15: =I15*'2.2 Jaime Contact Book'!E$29 -> 407.18221 | N15: =IF(OR(I15>1000,L15>500),"High",IF(OR(I15>500,L15>250),"Medium","Low")) -> Medium | O15: Medium | P15: Low | Q15: Monitor | R15: 45839 | S15: 46266 | T15: Initiated | Y15: =INDEX('2.2 Jaime Contact Book'!$AH$6:$AU$20, 3, MATCH($D$1, '2.2 Jaime Contact Book'!$AH$4:$AU$4, 0)) -> 0
C16: Retail | D16: USA B2B | E16: Melissa Blamey | F16: Jaime Castle | G16: ='2.2 Jaime Contact Book'!C49*(1+'2.2 Jaime Contact Book'!$H$7) -> 30 | H16: ='2.2 Jaime Contact Book'!E49*(1+'2.2 Jaime Contact Book'!$H$7) -> 210 | I16: ='2.2 Jaime Contact Book'!E49 -> 350 | J16: =G16*'2.2 Jaime Contact Book'!K$29 -> 14.399263 | K16: =H16*'2.2 Jaime Contact Book'!M$29 -> 109.18083 | L16: =I16*'2.2 Jaime Contact Book'!E$29 -> 190.01837 | N16: =IF(OR(I16>1000,L16>500),"High",IF(OR(I16>500,L16>250),"Medium","Low")) -> Low | O16: Medium | P16: Low | Q16: Monitor | R16: 45839 | S16: 46266 | T16: Initiated | Y16: =INDEX('2.2 Jaime Contact Book'!$AH$6:$AU$20, 4, MATCH($D$1, '2.2 Jaime Contact Book'!$AH$4:$AU$4, 0)) -> 0
C17: Medical Claims / Storytelling | D17: USA B2B | E17: Melissa Blamey | F17: Jaime Castle | G17: ='2.2 Jaime Contact Book'!K7-SUM(G13:G16) -> 8.849178 | H17: ='2.2 Jaime Contact Book'!M7-SUM(H13:H16) -> 13.804718 | I17: ='2.2 Jaime Contact Book'!E7-SUM(I13:I16) -> 23.007863 | J17: =G17*'2.2 Jaime Contact Book'!K$29 -> 4.2473881 | K17: =H17*'2.2 Jaime Contact Book'!M$29 -> 7.1771931 | L17: =I17*'2.2 Jaime Contact Book'!E$29 -> 12.49119 | N17: =IF(OR(I17>1000,L17>500),"High",IF(OR(I17>500,L17>250),"Medium","Low")) -> Low | O17: Medium | P17: High | Q17: Monitor | R17: 45839 | S17: 46082 | T17: Ongoing | Y17: =INDEX('2.2 Jaime Contact Book'!$AH$6:$AU$20, 5, MATCH($D$1, '2.2 Jaime Contact Book'!$AH$4:$AU$4, 0)) -> 0
B18: 2.3 US visibility | C18: Trade Show Sponsorship | D18: USA B2B | E18: Melissa Blamey | F18: N/A | G18: ='Initiatives Summary'!$G45*2/3 -> 60.432055 | H18: ='Initiatives Summary'!$AU45*50% -> 313.6055 | I18: ='2.3 US Visibility'!$E7*40% -> 358.40629 | J18: =G18*'2.3 US Visibility'!K$17+'2.3 US Visibility'!K20 -> -32.862997 | K18: =H18*'2.3 US Visibility'!M$17+'2.3 US Visibility'!M20 -> 149.38032 | L18: =I18*'2.3 US Visibility'!E$17+'2.3 US Visibility'!E20 -> 184.54894 | M18: ='2.3 US Visibility'!K20 -> -80 | N18: =IF(OR(I18>1000,L18>500),"High",IF(OR(I18>500,L18>250),"Medium","Low")) -> Low | O18: Medium | P18: High | Q18: Proceed | R18: 46023 | S18: =R18+6*30 -> 46203 | T18: Not yet started
C19: Specific PR and Merchandising Support | D19: USA B2B | E19: Melissa Blamey | F19: N/A | G19: ='Initiatives Summary'!$G45*1/3 -> 30.216027 | H19: ='Initiatives Summary'!$AU45*50% -> 313.6055 | I19: ='2.3 US Visibility'!$E7*60% -> 537.60944 | J19: ='2.3 US Visibility'!K28-J18 -> -117.99631 | K19: ='2.3 US Visibility'!M28-K18 -> 24.18422 | L19: ='2.3 US Visibility'!E28-L18 -> 173.14683 | M19: ='2.3 US Visibility'!K37-M18 -> -76.5 | N19: =IF(OR(I19>1000,L19>500),"High",IF(OR(I19>500,L19>250),"Medium","Low")) -> Medium | O19: Medium | P19: Medium | Q19: Proceed | R19: 46023 | S19: 46203 | T19: Not yet started
B20: 2.4 US Team | C20: Additional Team Members (+2 FTE) | D20: USA B2B | E20: Melissa Blamey | F20: N/A | G20: ='Initiatives Summary'!$H45 -> 84 | H20: ='Initiatives Summary'!$AV45 -> 644 | I20: ='2.4 US Team Expansion'!$E7 -> 920 | J20: ='Initiatives Summary'!$H68 -> -157.88 | K20: ='Initiatives Summary'!$AV68 -> 177.14 | L20: ='2.4 US Team Expansion'!$E28 -> 366.2 | M20: ='Initiatives Summary'!$H77 -> -111.7 | N20: =IF(OR(I20>1000,L20>500),"High",IF(OR(I20>500,L20>250),"Medium","Low")) -> Medium | O20: Medium | P20: High | Q20: Proceed | R20: 46113 | S20: =R20+6*30 -> 46293 | T20: Not yet started
B21: 3.1 China | C21: Investment opportunity e.g. KOL EU event | D21: China | E21: Suzanna Uden | F21: N/A | G21: ='Initiatives Summary'!$I45 -> 125 | H21: ='Initiatives Summary'!$AW45 -> 250 | I21: ='3.1 China'!$E7 -> 500 | J21: ='Initiatives Summary'!$I68 -> -33.75 | K21: ='Initiatives Summary'!$AW68 -> 33.75 | L21: ='3.1 China'!$E28 -> 192.5 | M21: ='Initiatives Summary'!$I77 -> -100 | N21: =IF(OR(I21>1000,L21>500),"High",IF(OR(I21>500,L21>250),"Medium","Low")) -> Low | O21: Medium | P21: Low | Q21: Proceed | R21: TBC | S21: TBC | T21: Not yet started
B22: 3.2 Lane Crawford | C22: Lane Crawford dept store HK opening | D22: China | E22: Clare Morgan | F22: N/A | G22: ='Initiatives Summary'!$J45 -> 50 | H22: ='Initiatives Summary'!$AX45 -> 150 | I22: ='3.2 Lane Crawford'!$E7 -> 300 | J22: ='Initiatives Summary'!$J68 -> -23.5 | K22: ='Initiatives Summary'!$AX68 -> 10.25 | L22: ='3.2 Lane Crawford'!$E28 -> 105.5 | M22: ='Initiatives Summary'!$J77 -> -30 | N22: =IF(OR(I22>1000,L22>500),"High",IF(OR(I22>500,L22>250),"Medium","Low")) -> Low | O22: Medium | P22: Medium | Q22: Monitor | R22: 45931 | S22: 46082 | T22: Initiated
B23: 4.1 Nadim Hammoud | C23: Middle East MedSpa / Clinic support | D23: Middle East | E23: Rainer Anskinewitsch | F23: Nadim Hammoud | G23: ='Initiatives Summary'!$K45 -> 35 | H23: ='Initiatives Summary'!$AY45 -> 166.25 | I23: ='4.1 Nadim ME'!$E7 -> 237.5 | J23: ='Initiatives Summary'!$K68 -> 22.4 | K23: ='Initiatives Summary'!$AY68 -> 107.23125 | L23: ='4.1 Nadim ME'!$E28 -> 153.1875 | M23: ='Initiatives Summary'!$K77 -> -15 | N23: =IF(OR(I23>1000,L23>500),"High",IF(OR(I23>500,L23>250),"Medium","Low")) -> Low | O23: Medium | P23: Low | Q23: Monitor | R23: 45839 | S23: 46082 | T23: Cancelled
B24: 4.2 ME Retail | C24: Investment opportunity e.g. Retail Lounge budget | D24: Middle East | E24: Rainer Anskinewitsch | F24: N/A | G24: ='Initiatives Summary'!$L45 -> 50 | H24: ='Initiatives Summary'!$AZ45 -> 125 | I24: ='4.2 ME Retail'!$E7 -> 250 | J24: ='Initiatives Summary'!$L68 -> -18 | K24: ='Initiatives Summary'!$AZ68 -> 30.625 | L24: ='4.2 ME Retail'!$E28 -> 111.25 | M24: ='Initiatives Summary'!$L77 -> 0 | N24: =IF(OR(I24>1000,L24>500),"High",IF(OR(I24>500,L24>250),"Medium","Low")) -> Low | O24: Medium | P24: Low | Q24: Proceed | R24: TBC | S24: TBC | T24: Not yet started
B25: 5.1 Mingo Ku | C25: New APAC distributors | D25: APAC | E25: Suzanna Uden | F25: Mingo Ku | G25: ='Initiatives Summary'!$M45 -> 37.5 | H25: ='Initiatives Summary'!$BA45 -> 75 | I25: ='5.1 Mingo'!$E7 -> 300 | J25: ='Initiatives Summary'!$M68 -> 25.125 | K25: ='Initiatives Summary'!$BA68 -> 50.625 | L25: ='5.1 Mingo'!$E28 -> 202.5 | M25: ='Initiatives Summary'!$M77 -> 0 | N25: =IF(OR(I25>1000,L25>500),"High",IF(OR(I25>500,L25>250),"Medium","Low")) -> Low | O25: Medium | P25: Low | Q25: Monitor | R25: 45839 | S25: 46174 | T25: Ongoing
B26: 5.2 Juan Albanell | C26: New APAC distributors (Malaysia, Singapore, Taiwan) | D26: APAC | E26: Suzanna Uden | F26: Juan Albanell | G26: ='5.2 Juan'!C46*(1+'5.2 Juan'!$H$7) -> 100 | H26: ='5.2 Juan'!E46*(1+'5.2 Juan'!$H$7) -> 200 | I26: ='5.2 Juan'!E46 -> 2000 | J26: =G26*'5.2 Juan'!K$29 -> 57.916667 | K26: =H26*'5.2 Juan'!M$29 -> 119.25153 | L26: =I26*'5.2 Juan'!E$29 -> 1302.9448 | M26: ='Initiatives Summary'!$N77 -> -33 | N26: =IF(OR(I26>1000,L26>500),"High",IF(OR(I26>500,L26>250),"Medium","Low")) -> High | O26: Medium | P26: Low | Q26: Complete | R26: 46023 | S26: 46082 | T26: Cancelled
C27: China sub-distributor support | D27: China | E27: Suzanna Uden | F27: Juan Albanell | G27: =('5.2 Juan'!K7-G26)*50% -> 10 | H27: =('5.2 Juan'!M7-H26)*50% -> 63 | I27: =('5.2 Juan'!E7-I26)*50% -> 630 | J27: =G27*'5.2 Juan'!K$29 -> 5.7916667 | K27: =H27*'5.2 Juan'!M$29 -> 37.564233 | L27: =I27*'5.2 Juan'!E$29 -> 410.42761 | N27: =IF(OR(I27>1000,L27>500),"High",IF(OR(I27>500,L27>250),"Medium","Low")) -> Medium | O27: Medium | P27: Low | Q27: Complete | R27: 46023 | S27: 46082 | T27: Cancelled
C28: Middle East sub-distributor support | D28: Middle East | E28: Rainer Anskinewitsch | F28: Juan Albanell | G28: =('5.2 Juan'!K7-G26)*50% -> 10 | H28: =('5.2 Juan'!M7-H26)*50% -> 63 | I28: =('5.2 Juan'!E7-I26)*50% -> 630 | J28: =G28*'5.2 Juan'!K$29 -> 5.7916667 | K28: =H28*'5.2 Juan'!M$29 -> 37.564233 | L28: =I28*'5.2 Juan'!E$29 -> 410.42761 | N28: =IF(OR(I28>1000,L28>500),"High",IF(OR(I28>500,L28>250),"Medium","Low")) -> Medium | O28: Medium | P28: Low | Q28: Complete | R28: 46023 | S28: 46082 | T28: Cancelled
B29: 5.3 Vishal Mishra | C29: Support opening of India | D29: APAC | E29: Suzanna Uden | F29: Vishal Mishra | G29: ='Initiatives Summary'!$O45 -> 25 | H29: ='Initiatives Summary'!$BC45 -> 50 | I29: ='5.3 Vishal_India'!$E7 -> 100 | J29: ='Initiatives Summary'!$O68 -> -19.25 | K29: ='Initiatives Summary'!$BC68 -> -9.81 | L29: ='5.3 Vishal_India'!$E28 -> 23.94 | M29: ='Initiatives Summary'!$O77 -> -18 | N29: =IF(OR(I29>1000,L29>500),"High",IF(OR(I29>500,L29>250),"Medium","Low")) -> Low | O29: Low | P29: Low | Q29: Monitor | R29: 45839 | S29: 46174 | T29: Ongoing
B30: 5.4 International Event | C30: International and US event (biannual) | D30: Export | E30: Viola Kleist | F30: N/A | G30: ='Initiatives Summary'!$P45 -> 36.459375 | H30: ='Initiatives Summary'!$BD45 -> 44.25 | I30: ='5.4 Export Event'!$E7 -> 59 | J30: ='Initiatives Summary'!$P68 -> -101.30141 | K30: ='Initiatives Summary'!$BD68 -> -108.01625 | L30: ='5.4 Export Event'!$E28 -> -98.355 | M30: ='Initiatives Summary'!$P77 -> -125 | N30: =IF(OR(I30>1000,L30>500),"High",IF(OR(I30>500,L30>250),"Medium","Low")) -> Low | O30: Medium | P30: High | Q30: Proceed | R30: 45992 | S30: 46113 | T30: Cancelled
B31: 5.5 ABC Brokers | C31: New global distributors from network of Eduardo Emilio | D31: Export | E31: Rainer Anskinewitsch | F31: Eduardo Emilio | G31: ='Initiatives Log'!G17 -> 250 | H31: ='Initiatives Log'!H17 -> 1000 | I31: ='Initiatives Log'!I17 -> 2000 | J31: ='Initiatives Log'!J17 -> 157.5 | K31: ='Initiatives Log'!K17 -> 655 | L31: ='Initiatives Log'!L17 -> 1330 | M31: ='Initiatives Log'!M17 -> -8 | N31: =IF(OR(I31>1000,L31>500),"High",IF(OR(I31>500,L31>250),"Medium","Low")) -> High | O31: Medium | P31: Low | Q31: Proceed | R31: 45992 | S31: 46174 | T31: Not yet started
B32: 6.1 eComm EU | C32: Additional EU eComm paid media | D32: eCommerce | E32: Viola Kleist | F32: N/A | G32: ='Initiatives Summary'!$R45 -> 252.7 | H32: ='Initiatives Summary'!$BF45 -> 484.69575 | I32: ='6.1 eComm Growth EU'!$E7 -> 692.4225 | J32: ='Initiatives Summary'!$R68 -> -46.293 | K32: ='Initiatives Summary'!$BF68 -> 134.80911 | L32: ='6.1 eComm Growth EU'!$E28 -> 320.72455 | M32: ='Initiatives Summary'!$R77 -> -22.599667 | N32: =IF(OR(I32>1000,L32>500),"High",IF(OR(I32>500,L32>250),"Medium","Low")) -> Medium | O32: Medium | P32: High | Q32: Proceed | R32: 46023 | S32: 46082 | T32: Not yet started
B33: 6.2 eComm US | C33: Additional US eComm paid media | D33: eCommerce | E33: Viola Kleist | F33: N/A | G33: ='Initiatives Summary'!$S45 -> 119.7 | H33: ='Initiatives Summary'!$BG45 -> 308.80325 | I33: ='6.2 eComm Growth US'!$E7 -> 441.1475 | J33: ='Initiatives Summary'!$S68 -> -7.944 | K33: ='Initiatives Summary'!$BG68 -> 148.39968 | L33: ='6.2 eComm Growth US'!$E28 -> 265.52434 | M33: ='Initiatives Summary'!$S77 -> -9.44 | N33: =IF(OR(I33>1000,L33>500),"High",IF(OR(I33>500,L33>250),"Medium","Low")) -> Medium | O33: Medium | P33: High | Q33: Proceed | R33: 46023 | S33: 46082 | T33: Not yet started
B34: 7.1 NPD | C34: Cambrium Longevity and 4th Gen Collagen projects | D34: All | E34: Stefanie Wriedt | F34: Cambrium | G34: ='Initiatives Summary'!$T45 -> 154.41748 | H34: ='Initiatives Summary'!$BH45 -> 810.13109 | I34: ='7.1 Cambrium NPD'!$E7 -> 1080.1748 | J34: ='Initiatives Summary'!$T68 -> 22.474211 | K34: ='Initiatives Summary'!$BH68 -> 573.25818 | L34: ='7.1 Cambrium NPD'!$E28 -> 769.34424 | M34: ='Initiatives Summary'!$T77 -> -300 | N34: =IF(OR(I34>1000,L34>500),"High",IF(OR(I34>500,L34>250),"Medium","Low")) -> High | O34: High | P34: High | Q34: Proceed | R34: 46023 | S34: 46296 | T34: Not yet started
B35: 7.2 Social Media | C35: Social Media and Awareness Campaign | D35: All | E35: Viola Kleist | F35: N/A | G35: ='Initiatives Summary'!$U45 -> 205.88997 | H35: ='Initiatives Summary'!$BI45 -> 405.06555 | I35: ='7.2 Social Media_Mkting'!$E7 -> 540.08739 | J35: ='Initiatives Summary'!$U68 -> -161.03438 | K35: ='Initiatives Summary'!$BI68 -> 60.879092 | L35: ='7.2 Social Media_Mkting'!$E7 -> 540.08739 | M35: ='Initiatives Summary'!$U77 -> -311 | N35: =IF(OR(I35>1000,L35>500),"High",IF(OR(I35>500,L35>250),"Medium","Low")) -> High | O35: High | P35: High | Q35: Proceed | R35: 46023 | S35: 46174 | T35: Not yet started
B37: Total | G37: =SUM(G4:G36) -> 4191.2873 | H37: =SUM(H4:H36) -> 13904.761 | I37: =SUM(I4:I36) -> 30537.178 | J37: =SUM(J4:J36) -> 128.24057 | K37: =SUM(K4:K36) -> 6078.3226 | L37: =SUM(L4:L36) -> 17080.607 | M37: =SUM(M4:M36) -> -2019.5974

Sheet BAU Log - Detailed
B1: Date: | C1: =TODAY() -> 46044 | D1: =MONTH(C1)&RIGHT(YEAR(C1), 2) -> 126 | F1: Update
B3: Segment | C3: Responsible Director | D3: 2026B Sales (kEUR) | E3: 2028B Sales (kEUR) | F3: Size of the prize | G3: Impact on Business Valuation | H3: Level of QMS Control / Influence | I3: Current status | J3: Roadblocks | K3: Enablers | L3: Accelerators | M3: Updates since last reporting | N3: Key activities until next reporting | O3: Expected long-term developments | P3: Notes | Q3: Sales Planned to date (kEUR) | R3: Sales achieved to date (kEUR)
B4: Core Markets | C4: Giovanni Russo | D4: ='3YP'!E11 -> 7837.575 | E4: ='3YP'!G11 -> 9226.8725 | F4: =IF(E4>3000,"High",IF(E4>1500,"Medium","Low")) -> High | G4: High | H4: High | I4: On Track | J4: 1. Lack of visibility / brand awareness 2. Team capability / flexibility 3. Saturated marketplace | L4: Initiatives 1.1 and 1.2
B5: UK B2B | C5: Clare Morgan | D5: ='3YP'!E15 -> 496.7 | E5: ='3YP'!G15 -> 850.57 | F5: =IF(E5>3000,"High",IF(E5>1500,"Medium","Low")) -> Low | G5: Low | H5: High | I5: On Track | J5: 1. Lack of visibility / brand awareness 2. Use of consultants to minimise team spend 3. Saturated marketplace
B6: USA B2B | C6: Melissa Blamey | D6: ='3YP'!E19 -> 1003.242 | E6: ='3YP'!G19 -> 1553.8575 | F6: =IF(E6>3000,"High",IF(E6>1500,"Medium","Low")) -> Medium | G6: High | H6: Medium | I6: Behind | J6: 1. Lack of visibility / brand awareness 2. Team rotation / capability 3. Saturated marketplace
B7: Export | C7: Rainer Anskinewitsch | D7: ='3YP'!E28 -> 1944.5 | E7: ='3YP'!G28 -> 2360 | F7: =IF(E7>3000,"High",IF(E7>1500,"Medium","Low")) -> Medium | G7: Medium | H7: Low | I7: On Track | J7: 1. Lack of visibility / brand awareness 2. No dedicated team for growth 3. Complicated regulatory environments 4. Limited high value markets left untouched
B8: Company 1 | D8: =SUM(D4:D7) -> 11282.017 | E8: =SUM(E4:E7) -> 13991.3 | F8: High | G8: High | H8: Medium | I8: On Track
B10: China | C10: Suzanna Uden | D10: ='3YP'!E32 -> 800 | E10: ='3YP'!G32 -> 1600 | F10: =IF(E10>3000,"High",IF(E10>1500,"Medium","Low")) -> Medium | G10: High | H10: Low | I10: Behind
B11: Middle East | C11: Rainer Anskinewitsch | D11: ='3YP'!E33 -> 200 | E11: ='3YP'!G33 -> 500 | F11: =IF(E11>3000,"High",IF(E11>1500,"Medium","Low")) -> Low | G11: Medium | H11: Low | I11: Behind
B12: APAC | C12: Suzanna Uden | D12: ='3YP'!E34 -> 145 | E12: ='3YP'!G34 -> 375 | F12: =IF(E12>3000,"High",IF(E12>1500,"Medium","Low")) -> Low | G12: Medium | H12: Low | I12: Behind
B13: Company 2 | D13: =SUM(D10:D12) -> 1145 | E13: =SUM(E10:E12) -> 2475 | F13: Medium | G13: Medium | H13: Low | I13: Behind
B15: eCommerce EU | C15: Viola Kleist | D15: ='3YP'!E38 -> 748 | E15: ='3YP'!G38 -> 888.624 | F15: =IF(E15>3000,"High",IF(E15>1500,"Medium","Low")) -> Low | G15: Medium | H15: High | I15: On Track
B16: eCommerce US | C16: Viola Kleist | D16: ='3YP'!E39 -> 406 | E16: ='3YP'!G39 -> 482.328 | F16: =IF(E16>3000,"High",IF(E16>1500,"Medium","Low")) -> Low | G16: Medium | H16: High | I16: Ahead
B17: Amazon | C17: Viola Kleist | D17: ='3YP'!E40 -> 110 | E17: ='3YP'!G40 -> 130.68 | F17: =IF(E17>3000,"High",IF(E17>1500,"Medium","Low")) -> Low | G17: Medium | H17: High | I17: Ahead
B18: Other Online | C18: Clare Morgan | D18: ='3YP'!E41 -> 34.981105 | E18: ='3YP'!G41 -> 34.981105 | F18: =IF(E18>3000,"High",IF(E18>1500,"Medium","Low")) -> Low | G18: Low | H18: Low | I18: On Track
B19: Company 3 | D19: =SUM(D15:D18) -> 1298.9811 | E19: =SUM(E15:E18) -> 1536.6131 | F19: Medium | G19: Medium | H19: High | I19: Ahead
B21: Total QMS | D21: =SUM(D19,D13,D8) -> 13725.998 | E21: =SUM(E19,E13,E8) -> 18002.913

Sheet Definition
C1: Definition | D1: Examples
B2: Roadblocks | C2: Factual issues that are both controllable and uncontrollable, that negatively impact our plans for success. | D2: 1. Lack of Brand Awareness 2. Internal Capabilities / existing team performance 3. Economic sanctions or macro-economic factors
B3: Enablers | C3: Controllable actions or factors that can be taken within our Base budget | D3: Actions: 1. Refocus PR / Marketing budget 2. Attendance of trade shows 3. Team changes - replace A with B (within budget) Factors: 1. Clear professional strategy 2. Capable, motivated, knowledgable team 3. Strong back-office to deliver excellent customer experience
B4: Accelerators | C4: Further controllable actions that could be taken with spend or actions outside of our Base Budget. These would be above and beyond the normal | D4: 1. Significant PR / Awareness campaigns 2. Attendance of 10+ trade shows 3. Additional Team members 4. Team restructuring

Sheet Initiatives >>

Sheet 1.1 Core Markets Visibility
Z1: 0.05 | AA1: 0.1 | AB1: 0.1 | AC1: 0.2 | AD1: 0.25 | AE1: 0.3
B2: More Trade Shows
B3: Significant PR and Media spend | R3: Monthly | S3: Monthly | T3: Monthly | U3: Monthly | V3: Monthly | W3: Monthly | X3: Monthly | Y3: Monthly | Z3: Monthly | AA3: Monthly | AB3: Monthly | AC3: Monthly | AD3: Monthly | AE3: Monthly | AG3: To date | AH3: To date | AI3: To date | AJ3: To date | AK3: To date | AL3: To date | AM3: To date | AN3: To date | AO3: To date | AP3: To date | AQ3: To date | AR3: To date | AS3: To date | AT3: To date
R4: =MONTH(R5)&RIGHT(YEAR(R5), 2) -> 1125 | S4: =MONTH(S5)&RIGHT(YEAR(S5), 2) -> 1225 | T4: =MONTH(T5)&RIGHT(YEAR(T5), 2) -> 126 | U4: =MONTH(U5)&RIGHT(YEAR(U5), 2) -> 226 | V4: =MONTH(V5)&RIGHT(YEAR(V5), 2) -> 326 | W4: =MONTH(W5)&RIGHT(YEAR(W5), 2) -> 426 | X4: =MONTH(X5)&RIGHT(YEAR(X5), 2) -> 526 | Y4: =MONTH(Y5)&RIGHT(YEAR(Y5), 2) -> 626 | ... AE4: =MONTH(AE5)&RIGHT(YEAR(AE5), 2) -> 1226 | AG4: =MONTH(AG5)&RIGHT(YEAR(AG5), 2) -> 1125 | AH4: =MONTH(AH5)&RIGHT(YEAR(AH5), 2) -> 1225 | AI4: =MONTH(AI5)&RIGHT(YEAR(AI5), 2) -> 126 | AJ4: =MONTH(AJ5)&RIGHT(YEAR(AJ5), 2) -> 226 | AK4: =MONTH(AK5)&RIGHT(YEAR(AK5), 2) -> 326 | AL4: =MONTH(AL5)&RIGHT(YEAR(AL5), 2) -> 426 | AM4: =MONTH(AM5)&RIGHT(YEAR(AM5), 2) -> 526 | AN4: =MONTH(AN5)&RIGHT(YEAR(AN5), 2) -> 626 | ... AT4: =MONTH(AT5)&RIGHT(YEAR(AT5), 2) -> 1226
C5: 2026 | D5: 2027 | E5: 2028 | H5: Risk Factor | K5: 2026 | L5: 2027 | M5: 2028 | R5: 45962 | S5: 45992 | T5: 46023 | U5: 46054 | V5: 46082 | W5: 46113 | X5: 46143 | Y5: 46174 | Z5: 46204 | AA5: 46235 | AB5: 46266 | AC5: 46296 | AD5: 46327 | AE5: 46357 | AG5: 45962 | AH5: 45992 | AI5: 46023 | AJ5: 46054 | AK5: 46082 | AL5: 46113 | AM5: 46143 | AN5: 46174 | AO5: 46204 | AP5: 46235 | AQ5: 46266 | AR5: 46296 | AS5: 46327 | AT5: 46357
Q6: Trade show - Sales | Z6: =$K7*50%*Z$1 -> 6.7397269 | AA6: =$K7*50%*AA$1 -> 13.479454 | AB6: =$K7*50%*AB$1 -> 13.479454 | AC6: =$K7*50%*AC$1 -> 26.958907 | AD6: =$K7*50%*AD$1 -> 33.698634 | AE6: =$K7*50%*AE$1 -> 40.438361 | AG6: =R6 -> 0 | AH6: =AG6+S6 -> 0 | AI6: =AH6+T6 -> 0 | AJ6: =AI6+U6 -> 0 | AK6: =AJ6+V6 -> 0 | AL6: =AK6+W6 -> 0 | AM6: =AL6+X6 -> 0 | AN6: =AM6+Y6 -> 0 | AO6: =AN6+Z6 -> 6.7397269 | ... AT6: =AS6+AE6 -> 134.79454
B7: Revenue | C7: =C46*10+'3YP'!E11*C47 -> 385.12725 | D7: =C46*20+D46*15+'3YP'!F11*D47 -> 930.46762 | E7: =C46*25+D46*20+E46*15+'3YP'!G11*E47 -> 1601.8062 | H7: -0.3 | J7: Revenue | K7: =C7*(1+$H$7) -> 269.58907 | L7: =D7*(1+$H$7) -> 651.32734 | M7: =E7*(1+$H$7) -> 1121.2643 | Q7: PR & Media - Sales | Z7: =$K7*50%*Z$1 -> 6.7397269 | AA7: =$K7*50%*AA$1 -> 13.479454 | AB7: =$K7*50%*AB$1 -> 13.479454 | AC7: =$K7*50%*AC$1 -> 26.958907 | AD7: =$K7*50%*AD$1 -> 33.698634 | AE7: =$K7*50%*AE$1 -> 40.438361 | AG7: =R7 -> 0 | AH7: =AG7+S7 -> 0 | AI7: =AH7+T7 -> 0 | AJ7: =AI7+U7 -> 0 | AK7: =AJ7+V7 -> 0 | AL7: =AK7+W7 -> 0 | AM7: =AL7+X7 -> 0 | AN7: =AM7+Y7 -> 0 | AO7: =AN7+Z7 -> 6.7397269 | ... AT7: =AS7+AE7 -> 134.79454
B8: Cost of Sales | C8: =-C7*(1-COGS!C3) -> -57.769088 | D8: =-D7*(1-COGS!D3) -> -137.24397 | E8: =-E7*(1-COGS!E3) -> -232.2619 | J8: Cost of Sales | K8: =C8*(1+$H$7) -> -40.438361 | L8: =D8*(1+$H$7) -> -96.070782 | M8: =E8*(1+$H$7) -> -162.58333
B10: Gross Profit I | C10: =SUM(C7:C8) -> 327.35816 | D10: =SUM(D7:D8) -> 793.22365 | E10: =SUM(E7:E8) -> 1369.5443 | J10: Gross Profit I | K10: =SUM(K7:K8) -> 229.15071 | L10: =SUM(L7:L8) -> 555.25656 | M10: =SUM(M7:M8) -> 958.681 | Q10: Trade show - adj. EBITDA | V10: =V6*$K$17+V14+SUM($K$25:$K$26)*(V6/SUM($T6:$AE6))/2 -> -12 | W10: =W6*$K$17+W14+SUM($K$25:$K$26)*(W6/SUM($T6:$AE6))/2 -> -12 | X10: =X6*$K$17+X14+SUM($K$25:$K$26)*(X6/SUM($T6:$AE6))/2 -> -12 | Y10: =Y6*$K$17+Y14+SUM($K$25:$K$26)*(Y6/SUM($T6:$AE6))/2 -> -12 | Z10: =Z6*$K$17+Z14+SUM($K$25:$K$26)*(Z6/SUM($T6:$AE6))/2 -> -7.1376021 | AA10: =AA6*$K$17+AA14+SUM($K$25:$K$26)*(AA6/SUM($T6:$AE6))/2 -> -2.2752042 | AB10: =AB6*$K$17+AB14+SUM($K$25:$K$26)*(AB6/SUM($T6:$AE6))/2 -> -2.2752042 | AC10: =AC6*$K$17+AC14+SUM($K$25:$K$26)*(AC6/SUM($T6:$AE6))/2 -> 7.4495915 | ... AE10: =AE6*$K$17+AE14+SUM($K$25:$K$26)*(AE6/SUM($T6:$AE6))/2 -> 17.174387 | AG10: =R10 -> 0 | AH10: =AG10+S10 -> 0 | AI10: =AH10+T10 -> 0 | AJ10: =AI10+U10 -> 0 | AK10: =AJ10+V10 -> -12 | AL10: =AK10+W10 -> -24 | AM10: =AL10+X10 -> -36 | AN10: =AM10+Y10 -> -48 | AO10: =AN10+Z10 -> -55.137602 | ... AT10: =AS10+AE10 -> -22.752042
B11: GP I % | C11: =C10/C$7 -> 0.85 | D11: =D10/D$7 -> 0.8525 | E11: =E10/E$7 -> 0.855 | J11: GP I % | K11: =K10/K$7 -> 0.85 | L11: =L10/L$7 -> 0.8525 | M11: =M10/M$7 -> 0.855 | Q11: PR & Media - adj. EBITDA | V11: =V7*$K$17+V15+SUM($K$25:$K$26)*(V7/SUM($T7:$AE7))/2 -> -54.29 | W11: =W7*$K$17+W15+SUM($K$25:$K$26)*(W7/SUM($T7:$AE7))/2 -> -54.29 | X11: =X7*$K$17+X15+SUM($K$25:$K$26)*(X7/SUM($T7:$AE7))/2 -> -54.29 | Y11: =Y7*$K$17+Y15+SUM($K$25:$K$26)*(Y7/SUM($T7:$AE7))/2 -> -54.29 | Z11: =Z7*$K$17+Z15+SUM($K$25:$K$26)*(Z7/SUM($T7:$AE7))/2 -> -49.427602 | AA11: =AA7*$K$17+AA15+SUM($K$25:$K$26)*(AA7/SUM($T7:$AE7))/2 -> -44.565204 | AB11: =AB7*$K$17+AB15+SUM($K$25:$K$26)*(AB7/SUM($T7:$AE7))/2 -> -44.565204 | AC11: =AC7*$K$17+AC15+SUM($K$25:$K$26)*(AC7/SUM($T7:$AE7))/2 -> -34.840408 | ... AE11: =AE7*$K$17+AE15+SUM($K$25:$K$26)*(AE7/SUM($T7:$AE7))/2 -> -25.115613 | AG11: =R11 -> 0 | AH11: =AG11+S11 -> 0 | AI11: =AH11+T11 -> 0 | AJ11: =AI11+U11 -> 0 | AK11: =AJ11+V11 -> -54.29 | AL11: =AK11+W11 -> -108.58 | AM11: =AL11+X11 -> -162.87 | AN11: =AM11+Y11 -> -217.16 | AO11: =AN11+Z11 -> -266.5876 | ... AT11: =AS11+AE11 -> -445.65204
B13: Shipping and distribution costs | C13: =-C7*'Other COS'!$C$4 -> -3.8512725 | D13: =-D7*'Other COS'!$C$4 -> -9.3046762 | E13: =-E7*'Other COS'!$C$4 -> -16.018062 | J13: Shipping and distribution costs | K13: =-K7*'Other COS'!$C$4 -> -2.6958907 | L13: =-L7*'Other COS'!$C$4 -> -6.5132734 | M13: =-M7*'Other COS'!$C$4 -> -11.212643
B14: Rebates | C14: 0 | D14: =-D7*3% -> -27.914029 | E14: =-E7*3% -> -48.054185 | J14: Rebates | K14: 0 | L14: =-L7*3% -> -19.53982 | M14: =-M7*3% -> -33.63793 | Q14: Trade show - Spend | V14: =$K20*10% -> -12 | W14: =$K20*10% -> -12 | X14: =$K20*10% -> -12 | Y14: =$K20*10% -> -12 | Z14: =$K20*10% -> -12 | AA14: =$K20*10% -> -12 | AB14: =$K20*10% -> -12 | AC14: =$K20*10% -> -12 | ... AE14: =$K20*10% -> -12
Q15: PR & Media - Spend | V15: =$K19*10% -> -54.29 | W15: =$K19*10% -> -54.29 | X15: =$K19*10% -> -54.29 | Y15: =$K19*10% -> -54.29 | Z15: =$K19*10% -> -54.29 | AA15: =$K19*10% -> -54.29 | AB15: =$K19*10% -> -54.29 | AC15: =$K19*10% -> -54.29 | ... AE15: =$K19*10% -> -54.29
B16: Gross profit II | C16: =SUM(C10,C13:C14) -> 323.50689 | D16: =SUM(D10,D13:D14) -> 756.00495 | E16: =SUM(E10,E13:E14) -> 1305.472 | J16: Gross profit II | K16: =SUM(K10,K13:K14) -> 226.45482 | L16: =SUM(L10,L13:L14) -> 529.20346 | M16: =SUM(M10,M13:M14) -> 913.83042
B17: GP II % | C17: =C16/C$7 -> 0.84 | D17: =D16/D$7 -> 0.8125 | E17: =E16/E$7 -> 0.815 | J17: GP II % | K17: =K16/K$7 -> 0.84 | L17: =L16/L$7 -> 0.8125 | M17: =M16/M$7 -> 0.815
B19: Advertising and Marketing | C19: =-Extra!F5/1000 -> -542.9 | D19: =C19*1.1 -> -597.19 | E19: =D19*1.1 -> -656.909 | J19: Advertising and Marketing | K19: =C19 -> -542.9 | L19: =D19 -> -597.19 | M19: =E19 -> -656.909
B20: Sales and Training Expenses | C20: =-Extra!F42/1000 -> -120 | D20: =C20*1.1 -> -132 | E20: =D20*1.1 -> -145.2 | J20: Sales and Training Expenses | K20: =C20 -> -120 | L20: =D20 -> -132 | M20: =E20 -> -145.2
B22: Gross profit III | C22: =SUM(C16,C19:C20) -> -339.39311 | D22: =SUM(D16,D19:D20) -> 26.814945 | E22: =SUM(E16,E19:E20) -> 503.36303 | J22: Gross profit III | K22: =SUM(K16,K19:K20) -> -436.44518 | L22: =SUM(L16,L19:L20) -> -199.98654 | M22: =SUM(M16,M19:M20) -> 111.72142
B23: GP III % | C23: =C22/C$7 -> -0.88124928 | D23: =D22/D$7 -> 0.028818784 | E23: =E22/E$7 -> 0.31424715 | J23: GP III % | K23: =K22/K$7 -> -1.6189275 | L23: =L22/L$7 -> -0.30704459 | M23: =M22/M$7 -> 0.099638792
B25: Personnel Expenses | C25: =-C7*10% -> -38.512725 | D25: =-D7*10% -> -93.046762 | E25: =-E7*10% -> -160.18062 | J25: Personnel Expenses | K25: =-K7*10% -> -26.958907 | L25: =-L7*10% -> -65.132734 | M25: =-M7*10% -> -112.12643
B26: Other Admin Expenses | C26: -5 | D26: -5 | E26: -5 | J26: Other Admin Expenses | K26: -5 | L26: -5 | M26: -5
B28: Adjusted EBITDA | C28: =SUM(C22,C25:C26) -> -382.90583 | D28: =SUM(D22,D25:D26) -> -71.231817 | E28: =SUM(E22,E25:E26) -> 338.18242 | J28: Adjusted EBITDA | K28: =SUM(K22,K25:K26) -> -468.40408 | L28: =SUM(L22,L25:L26) -> -270.11927 | M28: =SUM(M22,M25:M26) -> -5.4050094
B29: Adj EBITDA % | C29: =C28/C$7 -> -0.994232 | D29: =D28/D$7 -> -0.076554858 | E29: =E28/E$7 -> 0.21112568 | J29: Adj EBITDA % | K29: =K28/K$7 -> -1.7374743 | L29: =L28/L$7 -> -0.41472123 | M29: =M28/M$7 -> -0.0048204596
B31: Exceptionals | C31: 0 | D31: 0 | E31: 0 | J31: Exceptionals | K31: 0 | L31: 0 | M31: 0
B33: EBITDA | C33: =SUM(C28,C31) -> -382.90583 | D33: =SUM(D28,D31) -> -71.231817 | E33: =SUM(E28,E31) -> 338.18242 | J33: EBITDA | K33: =SUM(K28,K31) -> -468.40408 | L33: =SUM(L28,L31) -> -270.11927 | M33: =SUM(M28,M31) -> -5.4050094
B34: EBITDA % | C34: =C33/C$7 -> -0.994232 | D34: =D33/D$7 -> -0.076554858 | E34: =E33/E$7 -> 0.21112568 | J34: EBITDA % | K34: =K33/K$7 -> -1.7374743 | L34: =L33/L$7 -> -0.41472123 | M34: =M33/M$7 -> -0.0048204596
B37: Risk Amount | C37: =C20+C19*60% -> -445.74 | F37: 60% marketing spend plus full trade show budget | J37: Risk Amount | K37: =K20+K19*60% -> -445.74 | N37: 60% marketing spend plus full trade show budget
B44: Workings
B46: New doors | C46: 15 | D46: 25 | E46: 30
B47: Existing growth | C47: 0.03 | D47: 0.03 | E47: 0.03

Sheet 1.2 Core Markets Team expansion
U1: 0 | V1: 0 | W1: 0 | X1: 0 | Y1: 0 | Z1: 0 | AA1: 0.1 | AB1: 0.1 | AC1: 0.15 | AD1: 0.2 | AE1: 0.2 | AF1: 0.25
B2: +1 FTE CH
B3: +1 FTE DE | S3: Monthly | T3: Monthly | U3: Monthly | V3: Monthly | W3: Monthly | X3: Monthly | Y3: Monthly | Z3: Monthly | AA3: Monthly | AB3: Monthly | AC3: Monthly | AD3: Monthly | AE3: Monthly | AF3: Monthly | AH3: To date | AI3: To date | AJ3: To date | AK3: To date | AL3: To date | AM3: To date | AN3: To date | AO3: To date | AP3: To date | AQ3: To date | AR3: To date | AS3: To date | AT3: To date | AU3: To date
S4: =MONTH(S5)&RIGHT(YEAR(S5), 2) -> 1125 | T4: =MONTH(T5)&RIGHT(YEAR(T5), 2) -> 1225 | U4: =MONTH(U5)&RIGHT(YEAR(U5), 2) -> 126 | V4: =MONTH(V5)&RIGHT(YEAR(V5), 2) -> 226 | W4: =MONTH(W5)&RIGHT(YEAR(W5), 2) -> 326 | X4: =MONTH(X5)&RIGHT(YEAR(X5), 2) -> 426 | Y4: =MONTH(Y5)&RIGHT(YEAR(Y5), 2) -> 526 | Z4: =MONTH(Z5)&RIGHT(YEAR(Z5), 2) -> 626 | ... AF4: =MONTH(AF5)&RIGHT(YEAR(AF5), 2) -> 1226 | AH4: =MONTH(AH5)&RIGHT(YEAR(AH5), 2) -> 1125 | AI4: =MONTH(AI5)&RIGHT(YEAR(AI5), 2) -> 1225 | AJ4: =MONTH(AJ5)&RIGHT(YEAR(AJ5), 2) -> 126 | AK4: =MONTH(AK5)&RIGHT(YEAR(AK5), 2) -> 226 | AL4: =MONTH(AL5)&RIGHT(YEAR(AL5), 2) -> 326 | AM4: =MONTH(AM5)&RIGHT(YEAR(AM5), 2) -> 426 | AN4: =MONTH(AN5)&RIGHT(YEAR(AN5), 2) -> 526 | AO4: =MONTH(AO5)&RIGHT(YEAR(AO5), 2) -> 626 | ... AU4: =MONTH(AU5)&RIGHT(YEAR(AU5), 2) -> 1226
C5: 2026 | D5: 2027 | E5: 2028 | H5: Risk Factor | K5: 2026 | L5: 2027 | M5: 2028 | S5: 45962 | T5: 45992 | U5: 46023 | V5: 46054 | W5: 46082 | X5: 46113 | Y5: 46143 | Z5: 46174 | AA5: 46204 | AB5: 46235 | AC5: 46266 | AD5: 46296 | AE5: 46327 | AF5: 46357 | AH5: 45962 | AI5: 45992 | AJ5: 46023 | AK5: 46054 | AL5: 46082 | AM5: 46113 | AN5: 46143 | AO5: 46174 | AP5: 46204 | AQ5: 46235 | AR5: 46266 | AS5: 46296 | AT5: 46327 | AU5: 46357
B7: Revenue | C7: =C46*10 -> 120 | D7: =C46*20+D46*15 -> 480 | E7: =C46*25+D46*20+E46*15 -> 920 | H7: -0.3 | J7: Revenue | K7: =C7*(1+$H$7) -> 84 | L7: =D7*(1+$H$7) -> 336 | M7: =E7*(1+$H$7) -> 644 | R7: Sales | U7: =$K7*U1 -> 0 | V7: =$K7*V1 -> 0 | W7: =$K7*W1 -> 0 | X7: =$K7*X1 -> 0 | Y7: =$K7*Y1 -> 0 | Z7: =$K7*Z1 -> 0 | AA7: =$K7*AA1 -> 8.4 | AB7: =$K7*AB1 -> 8.4 | ... AF7: =$K7*AF1 -> 21 | AH7: =S7 -> 0 | AI7: =AH7+T7 -> 0 | AJ7: =AI7+U7 -> 0 | AK7: =AJ7+V7 -> 0 | AL7: =AK7+W7 -> 0 | AM7: =AL7+X7 -> 0 | AN7: =AM7+Y7 -> 0 | AO7: =AN7+Z7 -> 0 | AP7: =AO7+AA7 -> 8.4 | ... AU7: =AT7+AF7 -> 84
B8: Cost of Sales | C8: =-C7*(1-COGS!C3) -> -18 | D8: =-D7*(1-COGS!D3) -> -70.8 | E8: =-E7*(1-COGS!E3) -> -133.4 | J8: Cost of Sales | K8: =C8*(1+$H$7) -> -12.6 | L8: =D8*(1+$H$7) -> -49.56 | M8: =E8*(1+$H$7) -> -93.38
R9: EBITDA | U9: =U7*$K17-U11 -> 0 | V9: =V7*$K17-V11 -> 0 | W9: =W7*$K17-W11 -> 0 | X9: =X7*$K17-X11 -> -15 | Y9: =Y7*$K17-Y11 -> -15 | Z9: =Z7*$K17-Z11 -> -15 | AA9: =AA7*$K17-AA11 -> -8.784 | AB9: =AB7*$K17-AB11 -> -8.784 | ... AF9: =AF7*$K17-AF11 -> 0.54 | AH9: =S9 -> 0 | AI9: =AH9+T9 -> 0 | AJ9: =AI9+U9 -> 0 | AK9: =AJ9+V9 -> 0 | AL9: =AK9+W9 -> 0 | AM9: =AL9+X9 -> -15 | AN9: =AM9+Y9 -> -30 | AO9: =AN9+Z9 -> -45 | AP9: =AO9+AA9 -> -53.784 | ... AU9: =AT9+AF9 -> -72.84
B10: Gross Profit I | C10: =SUM(C7:C8) -> 102 | D10: =SUM(D7:D8) -> 409.2 | E10: =SUM(E7:E8) -> 786.6 | J10: Gross Profit I | K10: =SUM(K7:K8) -> 71.4 | L10: =SUM(L7:L8) -> 286.44 | M10: =SUM(M7:M8) -> 550.62
B11: GP I % | C11: =C10/C$7 -> 0.85 | D11: =D10/D$7 -> 0.8525 | E11: =E10/E$7 -> 0.855 | J11: GP I % | K11: =K10/K$7 -> 0.85 | L11: =L10/L$7 -> 0.8525 | M11: =M10/M$7 -> 0.855 | R11: Cost | X11: =-($K25+$K7*10%)/9+X7*10%-$K26/9 -> 15 | Y11: =-($K25+$K7*10%)/9+Y7*10%-$K26/9 -> 15 | Z11: =-($K25+$K7*10%)/9+Z7*10%-$K26/9 -> 15 | AA11: =-($K25+$K7*10%)/9+AA7*10%-$K26/9 -> 15.84 | AB11: =-($K25+$K7*10%)/9+AB7*10%-$K26/9 -> 15.84 | AC11: =-($K25+$K7*10%)/9+AC7*10%-$K26/9 -> 16.26 | AD11: =-($K25+$K7*10%)/9+AD7*10%-$K26/9 -> 16.68 | AE11: =-($K25+$K7*10%)/9+AE7*10%-$K26/9 -> 16.68 | AF11: =-($K25+$K7*10%)/9+AF7*10%-$K26/9 -> 17.1 | AH11: =S11 -> 0 | AI11: =AH11+T11 -> 0 | AJ11: =AI11+U11 -> 0 | AK11: =AJ11+V11 -> 0 | AL11: =AK11+W11 -> 0 | AM11: =AL11+X11 -> 15 | AN11: =AM11+Y11 -> 30 | AO11: =AN11+Z11 -> 45 | AP11: =AO11+AA11 -> 60.84 | ... AU11: =AT11+AF11 -> 143.4
B13: Shipping and distribution costs | C13: =-C7*'Other COS'!$C$4 -> -1.2 | D13: =-D7*'Other COS'!$C$4 -> -4.8 | E13: =-E7*'Other COS'!$C$4 -> -9.2 | J13: Shipping and distribution costs | K13: =C13*(1+$H$7) -> -0.84 | L13: =D13*(1+$H$7) -> -3.36 | M13: =E13*(1+$H$7) -> -6.44
B14: Rebates | C14: 0 | D14: =-D7*3% -> -14.4 | E14: =-E7*3% -> -27.6 | J14: Rebates | K14: =C14*(1+$H$7) -> 0 | L14: =D14*(1+$H$7) -> -10.08 | M14: =E14*(1+$H$7) -> -19.32
B16: Gross profit II | C16: =SUM(C10,C13:C14) -> 100.8 | D16: =SUM(D10,D13:D14) -> 390 | E16: =SUM(E10,E13:E14) -> 749.8 | J16: Gross profit II | K16: =SUM(K10,K13:K14) -> 70.56 | L16: =SUM(L10,L13:L14) -> 273 | M16: =SUM(M10,M13:M14) -> 524.86
B17: GP II % | C17: =C16/C$7 -> 0.84 | D17: =D16/D$7 -> 0.8125 | E17: =E16/E$7 -> 0.815 | J17: GP II % | K17: =K16/K$7 -> 0.84 | L17: =L16/L$7 -> 0.8125 | M17: =M16/M$7 -> 0.815
B19: Advertising and Marketing | C19: 0 | D19: 0 | E19: 0 | J19: Advertising and Marketing | K19: =C19 -> 0 | L19: =D19 -> 0 | M19: =E19 -> 0
B20: Sales and Training Expenses | C20: 0 | D20: 0 | E20: 0 | J20: Sales and Training Expenses | K20: =C20 -> 0 | L20: =D20 -> 0 | M20: =E20 -> 0
B22: Gross profit III | C22: =SUM(C16,C19:C20) -> 100.8 | D22: =SUM(D16,D19:D20) -> 390 | E22: =SUM(E16,E19:E20) -> 749.8 | J22: Gross profit III | K22: =SUM(K16,K19:K20) -> 70.56 | L22: =SUM(L16,L19:L20) -> 273 | M22: =SUM(M16,M19:M20) -> 524.86
B23: GP III % | C23: =C22/C$7 -> 0.84 | D23: =D22/D$7 -> 0.8125 | E23: =E22/E$7 -> 0.815 | J23: GP III % | K23: =K22/K$7 -> 0.84 | L23: =L22/L$7 -> 0.8125 | M23: =M22/M$7 -> 0.815
B25: Personnel Expenses | C25: =-C7*10%-60*2 -> -132 | D25: =-D7*10%-60*2*1.1 -> -180 | E25: =-E7*10%-60*2*1.1^2 -> -237.2 | J25: Personnel Expenses | K25: =-K7*10%-60*2 -> -128.4 | L25: =-L7*10%-60*2*1.1 -> -165.6 | M25: =-M7*10%-60*2*1.1^2 -> -209.6
B26: Other Admin Expenses | C26: -15 | D26: -20 | E26: -22 | J26: Other Admin Expenses | K26: =C26 -> -15 | L26: =D26 -> -20 | M26: =E26 -> -22
B28: Adjusted EBITDA | C28: =SUM(C22,C25:C26) -> -46.2 | D28: =SUM(D22,D25:D26) -> 190 | E28: =SUM(E22,E25:E26) -> 490.6 | J28: Adjusted EBITDA | K28: =SUM(K22,K25:K26) -> -72.84 | L28: =SUM(L22,L25:L26) -> 87.4 | M28: =SUM(M22,M25:M26) -> 293.26
B29: Adj EBITDA % | C29: =C28/C$7 -> -0.385 | D29: =D28/D$7 -> 0.39583333 | E29: =E28/E$7 -> 0.53326087 | J29: Adj EBITDA % | K29: =K28/K$7 -> -0.86714286 | L29: =L28/L$7 -> 0.26011905 | M29: =M28/M$7 -> 0.45537267
B31: Exceptionals | C31: 0 | D31: 0 | E31: 0 | J31: Exceptionals | K31: =C31 -> 0 | L31: =D31 -> 0 | M31: =E31 -> 0
B33: EBITDA | C33: =SUM(C28,C31) -> -46.2 | D33: =SUM(D28,D31) -> 190 | E33: =SUM(E28,E31) -> 490.6 | J33: EBITDA | K33: =SUM(K28,K31) -> -72.84 | L33: =SUM(L28,L31) -> 87.4 | M33: =SUM(M28,M31) -> 293.26
B34: EBITDA % | C34: =C33/C$7 -> -0.385 | D34: =D33/D$7 -> 0.39583333 | E34: =E33/E$7 -> 0.53326087 | J34: EBITDA % | K34: =K33/K$7 -> -0.86714286 | L34: =L33/L$7 -> 0.26011905 | M34: =M33/M$7 -> 0.45537267
B37: Risk Amount | C37: =(C25+C26)*6/12 -> -73.5 | F37: 6 months of employee costs | J37: Risk Amount | K37: =(K25+K26)*6/12 -> -71.7 | N37: 6 months of employee costs
B44: Workings
B46: New doors | C46: 12 | D46: 16 | E46: 20

Sheet 2.1 Mark Wuttke Contact Book
B2: Day Spas
B3: Coaching | S3: Monthly | T3: Monthly | U3: Monthly | V3: Monthly | W3: Monthly | X3: Monthly | Y3: Monthly | Z3: Monthly | AA3: Monthly | AB3: Monthly | AC3: Monthly | AD3: Monthly | AE3: Monthly | AF3: Monthly | AH3: To date | AI3: To date | AJ3: To date | AK3: To date | AL3: To date | AM3: To date | AN3: To date | AO3: To date | AP3: To date | AQ3: To date | AR3: To date | AS3: To date | AT3: To date | AU3: To date
S4: =MONTH(S5)&RIGHT(YEAR(S5), 2) -> 1125 | T4: =MONTH(T5)&RIGHT(YEAR(T5), 2) -> 1225 | U4: =MONTH(U5)&RIGHT(YEAR(U5), 2) -> 126 | V4: =MONTH(V5)&RIGHT(YEAR(V5), 2) -> 226 | W4: =MONTH(W5)&RIGHT(YEAR(W5), 2) -> 326 | X4: =MONTH(X5)&RIGHT(YEAR(X5), 2) -> 426 | Y4: =MONTH(Y5)&RIGHT(YEAR(Y5), 2) -> 526 | Z4: =MONTH(Z5)&RIGHT(YEAR(Z5), 2) -> 626 | ... AF4: =MONTH(AF5)&RIGHT(YEAR(AF5), 2) -> 1226 | AH4: =MONTH(AH5)&RIGHT(YEAR(AH5), 2) -> 1125 | AI4: =MONTH(AI5)&RIGHT(YEAR(AI5), 2) -> 1225 | AJ4: =MONTH(AJ5)&RIGHT(YEAR(AJ5), 2) -> 126 | AK4: =MONTH(AK5)&RIGHT(YEAR(AK5), 2) -> 226 | AL4: =MONTH(AL5)&RIGHT(YEAR(AL5), 2) -> 326 | AM4: =MONTH(AM5)&RIGHT(YEAR(AM5), 2) -> 426 | AN4: =MONTH(AN5)&RIGHT(YEAR(AN5), 2) -> 526 | AO4: =MONTH(AO5)&RIGHT(YEAR(AO5), 2) -> 626 | ... AU4: =MONTH(AU5)&RIGHT(YEAR(AU5), 2) -> 1226
C5: 2026 | D5: 2027 | E5: 2028 | H5: Risk Factor | K5: 2026 | L5: 2027 | M5: 2028 | S5: 45962 | T5: 45992 | U5: 46023 | V5: 46054 | W5: 46082 | X5: 46113 | Y5: 46143 | Z5: 46174 | AA5: 46204 | AB5: 46235 | AC5: 46266 | AD5: 46296 | AE5: 46327 | AF5: 46357 | AH5: 45962 | AI5: 45992 | AJ5: 46023 | AK5: 46054 | AL5: 46082 | AM5: 46113 | AN5: 46143 | AO5: 46174 | AP5: 46204 | AQ5: 46235 | AR5: 46266 | AS5: 46296 | AT5: 46327 | AU5: 46357
Q6: Spa Chains - Tosca | R6: Sales | U6: ='Initiative Log - Detailed'!$G7*U27 -> 0 | V6: ='Initiative Log - Detailed'!$G7*V27 -> 0 | W6: ='Initiative Log - Detailed'!$G7*W27 -> 0 | X6: ='Initiative Log - Detailed'!$G7*X27 -> 0 | Y6: ='Initiative Log - Detailed'!$G7*Y27 -> 0 | Z6: ='Initiative Log - Detailed'!$G7*Z27 -> 0 | AA6: ='Initiative Log - Detailed'!$G7*AA27 -> 0 | AB6: ='Initiative Log - Detailed'!$G7*AB27 -> 60 | ... AF6: ='Initiative Log - Detailed'!$G7*AF27 -> 40 | AH6: =S6 -> 0 | AI6: =AH6+T6 -> 0 | AJ6: =AI6+U6 -> 0 | AK6: =AJ6+V6 -> 0 | AL6: =AK6+W6 -> 0 | AM6: =AL6+X6 -> 0 | AN6: =AM6+Y6 -> 0 | AO6: =AN6+Z6 -> 0 | AP6: =AO6+AA6 -> 0 | ... AU6: =AT6+AF6 -> 200
B7: Revenue | C7: =SUM(C46:C49)+C51*30+'3YP'!E17*C52 -> 4089.4973 | D7: =SUM(D46:D49)+D51*30+C51*50+'3YP'!F17*D52 -> 8948.3464 | E7: =SUM(E46:E49)+E51*30+D51*50+C51*55+'3YP'!G17*E52 -> 11816.016 | H7: -0.67 | J7: Revenue | K7: =C7*(1+$H$7) -> 1349.5341 | L7: =D7*(1+$H$7) -> 2952.9543 | M7: =E7*(1+$H$7) -> 3899.2852 | Q7: Spa Chains - Woodhouse | R7: Sales | U7: ='Initiative Log - Detailed'!$G8*U28 -> 0 | V7: ='Initiative Log - Detailed'!$G8*V28 -> 0 | W7: ='Initiative Log - Detailed'!$G8*W28 -> 60 | X7: ='Initiative Log - Detailed'!$G8*X28 -> 18 | Y7: ='Initiative Log - Detailed'!$G8*Y28 -> 24 | Z7: ='Initiative Log - Detailed'!$G8*Z28 -> 24 | AA7: ='Initiative Log - Detailed'!$G8*AA28 -> 90 | AB7: ='Initiative Log - Detailed'!$G8*AB28 -> 42 | ... AF7: ='Initiative Log - Detailed'!$G8*AF28 -> 78 | AH7: =S7 -> 0 | AI7: =AH7+T7 -> 0 | AJ7: =AI7+U7 -> 0 | AK7: =AJ7+V7 -> 0 | AL7: =AK7+W7 -> 60 | AM7: =AL7+X7 -> 78 | AN7: =AM7+Y7 -> 102 | AO7: =AN7+Z7 -> 126 | AP7: =AO7+AA7 -> 216 | ... AU7: =AT7+AF7 -> 600
B8: Cost of Sales | C8: =-C7*(1-COGS!C15+5%) -> -817.89945 | D8: =-D7*(1-COGS!D15+5%) -> -1767.2984 | E8: =-E7*(1-COGS!E15+5%) -> -2304.1231 | J8: Cost of Sales | K8: =C8*(1+$H$7) -> -269.90682 | L8: =D8*(1+$H$7) -> -583.20848 | M8: =E8*(1+$H$7) -> -760.36061 | Q8: Spa Chains - Trilogy | R8: Sales | U8: ='Initiative Log - Detailed'!$G9*U29 -> 0 | V8: ='Initiative Log - Detailed'!$G9*V29 -> 0 | W8: ='Initiative Log - Detailed'!$G9*W29 -> 0 | X8: ='Initiative Log - Detailed'!$G9*X29 -> 40 | Y8: ='Initiative Log - Detailed'!$G9*Y29 -> 16 | Z8: ='Initiative Log - Detailed'!$G9*Z29 -> 24 | AA8: ='Initiative Log - Detailed'!$G9*AA29 -> 60 | AB8: ='Initiative Log - Detailed'!$G9*AB29 -> 28 | ... AF8: ='Initiative Log - Detailed'!$G9*AF29 -> 52 | AH8: =S8 -> 0 | AI8: =AH8+T8 -> 0 | AJ8: =AI8+U8 -> 0 | AK8: =AJ8+V8 -> 0 | AL8: =AK8+W8 -> 0 | AM8: =AL8+X8 -> 40 | AN8: =AM8+Y8 -> 56 | AO8: =AN8+Z8 -> 80 | AP8: =AO8+AA8 -> 140 | ... AU8: =AT8+AF8 -> 400
Q9: Spa Chains - Other | R9: Sales | U9: ='Initiative Log - Detailed'!$G10*U30 -> 0 | V9: ='Initiative Log - Detailed'!$G10*V30 -> 0 | W9: ='Initiative Log - Detailed'!$G10*W30 -> 0 | X9: ='Initiative Log - Detailed'!$G10*X30 -> 0 | Y9: ='Initiative Log - Detailed'!$G10*Y30 -> 0 | Z9: ='Initiative Log - Detailed'!$G10*Z30 -> 0 | AA9: ='Initiative Log - Detailed'!$G10*AA30 -> 0 | AB9: ='Initiative Log - Detailed'!$G10*AB30 -> 0 | ... AF9: ='Initiative Log - Detailed'!$G10*AF30 -> 25 | AH9: =S9 -> 0 | AI9: =AH9+T9 -> 0 | AJ9: =AI9+U9 -> 0 | AK9: =AJ9+V9 -> 0 | AL9: =AK9+W9 -> 0 | AM9: =AL9+X9 -> 0 | AN9: =AM9+Y9 -> 0 | AO9: =AN9+Z9 -> 0 | AP9: =AO9+AA9 -> 0 | ... AU9: =AT9+AF9 -> 100
B10: Gross Profit I | C10: =SUM(C7:C8) -> 3271.5978 | D10: =SUM(D7:D8) -> 7181.048 | E10: =SUM(E7:E8) -> 9511.8927 | J10: Gross Profit I | K10: =SUM(K7:K8) -> 1079.6273 | L10: =SUM(L7:L8) -> 2369.7458 | M10: =SUM(M7:M8) -> 3138.9246 | Q10: Key Account Openings | R10: Sales | U10: ='Initiative Log - Detailed'!$G11*U31 -> 0 | V10: ='Initiative Log - Detailed'!$G11*V31 -> 0 | W10: ='Initiative Log - Detailed'!$G11*W31 -> 0 | X10: ='Initiative Log - Detailed'!$G11*X31 -> 0 | Y10: ='Initiative Log - Detailed'!$G11*Y31 -> 0 | Z10: ='Initiative Log - Detailed'!$G11*Z31 -> 0 | AA10: ='Initiative Log - Detailed'!$G11*AA31 -> 1.98 | AB10: ='Initiative Log - Detailed'!$G11*AB31 -> 1.98 | ... AF10: ='Initiative Log - Detailed'!$G11*AF31 -> 4.95 | AH10: =S10 -> 0 | AI10: =AH10+T10 -> 0 | AJ10: =AI10+U10 -> 0 | AK10: =AJ10+V10 -> 0 | AL10: =AK10+W10 -> 0 | AM10: =AL10+X10 -> 0 | AN10: =AM10+Y10 -> 0 | AO10: =AN10+Z10 -> 0 | AP10: =AO10+AA10 -> 1.98 | ... AU10: =AT10+AF10 -> 19.8
B11: GP I % | C11: =C10/C$7 -> 0.8 | D11: =D10/D$7 -> 0.8025 | E11: =E10/E$7 -> 0.805 | J11: GP I % | K11: =K10/K$7 -> 0.8 | L11: =L10/L$7 -> 0.8025 | M11: =M10/M$7 -> 0.805 | Q11: Team Improvements / Coaching | R11: Sales | U11: ='Initiative Log - Detailed'!$G12*U32 -> 0 | V11: ='Initiative Log - Detailed'!$G12*V32 -> 0 | W11: ='Initiative Log - Detailed'!$G12*W32 -> 2.9734096 | X11: ='Initiative Log - Detailed'!$G12*X32 -> 2.9734096 | Y11: ='Initiative Log - Detailed'!$G12*Y32 -> 2.9734096 | Z11: ='Initiative Log - Detailed'!$G12*Z32 -> 2.9734096 | AA11: ='Initiative Log - Detailed'!$G12*AA32 -> 2.9734096 | AB11: ='Initiative Log - Detailed'!$G12*AB32 -> 2.9734096 | ... AF11: ='Initiative Log - Detailed'!$G12*AF32 -> 2.9734096 | AH11: =S11 -> 0 | AI11: =AH11+T11 -> 0 | AJ11: =AI11+U11 -> 0 | AK11: =AJ11+V11 -> 0 | AL11: =AK11+W11 -> 2.9734096 | AM11: =AL11+X11 -> 5.9468192 | AN11: =AM11+Y11 -> 8.9202287 | AO11: =AN11+Z11 -> 11.893638 | AP11: =AO11+AA11 -> 14.867048 | ... AU11: =AT11+AF11 -> 29.734096
B13: Shipping and distribution costs | C13: =-C7*'Other COS'!$C$16 -> -286.26481 | D13: =-D7*'Other COS'!$C$16 -> -626.38425 | E13: =-E7*'Other COS'!$C$16 -> -827.1211 | J13: Shipping and distribution costs | K13: =-K7*'Other COS'!$C$16 -> -94.467387 | L13: =-L7*'Other COS'!$C$16 -> -206.7068 | M13: =-M7*'Other COS'!$C$16 -> -272.94996
B14: Rebates | C14: =-SUM(C46:C49)*5% -> -200 | D14: =-SUM(D46:D49)*5% -> -437.5 | E14: =-SUM(E46:E49)*5% -> -575 | J14: Rebates | K14: =C14*(1+$H$7) -> -66 | L14: =D14*(1+$H$7) -> -144.375 | M14: =E14*(1+$H$7) -> -189.75 | Q14: Spa Chains - Tosca | R14: EBITDA | U14: ='Initiative Log - Detailed'!$J7*U27 -> 0 | V14: ='Initiative Log - Detailed'!$J7*V27 -> 0 | W14: ='Initiative Log - Detailed'!$J7*W27 -> 0 | X14: ='Initiative Log - Detailed'!$J7*X27 -> 0 | Y14: ='Initiative Log - Detailed'!$J7*Y27 -> 0 | Z14: ='Initiative Log - Detailed'!$J7*Z27 -> 0 | AA14: ='Initiative Log - Detailed'!$J7*AA27 -> 0 | AB14: ='Initiative Log - Detailed'!$J7*AB27 -> 30.385191 | ... AF14: ='Initiative Log - Detailed'!$J7*AF27 -> 20.256794 | AH14: =S14 -> 0 | AI14: =AH14+T14 -> 0 | AJ14: =AI14+U14 -> 0 | AK14: =AJ14+V14 -> 0 | AL14: =AK14+W14 -> 0 | AM14: =AL14+X14 -> 0 | AN14: =AM14+Y14 -> 0 | AO14: =AN14+Z14 -> 0 | AP14: =AO14+AA14 -> 0 | ... AU14: =AT14+AF14 -> 101.28397
Q15: Spa Chains - Woodhouse | R15: EBITDA | U15: ='Initiative Log - Detailed'!$J8*U28 -> 0 | V15: ='Initiative Log - Detailed'!$J8*V28 -> 0 | W15: ='Initiative Log - Detailed'!$J8*W28 -> 30.385191 | X15: ='Initiative Log - Detailed'!$J8*X28 -> 9.1155573 | Y15: ='Initiative Log - Detailed'!$J8*Y28 -> 12.154076 | Z15: ='Initiative Log - Detailed'!$J8*Z28 -> 12.154076 | AA15: ='Initiative Log - Detailed'!$J8*AA28 -> 45.577787 | AB15: ='Initiative Log - Detailed'!$J8*AB28 -> 21.269634 | ... AF15: ='Initiative Log - Detailed'!$J8*AF28 -> 39.500748 | AH15: =S15 -> 0 | AI15: =AH15+T15 -> 0 | AJ15: =AI15+U15 -> 0 | AK15: =AJ15+V15 -> 0 | AL15: =AK15+W15 -> 30.385191 | AM15: =AL15+X15 -> 39.500748 | AN15: =AM15+Y15 -> 51.654825 | AO15: =AN15+Z15 -> 63.808901 | AP15: =AO15+AA15 -> 109.38669 | ... AU15: =AT15+AF15 -> 303.85191
B16: Gross profit II | C16: =SUM(C10,C13:C14) -> 2785.333 | D16: =SUM(D10,D13:D14) -> 6117.1638 | E16: =SUM(E10,E13:E14) -> 8109.7716 | J16: Gross profit II | K16: =SUM(K10,K13:K14) -> 919.15989 | L16: =SUM(L10,L13:L14) -> 2018.664 | M16: =SUM(M10,M13:M14) -> 2676.2246 | Q16: Spa Chains - Trilogy | R16: EBITDA | U16: ='Initiative Log - Detailed'!$J9*U29 -> 0 | V16: ='Initiative Log - Detailed'!$J9*V29 -> 0 | W16: ='Initiative Log - Detailed'!$J9*W29 -> 0 | X16: ='Initiative Log - Detailed'!$J9*X29 -> 20.256794 | Y16: ='Initiative Log - Detailed'!$J9*Y29 -> 8.1027176 | Z16: ='Initiative Log - Detailed'!$J9*Z29 -> 12.154076 | AA16: ='Initiative Log - Detailed'!$J9*AA29 -> 30.385191 | AB16: ='Initiative Log - Detailed'!$J9*AB29 -> 14.179756 | ... AF16: ='Initiative Log - Detailed'!$J9*AF29 -> 26.333832 | AH16: =S16 -> 0 | AI16: =AH16+T16 -> 0 | AJ16: =AI16+U16 -> 0 | AK16: =AJ16+V16 -> 0 | AL16: =AK16+W16 -> 0 | AM16: =AL16+X16 -> 20.256794 | AN16: =AM16+Y16 -> 28.359512 | AO16: =AN16+Z16 -> 40.513588 | AP16: =AO16+AA16 -> 70.898779 | ... AU16: =AT16+AF16 -> 202.56794
B17: GP II % | C17: =C16/C$7 -> 0.68109423 | D17: =D16/D$7 -> 0.68360829 | E17: =E16/E$7 -> 0.68633723 | J17: GP II % | K17: =K16/K$7 -> 0.68109423 | L17: =L16/L$7 -> 0.68360829 | M17: =M16/M$7 -> 0.68633723 | Q17: Spa Chains - Other | R17: EBITDA | U17: ='Initiative Log - Detailed'!$J10*U30 -> 0 | V17: ='Initiative Log - Detailed'!$J10*V30 -> 0 | W17: ='Initiative Log - Detailed'!$J10*W30 -> 0 | X17: ='Initiative Log - Detailed'!$J10*X30 -> 0 | Y17: ='Initiative Log - Detailed'!$J10*Y30 -> 0 | Z17: ='Initiative Log - Detailed'!$J10*Z30 -> 0 | AA17: ='Initiative Log - Detailed'!$J10*AA30 -> 0 | AB17: ='Initiative Log - Detailed'!$J10*AB30 -> 0 | ... AF17: ='Initiative Log - Detailed'!$J10*AF30 -> 12.660496 | AH17: =S17 -> 0 | AI17: =AH17+T17 -> 0 | AJ17: =AI17+U17 -> 0 | AK17: =AJ17+V17 -> 0 | AL17: =AK17+W17 -> 0 | AM17: =AL17+X17 -> 0 | AN17: =AM17+Y17 -> 0 | AO17: =AN17+Z17 -> 0 | AP17: =AO17+AA17 -> 0 | ... AU17: =AT17+AF17 -> 50.641985
Q18: Key Account Openings | R18: EBITDA | U18: ='Initiative Log - Detailed'!$J11*U31 -> 0 | V18: ='Initiative Log - Detailed'!$J11*V31 -> 0 | W18: ='Initiative Log - Detailed'!$J11*W31 -> 0 | X18: ='Initiative Log - Detailed'!$J11*X31 -> 0 | Y18: ='Initiative Log - Detailed'!$J11*Y31 -> 0 | Z18: ='Initiative Log - Detailed'!$J11*Z31 -> 0 | AA18: ='Initiative Log - Detailed'!$J11*AA31 -> 1.0027113 | AB18: ='Initiative Log - Detailed'!$J11*AB31 -> 1.0027113 | ... AF18: ='Initiative Log - Detailed'!$J11*AF31 -> 2.5067783 | AH18: =S18 -> 0 | AI18: =AH18+T18 -> 0 | AJ18: =AI18+U18 -> 0 | AK18: =AJ18+V18 -> 0 | AL18: =AK18+W18 -> 0 | AM18: =AL18+X18 -> 0 | AN18: =AM18+Y18 -> 0 | AO18: =AN18+Z18 -> 0 | AP18: =AO18+AA18 -> 1.0027113 | ... AU18: =AT18+AF18 -> 10.027113
B19: Advertising and Marketing | C19: =-C7*3% -> -122.68492 | D19: =-D7*3% -> -268.45039 | E19: =-E7*3% -> -354.48047 | J19: Advertising and Marketing | K19: =-K7*3% -> -40.486023 | L19: =-L7*3% -> -88.58863 | M19: =-M7*3% -> -116.97856 | Q19: Team Improvements / Coaching | R19: EBITDA | U19: ='Initiative Log - Detailed'!$J12*U32 -> 0 | V19: ='Initiative Log - Detailed'!$J12*V32 -> 0 | W19: ='Initiative Log - Detailed'!$J12*W32 -> 1.5057936 | X19: ='Initiative Log - Detailed'!$J12*X32 -> 1.5057936 | Y19: ='Initiative Log - Detailed'!$J12*Y32 -> 1.5057936 | Z19: ='Initiative Log - Detailed'!$J12*Z32 -> 1.5057936 | AA19: ='Initiative Log - Detailed'!$J12*AA32 -> 1.5057936 | AB19: ='Initiative Log - Detailed'!$J12*AB32 -> 1.5057936 | ... AF19: ='Initiative Log - Detailed'!$J12*AF32 -> 1.5057936 | AH19: =S19 -> 0 | AI19: =AH19+T19 -> 0 | AJ19: =AI19+U19 -> 0 | AK19: =AJ19+V19 -> 0 | AL19: =AK19+W19 -> 1.5057936 | AM19: =AL19+X19 -> 3.0115873 | AN19: =AM19+Y19 -> 4.5173809 | AO19: =AN19+Z19 -> 6.0231745 | AP19: =AO19+AA19 -> 7.5289682 | ... AU19: =AT19+AF19 -> 15.057936
B20: Sales and Training Expenses | C20: =C19/2 -> -61.342459 | D20: =D19/2 -> -134.2252 | E20: =E19/2 -> -177.24024 | J20: Sales and Training Expenses | K20: =K19/2 -> -20.243011 | L20: =L19/2 -> -44.294315 | M20: =M19/2 -> -58.489278
R21: Costs | S21: 14 | T21: 14 | U21: =15+SUM(U6:U11)*0.05 -> 15 | V21: 15 | W21: =ROUND(15+SUM(W6:W11)*0.05, 0) -> 18 | X21: =ROUND(17+SUM(X6:X11)*0.05, 0) -> 20 | Y21: =ROUND(17+SUM(Y6:Y11)*0.05, 0) -> 19 | Z21: =ROUND(17+SUM(Z6:Z11)*0.05, 0) -> 20 | AA21: =ROUND(17+SUM(AA6:AA11)*0.05, 0) -> 25 | AB21: =ROUND(17+SUM(AB6:AB11)*0.05, 0) -> 24 | AC21: =ROUND(17+SUM(AC6:AC11)*0.05, 0) -> 24 | AD21: =ROUND(17+SUM(AD6:AD11)*0.05, 0) -> 32 | AE21: =ROUND(17+SUM(AE6:AE11)*0.05, 0) -> 27 | AF21: =ROUND(17+SUM(AF6:AF11)*0.05, 0)+4 -> 31 | AH21: =S21 -> 14 | AI21: =AH21+T21 -> 28 | AJ21: =AI21+U21 -> 43 | AK21: =AJ21+V21 -> 58 | AL21: =AK21+W21 -> 76 | AM21: =AL21+X21 -> 96 | AN21: =AM21+Y21 -> 115 | AO21: =AN21+Z21 -> 135 | AP21: =AO21+AA21 -> 160 | ... AU21: =AT21+AF21 -> 298
B22: Gross profit III | C22: =SUM(C16,C19:C20) -> 2601.3056 | D22: =SUM(D16,D19:D20) -> 5714.4882 | E22: =SUM(E16,E19:E20) -> 7578.0509 | J22: Gross profit III | K22: =SUM(K16,K19:K20) -> 858.43086 | L22: =SUM(L16,L19:L20) -> 1885.7811 | M22: =SUM(M16,M19:M20) -> 2500.7568
B23: GP III % | C23: =C22/C$7 -> 0.63609423 | D23: =D22/D$7 -> 0.63860829 | E23: =E22/E$7 -> 0.64133723 | J23: GP III % | K23: =K22/K$7 -> 0.63609423 | L23: =L22/L$7 -> 0.63860829 | M23: =M22/M$7 -> 0.64133723
B25: Personnel Expenses | C25: -250 | D25: -400 | E25: -450 | J25: Personnel Expenses | K25: =C25*50% -> -125 | L25: =C25 -> -250 | M25: =D25*75% -> -300
B26: Other Admin Expenses | C26: -50 | D26: -120 | E26: -150 | J26: Other Admin Expenses | K26: =C26 -> -50 | L26: =K26*1.3 -> -65 | M26: =L26*1.3 -> -84.5
Q27: Spa Chains - Tosca | R27: % phasing | AB27: 0.3 | AC27: 0.1 | AD27: 0.2 | AE27: 0.2 | AF27: 0.2
B28: Adjusted EBITDA | C28: =SUM(C22,C25:C26) -> 2301.3056 | D28: =SUM(D22,D25:D26) -> 5194.4882 | E28: =SUM(E22,E25:E26) -> 6978.0509 | J28: Adjusted EBITDA | K28: =SUM(K22,K25:K26) -> 683.43086 | L28: =SUM(L22,L25:L26) -> 1570.7811 | M28: =SUM(M22,M25:M26) -> 2116.2568 | Q28: Spa Chains - Woodhouse | R28: % phasing | W28: 0.1 | X28: 0.03 | Y28: 0.04 | Z28: 0.04 | AA28: 0.15 | AB28: 0.07 | AC28: 0.07 | AD28: 0.24 | AE28: 0.13 | AF28: 0.13
B29: Adj EBITDA % | C29: =C28/C$7 -> 0.56273558 | D29: =D28/D$7 -> 0.58049699 | E29: =E28/E$7 -> 0.5905587 | J29: Adj EBITDA % | K29: =K28/K$7 -> 0.50641985 | L29: =L28/L$7 -> 0.53193545 | M29: =M28/M$7 -> 0.54272942 | Q29: Spa Chains - Trilogy | R29: % phasing | X29: 0.1 | Y29: 0.04 | Z29: 0.06 | AA29: 0.15 | AB29: 0.07 | AC29: 0.08 | AD29: 0.24 | AE29: 0.13 | AF29: 0.13
Q30: Spa Chains - Other | R30: % phasing | AC30: 0.4 | AD30: 0.15 | AE30: 0.2 | AF30: 0.25
B31: Exceptionals | C31: =-250-120 -> -370 | D31: =-150-120 -> -270 | E31: =-30-120 -> -150 | J31: Exceptionals | K31: =C31+100 -> -270 | L31: =D31 -> -270 | M31: =E31 -> -150 | Q31: Key Account Openings | R31: % phasing | AA31: 0.1 | AB31: 0.1 | AC31: 0.15 | AD31: 0.2 | AE31: 0.2 | AF31: 0.25
Q32: Team Improvements / Coaching | R32: % phasing | W32: =1/10 -> 0.1 | X32: =1/10 -> 0.1 | Y32: =1/10 -> 0.1 | Z32: =1/10 -> 0.1 | AA32: =1/10 -> 0.1 | AB32: =1/10 -> 0.1 | AC32: =1/10 -> 0.1 | AD32: =1/10 -> 0.1 | ... AF32: =1/10 -> 0.1
B33: EBITDA | C33: =SUM(C28,C31) -> 1931.3056 | D33: =SUM(D28,D31) -> 4924.4882 | E33: =SUM(E28,E31) -> 6828.0509 | J33: EBITDA | K33: =SUM(K28,K31) -> 413.43086 | L33: =SUM(L28,L31) -> 1300.7811 | M33: =SUM(M28,M31) -> 1966.2568
B34: EBITDA % | C34: =C33/C$7 -> 0.47225991 | D34: =D33/D$7 -> 0.55032382 | E34: =E33/E$7 -> 0.57786406 | J34: EBITDA % | K34: =K33/K$7 -> 0.3063508 | L34: =L33/L$7 -> 0.4405016 | M34: =M33/M$7 -> 0.50426083
B37: Risk Amount | C37: =-120/2+C26/2+C20/2 -> -115.67123 | F37: 6 months of MW time, plus travel plus demos | J37: Risk Amount | K37: =-120/2+K26/2+K20/2 -> -95.121506
B44: Workings
B46: Toska | C46: 1000 | D46: 1500 | E46: 2000
B47: Woodhouse | C47: 1500 | D47: 5000 | E47: 6500
B48: Trilogy | C48: 1000 | D48: 1500 | E48: 2000
B49: Other | C49: 500 | D49: 750 | E49: 1000
B51: Key Accounts | C51: 2 | D51: 2 | E51: 2
B52: Existing growth | C52: 0.03 | D52: 0.03 | E52: 0.03

Sheet 2.2 Jaime Contact Book
B1: Med Spas | C1: Laurence Influencers / Speaches
B2: 1099er
B3: Cruise Ships | S3: Monthly | T3: Monthly | U3: Monthly | V3: Monthly | W3: Monthly | X3: Monthly | Y3: Monthly | Z3: Monthly | AA3: Monthly | AB3: Monthly | AC3: Monthly | AD3: Monthly | AE3: Monthly | AF3: Monthly | AH3: To date | AI3: To date | AJ3: To date | AK3: To date | AL3: To date | AM3: To date | AN3: To date | AO3: To date | AP3: To date | AQ3: To date | AR3: To date | AS3: To date | AT3: To date | AU3: To date
B4: Rescue Spa / Cosbar | S4: =MONTH(S5)&RIGHT(YEAR(S5), 2) -> 1125 | T4: =MONTH(T5)&RIGHT(YEAR(T5), 2) -> 1225 | U4: =MONTH(U5)&RIGHT(YEAR(U5), 2) -> 126 | V4: =MONTH(V5)&RIGHT(YEAR(V5), 2) -> 226 | W4: =MONTH(W5)&RIGHT(YEAR(W5), 2) -> 326 | X4: =MONTH(X5)&RIGHT(YEAR(X5), 2) -> 426 | Y4: =MONTH(Y5)&RIGHT(YEAR(Y5), 2) -> 526 | Z4: =MONTH(Z5)&RIGHT(YEAR(Z5), 2) -> 626 | ... AF4: =MONTH(AF5)&RIGHT(YEAR(AF5), 2) -> 1226 | AH4: =MONTH(AH5)&RIGHT(YEAR(AH5), 2) -> 1125 | AI4: =MONTH(AI5)&RIGHT(YEAR(AI5), 2) -> 1225 | AJ4: =MONTH(AJ5)&RIGHT(YEAR(AJ5), 2) -> 126 | AK4: =MONTH(AK5)&RIGHT(YEAR(AK5), 2) -> 226 | AL4: =MONTH(AL5)&RIGHT(YEAR(AL5), 2) -> 326 | AM4: =MONTH(AM5)&RIGHT(YEAR(AM5), 2) -> 426 | AN4: =MONTH(AN5)&RIGHT(YEAR(AN5), 2) -> 526 | AO4: =MONTH(AO5)&RIGHT(YEAR(AO5), 2) -> 626 | ... AU4: =MONTH(AU5)&RIGHT(YEAR(AU5), 2) -> 1226
C5: 2026 | D5: 2027 | E5: 2028 | H5: Risk Factor | K5: 2026 | L5: 2027 | M5: 2028 | S5: 45962 | T5: 45992 | U5: 46023 | V5: 46054 | W5: 46082 | X5: 46113 | Y5: 46143 | Z5: 46174 | AA5: 46204 | AB5: 46235 | AC5: 46266 | AD5: 46296 | AE5: 46327 | AF5: 46357 | AH5: 45962 | AI5: 45992 | AJ5: 46023 | AK5: 46054 | AL5: 46082 | AM5: 46113 | AN5: 46143 | AO5: 46174 | AP5: 46204 | AQ5: 46235 | AR5: 46266 | AS5: 46296 | AT5: 46327 | AU5: 46357
Q6: Med Spas | R6: Sales | U6: ='Initiative Log - Detailed'!$G13*'2.2 Jaime Contact Book'!U23 -> 0 | V6: ='Initiative Log - Detailed'!$G13*'2.2 Jaime Contact Book'!V23 -> 0 | W6: ='Initiative Log - Detailed'!$G13*'2.2 Jaime Contact Book'!W23 -> 40.8 | X6: ='Initiative Log - Detailed'!$G13*'2.2 Jaime Contact Book'!X23 -> 25.5 | Y6: ='Initiative Log - Detailed'!$G13*'2.2 Jaime Contact Book'!Y23 -> 30.6 | Z6: ='Initiative Log - Detailed'!$G13*'2.2 Jaime Contact Book'!Z23 -> 30.6 | AA6: ='Initiative Log - Detailed'!$G13*'2.2 Jaime Contact Book'!AA23 -> 51 | AB6: ='Initiative Log - Detailed'!$G13*'2.2 Jaime Contact Book'!AB23 -> 35.7 | ... AF6: ='Initiative Log - Detailed'!$G13*'2.2 Jaime Contact Book'!AF23 -> 66.3 | AH6: =S6 -> 0 | AI6: =AH6+T6 -> 0 | AJ6: =AI6+U6 -> 0 | AK6: =AJ6+V6 -> 0 | AL6: =AK6+W6 -> 40.8 | AM6: =AL6+X6 -> 66.3 | AN6: =AM6+Y6 -> 96.9 | AO6: =AN6+Z6 -> 127.5 | AP6: =AO6+AA6 -> 178.5 | ... AU6: =AT6+AF6 -> 510
B7: Revenue | C7: =SUM(C46:C49)+C51*30+'3YP'!E17*C52 -> 1419.7486 | D7: =SUM(D46:D49)+D51*30+C51*50+'3YP'!F17*D52 -> 3469.1732 | E7: =SUM(E46:E49)+E51*30+D51*50+C51*55+'3YP'!G17*E52 -> 4623.0079 | H7: -0.4 | J7: Revenue | K7: =C7*(1+$H$7) -> 851.84918 | L7: =D7*(1+$H$7) -> 2081.5039 | M7: =E7*(1+$H$7) -> 2773.8047 | Q7: 1099er | R7: Sales | U7: ='Initiative Log - Detailed'!$G14*'2.2 Jaime Contact Book'!U24 -> 0 | V7: ='Initiative Log - Detailed'!$G14*'2.2 Jaime Contact Book'!V24 -> 15 | W7: ='Initiative Log - Detailed'!$G14*'2.2 Jaime Contact Book'!W24 -> 15 | X7: ='Initiative Log - Detailed'!$G14*'2.2 Jaime Contact Book'!X24 -> 15 | Y7: ='Initiative Log - Detailed'!$G14*'2.2 Jaime Contact Book'!Y24 -> 15 | Z7: ='Initiative Log - Detailed'!$G14*'2.2 Jaime Contact Book'!Z24 -> 30 | AA7: ='Initiative Log - Detailed'!$G14*'2.2 Jaime Contact Book'!AA24 -> 30 | AB7: ='Initiative Log - Detailed'!$G14*'2.2 Jaime Contact Book'!AB24 -> 30 | ... AF7: ='Initiative Log - Detailed'!$G14*'2.2 Jaime Contact Book'!AF24 -> 30 | AH7: =S7 -> 0 | AI7: =AH7+T7 -> 0 | AJ7: =AI7+U7 -> 0 | AK7: =AJ7+V7 -> 15 | AL7: =AK7+W7 -> 30 | AM7: =AL7+X7 -> 45 | AN7: =AM7+Y7 -> 60 | AO7: =AN7+Z7 -> 90 | AP7: =AO7+AA7 -> 120 | ... AU7: =AT7+AF7 -> 300
B8: Cost of Sales | C8: =-C7*(1-COGS!C15+5%) -> -283.94973 | D8: =-D7*(1-COGS!D15+5%) -> -685.16171 | E8: =-E7*(1-COGS!E15+5%) -> -901.48653 | J8: Cost of Sales | K8: =C8*(1+$H$7) -> -170.36984 | L8: =D8*(1+$H$7) -> -411.09703 | M8: =E8*(1+$H$7) -> -540.89192 | Q8: Cruise Ships | R8: Sales | U8: ='Initiative Log - Detailed'!$G15*'2.2 Jaime Contact Book'!U25 -> 0 | V8: ='Initiative Log - Detailed'!$G15*'2.2 Jaime Contact Book'!V25 -> 0 | W8: ='Initiative Log - Detailed'!$G15*'2.2 Jaime Contact Book'!W25 -> 0 | X8: ='Initiative Log - Detailed'!$G15*'2.2 Jaime Contact Book'!X25 -> 0 | Y8: ='Initiative Log - Detailed'!$G15*'2.2 Jaime Contact Book'!Y25 -> 0 | Z8: ='Initiative Log - Detailed'!$G15*'2.2 Jaime Contact Book'!Z25 -> 0 | AA8: ='Initiative Log - Detailed'!$G15*'2.2 Jaime Contact Book'!AA25 -> 0 | AB8: ='Initiative Log - Detailed'!$G15*'2.2 Jaime Contact Book'!AB25 -> 0 | ... AF8: ='Initiative Log - Detailed'!$G15*'2.2 Jaime Contact Book'!AF25 -> 3 | AH8: =S8 -> 0 | AI8: =AH8+T8 -> 0 | AJ8: =AI8+U8 -> 0 | AK8: =AJ8+V8 -> 0 | AL8: =AK8+W8 -> 0 | AM8: =AL8+X8 -> 0 | AN8: =AM8+Y8 -> 0 | AO8: =AN8+Z8 -> 0 | AP8: =AO8+AA8 -> 0 | ... AU8: =AT8+AF8 -> 3
Q9: Retail | R9: Sales | U9: ='Initiative Log - Detailed'!$G16*'2.2 Jaime Contact Book'!U26 -> 0 | V9: ='Initiative Log - Detailed'!$G16*'2.2 Jaime Contact Book'!V26 -> 0 | W9: ='Initiative Log - Detailed'!$G16*'2.2 Jaime Contact Book'!W26 -> 0 | X9: ='Initiative Log - Detailed'!$G16*'2.2 Jaime Contact Book'!X26 -> 0 | Y9: ='Initiative Log - Detailed'!$G16*'2.2 Jaime Contact Book'!Y26 -> 0 | Z9: ='Initiative Log - Detailed'!$G16*'2.2 Jaime Contact Book'!Z26 -> 0 | AA9: ='Initiative Log - Detailed'!$G16*'2.2 Jaime Contact Book'!AA26 -> 0 | AB9: ='Initiative Log - Detailed'!$G16*'2.2 Jaime Contact Book'!AB26 -> 0 | ... AF9: ='Initiative Log - Detailed'!$G16*'2.2 Jaime Contact Book'!AF26 -> 30 | AH9: =S9 -> 0 | AI9: =AH9+T9 -> 0 | AJ9: =AI9+U9 -> 0 | AK9: =AJ9+V9 -> 0 | AL9: =AK9+W9 -> 0 | AM9: =AL9+X9 -> 0 | AN9: =AM9+Y9 -> 0 | AO9: =AN9+Z9 -> 0 | AP9: =AO9+AA9 -> 0 | ... AU9: =AT9+AF9 -> 30
B10: Gross Profit I | C10: =SUM(C7:C8) -> 1135.7989 | D10: =SUM(D7:D8) -> 2784.0115 | E10: =SUM(E7:E8) -> 3721.5213 | J10: Gross Profit I | K10: =SUM(K7:K8) -> 681.47934 | L10: =SUM(L7:L8) -> 1670.4069 | M10: =SUM(M7:M8) -> 2232.9128 | Q10: Medical Claims / Storytelling | R10: Sales | U10: ='Initiative Log - Detailed'!$G17*'2.2 Jaime Contact Book'!U27 -> 0 | V10: ='Initiative Log - Detailed'!$G17*'2.2 Jaime Contact Book'!V27 -> 0 | W10: ='Initiative Log - Detailed'!$G17*'2.2 Jaime Contact Book'!W27 -> 0.8849178 | X10: ='Initiative Log - Detailed'!$G17*'2.2 Jaime Contact Book'!X27 -> 0.8849178 | Y10: ='Initiative Log - Detailed'!$G17*'2.2 Jaime Contact Book'!Y27 -> 0.8849178 | Z10: ='Initiative Log - Detailed'!$G17*'2.2 Jaime Contact Book'!Z27 -> 0.8849178 | AA10: ='Initiative Log - Detailed'!$G17*'2.2 Jaime Contact Book'!AA27 -> 0.8849178 | AB10: ='Initiative Log - Detailed'!$G17*'2.2 Jaime Contact Book'!AB27 -> 0.8849178 | ... AF10: ='Initiative Log - Detailed'!$G17*'2.2 Jaime Contact Book'!AF27 -> 0.8849178 | AH10: =S10 -> 0 | AI10: =AH10+T10 -> 0 | AJ10: =AI10+U10 -> 0 | AK10: =AJ10+V10 -> 0 | AL10: =AK10+W10 -> 0.8849178 | AM10: =AL10+X10 -> 1.7698356 | AN10: =AM10+Y10 -> 2.6547534 | AO10: =AN10+Z10 -> 3.5396712 | AP10: =AO10+AA10 -> 4.424589 | ... AU10: =AT10+AF10 -> 8.849178
B11: GP I % | C11: =C10/C$7 -> 0.8 | D11: =D10/D$7 -> 0.8025 | E11: =E10/E$7 -> 0.805 | J11: GP I % | K11: =K10/K$7 -> 0.8 | L11: =L10/L$7 -> 0.8025 | M11: =M10/M$7 -> 0.805
B13: Shipping and distribution costs | C13: =-C7*'Other COS'!$C$16 -> -99.382404 | D13: =-D7*'Other COS'!$C$16 -> -242.84213 | E13: =-E7*'Other COS'!$C$16 -> -323.61055 | J13: Shipping and distribution costs | K13: =-K7*'Other COS'!$C$16 -> -59.629442 | L13: =-L7*'Other COS'!$C$16 -> -145.70528 | M13: =-M7*'Other COS'!$C$16 -> -194.16633 | Q13: Med Spas | R13: EBITDA | U13: ='Initiative Log - Detailed'!$J13*'2.2 Jaime Contact Book'!U23 -> 0 | V13: ='Initiative Log - Detailed'!$J13*'2.2 Jaime Contact Book'!V23 -> 0 | W13: ='Initiative Log - Detailed'!$J13*'2.2 Jaime Contact Book'!W23 -> 19.582998 | X13: ='Initiative Log - Detailed'!$J13*'2.2 Jaime Contact Book'!X23 -> 12.239374 | Y13: ='Initiative Log - Detailed'!$J13*'2.2 Jaime Contact Book'!Y23 -> 14.687249 | Z13: ='Initiative Log - Detailed'!$J13*'2.2 Jaime Contact Book'!Z23 -> 14.687249 | AA13: ='Initiative Log - Detailed'!$J13*'2.2 Jaime Contact Book'!AA23 -> 24.478748 | AB13: ='Initiative Log - Detailed'!$J13*'2.2 Jaime Contact Book'!AB23 -> 17.135123 | ... AF13: ='Initiative Log - Detailed'!$J13*'2.2 Jaime Contact Book'!AF23 -> 31.822372 | AH13: =S13 -> 0 | AI13: =AH13+T13 -> 0 | AJ13: =AI13+U13 -> 0 | AK13: =AJ13+V13 -> 0 | AL13: =AK13+W13 -> 19.582998 | AM13: =AL13+X13 -> 31.822372 | AN13: =AM13+Y13 -> 46.50962 | AO13: =AN13+Z13 -> 61.196869 | AP13: =AO13+AA13 -> 85.675617 | ... AU13: =AT13+AF13 -> 244.78748
B14: Rebates | C14: =-SUM(C46:C49)*5% -> -70.25 | D14: =-SUM(D46:D49)*5% -> -172.5 | E14: =-SUM(E46:E49)*5% -> -230 | J14: Rebates | K14: =C14*(1+$H$7) -> -42.15 | L14: =D14*(1+$H$7) -> -103.5 | M14: =E14*(1+$H$7) -> -138 | Q14: 1099er | R14: EBITDA | U14: ='Initiative Log - Detailed'!$J14*'2.2 Jaime Contact Book'!U24 -> 0 | V14: ='Initiative Log - Detailed'!$J14*'2.2 Jaime Contact Book'!V24 -> 7.1996317 | W14: ='Initiative Log - Detailed'!$J14*'2.2 Jaime Contact Book'!W24 -> 7.1996317 | X14: ='Initiative Log - Detailed'!$J14*'2.2 Jaime Contact Book'!X24 -> 7.1996317 | Y14: ='Initiative Log - Detailed'!$J14*'2.2 Jaime Contact Book'!Y24 -> 7.1996317 | Z14: ='Initiative Log - Detailed'!$J14*'2.2 Jaime Contact Book'!Z24 -> 14.399263 | AA14: ='Initiative Log - Detailed'!$J14*'2.2 Jaime Contact Book'!AA24 -> 14.399263 | AB14: ='Initiative Log - Detailed'!$J14*'2.2 Jaime Contact Book'!AB24 -> 14.399263 | ... AF14: ='Initiative Log - Detailed'!$J14*'2.2 Jaime Contact Book'!AF24 -> 14.399263 | AH14: =S14 -> 0 | AI14: =AH14+T14 -> 0 | AJ14: =AI14+U14 -> 0 | AK14: =AJ14+V14 -> 7.1996317 | AL14: =AK14+W14 -> 14.399263 | AM14: =AL14+X14 -> 21.598895 | AN14: =AM14+Y14 -> 28.798527 | AO14: =AN14+Z14 -> 43.19779 | AP14: =AO14+AA14 -> 57.597053 | ... AU14: =AT14+AF14 -> 143.99263
Q15: Cruise Ships | R15: EBITDA | U15: ='Initiative Log - Detailed'!$J15*'2.2 Jaime Contact Book'!U25 -> 0 | V15: ='Initiative Log - Detailed'!$J15*'2.2 Jaime Contact Book'!V25 -> 0 | W15: ='Initiative Log - Detailed'!$J15*'2.2 Jaime Contact Book'!W25 -> 0 | X15: ='Initiative Log - Detailed'!$J15*'2.2 Jaime Contact Book'!X25 -> 0 | Y15: ='Initiative Log - Detailed'!$J15*'2.2 Jaime Contact Book'!Y25 -> 0 | Z15: ='Initiative Log - Detailed'!$J15*'2.2 Jaime Contact Book'!Z25 -> 0 | AA15: ='Initiative Log - Detailed'!$J15*'2.2 Jaime Contact Book'!AA25 -> 0 | AB15: ='Initiative Log - Detailed'!$J15*'2.2 Jaime Contact Book'!AB25 -> 0 | ... AF15: ='Initiative Log - Detailed'!$J15*'2.2 Jaime Contact Book'!AF25 -> 1.4399263 | AH15: =S15 -> 0 | AI15: =AH15+T15 -> 0 | AJ15: =AI15+U15 -> 0 | AK15: =AJ15+V15 -> 0 | AL15: =AK15+W15 -> 0 | AM15: =AL15+X15 -> 0 | AN15: =AM15+Y15 -> 0 | AO15: =AN15+Z15 -> 0 | AP15: =AO15+AA15 -> 0 | ... AU15: =AT15+AF15 -> 1.4399263
B16: Gross profit II | C16: =SUM(C10,C13:C14) -> 966.1665 | D16: =SUM(D10,D13:D14) -> 2368.6694 | E16: =SUM(E10,E13:E14) -> 3167.9108 | J16: Gross profit II | K16: =SUM(K10,K13:K14) -> 579.6999 | L16: =SUM(L10,L13:L14) -> 1421.2016 | M16: =SUM(M10,M13:M14) -> 1900.7465 | Q16: Retail | R16: EBITDA | U16: ='Initiative Log - Detailed'!$J16*'2.2 Jaime Contact Book'!U26 -> 0 | V16: ='Initiative Log - Detailed'!$J16*'2.2 Jaime Contact Book'!V26 -> 0 | W16: ='Initiative Log - Detailed'!$J16*'2.2 Jaime Contact Book'!W26 -> 0 | X16: ='Initiative Log - Detailed'!$J16*'2.2 Jaime Contact Book'!X26 -> 0 | Y16: ='Initiative Log - Detailed'!$J16*'2.2 Jaime Contact Book'!Y26 -> 0 | Z16: ='Initiative Log - Detailed'!$J16*'2.2 Jaime Contact Book'!Z26 -> 0 | AA16: ='Initiative Log - Detailed'!$J16*'2.2 Jaime Contact Book'!AA26 -> 0 | AB16: ='Initiative Log - Detailed'!$J16*'2.2 Jaime Contact Book'!AB26 -> 0 | ... AF16: ='Initiative Log - Detailed'!$J16*'2.2 Jaime Contact Book'!AF26 -> 14.399263 | AH16: =S16 -> 0 | AI16: =AH16+T16 -> 0 | AJ16: =AI16+U16 -> 0 | AK16: =AJ16+V16 -> 0 | AL16: =AK16+W16 -> 0 | AM16: =AL16+X16 -> 0 | AN16: =AM16+Y16 -> 0 | AO16: =AN16+Z16 -> 0 | AP16: =AO16+AA16 -> 0 | ... AU16: =AT16+AF16 -> 14.399263
B17: GP II % | C17: =C16/C$7 -> 0.68051941 | D17: =D16/D$7 -> 0.68277634 | E17: =E16/E$7 -> 0.68524884 | J17: GP II % | K17: =K16/K$7 -> 0.68051941 | L17: =L16/L$7 -> 0.68277634 | M17: =M16/M$7 -> 0.68524884 | Q17: Medical Claims / Storytelling | R17: EBITDA | U17: ='Initiative Log - Detailed'!$J17*'2.2 Jaime Contact Book'!U27 -> 0 | V17: ='Initiative Log - Detailed'!$J17*'2.2 Jaime Contact Book'!V27 -> 0 | W17: ='Initiative Log - Detailed'!$J17*'2.2 Jaime Contact Book'!W27 -> 0.42473881 | X17: ='Initiative Log - Detailed'!$J17*'2.2 Jaime Contact Book'!X27 -> 0.42473881 | Y17: ='Initiative Log - Detailed'!$J17*'2.2 Jaime Contact Book'!Y27 -> 0.42473881 | Z17: ='Initiative Log - Detailed'!$J17*'2.2 Jaime Contact Book'!Z27 -> 0.42473881 | AA17: ='Initiative Log - Detailed'!$J17*'2.2 Jaime Contact Book'!AA27 -> 0.42473881 | AB17: ='Initiative Log - Detailed'!$J17*'2.2 Jaime Contact Book'!AB27 -> 0.42473881 | ... AF17: ='Initiative Log - Detailed'!$J17*'2.2 Jaime Contact Book'!AF27 -> 0.42473881 | AH17: =S17 -> 0 | AI17: =AH17+T17 -> 0 | AJ17: =AI17+U17 -> 0 | AK17: =AJ17+V17 -> 0 | AL17: =AK17+W17 -> 0.42473881 | AM17: =AL17+X17 -> 0.84947763 | AN17: =AM17+Y17 -> 1.2742164 | AO17: =AN17+Z17 -> 1.6989553 | AP17: =AO17+AA17 -> 2.1236941 | ... AU17: =AT17+AF17 -> 4.2473881
B19: Advertising and Marketing | C19: =-C7*3% -> -42.592459 | D19: =-D7*3% -> -104.0752 | E19: =-E7*3% -> -138.69024 | J19: Advertising and Marketing | K19: =-K7*3% -> -25.555475 | L19: =-L7*3% -> -62.445118 | M19: =-M7*3% -> -83.214142
B20: Sales and Training Expenses | C20: =C19/2 -> -21.296229 | D20: =D19/2 -> -52.037598 | E20: =E19/2 -> -69.345118 | J20: Sales and Training Expenses | K20: =K19/2 -> -12.777738 | L20: =L19/2 -> -31.222559 | M20: =M19/2 -> -41.607071 | R20: Costs | S20: =8+SUM(S6:S10)*5% -> 8 | T20: =8+SUM(T6:T10)*5% -> 8 | U20: =8+SUM(U6:U10)*5% -> 8 | V20: =8+SUM(V6:V10)*5% -> 8.75 | W20: =63/10+8+SUM(W6:W10)*5% -> 17.134246 | X20: =63/10+8+SUM(X6:X10)*5% -> 16.369246 | Y20: =63/10+8+SUM(Y6:Y10)*5% -> 16.624246 | Z20: =63/10+8+SUM(Z6:Z10)*5% -> 17.374246 | AA20: =63/10+8+SUM(AA6:AA10)*5% -> 18.394246 | AB20: =63/10+8+SUM(AB6:AB10)*5% -> 17.629246 | AC20: =63/10+8+SUM(AC6:AC10)*5% -> 18.394246 | AD20: =63/10+8+SUM(AD6:AD10)*5% -> 21.694246 | ... AF20: =63/10+8+SUM(AF6:AF10)*5% -> 20.809246 | AH20: =S20 -> 8 | AI20: =AH20+T20 -> 16 | AJ20: =AI20+U20 -> 24 | AK20: =AJ20+V20 -> 32.75 | AL20: =AK20+W20 -> 49.884246 | AM20: =AL20+X20 -> 66.253492 | AN20: =AM20+Y20 -> 82.877738 | AO20: =AN20+Z20 -> 100.25198 | AP20: =AO20+AA20 -> 118.64623 | ... AU20: =AT20+AF20 -> 217.59246
B22: Gross profit III | C22: =SUM(C16,C19:C20) -> 902.27781 | D22: =SUM(D16,D19:D20) -> 2212.5566 | E22: =SUM(E16,E19:E20) -> 2959.8754 | J22: Gross profit III | K22: =SUM(K16,K19:K20) -> 541.36669 | L22: =SUM(L16,L19:L20) -> 1327.534 | M22: =SUM(M16,M19:M20) -> 1775.9253
B23: GP III % | C23: =C22/C$7 -> 0.63551941 | D23: =D22/D$7 -> 0.63777634 | E23: =E22/E$7 -> 0.64024884 | J23: GP III % | K23: =K22/K$7 -> 0.63551941 | L23: =L22/L$7 -> 0.63777634 | M23: =M22/M$7 -> 0.64024884 | Q23: Med Spas | R23: % phasing | W23: 0.08 | X23: 0.05 | Y23: 0.06 | Z23: 0.06 | AA23: 0.1 | AB23: 0.07 | AC23: 0.1 | AD23: 0.2 | AE23: 0.15 | AF23: 0.13
Q24: 1099er | R24: % phasing | U24: 0 | V24: 0.05 | W24: 0.05 | X24: 0.05 | Y24: 0.05 | Z24: 0.1 | AA24: 0.1 | AB24: 0.1 | AC24: 0.1 | AD24: 0.15 | AE24: 0.15 | AF24: 0.1
B25: Personnel Expenses | C25: =-C47*10%-100 -> -150 | D25: =-D47*10%-150 -> -300 | E25: =-E47*10%-200 -> -400 | J25: Personnel Expenses | K25: =C25*75% -> -112.5 | L25: =D25*75% -> -225 | M25: =E25*75% -> -300 | Q25: Cruise Ships | R25: % phasing | AF25: 1
B26: Other Admin Expenses | C26: -20 | D26: -30 | E26: -50 | J26: Other Admin Expenses | K26: =C26 -> -20 | L26: =K26*1.3 -> -26 | M26: =L26*1.3 -> -33.8 | Q26: Retail | R26: % phasing | AF26: 1
Q27: Medical Claims / Storytelling | R27: % phasing | W27: =1/10 -> 0.1 | X27: =1/10 -> 0.1 | Y27: =1/10 -> 0.1 | Z27: =1/10 -> 0.1 | AA27: =1/10 -> 0.1 | AB27: =1/10 -> 0.1 | AC27: =1/10 -> 0.1 | AD27: =1/10 -> 0.1 | ... AF27: =1/10 -> 0.1
B28: Adjusted EBITDA | C28: =SUM(C22,C25:C26) -> 732.27781 | D28: =SUM(D22,D25:D26) -> 1882.5566 | E28: =SUM(E22,E25:E26) -> 2509.8754 | J28: Adjusted EBITDA | K28: =SUM(K22,K25:K26) -> 408.86669 | L28: =SUM(L22,L25:L26) -> 1076.534 | M28: =SUM(M22,M25:M26) -> 1442.1253
B29: Adj EBITDA % | C29: =C28/C$7 -> 0.5157799 | D29: =D28/D$7 -> 0.54265281 | E29: =E28/E$7 -> 0.54290962 | J29: Adj EBITDA % | K29: =K28/K$7 -> 0.47997544 | L29: =L28/L$7 -> 0.51719045 | M29: =M28/M$7 -> 0.51990872
B31: Exceptionals | C31: =-(8*12+C7*5%) -> -166.98743 | D31: =-(8*12*1.1+D7*5%) -> -279.05866 | E31: =-(8*12*1.1^2+E7*5%) -> -347.31039 | J31: Exceptionals | K31: =-(8*12+K7*5%) -> -138.59246 | L31: =-(8*12*1.1+L7*5%) -> -209.6752 | M31: =-(8*12*1.1^2+M7*5%) -> -254.85024
B33: EBITDA | C33: =SUM(C28,C31) -> 565.29038 | D33: =SUM(D28,D31) -> 1603.4979 | E33: =SUM(E28,E31) -> 2162.565 | J33: EBITDA | K33: =SUM(K28,K31) -> 270.27423 | L33: =SUM(L28,L31) -> 866.85876 | M33: =SUM(M28,M31) -> 1187.275
B34: EBITDA % | C34: =C33/C$7 -> 0.3981623 | D34: =D33/D$7 -> 0.46221328 | E34: =E33/E$7 -> 0.46778312 | J34: EBITDA % | K34: =K33/K$7 -> 0.31727944 | L34: =L33/L$7 -> 0.4164579 | M34: =M33/M$7 -> 0.42803122
B37: Risk Amount | C37: =C31/2+C26/2+(C25+100*6/12) -> -193.49372 | F37: 6 months of Jaime time, plus travel plus demos | J37: Risk Amount | K37: =K31/2+K26/2+(K25+50*6/12) -> -166.79623 | N37: 6 months of Jaime time, plus travel plus demos
B44: Workings
B46: Med Spas | C46: 850 | D46: 1200 | E46: 1500
B47: 1099er | C47: 500 | D47: 1500 | E47: 2000
B48: Cruise Ships | C48: 5 | D48: 500 | E48: 750
B49: Retail | C49: 50 | D49: 250 | E49: 350
B51: Key Accounts
B52: Existing growth | C52: 0.015 | D52: 0.015 | E52: 0.015

Sheet 2.3 US Visibility
Z1: 0.05 | AA1: 0.1 | AB1: 0.1 | AC1: 0.2 | AD1: 0.25 | AE1: 0.3
B2: Trade Show Sponsorship
B3: Additional PR and Media spend | R3: Monthly | S3: Monthly | T3: Monthly | U3: Monthly | V3: Monthly | W3: Monthly | X3: Monthly | Y3: Monthly | Z3: Monthly | AA3: Monthly | AB3: Monthly | AC3: Monthly | AD3: Monthly | AE3: Monthly | AG3: To date | AH3: To date | AI3: To date | AJ3: To date | AK3: To date | AL3: To date | AM3: To date | AN3: To date | AO3: To date | AP3: To date | AQ3: To date | AR3: To date | AS3: To date | AT3: To date
R4: =MONTH(R5)&RIGHT(YEAR(R5), 2) -> 1125 | S4: =MONTH(S5)&RIGHT(YEAR(S5), 2) -> 1225 | T4: =MONTH(T5)&RIGHT(YEAR(T5), 2) -> 126 | U4: =MONTH(U5)&RIGHT(YEAR(U5), 2) -> 226 | V4: =MONTH(V5)&RIGHT(YEAR(V5), 2) -> 326 | W4: =MONTH(W5)&RIGHT(YEAR(W5), 2) -> 426 | X4: =MONTH(X5)&RIGHT(YEAR(X5), 2) -> 526 | Y4: =MONTH(Y5)&RIGHT(YEAR(Y5), 2) -> 626 | ... AE4: =MONTH(AE5)&RIGHT(YEAR(AE5), 2) -> 1226 | AG4: =MONTH(AG5)&RIGHT(YEAR(AG5), 2) -> 1125 | AH4: =MONTH(AH5)&RIGHT(YEAR(AH5), 2) -> 1225 | AI4: =MONTH(AI5)&RIGHT(YEAR(AI5), 2) -> 126 | AJ4: =MONTH(AJ5)&RIGHT(YEAR(AJ5), 2) -> 226 | AK4: =MONTH(AK5)&RIGHT(YEAR(AK5), 2) -> 326 | AL4: =MONTH(AL5)&RIGHT(YEAR(AL5), 2) -> 426 | AM4: =MONTH(AM5)&RIGHT(YEAR(AM5), 2) -> 526 | AN4: =MONTH(AN5)&RIGHT(YEAR(AN5), 2) -> 626 | ... AT4: =MONTH(AT5)&RIGHT(YEAR(AT5), 2) -> 1226
C5: 2026 | D5: 2027 | E5: 2028 | H5: Risk Factor | K5: 2026 | L5: 2027 | M5: 2028 | R5: 45962 | S5: 45992 | T5: 46023 | U5: 46054 | V5: 46082 | W5: 46113 | X5: 46143 | Y5: 46174 | Z5: 46204 | AA5: 46235 | AB5: 46266 | AC5: 46296 | AD5: 46327 | AE5: 46357 | AG5: 45962 | AH5: 45992 | AI5: 46023 | AJ5: 46054 | AK5: 46082 | AL5: 46113 | AM5: 46143 | AN5: 46174 | AO5: 46204 | AP5: 46235 | AQ5: 46266 | AR5: 46296 | AS5: 46327 | AT5: 46357
Q6: Trade show - Sales | Z6: =$K7*50%*Z$1 -> 2.266202 | AA6: =$K7*50%*AA$1 -> 4.5324041 | AB6: =$K7*50%*AB$1 -> 4.5324041 | AC6: =$K7*50%*AC$1 -> 9.0648082 | AD6: =$K7*50%*AD$1 -> 11.33101 | AE6: =$K7*50%*AE$1 -> 13.597212 | AG6: =R6 -> 0 | AH6: =AG6+S6 -> 0 | AI6: =AH6+T6 -> 0 | AJ6: =AI6+U6 -> 0 | AK6: =AJ6+V6 -> 0 | AL6: =AK6+W6 -> 0 | AM6: =AL6+X6 -> 0 | AN6: =AM6+Y6 -> 0 | AO6: =AN6+Z6 -> 2.266202 | ... AT6: =AS6+AE6 -> 45.324041
B7: Revenue | C7: =C46*10+'3YP'!E17*C47 -> 129.49726 | D7: =C46*20+D46*15+'3YP'!F17*D47 -> 463.34644 | E7: =C46*25+D46*20+E46*15+'3YP'!G17*E47 -> 896.01573 | H7: -0.3 | J7: Revenue | K7: =C7*(1+$H$7) -> 90.648082 | L7: =D7*(1+$H$7) -> 324.34251 | M7: =E7*(1+$H$7) -> 627.21101 | Q7: PR & Media - Sales | Z7: =$K7*50%*Z$1 -> 2.266202 | AA7: =$K7*50%*AA$1 -> 4.5324041 | AB7: =$K7*50%*AB$1 -> 4.5324041 | AC7: =$K7*50%*AC$1 -> 9.0648082 | AD7: =$K7*50%*AD$1 -> 11.33101 | AE7: =$K7*50%*AE$1 -> 13.597212 | AG7: =R7 -> 0 | AH7: =AG7+S7 -> 0 | AI7: =AH7+T7 -> 0 | AJ7: =AI7+U7 -> 0 | AK7: =AJ7+V7 -> 0 | AL7: =AK7+W7 -> 0 | AM7: =AL7+X7 -> 0 | AN7: =AM7+Y7 -> 0 | AO7: =AN7+Z7 -> 2.266202 | ... AT7: =AS7+AE7 -> 45.324041
B8: Cost of Sales | C8: =-C7*(1-COGS!C15) -> -19.424589 | D8: =-D7*(1-COGS!D15) -> -68.3436 | E8: =-E7*(1-COGS!E15) -> -129.92228 | J8: Cost of Sales | K8: =C8*(1+$H$7) -> -13.597212 | L8: =D8*(1+$H$7) -> -47.84052 | M8: =E8*(1+$H$7) -> -90.945596
B10: Gross Profit I | C10: =SUM(C7:C8) -> 110.07267 | D10: =SUM(D7:D8) -> 395.00284 | E10: =SUM(E7:E8) -> 766.09345 | J10: Gross Profit I | K10: =SUM(K7:K8) -> 77.05087 | L10: =SUM(L7:L8) -> 276.50199 | M10: =SUM(M7:M8) -> 536.26541 | Q10: Trade show - adj. EBITDA | V10: =V6*$K$17+V14+SUM($K$25:$K$26)*(V6/SUM($T6:$AE6))/2 -> -8 | W10: =W6*$K$17+W14+SUM($K$25:$K$26)*(W6/SUM($T6:$AE6))/2 -> -8 | X10: =X6*$K$17+X14+SUM($K$25:$K$26)*(X6/SUM($T6:$AE6))/2 -> -8 | Y10: =Y6*$K$17+Y14+SUM($K$25:$K$26)*(Y6/SUM($T6:$AE6))/2 -> -8 | Z10: =Z6*$K$17+Z14+SUM($K$25:$K$26)*(Z6/SUM($T6:$AE6))/2 -> -6.5839826 | AA10: =AA6*$K$17+AA14+SUM($K$25:$K$26)*(AA6/SUM($T6:$AE6))/2 -> -5.1679652 | AB10: =AB6*$K$17+AB14+SUM($K$25:$K$26)*(AB6/SUM($T6:$AE6))/2 -> -5.1679652 | AC10: =AC6*$K$17+AC14+SUM($K$25:$K$26)*(AC6/SUM($T6:$AE6))/2 -> -2.3359304 | ... AE10: =AE6*$K$17+AE14+SUM($K$25:$K$26)*(AE6/SUM($T6:$AE6))/2 -> 0.49610436 | AG10: =R10 -> 0 | AH10: =AG10+S10 -> 0 | AI10: =AH10+T10 -> 0 | AJ10: =AI10+U10 -> 0 | AK10: =AJ10+V10 -> -8 | AL10: =AK10+W10 -> -16 | AM10: =AL10+X10 -> -24 | AN10: =AM10+Y10 -> -32 | AO10: =AN10+Z10 -> -38.583983 | ... AT10: =AS10+AE10 -> -51.679652
B11: GP I % | C11: =C10/C$7 -> 0.85 | D11: =D10/D$7 -> 0.8525 | E11: =E10/E$7 -> 0.855 | J11: GP I % | K11: =K10/K$7 -> 0.85 | L11: =L10/L$7 -> 0.8525 | M11: =M10/M$7 -> 0.855 | Q11: PR & Media - adj. EBITDA | V11: =V7*$K$17+V15+SUM($K$25:$K$26)*(V7/SUM($T7:$AE7))/2 -> -12.75 | W11: =W7*$K$17+W15+SUM($K$25:$K$26)*(W7/SUM($T7:$AE7))/2 -> -12.75 | X11: =X7*$K$17+X15+SUM($K$25:$K$26)*(X7/SUM($T7:$AE7))/2 -> -12.75 | Y11: =Y7*$K$17+Y15+SUM($K$25:$K$26)*(Y7/SUM($T7:$AE7))/2 -> -12.75 | Z11: =Z7*$K$17+Z15+SUM($K$25:$K$26)*(Z7/SUM($T7:$AE7))/2 -> -11.333983 | AA11: =AA7*$K$17+AA15+SUM($K$25:$K$26)*(AA7/SUM($T7:$AE7))/2 -> -9.9179652 | AB11: =AB7*$K$17+AB15+SUM($K$25:$K$26)*(AB7/SUM($T7:$AE7))/2 -> -9.9179652 | AC11: =AC7*$K$17+AC15+SUM($K$25:$K$26)*(AC7/SUM($T7:$AE7))/2 -> -7.0859304 | ... AE11: =AE7*$K$17+AE15+SUM($K$25:$K$26)*(AE7/SUM($T7:$AE7))/2 -> -4.2538956 | AG11: =R11 -> 0 | AH11: =AG11+S11 -> 0 | AI11: =AH11+T11 -> 0 | AJ11: =AI11+U11 -> 0 | AK11: =AJ11+V11 -> -12.75 | AL11: =AK11+W11 -> -25.5 | AM11: =AL11+X11 -> -38.25 | AN11: =AM11+Y11 -> -51 | AO11: =AN11+Z11 -> -62.333983 | ... AT11: =AS11+AE11 -> -99.179652
B13: Shipping and distribution costs | C13: =-C7*'Other COS'!$C$16 -> -9.0648082 | D13: =-D7*'Other COS'!$C$16 -> -32.434251 | E13: =-E7*'Other COS'!$C$16 -> -62.721101 | J13: Shipping and distribution costs | K13: =-K7*'Other COS'!$C$16 -> -6.3453657 | L13: =-L7*'Other COS'!$C$16 -> -22.703975 | M13: =-M7*'Other COS'!$C$16 -> -43.904771
B14: Rebates | C14: 0 | D14: 0 | E14: 0 | J14: Rebates | K14: 0 | L14: 0 | M14: 0 | Q14: Trade show - Spend | V14: =$K20*10% -> -8 | W14: =$K20*10% -> -8 | X14: =$K20*10% -> -8 | Y14: =$K20*10% -> -8 | Z14: =$K20*10% -> -8 | AA14: =$K20*10% -> -8 | AB14: =$K20*10% -> -8 | AC14: =$K20*10% -> -8 | ... AE14: =$K20*10% -> -8 | AG14: =R14 -> 0 | AH14: =AG14+S14 -> 0 | AI14: =AH14+T14 -> 0 | AJ14: =AI14+U14 -> 0 | AK14: =AJ14+V14 -> -8 | AL14: =AK14+W14 -> -16 | AM14: =AL14+X14 -> -24 | AN14: =AM14+Y14 -> -32 | AO14: =AN14+Z14 -> -40 | ... AT14: =AS14+AE14 -> -80
Q15: PR & Media - Spend | V15: =$K19*10% -> -12.75 | W15: =$K19*10% -> -12.75 | X15: =$K19*10% -> -12.75 | Y15: =$K19*10% -> -12.75 | Z15: =$K19*10% -> -12.75 | AA15: =$K19*10% -> -12.75 | AB15: =$K19*10% -> -12.75 | AC15: =$K19*10% -> -12.75 | ... AE15: =$K19*10% -> -12.75 | AG15: =R15 -> 0 | AH15: =AG15+S15 -> 0 | AI15: =AH15+T15 -> 0 | AJ15: =AI15+U15 -> 0 | AK15: =AJ15+V15 -> -12.75 | AL15: =AK15+W15 -> -25.5 | AM15: =AL15+X15 -> -38.25 | AN15: =AM15+Y15 -> -51 | AO15: =AN15+Z15 -> -63.75 | ... AT15: =AS15+AE15 -> -127.5
B16: Gross profit II | C16: =SUM(C10,C13:C14) -> 101.00786 | D16: =SUM(D10,D13:D14) -> 362.56859 | E16: =SUM(E10,E13:E14) -> 703.37234 | J16: Gross profit II | K16: =SUM(K10,K13:K14) -> 70.705504 | L16: =SUM(L10,L13:L14) -> 253.79801 | M16: =SUM(M10,M13:M14) -> 492.36064
B17: GP II % | C17: =C16/C$7 -> 0.78 | D17: =D16/D$7 -> 0.7825 | E17: =E16/E$7 -> 0.785 | J17: GP II % | K17: =K16/K$7 -> 0.78 | L17: =L16/L$7 -> 0.7825 | M17: =M16/M$7 -> 0.785
B19: Advertising and Marketing | C19: =-Extra!M5/1000 -> -127.5 | D19: =C19*1.1 -> -140.25 | E19: =D19*1.1 -> -154.275 | J19: Advertising and Marketing | K19: =C19 -> -127.5 | L19: =D19 -> -140.25 | M19: =E19 -> -154.275
B20: Sales and Training Expenses | C20: =-Extra!M42/1000 -> -80 | D20: =C20*1.1 -> -88 | E20: =D20*1.1 -> -96.8 | J20: Sales and Training Expenses | K20: =C20 -> -80 | L20: =D20 -> -88 | M20: =E20 -> -96.8
B22: Gross profit III | C22: =SUM(C16,C19:C20) -> -106.49214 | D22: =SUM(D16,D19:D20) -> 134.31859 | E22: =SUM(E16,E19:E20) -> 452.29734 | J22: Gross profit III | K22: =SUM(K16,K19:K20) -> -136.7945 | L22: =SUM(L16,L19:L20) -> 25.548011 | M22: =SUM(M16,M19:M20) -> 241.28564
B23: GP III % | C23: =C22/C$7 -> -0.82235051 | D23: =D22/D$7 -> 0.28988803 | E23: =E22/E$7 -> 0.50478728 | J23: GP III % | K23: =K22/K$7 -> -1.5090722 | L23: =L22/L$7 -> 0.078768619 | M23: =M22/M$7 -> 0.38469612
B25: Personnel Expenses | C25: =-C7*10% -> -12.949726 | D25: =-D7*10% -> -46.334644 | E25: =-E7*10% -> -89.601573 | J25: Personnel Expenses | K25: =-K7*10% -> -9.0648082 | L25: =-L7*10% -> -32.434251 | M25: =-M7*10% -> -62.721101
B26: Other Admin Expenses | C26: -5 | D26: -5 | E26: -5 | J26: Other Admin Expenses | K26: -5 | L26: -5 | M26: -5
B28: Adjusted EBITDA | C28: =SUM(C22,C25:C26) -> -124.44186 | D28: =SUM(D22,D25:D26) -> 82.983944 | E28: =SUM(E22,E25:E26) -> 357.69577 | J28: Adjusted EBITDA | K28: =SUM(K22,K25:K26) -> -150.8593 | L28: =SUM(L22,L25:L26) -> -11.886239 | M28: =SUM(M22,M25:M26) -> 173.56454
B29: Adj EBITDA % | C29: =C28/C$7 -> -0.96096136 | D29: =D28/D$7 -> 0.17909697 | E29: =E28/E$7 -> 0.39920702 | J29: Adj EBITDA % | K29: =K28/K$7 -> -1.6642305 | L29: =L28/L$7 -> -0.036647183 | M29: =M28/M$7 -> 0.27672432
B31: Exceptionals | C31: 0 | D31: 0 | E31: 0 | J31: Exceptionals | K31: 0 | L31: 0 | M31: 0
B33: EBITDA | C33: =SUM(C28,C31) -> -124.44186 | D33: =SUM(D28,D31) -> 82.983944 | E33: =SUM(E28,E31) -> 357.69577 | J33: EBITDA | K33: =SUM(K28,K31) -> -150.8593 | L33: =SUM(L28,L31) -> -11.886239 | M33: =SUM(M28,M31) -> 173.56454
B34: EBITDA % | C34: =C33/C$7 -> -0.96096136 | D34: =D33/D$7 -> 0.17909697 | E34: =E33/E$7 -> 0.39920702 | J34: EBITDA % | K34: =K33/K$7 -> -1.6642305 | L34: =L33/L$7 -> -0.036647183 | M34: =M33/M$7 -> 0.27672432
B37: Risk Amount | C37: =C20+C19*60% -> -156.5 | F37: 60% marketing spend plus full trade show budget | J37: Risk Amount | K37: =K20+K19*60% -> -156.5 | N37: 60% marketing spend plus full trade show budget
B44: Workings
B46: New doors | C46: 10 | D46: 15 | E46: 20
B47: Existing growth | C47: 0.03 | D47: 0.03 | E47: 0.03

Sheet 2.4 US Team Expansion
V1: 0 | W1: 0 | X1: 0 | Y1: 0 | Z1: 0 | AA1: 0 | AB1: 0.1 | AC1: 0.1 | AD1: 0.15 | AE1: 0.2 | AF1: 0.2 | AG1: 0.25
B2: +1 FTE NE
B3: +1 FTE Central | T3: Monthly | U3: Monthly | V3: Monthly | W3: Monthly | X3: Monthly | Y3: Monthly | Z3: Monthly | AA3: Monthly | AB3: Monthly | AC3: Monthly | AD3: Monthly | AE3: Monthly | AF3: Monthly | AG3: Monthly | AI3: To date | AJ3: To date | AK3: To date | AL3: To date | AM3: To date | AN3: To date | AO3: To date | AP3: To date | AQ3: To date | AR3: To date | AS3: To date | AT3: To date | AU3: To date | AV3: To date
T4: =MONTH(T5)&RIGHT(YEAR(T5), 2) -> 1125 | U4: =MONTH(U5)&RIGHT(YEAR(U5), 2) -> 1225 | V4: =MONTH(V5)&RIGHT(YEAR(V5), 2) -> 126 | W4: =MONTH(W5)&RIGHT(YEAR(W5), 2) -> 226 | X4: =MONTH(X5)&RIGHT(YEAR(X5), 2) -> 326 | Y4: =MONTH(Y5)&RIGHT(YEAR(Y5), 2) -> 426 | Z4: =MONTH(Z5)&RIGHT(YEAR(Z5), 2) -> 526 | AA4: =MONTH(AA5)&RIGHT(YEAR(AA5), 2) -> 626 | ... AG4: =MONTH(AG5)&RIGHT(YEAR(AG5), 2) -> 1226 | AI4: =MONTH(AI5)&RIGHT(YEAR(AI5), 2) -> 1125 | AJ4: =MONTH(AJ5)&RIGHT(YEAR(AJ5), 2) -> 1225 | AK4: =MONTH(AK5)&RIGHT(YEAR(AK5), 2) -> 126 | AL4: =MONTH(AL5)&RIGHT(YEAR(AL5), 2) -> 226 | AM4: =MONTH(AM5)&RIGHT(YEAR(AM5), 2) -> 326 | AN4: =MONTH(AN5)&RIGHT(YEAR(AN5), 2) -> 426 | AO4: =MONTH(AO5)&RIGHT(YEAR(AO5), 2) -> 526 | AP4: =MONTH(AP5)&RIGHT(YEAR(AP5), 2) -> 626 | ... AV4: =MONTH(AV5)&RIGHT(YEAR(AV5), 2) -> 1226
C5: 2026 | D5: 2027 | E5: 2028 | H5: Risk Factor | K5: 2026 | L5: 2027 | M5: 2028 | T5: 45962 | U5: 45992 | V5: 46023 | W5: 46054 | X5: 46082 | Y5: 46113 | Z5: 46143 | AA5: 46174 | AB5: 46204 | AC5: 46235 | AD5: 46266 | AE5: 46296 | AF5: 46327 | AG5: 46357 | AI5: 45962 | AJ5: 45992 | AK5: 46023 | AL5: 46054 | AM5: 46082 | AN5: 46113 | AO5: 46143 | AP5: 46174 | AQ5: 46204 | AR5: 46235 | AS5: 46266 | AT5: 46296 | AU5: 46327 | AV5: 46357
B7: Revenue | C7: =C46*10 -> 120 | D7: =C46*20+D46*15 -> 480 | E7: =C46*25+D46*20+E46*15 -> 920 | H7: -0.3 | J7: Revenue | K7: =C7*(1+$H$7) -> 84 | L7: =D7*(1+$H$7) -> 336 | M7: =E7*(1+$H$7) -> 644 | S7: Sales | V7: =$K7*V1 -> 0 | W7: =$K7*W1 -> 0 | X7: =$K7*X1 -> 0 | Y7: =$K7*Y1 -> 0 | Z7: =$K7*Z1 -> 0 | AA7: =$K7*AA1 -> 0 | AB7: =$K7*AB1 -> 8.4 | AC7: =$K7*AC1 -> 8.4 | ... AG7: =$K7*AG1 -> 21 | AI7: =T7 -> 0 | AJ7: =AI7+U7 -> 0 | AK7: =AJ7+V7 -> 0 | AL7: =AK7+W7 -> 0 | AM7: =AL7+X7 -> 0 | AN7: =AM7+Y7 -> 0 | AO7: =AN7+Z7 -> 0 | AP7: =AO7+AA7 -> 0 | AQ7: =AP7+AB7 -> 8.4 | ... AV7: =AU7+AG7 -> 84
B8: Cost of Sales | C8: =-C7*(1-COGS!C15) -> -18 | D8: =-D7*(1-COGS!D15) -> -70.8 | E8: =-E7*(1-COGS!E15) -> -133.4 | J8: Cost of Sales | K8: =C8*(1+$H$7) -> -12.6 | L8: =D8*(1+$H$7) -> -49.56 | M8: =E8*(1+$H$7) -> -93.38
S9: EBITDA | V9: =V7*$K17-V11 -> 0 | W9: =W7*$K17-W11 -> 0 | X9: =X7*$K17-X11 -> 0 | Y9: =Y7*$K17-Y11 -> -23.888889 | Z9: =Z7*$K17-Z11 -> -23.888889 | AA9: =AA7*$K17-AA11 -> -23.888889 | AB9: =AB7*$K17-AB11 -> -18.176889 | AC9: =AC7*$K17-AC11 -> -18.176889 | ... AG9: =AG7*$K17-AG11 -> -9.6088889 | AI9: =T9 -> 0 | AJ9: =AI9+U9 -> 0 | AK9: =AJ9+V9 -> 0 | AL9: =AK9+W9 -> 0 | AM9: =AL9+X9 -> 0 | AN9: =AM9+Y9 -> -23.888889 | AO9: =AN9+Z9 -> -47.777778 | AP9: =AO9+AA9 -> -71.666667 | AQ9: =AP9+AB9 -> -89.843556 | ... AV9: =AU9+AG9 -> -157.88
B10: Gross Profit I | C10: =SUM(C7:C8) -> 102 | D10: =SUM(D7:D8) -> 409.2 | E10: =SUM(E7:E8) -> 786.6 | J10: Gross Profit I | K10: =SUM(K7:K8) -> 71.4 | L10: =SUM(L7:L8) -> 286.44 | M10: =SUM(M7:M8) -> 550.62
B11: GP I % | C11: =C10/C$7 -> 0.85 | D11: =D10/D$7 -> 0.8525 | E11: =E10/E$7 -> 0.855 | J11: GP I % | K11: =K10/K$7 -> 0.85 | L11: =L10/L$7 -> 0.8525 | M11: =M10/M$7 -> 0.855 | S11: Cost | Y11: =-($K25+$K7*10%)/9+Y7*10%-$K26/9 -> 23.888889 | Z11: =-($K25+$K7*10%)/9+Z7*10%-$K26/9 -> 23.888889 | AA11: =-($K25+$K7*10%)/9+AA7*10%-$K26/9 -> 23.888889 | AB11: =-($K25+$K7*10%)/9+AB7*10%-$K26/9 -> 24.728889 | AC11: =-($K25+$K7*10%)/9+AC7*10%-$K26/9 -> 24.728889 | AD11: =-($K25+$K7*10%)/9+AD7*10%-$K26/9 -> 25.148889 | AE11: =-($K25+$K7*10%)/9+AE7*10%-$K26/9 -> 25.568889 | AF11: =-($K25+$K7*10%)/9+AF7*10%-$K26/9 -> 25.568889 | AG11: =-($K25+$K7*10%)/9+AG7*10%-$K26/9 -> 25.988889 | AI11: =T11 -> 0 | AJ11: =AI11+U11 -> 0 | AK11: =AJ11+V11 -> 0 | AL11: =AK11+W11 -> 0 | AM11: =AL11+X11 -> 0 | AN11: =AM11+Y11 -> 23.888889 | AO11: =AN11+Z11 -> 47.777778 | AP11: =AO11+AA11 -> 71.666667 | AQ11: =AP11+AB11 -> 96.395556 | ... AV11: =AU11+AG11 -> 223.4
B13: Shipping and distribution costs | C13: =-C7*'Other COS'!$C$17 -> -8.4 | D13: =-D7*'Other COS'!$C$17 -> -33.6 | E13: =-E7*'Other COS'!$C$17 -> -64.4 | J13: Shipping and distribution costs | K13: =C13*(1+$H$7) -> -5.88 | L13: =D13*(1+$H$7) -> -23.52 | M13: =E13*(1+$H$7) -> -45.08
B14: Rebates | C14: 0 | D14: 0 | E14: 0 | J14: Rebates | K14: =C14*(1+$H$7) -> 0 | L14: =D14*(1+$H$7) -> 0 | M14: =E14*(1+$H$7) -> 0
B16: Gross profit II | C16: =SUM(C10,C13:C14) -> 93.6 | D16: =SUM(D10,D13:D14) -> 375.6 | E16: =SUM(E10,E13:E14) -> 722.2 | J16: Gross profit II | K16: =SUM(K10,K13:K14) -> 65.52 | L16: =SUM(L10,L13:L14) -> 262.92 | M16: =SUM(M10,M13:M14) -> 505.54
B17: GP II % | C17: =C16/C$7 -> 0.78 | D17: =D16/D$7 -> 0.7825 | E17: =E16/E$7 -> 0.785 | J17: GP II % | K17: =K16/K$7 -> 0.78 | L17: =L16/L$7 -> 0.7825 | M17: =M16/M$7 -> 0.785
B19: Advertising and Marketing | C19: 0 | D19: 0 | E19: 0 | J19: Advertising and Marketing | K19: =C19 -> 0 | L19: =D19 -> 0 | M19: =E19 -> 0
B20: Sales and Training Expenses | C20: 0 | D20: 0 | E20: 0 | J20: Sales and Training Expenses | K20: =C20 -> 0 | L20: =D20 -> 0 | M20: =E20 -> 0
B22: Gross profit III | C22: =SUM(C16,C19:C20) -> 93.6 | D22: =SUM(D16,D19:D20) -> 375.6 | E22: =SUM(E16,E19:E20) -> 722.2 | J22: Gross profit III | K22: =SUM(K16,K19:K20) -> 65.52 | L22: =SUM(L16,L19:L20) -> 262.92 | M22: =SUM(M16,M19:M20) -> 505.54
B23: GP III % | C23: =C22/C$7 -> 0.78 | D23: =D22/D$7 -> 0.7825 | E23: =E22/E$7 -> 0.785 | J23: GP III % | K23: =K22/K$7 -> 0.78 | L23: =L22/L$7 -> 0.7825 | M23: =M22/M$7 -> 0.785
B25: Personnel Expenses | C25: =-C7*10%-100*2 -> -212 | D25: =-D7*10%-100*2*1.1 -> -268 | E25: =-E7*10%-100*2*1.1^2 -> -334 | J25: Personnel Expenses | K25: =-K7*10%-100*2 -> -208.4 | L25: =-L7*10%-100*2*1.1 -> -253.6 | M25: =-M7*10%-100*2*1.1^2 -> -306.4
B26: Other Admin Expenses | C26: -15 | D26: -20 | E26: -22 | J26: Other Admin Expenses | K26: =C26 -> -15 | L26: =D26 -> -20 | M26: =E26 -> -22
Q27: =599+1418 -> 2017
B28: Adjusted EBITDA | C28: =SUM(C22,C25:C26) -> -133.4 | D28: =SUM(D22,D25:D26) -> 87.6 | E28: =SUM(E22,E25:E26) -> 366.2 | J28: Adjusted EBITDA | K28: =SUM(K22,K25:K26) -> -157.88 | L28: =SUM(L22,L25:L26) -> -10.68 | M28: =SUM(M22,M25:M26) -> 177.14
B29: Adj EBITDA % | C29: =C28/C$7 -> -1.1116667 | D29: =D28/D$7 -> 0.1825 | E29: =E28/E$7 -> 0.39804348 | J29: Adj EBITDA % | K29: =K28/K$7 -> -1.8795238 | L29: =L28/L$7 -> -0.031785714 | M29: =M28/M$7 -> 0.27506211
B31: Exceptionals | C31: 0 | D31: 0 | E31: 0 | J31: Exceptionals | K31: =C31 -> 0 | L31: =D31 -> 0 | M31: =E31 -> 0
B33: EBITDA | C33: =SUM(C28,C31) -> -133.4 | D33: =SUM(D28,D31) -> 87.6 | E33: =SUM(E28,E31) -> 366.2 | J33: EBITDA | K33: =SUM(K28,K31) -> -157.88 | L33: =SUM(L28,L31) -> -10.68 | M33: =SUM(M28,M31) -> 177.14
B34: EBITDA % | C34: =C33/C$7 -> -1.1116667 | D34: =D33/D$7 -> 0.1825 | E34: =E33/E$7 -> 0.39804348 | J34: EBITDA % | K34: =K33/K$7 -> -1.8795238 | L34: =L33/L$7 -> -0.031785714 | M34: =M33/M$7 -> 0.27506211
B37: Risk Amount | C37: =(C25+C26)*6/12 -> -113.5 | F37: 6 months of employee costs | J37: Risk Amount | K37: =(K25+K26)*6/12 -> -111.7 | N37: 6 months of employee costs
B44: Workings
B46: New doors | C46: 12 | D46: 16 | E46: 20

Sheet 3.1 China
S3: Monthly | T3: Monthly | U3: Monthly | V3: Monthly | W3: Monthly | X3: Monthly | Y3: Monthly | Z3: Monthly | AA3: Monthly | AB3: Monthly | AC3: Monthly | AD3: Monthly | AE3: Monthly | AF3: Monthly | AH3: To date | AI3: To date | AJ3: To date | AK3: To date | AL3: To date | AM3: To date | AN3: To date | AO3: To date | AP3: To date | AQ3: To date | AR3: To date | AS3: To date | AT3: To date | AU3: To date
S4: =MONTH(S5)&RIGHT(YEAR(S5), 2) -> 1125 | T4: =MONTH(T5)&RIGHT(YEAR(T5), 2) -> 1225 | U4: =MONTH(U5)&RIGHT(YEAR(U5), 2) -> 126 | V4: =MONTH(V5)&RIGHT(YEAR(V5), 2) -> 226 | W4: =MONTH(W5)&RIGHT(YEAR(W5), 2) -> 326 | X4: =MONTH(X5)&RIGHT(YEAR(X5), 2) -> 426 | Y4: =MONTH(Y5)&RIGHT(YEAR(Y5), 2) -> 526 | Z4: =MONTH(Z5)&RIGHT(YEAR(Z5), 2) -> 626 | ... AF4: =MONTH(AF5)&RIGHT(YEAR(AF5), 2) -> 1226 | AH4: =MONTH(AH5)&RIGHT(YEAR(AH5), 2) -> 1125 | AI4: =MONTH(AI5)&RIGHT(YEAR(AI5), 2) -> 1225 | AJ4: =MONTH(AJ5)&RIGHT(YEAR(AJ5), 2) -> 126 | AK4: =MONTH(AK5)&RIGHT(YEAR(AK5), 2) -> 226 | AL4: =MONTH(AL5)&RIGHT(YEAR(AL5), 2) -> 326 | AM4: =MONTH(AM5)&RIGHT(YEAR(AM5), 2) -> 426 | AN4: =MONTH(AN5)&RIGHT(YEAR(AN5), 2) -> 526 | AO4: =MONTH(AO5)&RIGHT(YEAR(AO5), 2) -> 626 | ... AU4: =MONTH(AU5)&RIGHT(YEAR(AU5), 2) -> 1226
C5: 2026 | D5: 2027 | E5: 2028 | H5: Risk Factor | K5: 2026 | L5: 2027 | M5: 2028 | S5: 45962 | T5: 45992 | U5: 46023 | V5: 46054 | W5: 46082 | X5: 46113 | Y5: 46143 | Z5: 46174 | AA5: 46204 | AB5: 46235 | AC5: 46266 | AD5: 46296 | AE5: 46327 | AF5: 46357 | AH5: 45962 | AI5: 45992 | AJ5: 46023 | AK5: 46054 | AL5: 46082 | AM5: 46113 | AN5: 46143 | AO5: 46174 | AP5: 46204 | AQ5: 46235 | AR5: 46266 | AS5: 46296 | AT5: 46327 | AU5: 46357
B7: Revenue | C7: =C46+'3YP'!E32*C47 -> 250 | D7: =D46+'3YP'!F32*D47 -> 350 | E7: =E46+'3YP'!G32*E47 -> 500 | H7: -0.5 | J7: Revenue | K7: =C7*(1+$H$7) -> 125 | L7: =D7*(1+$H$7) -> 175 | M7: =E7*(1+$H$7) -> 250 | Y7: =$K7*'2026B'!Q32/SUM('2026B'!$Q$32:$X$32) -> 11.627907 | Z7: =$K7*'2026B'!R32/SUM('2026B'!$Q$32:$X$32) -> 8.7209302 | AA7: =$K7*'2026B'!S32/SUM('2026B'!$Q$32:$X$32) -> 8.7209302 | AB7: =$K7*'2026B'!T32/SUM('2026B'!$Q$32:$X$32) -> 8.7209302 | AC7: =$K7*'2026B'!U32/SUM('2026B'!$Q$32:$X$32) -> 36.337209 | AD7: =$K7*'2026B'!V32/SUM('2026B'!$Q$32:$X$32) -> 21.802326 | AE7: =$K7*'2026B'!W32/SUM('2026B'!$Q$32:$X$32) -> 14.534884 | AF7: =$K7*'2026B'!X32/SUM('2026B'!$Q$32:$X$32) -> 14.534884 | AH7: =S7 -> 0 | AI7: =AH7+T7 -> 0 | AJ7: =AI7+U7 -> 0 | AK7: =AJ7+V7 -> 0 | AL7: =AK7+W7 -> 0 | AM7: =AL7+X7 -> 0 | AN7: =AM7+Y7 -> 11.627907 | AO7: =AN7+Z7 -> 20.348837 | AP7: =AO7+AA7 -> 29.069767 | ... AU7: =AT7+AF7 -> 125
B8: Cost of Sales | C8: =-C7*(1-COGS!C30) -> -100 | D8: =-D7*(1-COGS!D30) -> -139.125 | E8: =-E7*(1-COGS!E30) -> -197.5 | J8: Cost of Sales | K8: =C8*(1+$H$7) -> -50 | L8: =D8*(1+$H$7) -> -69.5625 | M8: =E8*(1+$H$7) -> -98.75 | Y8: =Y7*$K8/$K7 -> -4.6511628 | Z8: =Z7*$K8/$K7 -> -3.4883721 | AA8: =AA7*$K8/$K7 -> -3.4883721 | AB8: =AB7*$K8/$K7 -> -3.4883721 | AC8: =AC7*$K8/$K7 -> -14.534884 | AD8: =AD7*$K8/$K7 -> -8.7209302 | AE8: =AE7*$K8/$K7 -> -5.8139535 | AF8: =AF7*$K8/$K7 -> -5.8139535 | AH8: =S8 -> 0 | AI8: =AH8+T8 -> 0 | AJ8: =AI8+U8 -> 0 | AK8: =AJ8+V8 -> 0 | AL8: =AK8+W8 -> 0 | AM8: =AL8+X8 -> 0 | AN8: =AM8+Y8 -> -4.6511628 | AO8: =AN8+Z8 -> -8.1395349 | AP8: =AO8+AA8 -> -11.627907 | ... AU8: =AT8+AF8 -> -50
B10: Gross Profit I | C10: =SUM(C7:C8) -> 150 | D10: =SUM(D7:D8) -> 210.875 | E10: =SUM(E7:E8) -> 302.5 | J10: Gross Profit I | K10: =SUM(K7:K8) -> 75 | L10: =SUM(L7:L8) -> 105.4375 | M10: =SUM(M7:M8) -> 151.25 | S10: =SUM(S7:S8) -> 0 | T10: =SUM(T7:T8) -> 0 | U10: =SUM(U7:U8) -> 0 | V10: =SUM(V7:V8) -> 0 | W10: =SUM(W7:W8) -> 0 | X10: =SUM(X7:X8) -> 0 | Y10: =SUM(Y7:Y8) -> 6.9767442 | Z10: =SUM(Z7:Z8) -> 5.2325581 | ... AF10: =SUM(AF7:AF8) -> 8.7209302 | AH10: =SUM(AH7:AH8) -> 0 | AI10: =SUM(AI7:AI8) -> 0 | AJ10: =SUM(AJ7:AJ8) -> 0 | AK10: =SUM(AK7:AK8) -> 0 | AL10: =SUM(AL7:AL8) -> 0 | AM10: =SUM(AM7:AM8) -> 0 | AN10: =SUM(AN7:AN8) -> 6.9767442 | AO10: =SUM(AO7:AO8) -> 12.209302 | ... AU10: =SUM(AU7:AU8) -> 75
B11: GP I % | C11: =C10/C$7 -> 0.6 | D11: =D10/D$7 -> 0.6025 | E11: =E10/E$7 -> 0.605 | J11: GP I % | K11: =K10/K$7 -> 0.6 | L11: =L10/L$7 -> 0.6025 | M11: =M10/M$7 -> 0.605 | S11: =S10/S$7 -> #DIV/0! | T11: =T10/T$7 -> #DIV/0! | U11: =U10/U$7 -> #DIV/0! | V11: =V10/V$7 -> #DIV/0! | W11: =W10/W$7 -> #DIV/0! | X11: =X10/X$7 -> #DIV/0! | Y11: =Y10/Y$7 -> 0.6 | Z11: =Z10/Z$7 -> 0.6 | ... AF11: =AF10/AF$7 -> 0.6 | AH11: =AH10/AH$7 -> #DIV/0! | AI11: =AI10/AI$7 -> #DIV/0! | AJ11: =AJ10/AJ$7 -> #DIV/0! | AK11: =AK10/AK$7 -> #DIV/0! | AL11: =AL10/AL$7 -> #DIV/0! | AM11: =AM10/AM$7 -> #DIV/0! | AN11: =AN10/AN$7 -> 0.6 | AO11: =AO10/AO$7 -> 0.6 | ... AU11: =AU10/AU$7 -> 0.6
B13: Shipping and distribution costs | C13: =-C7*'Other COS'!$C$31 -> -5 | D13: =-D7*'Other COS'!$C$31 -> -7 | E13: =-E7*'Other COS'!$C$31 -> -10 | J13: Shipping and distribution costs | K13: =-K7*'Other COS'!$C$16 -> -8.75 | L13: =-L7*'Other COS'!$C$16 -> -12.25 | M13: =-M7*'Other COS'!$C$16 -> -17.5 | Y13: =Y7*$K13/$K7 -> -0.81395349 | Z13: =Z7*$K13/$K7 -> -0.61046512 | AA13: =AA7*$K13/$K7 -> -0.61046512 | AB13: =AB7*$K13/$K7 -> -0.61046512 | AC13: =AC7*$K13/$K7 -> -2.5436047 | AD13: =AD7*$K13/$K7 -> -1.5261628 | AE13: =AE7*$K13/$K7 -> -1.0174419 | AF13: =AF7*$K13/$K7 -> -1.0174419 | AH13: =S13 -> 0 | AI13: =AH13+T13 -> 0 | AJ13: =AI13+U13 -> 0 | AK13: =AJ13+V13 -> 0 | AL13: =AK13+W13 -> 0 | AM13: =AL13+X13 -> 0 | AN13: =AM13+Y13 -> -0.81395349 | AO13: =AN13+Z13 -> -1.4244186 | AP13: =AO13+AA13 -> -2.0348837 | ... AU13: =AT13+AF13 -> -8.75
B14: Rebates | C14: 0 | D14: 0 | E14: 0 | J14: Rebates | K14: 0 | L14: 0 | M14: 0
B16: Gross profit II | C16: =SUM(C10,C13:C14) -> 145 | D16: =SUM(D10,D13:D14) -> 203.875 | E16: =SUM(E10,E13:E14) -> 292.5 | J16: Gross profit II | K16: =SUM(K10,K13:K14) -> 66.25 | L16: =SUM(L10,L13:L14) -> 93.1875 | M16: =SUM(M10,M13:M14) -> 133.75 | S16: =SUM(S10,S13:S14) -> 0 | T16: =SUM(T10,T13:T14) -> 0 | U16: =SUM(U10,U13:U14) -> 0 | V16: =SUM(V10,V13:V14) -> 0 | W16: =SUM(W10,W13:W14) -> 0 | X16: =SUM(X10,X13:X14) -> 0 | Y16: =SUM(Y10,Y13:Y14) -> 6.1627907 | Z16: =SUM(Z10,Z13:Z14) -> 4.622093 | ... AF16: =SUM(AF10,AF13:AF14) -> 7.7034884 | AH16: =SUM(AH10,AH13:AH14) -> 0 | AI16: =SUM(AI10,AI13:AI14) -> 0 | AJ16: =SUM(AJ10,AJ13:AJ14) -> 0 | AK16: =SUM(AK10,AK13:AK14) -> 0 | AL16: =SUM(AL10,AL13:AL14) -> 0 | AM16: =SUM(AM10,AM13:AM14) -> 0 | AN16: =SUM(AN10,AN13:AN14) -> 6.1627907 | AO16: =SUM(AO10,AO13:AO14) -> 10.784884 | ... AU16: =SUM(AU10,AU13:AU14) -> 66.25
B17: GP II % | C17: =C16/C$7 -> 0.58 | D17: =D16/D$7 -> 0.5825 | E17: =E16/E$7 -> 0.585 | J17: GP II % | K17: =K16/K$7 -> 0.53 | L17: =L16/L$7 -> 0.5325 | M17: =M16/M$7 -> 0.535 | S17: =S16/S$7 -> #DIV/0! | T17: =T16/T$7 -> #DIV/0! | U17: =U16/U$7 -> #DIV/0! | V17: =V16/V$7 -> #DIV/0! | W17: =W16/W$7 -> #DIV/0! | X17: =X16/X$7 -> #DIV/0! | Y17: =Y16/Y$7 -> 0.53 | Z17: =Z16/Z$7 -> 0.53 | ... AF17: =AF16/AF$7 -> 0.53 | AH17: =AH16/AH$7 -> #DIV/0! | AI17: =AI16/AI$7 -> #DIV/0! | AJ17: =AJ16/AJ$7 -> #DIV/0! | AK17: =AK16/AK$7 -> #DIV/0! | AL17: =AL16/AL$7 -> #DIV/0! | AM17: =AM16/AM$7 -> #DIV/0! | AN17: =AN16/AN$7 -> 0.53 | AO17: =AO16/AO$7 -> 0.53 | ... AU17: =AU16/AU$7 -> 0.53
B19: Advertising and Marketing | C19: =C49 -> -100 | D19: =D49 -> -100 | E19: =E49 -> -100 | J19: Advertising and Marketing | K19: =C19 -> -100 | L19: =D19 -> -100 | M19: =E19 -> -100 | X19: =K19*30% -> -30 | AB19: =K19*60% -> -60 | AE19: =K19*10% -> -10 | AH19: =S19 -> 0 | AI19: =AH19+T19 -> 0 | AJ19: =AI19+U19 -> 0 | AK19: =AJ19+V19 -> 0 | AL19: =AK19+W19 -> 0 | AM19: =AL19+X19 -> -30 | AN19: =AM19+Y19 -> -30 | AO19: =AN19+Z19 -> -30 | AP19: =AO19+AA19 -> -30 | ... AU19: =AT19+AF19 -> -100
B20: Sales and Training Expenses | C20: =C50 -> 0 | D20: =D50 -> 0 | E20: =E50 -> 0 | J20: Sales and Training Expenses | K20: =C20 -> 0 | L20: =D20 -> 0 | M20: =E20 -> 0
B22: Gross profit III | C22: =SUM(C16,C19:C20) -> 45 | D22: =SUM(D16,D19:D20) -> 103.875 | E22: =SUM(E16,E19:E20) -> 192.5 | J22: Gross profit III | K22: =SUM(K16,K19:K20) -> -33.75 | L22: =SUM(L16,L19:L20) -> -6.8125 | M22: =SUM(M16,M19:M20) -> 33.75 | S22: =SUM(S16,S19:S20) -> 0 | T22: =SUM(T16,T19:T20) -> 0 | U22: =SUM(U16,U19:U20) -> 0 | V22: =SUM(V16,V19:V20) -> 0 | W22: =SUM(W16,W19:W20) -> 0 | X22: =SUM(X16,X19:X20) -> -30 | Y22: =SUM(Y16,Y19:Y20) -> 6.1627907 | Z22: =SUM(Z16,Z19:Z20) -> 4.622093 | ... AF22: =SUM(AF16,AF19:AF20) -> 7.7034884 | AH22: =SUM(AH16,AH19:AH20) -> 0 | AI22: =SUM(AI16,AI19:AI20) -> 0 | AJ22: =SUM(AJ16,AJ19:AJ20) -> 0 | AK22: =SUM(AK16,AK19:AK20) -> 0 | AL22: =SUM(AL16,AL19:AL20) -> 0 | AM22: =SUM(AM16,AM19:AM20) -> -30 | AN22: =SUM(AN16,AN19:AN20) -> -23.837209 | AO22: =SUM(AO16,AO19:AO20) -> -19.215116 | ... AU22: =SUM(AU16,AU19:AU20) -> -33.75
B23: GP III % | C23: =C22/C$7 -> 0.18 | D23: =D22/D$7 -> 0.29678571 | E23: =E22/E$7 -> 0.385 | J23: GP III % | K23: =K22/K$7 -> -0.27 | L23: =L22/L$7 -> -0.038928571 | M23: =M22/M$7 -> 0.135 | S23: =S22/S$7 -> #DIV/0! | T23: =T22/T$7 -> #DIV/0! | U23: =U22/U$7 -> #DIV/0! | V23: =V22/V$7 -> #DIV/0! | W23: =W22/W$7 -> #DIV/0! | X23: =X22/X$7 -> #DIV/0! | Y23: =Y22/Y$7 -> 0.53 | Z23: =Z22/Z$7 -> 0.53 | ... AF23: =AF22/AF$7 -> 0.53 | AH23: =AH22/AH$7 -> #DIV/0! | AI23: =AI22/AI$7 -> #DIV/0! | AJ23: =AJ22/AJ$7 -> #DIV/0! | AK23: =AK22/AK$7 -> #DIV/0! | AL23: =AL22/AL$7 -> #DIV/0! | AM23: =AM22/AM$7 -> #DIV/0! | AN23: =AN22/AN$7 -> -2.05 | AO23: =AO22/AO$7 -> -0.94428571 | ... AU23: =AU22/AU$7 -> -0.27
B25: Personnel Expenses | C25: 0 | D25: 0 | E25: 0 | J25: Personnel Expenses | K25: =C25 -> 0 | L25: =D25 -> 0 | M25: =E25 -> 0
B26: Other Admin Expenses | C26: =C52 -> 0 | D26: =D52 -> 0 | E26: =E52 -> 0 | J26: Other Admin Expenses | K26: =C26 -> 0 | L26: =D26 -> 0 | M26: =E26 -> 0
B28: Adjusted EBITDA | C28: =SUM(C22,C25:C26) -> 45 | D28: =SUM(D22,D25:D26) -> 103.875 | E28: =SUM(E22,E25:E26) -> 192.5 | J28: Adjusted EBITDA | K28: =SUM(K22,K25:K26) -> -33.75 | L28: =SUM(L22,L25:L26) -> -6.8125 | M28: =SUM(M22,M25:M26) -> 33.75 | S28: =SUM(S22,S25:S26) -> 0 | T28: =SUM(T22,T25:T26) -> 0 | U28: =SUM(U22,U25:U26) -> 0 | V28: =SUM(V22,V25:V26) -> 0 | W28: =SUM(W22,W25:W26) -> 0 | X28: =SUM(X22,X25:X26) -> -30 | Y28: =SUM(Y22,Y25:Y26) -> 6.1627907 | Z28: =SUM(Z22,Z25:Z26) -> 4.622093 | ... AF28: =SUM(AF22,AF25:AF26) -> 7.7034884 | AH28: =SUM(AH22,AH25:AH26) -> 0 | AI28: =SUM(AI22,AI25:AI26) -> 0 | AJ28: =SUM(AJ22,AJ25:AJ26) -> 0 | AK28: =SUM(AK22,AK25:AK26) -> 0 | AL28: =SUM(AL22,AL25:AL26) -> 0 | AM28: =SUM(AM22,AM25:AM26) -> -30 | AN28: =SUM(AN22,AN25:AN26) -> -23.837209 | AO28: =SUM(AO22,AO25:AO26) -> -19.215116 | ... AU28: =SUM(AU22,AU25:AU26) -> -33.75
B29: Adj EBITDA % | C29: =C28/C$7 -> 0.18 | D29: =D28/D$7 -> 0.29678571 | E29: =E28/E$7 -> 0.385 | J29: Adj EBITDA % | K29: =K28/K$7 -> -0.27 | L29: =L28/L$7 -> -0.038928571 | M29: =M28/M$7 -> 0.135 | S29: =S28/S$7 -> #DIV/0! | T29: =T28/T$7 -> #DIV/0! | U29: =U28/U$7 -> #DIV/0! | V29: =V28/V$7 -> #DIV/0! | W29: =W28/W$7 -> #DIV/0! | X29: =X28/X$7 -> #DIV/0! | Y29: =Y28/Y$7 -> 0.53 | Z29: =Z28/Z$7 -> 0.53 | ... AF29: =AF28/AF$7 -> 0.53 | AH29: =AH28/AH$7 -> #DIV/0! | AI29: =AI28/AI$7 -> #DIV/0! | AJ29: =AJ28/AJ$7 -> #DIV/0! | AK29: =AK28/AK$7 -> #DIV/0! | AL29: =AL28/AL$7 -> #DIV/0! | AM29: =AM28/AM$7 -> #DIV/0! | AN29: =AN28/AN$7 -> -2.05 | AO29: =AO28/AO$7 -> -0.94428571 | ... AU29: =AU28/AU$7 -> -0.27
B31: Exceptionals | C31: =C54 -> 0 | D31: =D54 -> 0 | E31: =E54 -> 0 | J31: Exceptionals | K31: 0 | L31: 0 | M31: 0
B33: EBITDA | C33: =SUM(C28,C31) -> 45 | D33: =SUM(D28,D31) -> 103.875 | E33: =SUM(E28,E31) -> 192.5 | J33: EBITDA | K33: =SUM(K28,K31) -> -33.75 | L33: =SUM(L28,L31) -> -6.8125 | M33: =SUM(M28,M31) -> 33.75 | S33: =SUM(S28,S31) -> 0 | T33: =SUM(T28,T31) -> 0 | U33: =SUM(U28,U31) -> 0 | V33: =SUM(V28,V31) -> 0 | W33: =SUM(W28,W31) -> 0 | X33: =SUM(X28,X31) -> -30 | Y33: =SUM(Y28,Y31) -> 6.1627907 | Z33: =SUM(Z28,Z31) -> 4.622093 | ... AF33: =SUM(AF28,AF31) -> 7.7034884 | AH33: =SUM(AH28,AH31) -> 0 | AI33: =SUM(AI28,AI31) -> 0 | AJ33: =SUM(AJ28,AJ31) -> 0 | AK33: =SUM(AK28,AK31) -> 0 | AL33: =SUM(AL28,AL31) -> 0 | AM33: =SUM(AM28,AM31) -> -30 | AN33: =SUM(AN28,AN31) -> -23.837209 | AO33: =SUM(AO28,AO31) -> -19.215116 | ... AU33: =SUM(AU28,AU31) -> -33.75
B34: EBITDA % | C34: =C33/C$7 -> 0.18 | D34: =D33/D$7 -> 0.29678571 | E34: =E33/E$7 -> 0.385 | J34: EBITDA % | K34: =K33/K$7 -> -0.27 | L34: =L33/L$7 -> -0.038928571 | M34: =M33/M$7 -> 0.135 | S34: =S33/S$7 -> #DIV/0! | T34: =T33/T$7 -> #DIV/0! | U34: =U33/U$7 -> #DIV/0! | V34: =V33/V$7 -> #DIV/0! | W34: =W33/W$7 -> #DIV/0! | X34: =X33/X$7 -> #DIV/0! | Y34: =Y33/Y$7 -> 0.53 | Z34: =Z33/Z$7 -> 0.53 | ... AF34: =AF33/AF$7 -> 0.53 | AH34: =AH33/AH$7 -> #DIV/0! | AI34: =AI33/AI$7 -> #DIV/0! | AJ34: =AJ33/AJ$7 -> #DIV/0! | AK34: =AK33/AK$7 -> #DIV/0! | AL34: =AL33/AL$7 -> #DIV/0! | AM34: =AM33/AM$7 -> #DIV/0! | AN34: =AN33/AN$7 -> -2.05 | AO34: =AO33/AO$7 -> -0.94428571 | ... AU34: =AU33/AU$7 -> -0.27
B37: Risk Amount | C37: =C19 -> -100 | J37: Risk Amount | K37: =K19 -> -100
B44: Workings
B46: Growth Sales | C46: 250 | D46: 350 | E46: 500
B47: Existing growth %
B49: Advertising and Marketing | C49: -100 | D49: -100 | E49: -100
B50: Sales and Training Expenses
B52: Other Admin Expenses
B54: Exceptionals

Sheet 3.2 Lane Crawford
S3: Monthly | T3: Monthly | U3: Monthly | V3: Monthly | W3: Monthly | X3: Monthly | Y3: Monthly | Z3: Monthly | AA3: Monthly | AB3: Monthly | AC3: Monthly | AD3: Monthly | AE3: Monthly | AF3: Monthly | AH3: To date | AI3: To date | AJ3: To date | AK3: To date | AL3: To date | AM3: To date | AN3: To date | AO3: To date | AP3: To date | AQ3: To date | AR3: To date | AS3: To date | AT3: To date | AU3: To date
S4: =MONTH(S5)&RIGHT(YEAR(S5), 2) -> 1125 | T4: =MONTH(T5)&RIGHT(YEAR(T5), 2) -> 1225 | U4: =MONTH(U5)&RIGHT(YEAR(U5), 2) -> 126 | V4: =MONTH(V5)&RIGHT(YEAR(V5), 2) -> 226 | W4: =MONTH(W5)&RIGHT(YEAR(W5), 2) -> 326 | X4: =MONTH(X5)&RIGHT(YEAR(X5), 2) -> 426 | Y4: =MONTH(Y5)&RIGHT(YEAR(Y5), 2) -> 526 | Z4: =MONTH(Z5)&RIGHT(YEAR(Z5), 2) -> 626 | ... AF4: =MONTH(AF5)&RIGHT(YEAR(AF5), 2) -> 1226 | AH4: =MONTH(AH5)&RIGHT(YEAR(AH5), 2) -> 1125 | AI4: =MONTH(AI5)&RIGHT(YEAR(AI5), 2) -> 1225 | AJ4: =MONTH(AJ5)&RIGHT(YEAR(AJ5), 2) -> 126 | AK4: =MONTH(AK5)&RIGHT(YEAR(AK5), 2) -> 226 | AL4: =MONTH(AL5)&RIGHT(YEAR(AL5), 2) -> 326 | AM4: =MONTH(AM5)&RIGHT(YEAR(AM5), 2) -> 426 | AN4: =MONTH(AN5)&RIGHT(YEAR(AN5), 2) -> 526 | AO4: =MONTH(AO5)&RIGHT(YEAR(AO5), 2) -> 626 | ... AU4: =MONTH(AU5)&RIGHT(YEAR(AU5), 2) -> 1226
C5: 2026 | D5: 2027 | E5: 2028 | H5: Risk Factor | K5: 2026 | L5: 2027 | M5: 2028 | S5: 45962 | T5: 45992 | U5: 46023 | V5: 46054 | W5: 46082 | X5: 46113 | Y5: 46143 | Z5: 46174 | AA5: 46204 | AB5: 46235 | AC5: 46266 | AD5: 46296 | AE5: 46327 | AF5: 46357 | AH5: 45962 | AI5: 45992 | AJ5: 46023 | AK5: 46054 | AL5: 46082 | AM5: 46113 | AN5: 46143 | AO5: 46174 | AP5: 46204 | AQ5: 46235 | AR5: 46266 | AS5: 46296 | AT5: 46327 | AU5: 46357
B7: Revenue | C7: =C46+'3YP'!E32*C47 -> 100 | D7: =D46+'3YP'!F32*D47 -> 200 | E7: =E46+'3YP'!G32*E47 -> 300 | H7: -0.5 | J7: Revenue | K7: =C7*(1+$H$7) -> 50 | L7: =D7*(1+$H$7) -> 100 | M7: =E7*(1+$H$7) -> 150
B8: Cost of Sales | C8: =-C7*(1-COGS!C30) -> -40 | D8: =-D7*(1-COGS!D30) -> -79.5 | E8: =-E7*(1-COGS!E30) -> -118.5 | J8: Cost of Sales | K8: =C8*(1+$H$7) -> -20 | L8: =D8*(1+$H$7) -> -39.75 | M8: =E8*(1+$H$7) -> -59.25
B10: Gross Profit I | C10: =SUM(C7:C8) -> 60 | D10: =SUM(D7:D8) -> 120.5 | E10: =SUM(E7:E8) -> 181.5 | J10: Gross Profit I | K10: =SUM(K7:K8) -> 30 | L10: =SUM(L7:L8) -> 60.25 | M10: =SUM(M7:M8) -> 90.75
B11: GP I % | C11: =C10/C$7 -> 0.6 | D11: =D10/D$7 -> 0.6025 | E11: =E10/E$7 -> 0.605 | J11: GP I % | K11: =K10/K$7 -> 0.6 | L11: =L10/L$7 -> 0.6025 | M11: =M10/M$7 -> 0.605
B13: Shipping and distribution costs | C13: =-C7*'Other COS'!$C$31 -> -2 | D13: =-D7*'Other COS'!$C$31 -> -4 | E13: =-E7*'Other COS'!$C$31 -> -6 | J13: Shipping and distribution costs | K13: =-K7*'Other COS'!$C$16 -> -3.5 | L13: =-L7*'Other COS'!$C$16 -> -7 | M13: =-M7*'Other COS'!$C$16 -> -10.5
B14: Rebates | C14: 0 | D14: 0 | E14: 0 | J14: Rebates | K14: 0 | L14: 0 | M14: 0
B16: Gross profit II | C16: =SUM(C10,C13:C14) -> 58 | D16: =SUM(D10,D13:D14) -> 116.5 | E16: =SUM(E10,E13:E14) -> 175.5 | J16: Gross profit II | K16: =SUM(K10,K13:K14) -> 26.5 | L16: =SUM(L10,L13:L14) -> 53.25 | M16: =SUM(M10,M13:M14) -> 80.25
B17: GP II % | C17: =C16/C$7 -> 0.58 | D17: =D16/D$7 -> 0.5825 | E17: =E16/E$7 -> 0.585 | J17: GP II % | K17: =K16/K$7 -> 0.53 | L17: =L16/L$7 -> 0.5325 | M17: =M16/M$7 -> 0.535
B19: Advertising and Marketing | C19: =C49 -> -50 | D19: =D49 -> -60 | E19: =E49 -> -70 | J19: Advertising and Marketing | K19: =C19 -> -50 | L19: =D19 -> -60 | M19: =E19 -> -70
B20: Sales and Training Expenses | C20: =C50 -> 0 | D20: =D50 -> 0 | E20: =E50 -> 0 | J20: Sales and Training Expenses | K20: =C20 -> 0 | L20: =D20 -> 0 | M20: =E20 -> 0
B22: Gross profit III | C22: =SUM(C16,C19:C20) -> 8 | D22: =SUM(D16,D19:D20) -> 56.5 | E22: =SUM(E16,E19:E20) -> 105.5 | J22: Gross profit III | K22: =SUM(K16,K19:K20) -> -23.5 | L22: =SUM(L16,L19:L20) -> -6.75 | M22: =SUM(M16,M19:M20) -> 10.25
B23: GP III % | C23: =C22/C$7 -> 0.08 | D23: =D22/D$7 -> 0.2825 | E23: =E22/E$7 -> 0.35166667 | J23: GP III % | K23: =K22/K$7 -> -0.47 | L23: =L22/L$7 -> -0.0675 | M23: =M22/M$7 -> 0.068333333
B25: Personnel Expenses | C25: 0 | D25: 0 | E25: 0 | J25: Personnel Expenses | K25: =C25 -> 0 | L25: =D25 -> 0 | M25: =E25 -> 0
B26: Other Admin Expenses | C26: =C52 -> 0 | D26: =D52 -> 0 | E26: =E52 -> 0 | J26: Other Admin Expenses | K26: =C26 -> 0 | L26: =D26 -> 0 | M26: =E26 -> 0
B28: Adjusted EBITDA | C28: =SUM(C22,C25:C26) -> 8 | D28: =SUM(D22,D25:D26) -> 56.5 | E28: =SUM(E22,E25:E26) -> 105.5 | J28: Adjusted EBITDA | K28: =SUM(K22,K25:K26) -> -23.5 | L28: =SUM(L22,L25:L26) -> -6.75 | M28: =SUM(M22,M25:M26) -> 10.25
B29: Adj EBITDA % | C29: =C28/C$7 -> 0.08 | D29: =D28/D$7 -> 0.2825 | E29: =E28/E$7 -> 0.35166667 | J29: Adj EBITDA % | K29: =K28/K$7 -> -0.47 | L29: =L28/L$7 -> -0.0675 | M29: =M28/M$7 -> 0.068333333
B31: Exceptionals | C31: =C54 -> 0 | D31: =D54 -> 0 | E31: =E54 -> 0 | J31: Exceptionals | K31: 0 | L31: 0 | M31: 0
B33: EBITDA | C33: =SUM(C28,C31) -> 8 | D33: =SUM(D28,D31) -> 56.5 | E33: =SUM(E28,E31) -> 105.5 | J33: EBITDA | K33: =SUM(K28,K31) -> -23.5 | L33: =SUM(L28,L31) -> -6.75 | M33: =SUM(M28,M31) -> 10.25
B34: EBITDA % | C34: =C33/C$7 -> 0.08 | D34: =D33/D$7 -> 0.2825 | E34: =E33/E$7 -> 0.35166667 | J34: EBITDA % | K34: =K33/K$7 -> -0.47 | L34: =L33/L$7 -> -0.0675 | M34: =M33/M$7 -> 0.068333333
B37: Risk Amount | C37: =C20+C19*60% -> -30 | J37: Risk Amount | K37: =K20+K19*60% -> -30
B44: Workings
B46: Growth Sales | C46: 100 | D46: 200 | E46: 300
B47: Existing growth %
B49: Advertising and Marketing | C49: -50 | D49: -60 | E49: -70
B50: Sales and Training Expenses
B52: Other Admin Expenses
B54: Exceptionals

Sheet 4.1 Nadim ME
S3: Monthly | T3: Monthly | U3: Monthly | V3: Monthly | W3: Monthly | X3: Monthly | Y3: Monthly | Z3: Monthly | AA3: Monthly | AB3: Monthly | AC3: Monthly | AD3: Monthly | AE3: Monthly | AF3: Monthly | AH3: To date | AI3: To date | AJ3: To date | AK3: To date | AL3: To date | AM3: To date | AN3: To date | AO3: To date | AP3: To date | AQ3: To date | AR3: To date | AS3: To date | AT3: To date | AU3: To date
S4: =MONTH(S5)&RIGHT(YEAR(S5), 2) -> 1125 | T4: =MONTH(T5)&RIGHT(YEAR(T5), 2) -> 1225 | U4: =MONTH(U5)&RIGHT(YEAR(U5), 2) -> 126 | V4: =MONTH(V5)&RIGHT(YEAR(V5), 2) -> 226 | W4: =MONTH(W5)&RIGHT(YEAR(W5), 2) -> 326 | X4: =MONTH(X5)&RIGHT(YEAR(X5), 2) -> 426 | Y4: =MONTH(Y5)&RIGHT(YEAR(Y5), 2) -> 526 | Z4: =MONTH(Z5)&RIGHT(YEAR(Z5), 2) -> 626 | ... AF4: =MONTH(AF5)&RIGHT(YEAR(AF5), 2) -> 1226 | AH4: =MONTH(AH5)&RIGHT(YEAR(AH5), 2) -> 1125 | AI4: =MONTH(AI5)&RIGHT(YEAR(AI5), 2) -> 1225 | AJ4: =MONTH(AJ5)&RIGHT(YEAR(AJ5), 2) -> 126 | AK4: =MONTH(AK5)&RIGHT(YEAR(AK5), 2) -> 226 | AL4: =MONTH(AL5)&RIGHT(YEAR(AL5), 2) -> 326 | AM4: =MONTH(AM5)&RIGHT(YEAR(AM5), 2) -> 426 | AN4: =MONTH(AN5)&RIGHT(YEAR(AN5), 2) -> 526 | AO4: =MONTH(AO5)&RIGHT(YEAR(AO5), 2) -> 626 | ... AU4: =MONTH(AU5)&RIGHT(YEAR(AU5), 2) -> 1226
C5: 2026 | D5: 2027 | E5: 2028 | H5: Risk Factor | K5: 2026 | L5: 2027 | M5: 2028 | S5: 45962 | T5: 45992 | U5: 46023 | V5: 46054 | W5: 46082 | X5: 46113 | Y5: 46143 | Z5: 46174 | AA5: 46204 | AB5: 46235 | AC5: 46266 | AD5: 46296 | AE5: 46327 | AF5: 46357 | AH5: 45962 | AI5: 45992 | AJ5: 46023 | AK5: 46054 | AL5: 46082 | AM5: 46113 | AN5: 46143 | AO5: 46174 | AP5: 46204 | AQ5: 46235 | AR5: 46266 | AS5: 46296 | AT5: 46327 | AU5: 46357
B7: Revenue | C7: =C46+'3YP'!E32*C47 -> 50 | D7: =D46+'3YP'!F32*D47 -> 125 | E7: =E46+'3YP'!G32*E47 -> 237.5 | H7: -0.3 | J7: Revenue | K7: =C7*(1+$H$7) -> 35 | L7: =D7*(1+$H$7) -> 87.5 | M7: =E7*(1+$H$7) -> 166.25
B8: Cost of Sales | C8: =-C7*(1-COGS!C31) -> -17.5 | D8: =-D7*(1-COGS!D31) -> -43.4375 | E8: =-E7*(1-COGS!E31) -> -81.9375 | J8: Cost of Sales | K8: =C8*(1+$H$7) -> -12.25 | L8: =D8*(1+$H$7) -> -30.40625 | M8: =E8*(1+$H$7) -> -57.35625
B10: Gross Profit I | C10: =SUM(C7:C8) -> 32.5 | D10: =SUM(D7:D8) -> 81.5625 | E10: =SUM(E7:E8) -> 155.5625 | J10: Gross Profit I | K10: =SUM(K7:K8) -> 22.75 | L10: =SUM(L7:L8) -> 57.09375 | M10: =SUM(M7:M8) -> 108.89375
B11: GP I % | C11: =C10/C$7 -> 0.65 | D11: =D10/D$7 -> 0.6525 | E11: =E10/E$7 -> 0.655 | J11: GP I % | K11: =K10/K$7 -> 0.65 | L11: =L10/L$7 -> 0.6525 | M11: =M10/M$7 -> 0.655
B13: Shipping and distribution costs | C13: =-C7*'Other COS'!$C$32 -> -0.5 | D13: =-D7*'Other COS'!$C$32 -> -1.25 | E13: =-E7*'Other COS'!$C$32 -> -2.375 | J13: Shipping and distribution costs | K13: =-K7*'Other COS'!$C$32 -> -0.35 | L13: =-L7*'Other COS'!$C$32 -> -0.875 | M13: =-M7*'Other COS'!$C$32 -> -1.6625
B14: Rebates | C14: 0 | D14: 0 | E14: 0 | J14: Rebates | K14: 0 | L14: 0 | M14: 0
B16: Gross profit II | C16: =SUM(C10,C13:C14) -> 32 | D16: =SUM(D10,D13:D14) -> 80.3125 | E16: =SUM(E10,E13:E14) -> 153.1875 | J16: Gross profit II | K16: =SUM(K10,K13:K14) -> 22.4 | L16: =SUM(L10,L13:L14) -> 56.21875 | M16: =SUM(M10,M13:M14) -> 107.23125
B17: GP II % | C17: =C16/C$7 -> 0.64 | D17: =D16/D$7 -> 0.6425 | E17: =E16/E$7 -> 0.645 | J17: GP II % | K17: =K16/K$7 -> 0.64 | L17: =L16/L$7 -> 0.6425 | M17: =M16/M$7 -> 0.645
B19: Advertising and Marketing | C19: =C49 -> 0 | D19: =D49 -> 0 | E19: =E49 -> 0 | J19: Advertising and Marketing | K19: =C19 -> 0 | L19: =D19 -> 0 | M19: =E19 -> 0
B20: Sales and Training Expenses | C20: =C50 -> 0 | D20: =D50 -> 0 | E20: =E50 -> 0 | J20: Sales and Training Expenses | K20: =C20 -> 0 | L20: =D20 -> 0 | M20: =E20 -> 0
B22: Gross profit III | C22: =SUM(C16,C19:C20) -> 32 | D22: =SUM(D16,D19:D20) -> 80.3125 | E22: =SUM(E16,E19:E20) -> 153.1875 | J22: Gross profit III | K22: =SUM(K16,K19:K20) -> 22.4 | L22: =SUM(L16,L19:L20) -> 56.21875 | M22: =SUM(M16,M19:M20) -> 107.23125
B23: GP III % | C23: =C22/C$7 -> 0.64 | D23: =D22/D$7 -> 0.6425 | E23: =E22/E$7 -> 0.645 | J23: GP III % | K23: =K22/K$7 -> 0.64 | L23: =L22/L$7 -> 0.6425 | M23: =M22/M$7 -> 0.645
B25: Personnel Expenses | C25: 0 | D25: 0 | E25: 0 | J25: Personnel Expenses | K25: =C25 -> 0 | L25: =D25 -> 0 | M25: =E25 -> 0
B26: Other Admin Expenses | C26: =C52 -> 0 | D26: =D52 -> 0 | E26: =E52 -> 0 | J26: Other Admin Expenses | K26: =C26 -> 0 | L26: =D26 -> 0 | M26: =E26 -> 0
B28: Adjusted EBITDA | C28: =SUM(C22,C25:C26) -> 32 | D28: =SUM(D22,D25:D26) -> 80.3125 | E28: =SUM(E22,E25:E26) -> 153.1875 | J28: Adjusted EBITDA | K28: =SUM(K22,K25:K26) -> 22.4 | L28: =SUM(L22,L25:L26) -> 56.21875 | M28: =SUM(M22,M25:M26) -> 107.23125
B29: Adj EBITDA % | C29: =C28/C$7 -> 0.64 | D29: =D28/D$7 -> 0.6425 | E29: =E28/E$7 -> 0.645 | J29: Adj EBITDA % | K29: =K28/K$7 -> 0.64 | L29: =L28/L$7 -> 0.6425 | M29: =M28/M$7 -> 0.645
B31: Exceptionals | C31: =C54 -> -30 | D31: =D54 -> 0 | E31: =E54 -> 0 | J31: Exceptionals | K31: =C31 -> -30 | L31: =D31 -> 0 | M31: =E31 -> 0
B33: EBITDA | C33: =SUM(C28,C31) -> 2 | D33: =SUM(D28,D31) -> 80.3125 | E33: =SUM(E28,E31) -> 153.1875 | J33: EBITDA | K33: =SUM(K28,K31) -> -7.6 | L33: =SUM(L28,L31) -> 56.21875 | M33: =SUM(M28,M31) -> 107.23125
B34: EBITDA % | C34: =C33/C$7 -> 0.04 | D34: =D33/D$7 -> 0.6425 | E34: =E33/E$7 -> 0.645 | J34: EBITDA % | K34: =K33/K$7 -> -0.21714286 | L34: =L33/L$7 -> 0.6425 | M34: =M33/M$7 -> 0.645
B37: Risk Amount | C37: =C31/2 -> -15 | F37: 3 months Nadim | J37: Risk Amount | K37: =K31/2 -> -15 | N37: 3 months Nadim
B44: Workings
B46: Growth Sales | C46: =100*50% -> 50 | D46: =C46*1.5+100*50% -> 125 | E46: =D46*1.5+100*50% -> 237.5
B47: Existing growth %
B49: Advertising and Marketing
B50: Sales and Training Expenses
B52: Other Admin Expenses
B54: Exceptionals | C54: =-5*6 -> -30

Sheet 4.2 ME Retail
S3: Monthly | T3: Monthly | U3: Monthly | V3: Monthly | W3: Monthly | X3: Monthly | Y3: Monthly | Z3: Monthly | AA3: Monthly | AB3: Monthly | AC3: Monthly | AD3: Monthly | AE3: Monthly | AF3: Monthly | AH3: To date | AI3: To date | AJ3: To date | AK3: To date | AL3: To date | AM3: To date | AN3: To date | AO3: To date | AP3: To date | AQ3: To date | AR3: To date | AS3: To date | AT3: To date | AU3: To date
S4: =MONTH(S5)&RIGHT(YEAR(S5), 2) -> 1125 | T4: =MONTH(T5)&RIGHT(YEAR(T5), 2) -> 1225 | U4: =MONTH(U5)&RIGHT(YEAR(U5), 2) -> 126 | V4: =MONTH(V5)&RIGHT(YEAR(V5), 2) -> 226 | W4: =MONTH(W5)&RIGHT(YEAR(W5), 2) -> 326 | X4: =MONTH(X5)&RIGHT(YEAR(X5), 2) -> 426 | Y4: =MONTH(Y5)&RIGHT(YEAR(Y5), 2) -> 526 | Z4: =MONTH(Z5)&RIGHT(YEAR(Z5), 2) -> 626 | ... AF4: =MONTH(AF5)&RIGHT(YEAR(AF5), 2) -> 1226 | AH4: =MONTH(AH5)&RIGHT(YEAR(AH5), 2) -> 1125 | AI4: =MONTH(AI5)&RIGHT(YEAR(AI5), 2) -> 1225 | AJ4: =MONTH(AJ5)&RIGHT(YEAR(AJ5), 2) -> 126 | AK4: =MONTH(AK5)&RIGHT(YEAR(AK5), 2) -> 226 | AL4: =MONTH(AL5)&RIGHT(YEAR(AL5), 2) -> 326 | AM4: =MONTH(AM5)&RIGHT(YEAR(AM5), 2) -> 426 | AN4: =MONTH(AN5)&RIGHT(YEAR(AN5), 2) -> 526 | AO4: =MONTH(AO5)&RIGHT(YEAR(AO5), 2) -> 626 | ... AU4: =MONTH(AU5)&RIGHT(YEAR(AU5), 2) -> 1226
C5: 2026 | D5: 2027 | E5: 2028 | H5: Risk Factor | K5: 2026 | L5: 2027 | M5: 2028 | S5: 45962 | T5: 45992 | U5: 46023 | V5: 46054 | W5: 46082 | X5: 46113 | Y5: 46143 | Z5: 46174 | AA5: 46204 | AB5: 46235 | AC5: 46266 | AD5: 46296 | AE5: 46327 | AF5: 46357 | AH5: 45962 | AI5: 45992 | AJ5: 46023 | AK5: 46054 | AL5: 46082 | AM5: 46113 | AN5: 46143 | AO5: 46174 | AP5: 46204 | AQ5: 46235 | AR5: 46266 | AS5: 46296 | AT5: 46327 | AU5: 46357
B7: Revenue | C7: =C46+'3YP'!E32*C47 -> 100 | D7: =D46+'3YP'!F32*D47 -> 150 | E7: =E46+'3YP'!G32*E47 -> 250 | H7: -0.5 | J7: Revenue | K7: =C7*(1+$H$7) -> 50 | L7: =D7*(1+$H$7) -> 75 | M7: =E7*(1+$H$7) -> 125
B8: Cost of Sales | C8: =-C7*(1-COGS!C31) -> -35 | D8: =-D7*(1-COGS!D31) -> -52.125 | E8: =-E7*(1-COGS!E31) -> -86.25 | J8: Cost of Sales | K8: =C8*(1+$H$7) -> -17.5 | L8: =D8*(1+$H$7) -> -26.0625 | M8: =E8*(1+$H$7) -> -43.125
B10: Gross Profit I | C10: =SUM(C7:C8) -> 65 | D10: =SUM(D7:D8) -> 97.875 | E10: =SUM(E7:E8) -> 163.75 | J10: Gross Profit I | K10: =SUM(K7:K8) -> 32.5 | L10: =SUM(L7:L8) -> 48.9375 | M10: =SUM(M7:M8) -> 81.875
B11: GP I % | C11: =C10/C$7 -> 0.65 | D11: =D10/D$7 -> 0.6525 | E11: =E10/E$7 -> 0.655 | J11: GP I % | K11: =K10/K$7 -> 0.65 | L11: =L10/L$7 -> 0.6525 | M11: =M10/M$7 -> 0.655
B13: Shipping and distribution costs | C13: =-C7*'Other COS'!$C$32 -> -1 | D13: =-D7*'Other COS'!$C$32 -> -1.5 | E13: =-E7*'Other COS'!$C$32 -> -2.5 | J13: Shipping and distribution costs | K13: =-K7*'Other COS'!$C$32 -> -0.5 | L13: =-L7*'Other COS'!$C$32 -> -0.75 | M13: =-M7*'Other COS'!$C$32 -> -1.25
B14: Rebates | C14: 0 | D14: 0 | E14: 0 | J14: Rebates | K14: 0 | L14: 0 | M14: 0
B16: Gross profit II | C16: =SUM(C10,C13:C14) -> 64 | D16: =SUM(D10,D13:D14) -> 96.375 | E16: =SUM(E10,E13:E14) -> 161.25 | J16: Gross profit II | K16: =SUM(K10,K13:K14) -> 32 | L16: =SUM(L10,L13:L14) -> 48.1875 | M16: =SUM(M10,M13:M14) -> 80.625
B17: GP II % | C17: =C16/C$7 -> 0.64 | D17: =D16/D$7 -> 0.6425 | E17: =E16/E$7 -> 0.645 | J17: GP II % | K17: =K16/K$7 -> 0.64 | L17: =L16/L$7 -> 0.6425 | M17: =M16/M$7 -> 0.645
B19: Advertising and Marketing | C19: =C49 -> -50 | D19: =D49 -> -50 | E19: =E49 -> -50 | J19: Advertising and Marketing | K19: =C19 -> -50 | L19: =D19 -> -50 | M19: =E19 -> -50
B20: Sales and Training Expenses | C20: =C50 -> 0 | D20: =D50 -> 0 | E20: =E50 -> 0 | J20: Sales and Training Expenses | K20: =C20 -> 0 | L20: =D20 -> 0 | M20: =E20 -> 0
B22: Gross profit III | C22: =SUM(C16,C19:C20) -> 14 | D22: =SUM(D16,D19:D20) -> 46.375 | E22: =SUM(E16,E19:E20) -> 111.25 | J22: Gross profit III | K22: =SUM(K16,K19:K20) -> -18 | L22: =SUM(L16,L19:L20) -> -1.8125 | M22: =SUM(M16,M19:M20) -> 30.625
B23: GP III % | C23: =C22/C$7 -> 0.14 | D23: =D22/D$7 -> 0.30916667 | E23: =E22/E$7 -> 0.445 | J23: GP III % | K23: =K22/K$7 -> -0.36 | L23: =L22/L$7 -> -0.024166667 | M23: =M22/M$7 -> 0.245
B25: Personnel Expenses | C25: 0 | D25: 0 | E25: 0 | J25: Personnel Expenses | K25: =C25 -> 0 | L25: =D25 -> 0 | M25: =E25 -> 0
B26: Other Admin Expenses | C26: =C52 -> 0 | D26: =D52 -> 0 | E26: =E52 -> 0 | J26: Other Admin Expenses | K26: =C26 -> 0 | L26: =D26 -> 0 | M26: =E26 -> 0
B28: Adjusted EBITDA | C28: =SUM(C22,C25:C26) -> 14 | D28: =SUM(D22,D25:D26) -> 46.375 | E28: =SUM(E22,E25:E26) -> 111.25 | J28: Adjusted EBITDA | K28: =SUM(K22,K25:K26) -> -18 | L28: =SUM(L22,L25:L26) -> -1.8125 | M28: =SUM(M22,M25:M26) -> 30.625
B29: Adj EBITDA % | C29: =C28/C$7 -> 0.14 | D29: =D28/D$7 -> 0.30916667 | E29: =E28/E$7 -> 0.445 | J29: Adj EBITDA % | K29: =K28/K$7 -> -0.36 | L29: =L28/L$7 -> -0.024166667 | M29: =M28/M$7 -> 0.245
B31: Exceptionals | C31: =C54 -> 0 | D31: =D54 -> 0 | E31: =E54 -> 0 | J31: Exceptionals | K31: =C31 -> 0 | L31: =D31 -> 0 | M31: =E31 -> 0
B33: EBITDA | C33: =SUM(C28,C31) -> 14 | D33: =SUM(D28,D31) -> 46.375 | E33: =SUM(E28,E31) -> 111.25 | J33: EBITDA | K33: =SUM(K28,K31) -> -18 | L33: =SUM(L28,L31) -> -1.8125 | M33: =SUM(M28,M31) -> 30.625
B34: EBITDA % | C34: =C33/C$7 -> 0.14 | D34: =D33/D$7 -> 0.30916667 | E34: =E33/E$7 -> 0.445 | J34: EBITDA % | K34: =K33/K$7 -> -0.36 | L34: =L33/L$7 -> -0.024166667 | M34: =M33/M$7 -> 0.245
B37: Risk Amount | C37: =C31/2 -> 0 | J37: Risk Amount | K37: =K31/2 -> 0
B44: Workings
B46: Growth Sales | C46: 100 | D46: 150 | E46: 250
B47: Existing growth %
B49: Advertising and Marketing | C49: -50 | D49: -50 | E49: -50
B50: Sales and Training Expenses
B52: Other Admin Expenses
B54: Exceptionals

Sheet 5.1 Mingo
B2: Open new markets
S3: Monthly | T3: Monthly | U3: Monthly | V3: Monthly | W3: Monthly | X3: Monthly | Y3: Monthly | Z3: Monthly | AA3: Monthly | AB3: Monthly | AC3: Monthly | AD3: Monthly | AE3: Monthly | AF3: Monthly | AH3: To date | AI3: To date | AJ3: To date | AK3: To date | AL3: To date | AM3: To date | AN3: To date | AO3: To date | AP3: To date | AQ3: To date | AR3: To date | AS3: To date | AT3: To date | AU3: To date
S4: =MONTH(S5)&RIGHT(YEAR(S5), 2) -> 1125 | T4: =MONTH(T5)&RIGHT(YEAR(T5), 2) -> 1225 | U4: =MONTH(U5)&RIGHT(YEAR(U5), 2) -> 126 | V4: =MONTH(V5)&RIGHT(YEAR(V5), 2) -> 226 | W4: =MONTH(W5)&RIGHT(YEAR(W5), 2) -> 326 | X4: =MONTH(X5)&RIGHT(YEAR(X5), 2) -> 426 | Y4: =MONTH(Y5)&RIGHT(YEAR(Y5), 2) -> 526 | Z4: =MONTH(Z5)&RIGHT(YEAR(Z5), 2) -> 626 | ... AF4: =MONTH(AF5)&RIGHT(YEAR(AF5), 2) -> 1226 | AH4: =MONTH(AH5)&RIGHT(YEAR(AH5), 2) -> 1125 | AI4: =MONTH(AI5)&RIGHT(YEAR(AI5), 2) -> 1225 | AJ4: =MONTH(AJ5)&RIGHT(YEAR(AJ5), 2) -> 126 | AK4: =MONTH(AK5)&RIGHT(YEAR(AK5), 2) -> 226 | AL4: =MONTH(AL5)&RIGHT(YEAR(AL5), 2) -> 326 | AM4: =MONTH(AM5)&RIGHT(YEAR(AM5), 2) -> 426 | AN4: =MONTH(AN5)&RIGHT(YEAR(AN5), 2) -> 526 | AO4: =MONTH(AO5)&RIGHT(YEAR(AO5), 2) -> 626 | ... AU4: =MONTH(AU5)&RIGHT(YEAR(AU5), 2) -> 1226
C5: 2026 | D5: 2027 | E5: 2028 | H5: Risk Factor | K5: 2026 | L5: 2027 | M5: 2028 | S5: 45962 | T5: 45992 | U5: 46023 | V5: 46054 | W5: 46082 | X5: 46113 | Y5: 46143 | Z5: 46174 | AA5: 46204 | AB5: 46235 | AC5: 46266 | AD5: 46296 | AE5: 46327 | AF5: 46357 | AH5: 45962 | AI5: 45992 | AJ5: 46023 | AK5: 46054 | AL5: 46082 | AM5: 46113 | AN5: 46143 | AO5: 46174 | AP5: 46204 | AQ5: 46235 | AR5: 46266 | AS5: 46296 | AT5: 46327 | AU5: 46357
B7: Revenue | C7: =C46+'3YP'!E33*C47 -> 150 | D7: =D46+'3YP'!F33*D47 -> 200 | E7: =E46+'3YP'!G33*E47 -> 300 | H7: -0.75 | J7: Revenue | K7: =C7*(1+$H$7) -> 37.5 | L7: =D7*(1+$H$7) -> 50 | M7: =E7*(1+$H$7) -> 75
B8: Cost of Sales | C8: =-C7*(1-COGS!C32) -> -49.5 | D8: =-D7*(1-COGS!D32) -> -65.5 | E8: =-E7*(1-COGS!E32) -> -97.5 | J8: Cost of Sales | K8: =C8*(1+$H$7) -> -12.375 | L8: =D8*(1+$H$7) -> -16.375 | M8: =E8*(1+$H$7) -> -24.375
B10: Gross Profit I | C10: =SUM(C7:C8) -> 100.5 | D10: =SUM(D7:D8) -> 134.5 | E10: =SUM(E7:E8) -> 202.5 | J10: Gross Profit I | K10: =SUM(K7:K8) -> 25.125 | L10: =SUM(L7:L8) -> 33.625 | M10: =SUM(M7:M8) -> 50.625
B11: GP I % | C11: =C10/C$7 -> 0.67 | D11: =D10/D$7 -> 0.6725 | E11: =E10/E$7 -> 0.675 | J11: GP I % | K11: =K10/K$7 -> 0.67 | L11: =L10/L$7 -> 0.6725 | M11: =M10/M$7 -> 0.675
B13: Shipping and distribution costs | C13: =-C7*'Other COS'!$C$34 -> 0 | D13: =-D7*'Other COS'!$C$34 -> 0 | E13: =-E7*'Other COS'!$C$34 -> 0 | J13: Shipping and distribution costs | K13: =-K7*'Other COS'!$C$34 -> 0 | L13: =-L7*'Other COS'!$C$34 -> 0 | M13: =-M7*'Other COS'!$C$34 -> 0
B14: Rebates | C14: 0 | D14: 0 | E14: 0 | J14: Rebates | K14: 0 | L14: 0 | M14: 0
B16: Gross profit II | C16: =SUM(C10,C13:C14) -> 100.5 | D16: =SUM(D10,D13:D14) -> 134.5 | E16: =SUM(E10,E13:E14) -> 202.5 | J16: Gross profit II | K16: =SUM(K10,K13:K14) -> 25.125 | L16: =SUM(L10,L13:L14) -> 33.625 | M16: =SUM(M10,M13:M14) -> 50.625
B17: GP II % | C17: =C16/C$7 -> 0.67 | D17: =D16/D$7 -> 0.6725 | E17: =E16/E$7 -> 0.675 | J17: GP II % | K17: =K16/K$7 -> 0.67 | L17: =L16/L$7 -> 0.6725 | M17: =M16/M$7 -> 0.675
B19: Advertising and Marketing | C19: =C49 -> 0 | D19: =D49 -> 0 | E19: =E49 -> 0 | J19: Advertising and Marketing | K19: =C19 -> 0 | L19: =D19 -> 0 | M19: =E19 -> 0
B20: Sales and Training Expenses | C20: =C50 -> 0 | D20: =D50 -> 0 | E20: =E50 -> 0 | J20: Sales and Training Expenses | K20: =C20 -> 0 | L20: =D20 -> 0 | M20: =E20 -> 0
B22: Gross profit III | C22: =SUM(C16,C19:C20) -> 100.5 | D22: =SUM(D16,D19:D20) -> 134.5 | E22: =SUM(E16,E19:E20) -> 202.5 | J22: Gross profit III | K22: =SUM(K16,K19:K20) -> 25.125 | L22: =SUM(L16,L19:L20) -> 33.625 | M22: =SUM(M16,M19:M20) -> 50.625
B23: GP III % | C23: =C22/C$7 -> 0.67 | D23: =D22/D$7 -> 0.6725 | E23: =E22/E$7 -> 0.675 | J23: GP III % | K23: =K22/K$7 -> 0.67 | L23: =L22/L$7 -> 0.6725 | M23: =M22/M$7 -> 0.675
B25: Personnel Expenses | C25: 0 | D25: 0 | E25: 0 | J25: Personnel Expenses | K25: =C25 -> 0 | L25: =D25 -> 0 | M25: =E25 -> 0
B26: Other Admin Expenses | C26: =C52 -> 0 | D26: =D52 -> 0 | E26: =E52 -> 0 | J26: Other Admin Expenses | K26: =C26 -> 0 | L26: =D26 -> 0 | M26: =E26 -> 0
B28: Adjusted EBITDA | C28: =SUM(C22,C25:C26) -> 100.5 | D28: =SUM(D22,D25:D26) -> 134.5 | E28: =SUM(E22,E25:E26) -> 202.5 | J28: Adjusted EBITDA | K28: =SUM(K22,K25:K26) -> 25.125 | L28: =SUM(L22,L25:L26) -> 33.625 | M28: =SUM(M22,M25:M26) -> 50.625
B29: Adj EBITDA % | C29: =C28/C$7 -> 0.67 | D29: =D28/D$7 -> 0.6725 | E29: =E28/E$7 -> 0.675 | J29: Adj EBITDA % | K29: =K28/K$7 -> 0.67 | L29: =L28/L$7 -> 0.6725 | M29: =M28/M$7 -> 0.675
B31: Exceptionals | C31: =-C7*10% -> -15 | D31: =-D7*10% -> -20 | E31: =-E7*10% -> -30 | J31: Exceptionals | K31: =-K7*10% -> -3.75 | L31: =-L7*10% -> -5 | M31: =-M7*10% -> -7.5
B33: EBITDA | C33: =SUM(C28,C31) -> 85.5 | D33: =SUM(D28,D31) -> 114.5 | E33: =SUM(E28,E31) -> 172.5 | J33: EBITDA | K33: =SUM(K28,K31) -> 21.375 | L33: =SUM(L28,L31) -> 28.625 | M33: =SUM(M28,M31) -> 43.125
B34: EBITDA % | C34: =C33/C$7 -> 0.57 | D34: =D33/D$7 -> 0.5725 | E34: =E33/E$7 -> 0.575 | J34: EBITDA % | K34: =K33/K$7 -> 0.57 | L34: =L33/L$7 -> 0.5725 | M34: =M33/M$7 -> 0.575
B37: Risk Amount | C37: 0 | F37: 0 risk, commission only | J37: Risk Amount | K37: 0 | N37: 0 risk, commission only
B44: Workings
B46: Growth Sales | C46: 150 | D46: 200 | E46: 300
B47: Existing growth %
B49: Advertising and Marketing
B50: Sales and Training Expenses
B52: Other Admin Expenses
B54: Exceptionals

Sheet 5.2 Juan
B2: Open new markets
S3: Monthly | T3: Monthly | U3: Monthly | V3: Monthly | W3: Monthly | X3: Monthly | Y3: Monthly | Z3: Monthly | AA3: Monthly | AB3: Monthly | AC3: Monthly | AD3: Monthly | AE3: Monthly | AF3: Monthly | AH3: To date | AI3: To date | AJ3: To date | AK3: To date | AL3: To date | AM3: To date | AN3: To date | AO3: To date | AP3: To date | AQ3: To date | AR3: To date | AS3: To date | AT3: To date | AU3: To date
S4: =MONTH(S5)&RIGHT(YEAR(S5), 2) -> 1125 | T4: =MONTH(T5)&RIGHT(YEAR(T5), 2) -> 1225 | U4: =MONTH(U5)&RIGHT(YEAR(U5), 2) -> 126 | V4: =MONTH(V5)&RIGHT(YEAR(V5), 2) -> 226 | W4: =MONTH(W5)&RIGHT(YEAR(W5), 2) -> 326 | X4: =MONTH(X5)&RIGHT(YEAR(X5), 2) -> 426 | Y4: =MONTH(Y5)&RIGHT(YEAR(Y5), 2) -> 526 | Z4: =MONTH(Z5)&RIGHT(YEAR(Z5), 2) -> 626 | ... AF4: =MONTH(AF5)&RIGHT(YEAR(AF5), 2) -> 1226 | AH4: =MONTH(AH5)&RIGHT(YEAR(AH5), 2) -> 1125 | AI4: =MONTH(AI5)&RIGHT(YEAR(AI5), 2) -> 1225 | AJ4: =MONTH(AJ5)&RIGHT(YEAR(AJ5), 2) -> 126 | AK4: =MONTH(AK5)&RIGHT(YEAR(AK5), 2) -> 226 | AL4: =MONTH(AL5)&RIGHT(YEAR(AL5), 2) -> 326 | AM4: =MONTH(AM5)&RIGHT(YEAR(AM5), 2) -> 426 | AN4: =MONTH(AN5)&RIGHT(YEAR(AN5), 2) -> 526 | AO4: =MONTH(AO5)&RIGHT(YEAR(AO5), 2) -> 626 | ... AU4: =MONTH(AU5)&RIGHT(YEAR(AU5), 2) -> 1226
C5: 2026 | D5: 2027 | E5: 2028 | H5: Risk Factor | K5: 2026 | L5: 2027 | M5: 2028 | S5: 45962 | T5: 45992 | U5: 46023 | V5: 46054 | W5: 46082 | X5: 46113 | Y5: 46143 | Z5: 46174 | AA5: 46204 | AB5: 46235 | AC5: 46266 | AD5: 46296 | AE5: 46327 | AF5: 46357 | AH5: 45962 | AI5: 45992 | AJ5: 46023 | AK5: 46054 | AL5: 46082 | AM5: 46113 | AN5: 46143 | AO5: 46174 | AP5: 46204 | AQ5: 46235 | AR5: 46266 | AS5: 46296 | AT5: 46327 | AU5: 46357
B7: Revenue | C7: =C46+SUM('3YP'!E32:E33)*C47 -> 1200 | D7: =D46+SUM('3YP'!F32:F33)*D47 -> 2400 | E7: =E46+SUM('3YP'!G32:G33)*E47 -> 3260 | H7: -0.9 | J7: Revenue | K7: =C7*(1+$H$7) -> 120 | L7: =D7*(1+$H$7) -> 240 | M7: =E7*(1+$H$7) -> 326
B8: Cost of Sales | C8: =-C46*(1-COGS!C32)-(C7-C46) *(1-AVERAGE(COGS!C30:C31)) -> -405 | D8: =-D46*(1-COGS!D32)-(D7-D46) *(1-AVERAGE(COGS!D30:D31)) -> -813 | E8: =-E46*(1-COGS!E32)-(E7-E46) *(1-AVERAGE(COGS!E30:E31)) -> -1116.2 | J8: Cost of Sales | K8: =C8*(1+$H$7) -> -40.5 | L8: =D8*(1+$H$7) -> -81.3 | M8: =E8*(1+$H$7) -> -111.62
B10: Gross Profit I | C10: =SUM(C7:C8) -> 795 | D10: =SUM(D7:D8) -> 1587 | E10: =SUM(E7:E8) -> 2143.8 | J10: Gross Profit I | K10: =SUM(K7:K8) -> 79.5 | L10: =SUM(L7:L8) -> 158.7 | M10: =SUM(M7:M8) -> 214.38
B11: GP I % | C11: =C10/C$7 -> 0.6625 | D11: =D10/D$7 -> 0.66125 | E11: =E10/E$7 -> 0.65760736 | J11: GP I % | K11: =K10/K$7 -> 0.6625 | L11: =L10/L$7 -> 0.66125 | M11: =M10/M$7 -> 0.65760736
B13: Shipping and distribution costs | C13: =-C7*'Other COS'!$C$34 -> 0 | D13: =-D7*'Other COS'!$C$34 -> 0 | E13: =-E7*'Other COS'!$C$34 -> 0 | J13: Shipping and distribution costs | K13: =-K7*'Other COS'!$C$34 -> 0 | L13: =-L7*'Other COS'!$C$34 -> 0 | M13: =-M7*'Other COS'!$C$34 -> 0
B14: Rebates | C14: 0 | D14: 0 | E14: 0 | J14: Rebates | K14: 0 | L14: 0 | M14: 0
B16: Gross profit II | C16: =SUM(C10,C13:C14) -> 795 | D16: =SUM(D10,D13:D14) -> 1587 | E16: =SUM(E10,E13:E14) -> 2143.8 | J16: Gross profit II | K16: =SUM(K10,K13:K14) -> 79.5 | L16: =SUM(L10,L13:L14) -> 158.7 | M16: =SUM(M10,M13:M14) -> 214.38
B17: GP II % | C17: =C16/C$7 -> 0.6625 | D17: =D16/D$7 -> 0.66125 | E17: =E16/E$7 -> 0.65760736 | J17: GP II % | K17: =K16/K$7 -> 0.6625 | L17: =L16/L$7 -> 0.66125 | M17: =M16/M$7 -> 0.65760736
B19: Advertising and Marketing | C19: =C49 -> 0 | D19: =D49 -> 0 | E19: =E49 -> 0 | J19: Advertising and Marketing | K19: =C19 -> 0 | L19: =D19 -> 0 | M19: =E19 -> 0
B20: Sales and Training Expenses | C20: =C50 -> 0 | D20: =D50 -> 0 | E20: =E50 -> 0 | J20: Sales and Training Expenses | K20: =C20 -> 0 | L20: =D20 -> 0 | M20: =E20 -> 0
B22: Gross profit III | C22: =SUM(C16,C19:C20) -> 795 | D22: =SUM(D16,D19:D20) -> 1587 | E22: =SUM(E16,E19:E20) -> 2143.8 | J22: Gross profit III | K22: =SUM(K16,K19:K20) -> 79.5 | L22: =SUM(L16,L19:L20) -> 158.7 | M22: =SUM(M16,M19:M20) -> 214.38
B23: GP III % | C23: =C22/C$7 -> 0.6625 | D23: =D22/D$7 -> 0.66125 | E23: =E22/E$7 -> 0.65760736 | J23: GP III % | K23: =K22/K$7 -> 0.6625 | L23: =L22/L$7 -> 0.66125 | M23: =M22/M$7 -> 0.65760736
B25: Personnel Expenses | C25: 0 | D25: 0 | E25: 0 | J25: Personnel Expenses | K25: =C25 -> 0 | L25: =D25 -> 0 | M25: =E25 -> 0
B26: Other Admin Expenses | C26: =C52 -> -10 | D26: =D52 -> -15 | E26: =E52 -> -20 | J26: Other Admin Expenses | K26: =C26 -> -10 | L26: =D26 -> -15 | M26: =E26 -> -20
B28: Adjusted EBITDA | C28: =SUM(C22,C25:C26) -> 785 | D28: =SUM(D22,D25:D26) -> 1572 | E28: =SUM(E22,E25:E26) -> 2123.8 | J28: Adjusted EBITDA | K28: =SUM(K22,K25:K26) -> 69.5 | L28: =SUM(L22,L25:L26) -> 143.7 | M28: =SUM(M22,M25:M26) -> 194.38
B29: Adj EBITDA % | C29: =C28/C$7 -> 0.65416667 | D29: =D28/D$7 -> 0.655 | E29: =E28/E$7 -> 0.65147239 | J29: Adj EBITDA % | K29: =K28/K$7 -> 0.57916667 | L29: =L28/L$7 -> 0.59875 | M29: =M28/M$7 -> 0.59625767 | R29: =140+167+15+130+30+52 -> 534
B31: Exceptionals | C31: =-C7*10%-10*12 -> -240 | D31: =-D7*10%-10*12*1.1 -> -372 | E31: =-E7*10%-10*12*1.1^2 -> -471.2 | J31: Exceptionals | K31: =-K7*10%-10*12 -> -132 | L31: =-L7*10%-10*12*1.1 -> -156 | M31: =-M7*10%-10*12*1.1^2 -> -177.8
B33: EBITDA | C33: =SUM(C28,C31) -> 545 | D33: =SUM(D28,D31) -> 1200 | E33: =SUM(E28,E31) -> 1652.6 | J33: EBITDA | K33: =SUM(K28,K31) -> -62.5 | L33: =SUM(L28,L31) -> -12.3 | M33: =SUM(M28,M31) -> 16.58
B34: EBITDA % | C34: =C33/C$7 -> 0.45416667 | D34: =D33/D$7 -> 0.5 | E34: =E33/E$7 -> 0.50693252 | J34: EBITDA % | K34: =K33/K$7 -> -0.52083333 | L34: =L33/L$7 -> -0.05125 | M34: =M33/M$7 -> 0.050858896
B37: Risk Amount | C37: =C31*3/12 -> -60 | F37: 3 months Juan | J37: Risk Amount | K37: =K31*3/12 -> -33 | N37: 3 months Juan
B44: Workings
B46: Growth Sales | C46: 1000 | D46: 1800 | E46: 2000
B47: Existing growth % | C47: 0.2 | D47: 0.4 | E47: 0.6 | F47: CN and ME
B49: Advertising and Marketing
B50: Sales and Training Expenses
B52: Other Admin Expenses | C52: -10 | D52: -15 | E52: -20
B54: Exceptionals

Sheet 5.3 Vishal_India
B2: Develop India
S3: Monthly | T3: Monthly | U3: Monthly | V3: Monthly | W3: Monthly | X3: Monthly | Y3: Monthly | Z3: Monthly | AA3: Monthly | AB3: Monthly | AC3: Monthly | AD3: Monthly | AE3: Monthly | AF3: Monthly | AH3: To date | AI3: To date | AJ3: To date | AK3: To date | AL3: To date | AM3: To date | AN3: To date | AO3: To date | AP3: To date | AQ3: To date | AR3: To date | AS3: To date | AT3: To date | AU3: To date
S4: =MONTH(S5)&RIGHT(YEAR(S5), 2) -> 1125 | T4: =MONTH(T5)&RIGHT(YEAR(T5), 2) -> 1225 | U4: =MONTH(U5)&RIGHT(YEAR(U5), 2) -> 126 | V4: =MONTH(V5)&RIGHT(YEAR(V5), 2) -> 226 | W4: =MONTH(W5)&RIGHT(YEAR(W5), 2) -> 326 | X4: =MONTH(X5)&RIGHT(YEAR(X5), 2) -> 426 | Y4: =MONTH(Y5)&RIGHT(YEAR(Y5), 2) -> 526 | Z4: =MONTH(Z5)&RIGHT(YEAR(Z5), 2) -> 626 | ... AF4: =MONTH(AF5)&RIGHT(YEAR(AF5), 2) -> 1226 | AH4: =MONTH(AH5)&RIGHT(YEAR(AH5), 2) -> 1125 | AI4: =MONTH(AI5)&RIGHT(YEAR(AI5), 2) -> 1225 | AJ4: =MONTH(AJ5)&RIGHT(YEAR(AJ5), 2) -> 126 | AK4: =MONTH(AK5)&RIGHT(YEAR(AK5), 2) -> 226 | AL4: =MONTH(AL5)&RIGHT(YEAR(AL5), 2) -> 326 | AM4: =MONTH(AM5)&RIGHT(YEAR(AM5), 2) -> 426 | AN4: =MONTH(AN5)&RIGHT(YEAR(AN5), 2) -> 526 | AO4: =MONTH(AO5)&RIGHT(YEAR(AO5), 2) -> 626 | ... AU4: =MONTH(AU5)&RIGHT(YEAR(AU5), 2) -> 1226
C5: 2026 | D5: 2027 | E5: 2028 | H5: Risk Factor | K5: 2026 | L5: 2027 | M5: 2028 | S5: 45962 | T5: 45992 | U5: 46023 | V5: 46054 | W5: 46082 | X5: 46113 | Y5: 46143 | Z5: 46174 | AA5: 46204 | AB5: 46235 | AC5: 46266 | AD5: 46296 | AE5: 46327 | AF5: 46357 | AH5: 45962 | AI5: 45992 | AJ5: 46023 | AK5: 46054 | AL5: 46082 | AM5: 46113 | AN5: 46143 | AO5: 46174 | AP5: 46204 | AQ5: 46235 | AR5: 46266 | AS5: 46296 | AT5: 46327 | AU5: 46357
B7: Revenue | C7: =C46+'3YP'!E33*C47 -> 50 | D7: =D46+'3YP'!F33*D47 -> 75 | E7: =E46+'3YP'!G33*E47 -> 100 | H7: -0.5 | J7: Revenue | K7: =C7*(1+$H$7) -> 25 | L7: =D7*(1+$H$7) -> 37.5 | M7: =E7*(1+$H$7) -> 50
B8: Cost of Sales | C8: =-C7*(1-COGS!C32) -> -16.5 | D8: =-D7*(1-COGS!D32) -> -24.5625 | E8: =-E7*(1-COGS!E32) -> -32.5 | J8: Cost of Sales | K8: =C8*(1+$H$7) -> -8.25 | L8: =D8*(1+$H$7) -> -12.28125 | M8: =E8*(1+$H$7) -> -16.25
B10: Gross Profit I | C10: =SUM(C7:C8) -> 33.5 | D10: =SUM(D7:D8) -> 50.4375 | E10: =SUM(E7:E8) -> 67.5 | J10: Gross Profit I | K10: =SUM(K7:K8) -> 16.75 | L10: =SUM(L7:L8) -> 25.21875 | M10: =SUM(M7:M8) -> 33.75
B11: GP I % | C11: =C10/C$7 -> 0.67 | D11: =D10/D$7 -> 0.6725 | E11: =E10/E$7 -> 0.675 | J11: GP I % | K11: =K10/K$7 -> 0.67 | L11: =L10/L$7 -> 0.6725 | M11: =M10/M$7 -> 0.675
B13: Shipping and distribution costs | C13: =-C7*'Other COS'!$C$34 -> 0 | D13: =-D7*'Other COS'!$C$34 -> 0 | E13: =-E7*'Other COS'!$C$34 -> 0 | J13: Shipping and distribution costs | K13: =-K7*'Other COS'!$C$34 -> 0 | L13: =-L7*'Other COS'!$C$34 -> 0 | M13: =-M7*'Other COS'!$C$34 -> 0
B14: Rebates | C14: 0 | D14: 0 | E14: 0 | J14: Rebates | K14: 0 | L14: 0 | M14: 0
B16: Gross profit II | C16: =SUM(C10,C13:C14) -> 33.5 | D16: =SUM(D10,D13:D14) -> 50.4375 | E16: =SUM(E10,E13:E14) -> 67.5 | J16: Gross profit II | K16: =SUM(K10,K13:K14) -> 16.75 | L16: =SUM(L10,L13:L14) -> 25.21875 | M16: =SUM(M10,M13:M14) -> 33.75
B17: GP II % | C17: =C16/C$7 -> 0.67 | D17: =D16/D$7 -> 0.6725 | E17: =E16/E$7 -> 0.675 | J17: GP II % | K17: =K16/K$7 -> 0.67 | L17: =L16/L$7 -> 0.6725 | M17: =M16/M$7 -> 0.675
B19: Advertising and Marketing | C19: =C49 -> 0 | D19: =D49 -> 0 | E19: =E49 -> 0 | J19: Advertising and Marketing | K19: =C19 -> 0 | L19: =D19 -> 0 | M19: =E19 -> 0
B20: Sales and Training Expenses | C20: =C50 -> -36 | D20: =D50 -> -39.6 | E20: =E50 -> -43.56 | J20: Sales and Training Expenses | K20: =C20 -> -36 | L20: =D20 -> -39.6 | M20: =E20 -> -43.56
B22: Gross profit III | C22: =SUM(C16,C19:C20) -> -2.5 | D22: =SUM(D16,D19:D20) -> 10.8375 | E22: =SUM(E16,E19:E20) -> 23.94 | J22: Gross profit III | K22: =SUM(K16,K19:K20) -> -19.25 | L22: =SUM(L16,L19:L20) -> -14.38125 | M22: =SUM(M16,M19:M20) -> -9.81
B23: GP III % | C23: =C22/C$7 -> -0.05 | D23: =D22/D$7 -> 0.1445 | E23: =E22/E$7 -> 0.2394 | J23: GP III % | K23: =K22/K$7 -> -0.77 | L23: =L22/L$7 -> -0.3835 | M23: =M22/M$7 -> -0.1962
B25: Personnel Expenses | C25: 0 | D25: 0 | E25: 0 | J25: Personnel Expenses | K25: =C25 -> 0 | L25: =D25 -> 0 | M25: =E25 -> 0
B26: Other Admin Expenses | C26: =C52 -> 0 | D26: =D52 -> 0 | E26: =E52 -> 0 | J26: Other Admin Expenses | K26: =C26 -> 0 | L26: =D26 -> 0 | M26: =E26 -> 0
B28: Adjusted EBITDA | C28: =SUM(C22,C25:C26) -> -2.5 | D28: =SUM(D22,D25:D26) -> 10.8375 | E28: =SUM(E22,E25:E26) -> 23.94 | J28: Adjusted EBITDA | K28: =SUM(K22,K25:K26) -> -19.25 | L28: =SUM(L22,L25:L26) -> -14.38125 | M28: =SUM(M22,M25:M26) -> -9.81
B29: Adj EBITDA % | C29: =C28/C$7 -> -0.05 | D29: =D28/D$7 -> 0.1445 | E29: =E28/E$7 -> 0.2394 | J29: Adj EBITDA % | K29: =K28/K$7 -> -0.77 | L29: =L28/L$7 -> -0.3835 | M29: =M28/M$7 -> -0.1962
B31: Exceptionals | C31: 0 | D31: 0 | E31: 0 | J31: Exceptionals | K31: 0 | L31: 0 | M31: 0
B33: EBITDA | C33: =SUM(C28,C31) -> -2.5 | D33: =SUM(D28,D31) -> 10.8375 | E33: =SUM(E28,E31) -> 23.94 | J33: EBITDA | K33: =SUM(K28,K31) -> -19.25 | L33: =SUM(L28,L31) -> -14.38125 | M33: =SUM(M28,M31) -> -9.81
B34: EBITDA % | C34: =C33/C$7 -> -0.05 | D34: =D33/D$7 -> 0.1445 | E34: =E33/E$7 -> 0.2394 | J34: EBITDA % | K34: =K33/K$7 -> -0.77 | L34: =L33/L$7 -> -0.3835 | M34: =M33/M$7 -> -0.1962
B37: Risk Amount | C37: =C20*6/12 -> -18 | F37: 6 months Vishal | J37: Risk Amount | K37: =K20*6/12 -> -18 | N37: 6 months Vishal
B44: Workings
B46: Growth Sales | C46: 50 | D46: 75 | E46: 100
B47: Existing growth %
B49: Advertising and Marketing
B50: Sales and Training Expenses | C50: =-3*12 -> -36 | D50: =C50*1.1 -> -39.6 | E50: =D50*1.1 -> -43.56
B52: Other Admin Expenses
B54: Exceptionals

Sheet 5.4 Export Event
B2: Int'l event
S3: Monthly | T3: Monthly | U3: Monthly | V3: Monthly | W3: Monthly | X3: Monthly | Y3: Monthly | Z3: Monthly | AA3: Monthly | AB3: Monthly | AC3: Monthly | AD3: Monthly | AE3: Monthly | AF3: Monthly | AH3: To date | AI3: To date | AJ3: To date | AK3: To date | AL3: To date | AM3: To date | AN3: To date | AO3: To date | AP3: To date | AQ3: To date | AR3: To date | AS3: To date | AT3: To date | AU3: To date
S4: =MONTH(S5)&RIGHT(YEAR(S5), 2) -> 1125 | T4: =MONTH(T5)&RIGHT(YEAR(T5), 2) -> 1225 | U4: =MONTH(U5)&RIGHT(YEAR(U5), 2) -> 126 | V4: =MONTH(V5)&RIGHT(YEAR(V5), 2) -> 226 | W4: =MONTH(W5)&RIGHT(YEAR(W5), 2) -> 326 | X4: =MONTH(X5)&RIGHT(YEAR(X5), 2) -> 426 | Y4: =MONTH(Y5)&RIGHT(YEAR(Y5), 2) -> 526 | Z4: =MONTH(Z5)&RIGHT(YEAR(Z5), 2) -> 626 | ... AF4: =MONTH(AF5)&RIGHT(YEAR(AF5), 2) -> 1226 | AH4: =MONTH(AH5)&RIGHT(YEAR(AH5), 2) -> 1125 | AI4: =MONTH(AI5)&RIGHT(YEAR(AI5), 2) -> 1225 | AJ4: =MONTH(AJ5)&RIGHT(YEAR(AJ5), 2) -> 126 | AK4: =MONTH(AK5)&RIGHT(YEAR(AK5), 2) -> 226 | AL4: =MONTH(AL5)&RIGHT(YEAR(AL5), 2) -> 326 | AM4: =MONTH(AM5)&RIGHT(YEAR(AM5), 2) -> 426 | AN4: =MONTH(AN5)&RIGHT(YEAR(AN5), 2) -> 526 | AO4: =MONTH(AO5)&RIGHT(YEAR(AO5), 2) -> 626 | ... AU4: =MONTH(AU5)&RIGHT(YEAR(AU5), 2) -> 1226
C5: 2026 | D5: 2027 | E5: 2028 | H5: Risk Factor | K5: 2026 | L5: 2027 | M5: 2028 | S5: 45962 | T5: 45992 | U5: 46023 | V5: 46054 | W5: 46082 | X5: 46113 | Y5: 46143 | Z5: 46174 | AA5: 46204 | AB5: 46235 | AC5: 46266 | AD5: 46296 | AE5: 46327 | AF5: 46357 | AH5: 45962 | AI5: 45992 | AJ5: 46023 | AK5: 46054 | AL5: 46082 | AM5: 46113 | AN5: 46143 | AO5: 46174 | AP5: 46204 | AQ5: 46235 | AR5: 46266 | AS5: 46296 | AT5: 46327 | AU5: 46357
B7: Revenue | C7: =C46+'3YP'!E28*C47 -> 48.6125 | D7: =D46+'3YP'!F28*D47 -> 52.9 | E7: =E46+'3YP'!G28*E47 -> 59 | H7: -0.25 | J7: Revenue | K7: =C7*(1+$H$7) -> 36.459375 | L7: =D7*(1+$H$7) -> 39.675 | M7: =E7*(1+$H$7) -> 44.25
B8: Cost of Sales | C8: =-C7*(1-COGS!C19) -> -17.014375 | D8: =-D7*(1-COGS!D19) -> -18.38275 | E8: =-E7*(1-COGS!E19) -> -20.355 | J8: Cost of Sales | K8: =C8*(1+$H$7) -> -12.760781 | L8: =D8*(1+$H$7) -> -13.787063 | M8: =E8*(1+$H$7) -> -15.26625
B10: Gross Profit I | C10: =SUM(C7:C8) -> 31.598125 | D10: =SUM(D7:D8) -> 34.51725 | E10: =SUM(E7:E8) -> 38.645 | J10: Gross Profit I | K10: =SUM(K7:K8) -> 23.698594 | L10: =SUM(L7:L8) -> 25.887937 | M10: =SUM(M7:M8) -> 28.98375
B11: GP I % | C11: =C10/C$7 -> 0.65 | D11: =D10/D$7 -> 0.6525 | E11: =E10/E$7 -> 0.655 | J11: GP I % | K11: =K10/K$7 -> 0.65 | L11: =L10/L$7 -> 0.6525 | M11: =M10/M$7 -> 0.655
B13: Shipping and distribution costs | C13: =-C7*'Other COS'!$C$34 -> 0 | D13: =-D7*'Other COS'!$C$34 -> 0 | E13: =-E7*'Other COS'!$C$34 -> 0 | J13: Shipping and distribution costs | K13: =-K7*'Other COS'!$C$34 -> 0 | L13: =-L7*'Other COS'!$C$34 -> 0 | M13: =-M7*'Other COS'!$C$34 -> 0
B14: Rebates | C14: 0 | D14: 0 | E14: 0 | J14: Rebates | K14: 0 | L14: 0 | M14: 0
B16: Gross profit II | C16: =SUM(C10,C13:C14) -> 31.598125 | D16: =SUM(D10,D13:D14) -> 34.51725 | E16: =SUM(E10,E13:E14) -> 38.645 | J16: Gross profit II | K16: =SUM(K10,K13:K14) -> 23.698594 | L16: =SUM(L10,L13:L14) -> 25.887937 | M16: =SUM(M10,M13:M14) -> 28.98375
B17: GP II % | C17: =C16/C$7 -> 0.65 | D17: =D16/D$7 -> 0.6525 | E17: =E16/E$7 -> 0.655 | J17: GP II % | K17: =K16/K$7 -> 0.65 | L17: =L16/L$7 -> 0.6525 | M17: =M16/M$7 -> 0.655
B19: Advertising and Marketing | C19: =C49 -> 0 | D19: =D49 -> 0 | E19: =E49 -> 0 | J19: Advertising and Marketing | K19: =C19 -> 0 | L19: =D19 -> 0 | M19: =E19 -> 0
B20: Sales and Training Expenses | C20: =-Extra!N42/1000 -> -120 | E20: =C20*1.1 -> -132 | J20: Sales and Training Expenses | K20: =C20 -> -120 | L20: =D20 -> 0 | M20: =E20 -> -132
B22: Gross profit III | C22: =SUM(C16,C19:C20) -> -88.401875 | D22: =SUM(D16,D19:D20) -> 34.51725 | E22: =SUM(E16,E19:E20) -> -93.355 | J22: Gross profit III | K22: =SUM(K16,K19:K20) -> -96.301406 | L22: =SUM(L16,L19:L20) -> 25.887937 | M22: =SUM(M16,M19:M20) -> -103.01625
B23: GP III % | C23: =C22/C$7 -> -1.8185009 | D23: =D22/D$7 -> 0.6525 | E23: =E22/E$7 -> -1.5822881 | J23: GP III % | K23: =K22/K$7 -> -2.6413345 | L23: =L22/L$7 -> 0.6525 | M23: =M22/M$7 -> -2.3280508
B25: Personnel Expenses | C25: 0 | D25: 0 | E25: 0 | J25: Personnel Expenses | K25: =C25 -> 0 | L25: =D25 -> 0 | M25: =E25 -> 0
B26: Other Admin Expenses | C26: =C52 -> -5 | D26: =D52 -> 0 | E26: =E52 -> -5 | J26: Other Admin Expenses | K26: =C26 -> -5 | L26: =D26 -> 0 | M26: =E26 -> -5
B28: Adjusted EBITDA | C28: =SUM(C22,C25:C26) -> -93.401875 | D28: =SUM(D22,D25:D26) -> 34.51725 | E28: =SUM(E22,E25:E26) -> -98.355 | J28: Adjusted EBITDA | K28: =SUM(K22,K25:K26) -> -101.30141 | L28: =SUM(L22,L25:L26) -> 25.887937 | M28: =SUM(M22,M25:M26) -> -108.01625
B29: Adj EBITDA % | C29: =C28/C$7 -> -1.9213551 | D29: =D28/D$7 -> 0.6525 | E29: =E28/E$7 -> -1.6670339 | J29: Adj EBITDA % | K29: =K28/K$7 -> -2.7784735 | L29: =L28/L$7 -> 0.6525 | M29: =M28/M$7 -> -2.4410452
B31: Exceptionals | C31: 0 | D31: 0 | E31: 0 | J31: Exceptionals | K31: 0 | L31: 0 | M31: 0
B33: EBITDA | C33: =SUM(C28,C31) -> -93.401875 | D33: =SUM(D28,D31) -> 34.51725 | E33: =SUM(E28,E31) -> -98.355 | J33: EBITDA | K33: =SUM(K28,K31) -> -101.30141 | L33: =SUM(L28,L31) -> 25.887937 | M33: =SUM(M28,M31) -> -108.01625
B34: EBITDA % | C34: =C33/C$7 -> -1.9213551 | D34: =D33/D$7 -> 0.6525 | E34: =E33/E$7 -> -1.6670339 | J34: EBITDA % | K34: =K33/K$7 -> -2.7784735 | L34: =L33/L$7 -> 0.6525 | M34: =M33/M$7 -> -2.4410452
B37: Risk Amount | C37: =C20+C26 -> -125 | F37: Full event cost | J37: Risk Amount | K37: =K20+K26 -> -125 | N37: Full event cost
B44: Workings
B46: Growth Sales
B47: Existing growth % | C47: 0.025 | D47: 0.025 | E47: 0.025
B49: Advertising and Marketing
B50: Sales and Training Expenses | C50: =-3*12 -> -36 | D50: =C50*1.1 -> -39.6 | E50: =D50*1.1 -> -43.56
B52: Other Admin Expenses | C52: -5 | E52: -5
B54: Exceptionals

Sheet 5.5 ABC Brokers
B2: Open new markets
S3: Monthly | T3: Monthly | U3: Monthly | V3: Monthly | W3: Monthly | X3: Monthly | Y3: Monthly | Z3: Monthly | AA3: Monthly | AB3: Monthly | AC3: Monthly | AD3: Monthly | AE3: Monthly | AF3: Monthly | AH3: To date | AI3: To date | AJ3: To date | AK3: To date | AL3: To date | AM3: To date | AN3: To date | AO3: To date | AP3: To date | AQ3: To date | AR3: To date | AS3: To date | AT3: To date | AU3: To date
S4: =MONTH(S5)&RIGHT(YEAR(S5), 2) -> 1125 | T4: =MONTH(T5)&RIGHT(YEAR(T5), 2) -> 1225 | U4: =MONTH(U5)&RIGHT(YEAR(U5), 2) -> 126 | V4: =MONTH(V5)&RIGHT(YEAR(V5), 2) -> 226 | W4: =MONTH(W5)&RIGHT(YEAR(W5), 2) -> 326 | X4: =MONTH(X5)&RIGHT(YEAR(X5), 2) -> 426 | Y4: =MONTH(Y5)&RIGHT(YEAR(Y5), 2) -> 526 | Z4: =MONTH(Z5)&RIGHT(YEAR(Z5), 2) -> 626 | ... AF4: =MONTH(AF5)&RIGHT(YEAR(AF5), 2) -> 1226 | AH4: =MONTH(AH5)&RIGHT(YEAR(AH5), 2) -> 1125 | AI4: =MONTH(AI5)&RIGHT(YEAR(AI5), 2) -> 1225 | AJ4: =MONTH(AJ5)&RIGHT(YEAR(AJ5), 2) -> 126 | AK4: =MONTH(AK5)&RIGHT(YEAR(AK5), 2) -> 226 | AL4: =MONTH(AL5)&RIGHT(YEAR(AL5), 2) -> 326 | AM4: =MONTH(AM5)&RIGHT(YEAR(AM5), 2) -> 426 | AN4: =MONTH(AN5)&RIGHT(YEAR(AN5), 2) -> 526 | AO4: =MONTH(AO5)&RIGHT(YEAR(AO5), 2) -> 626 | ... AU4: =MONTH(AU5)&RIGHT(YEAR(AU5), 2) -> 1226
C5: 2026 | D5: 2027 | E5: 2028 | H5: Risk Factor | K5: 2026 | L5: 2027 | M5: 2028 | S5: 45962 | T5: 45992 | U5: 46023 | V5: 46054 | W5: 46082 | X5: 46113 | Y5: 46143 | Z5: 46174 | AA5: 46204 | AB5: 46235 | AC5: 46266 | AD5: 46296 | AE5: 46327 | AF5: 46357 | AH5: 45962 | AI5: 45992 | AJ5: 46023 | AK5: 46054 | AL5: 46082 | AM5: 46113 | AN5: 46143 | AO5: 46174 | AP5: 46204 | AQ5: 46235 | AR5: 46266 | AS5: 46296 | AT5: 46327 | AU5: 46357
B7: Revenue | C7: =C46+SUM('3YP'!E32:E33)*C47 -> 500 | D7: =D46+SUM('3YP'!F32:F33)*D47 -> 1000 | E7: =E46+SUM('3YP'!G32:G33)*E47 -> 2000 | H7: -0.5 | J7: Revenue | K7: =C7*(1+$H$7) -> 250 | L7: =D7*(1+$H$7) -> 500 | M7: =E7*(1+$H$7) -> 1000
B8: Cost of Sales | C8: =-C46*(1-COGS!C32) -> -165 | D8: =-D46*(1-COGS!D32) -> -327.5 | E8: =-E46*(1-COGS!E32) -> -650 | J8: Cost of Sales | K8: =C8*(1+$H$7) -> -82.5 | L8: =D8*(1+$H$7) -> -163.75 | M8: =E8*(1+$H$7) -> -325
B10: Gross Profit I | C10: =SUM(C7:C8) -> 335 | D10: =SUM(D7:D8) -> 672.5 | E10: =SUM(E7:E8) -> 1350 | J10: Gross Profit I | K10: =SUM(K7:K8) -> 167.5 | L10: =SUM(L7:L8) -> 336.25 | M10: =SUM(M7:M8) -> 675
B11: GP I % | C11: =C10/C$7 -> 0.67 | D11: =D10/D$7 -> 0.6725 | E11: =E10/E$7 -> 0.675 | J11: GP I % | K11: =K10/K$7 -> 0.67 | L11: =L10/L$7 -> 0.6725 | M11: =M10/M$7 -> 0.675
B13: Shipping and distribution costs | C13: =-C7*'Other COS'!$C$34 -> 0 | D13: =-D7*'Other COS'!$C$34 -> 0 | E13: =-E7*'Other COS'!$C$34 -> 0 | J13: Shipping and distribution costs | K13: =-K7*'Other COS'!$C$34 -> 0 | L13: =-L7*'Other COS'!$C$34 -> 0 | M13: =-M7*'Other COS'!$C$34 -> 0
B14: Rebates | C14: 0 | D14: 0 | E14: 0 | J14: Rebates | K14: 0 | L14: 0 | M14: 0
B16: Gross profit II | C16: =SUM(C10,C13:C14) -> 335 | D16: =SUM(D10,D13:D14) -> 672.5 | E16: =SUM(E10,E13:E14) -> 1350 | J16: Gross profit II | K16: =SUM(K10,K13:K14) -> 167.5 | L16: =SUM(L10,L13:L14) -> 336.25 | M16: =SUM(M10,M13:M14) -> 675
B17: GP II % | C17: =C16/C$7 -> 0.67 | D17: =D16/D$7 -> 0.6725 | E17: =E16/E$7 -> 0.675 | J17: GP II % | K17: =K16/K$7 -> 0.67 | L17: =L16/L$7 -> 0.6725 | M17: =M16/M$7 -> 0.675
B19: Advertising and Marketing | C19: =C49 -> 0 | D19: =D49 -> 0 | E19: =E49 -> 0 | J19: Advertising and Marketing | K19: =C19 -> 0 | L19: =D19 -> 0 | M19: =E19 -> 0
B20: Sales and Training Expenses | C20: =C50 -> 0 | D20: =D50 -> 0 | E20: =E50 -> 0 | J20: Sales and Training Expenses | K20: =C20 -> 0 | L20: =D20 -> 0 | M20: =E20 -> 0
B22: Gross profit III | C22: =SUM(C16,C19:C20) -> 335 | D22: =SUM(D16,D19:D20) -> 672.5 | E22: =SUM(E16,E19:E20) -> 1350 | J22: Gross profit III | K22: =SUM(K16,K19:K20) -> 167.5 | L22: =SUM(L16,L19:L20) -> 336.25 | M22: =SUM(M16,M19:M20) -> 675
B23: GP III % | C23: =C22/C$7 -> 0.67 | D23: =D22/D$7 -> 0.6725 | E23: =E22/E$7 -> 0.675 | J23: GP III % | K23: =K22/K$7 -> 0.67 | L23: =L22/L$7 -> 0.6725 | M23: =M22/M$7 -> 0.675
B25: Personnel Expenses | C25: 0 | D25: 0 | E25: 0 | J25: Personnel Expenses | K25: =C25 -> 0 | L25: =D25 -> 0 | M25: =E25 -> 0
B26: Other Admin Expenses | C26: =C52 -> -10 | D26: =D52 -> -15 | E26: =E52 -> -20 | J26: Other Admin Expenses | K26: =C26 -> -10 | L26: =D26 -> -15 | M26: =E26 -> -20
B28: Adjusted EBITDA | C28: =SUM(C22,C25:C26) -> 325 | D28: =SUM(D22,D25:D26) -> 657.5 | E28: =SUM(E22,E25:E26) -> 1330 | J28: Adjusted EBITDA | K28: =SUM(K22,K25:K26) -> 157.5 | L28: =SUM(L22,L25:L26) -> 321.25 | M28: =SUM(M22,M25:M26) -> 655
B29: Adj EBITDA % | C29: =C28/C$7 -> 0.65 | D29: =D28/D$7 -> 0.6575 | E29: =E28/E$7 -> 0.665 | J29: Adj EBITDA % | K29: =K28/K$7 -> 0.63 | L29: =L28/L$7 -> 0.6425 | M29: =M28/M$7 -> 0.655 | R29: =140+167+15+130+30+52 -> 534
B31: Exceptionals | C31: =-8-C7*20% -> -108 | D31: =-D7*20% -> -200 | E31: =-E7*20% -> -400 | J31: Exceptionals | K31: =-K7*10%-10*12 -> -145 | L31: =-L7*10%-10*12*1.1 -> -182 | M31: =-M7*10%-10*12*1.1^2 -> -245.2
B33: EBITDA | C33: =SUM(C28,C31) -> 217 | D33: =SUM(D28,D31) -> 457.5 | E33: =SUM(E28,E31) -> 930 | J33: EBITDA | K33: =SUM(K28,K31) -> 12.5 | L33: =SUM(L28,L31) -> 139.25 | M33: =SUM(M28,M31) -> 409.8
B34: EBITDA % | C34: =C33/C$7 -> 0.434 | D34: =D33/D$7 -> 0.4575 | E34: =E33/E$7 -> 0.465 | J34: EBITDA % | K34: =K33/K$7 -> 0.05 | L34: =L33/L$7 -> 0.2785 | M34: =M33/M$7 -> 0.4098
B37: Risk Amount | C37: -8 | F37: Initial Cost | J37: Risk Amount | K37: =C37 -> -8 | N37: 3 months Juan
B44: Workings
B46: Growth Sales | C46: 500 | D46: 1000 | E46: 2000
B47: Existing growth %
B49: Advertising and Marketing
B50: Sales and Training Expenses
B52: Other Admin Expenses | C52: -10 | D52: -15 | E52: -20
B54: Exceptionals

Sheet 6.1 eComm Growth EU
S3: Monthly | T3: Monthly | U3: Monthly | V3: Monthly | W3: Monthly | X3: Monthly | Y3: Monthly | Z3: Monthly | AA3: Monthly | AB3: Monthly | AC3: Monthly | AD3: Monthly | AE3: Monthly | AF3: Monthly | AH3: To date | AI3: To date | AJ3: To date | AK3: To date | AL3: To date | AM3: To date | AN3: To date | AO3: To date | AP3: To date | AQ3: To date | AR3: To date | AS3: To date | AT3: To date | AU3: To date
S4: =MONTH(S5)&RIGHT(YEAR(S5), 2) -> 1125 | T4: =MONTH(T5)&RIGHT(YEAR(T5), 2) -> 1225 | U4: =MONTH(U5)&RIGHT(YEAR(U5), 2) -> 126 | V4: =MONTH(V5)&RIGHT(YEAR(V5), 2) -> 226 | W4: =MONTH(W5)&RIGHT(YEAR(W5), 2) -> 326 | X4: =MONTH(X5)&RIGHT(YEAR(X5), 2) -> 426 | Y4: =MONTH(Y5)&RIGHT(YEAR(Y5), 2) -> 526 | Z4: =MONTH(Z5)&RIGHT(YEAR(Z5), 2) -> 626 | ... AF4: =MONTH(AF5)&RIGHT(YEAR(AF5), 2) -> 1226 | AH4: =MONTH(AH5)&RIGHT(YEAR(AH5), 2) -> 1125 | AI4: =MONTH(AI5)&RIGHT(YEAR(AI5), 2) -> 1225 | AJ4: =MONTH(AJ5)&RIGHT(YEAR(AJ5), 2) -> 126 | AK4: =MONTH(AK5)&RIGHT(YEAR(AK5), 2) -> 226 | AL4: =MONTH(AL5)&RIGHT(YEAR(AL5), 2) -> 326 | AM4: =MONTH(AM5)&RIGHT(YEAR(AM5), 2) -> 426 | AN4: =MONTH(AN5)&RIGHT(YEAR(AN5), 2) -> 526 | AO4: =MONTH(AO5)&RIGHT(YEAR(AO5), 2) -> 626 | ... AU4: =MONTH(AU5)&RIGHT(YEAR(AU5), 2) -> 1226
C5: 2026 | D5: 2027 | E5: 2028 | H5: Risk Factor | K5: 2026 | L5: 2027 | M5: 2028 | S5: 45962 | T5: 45992 | U5: 46023 | V5: 46054 | W5: 46082 | X5: 46113 | Y5: 46143 | Z5: 46174 | AA5: 46204 | AB5: 46235 | AC5: 46266 | AD5: 46296 | AE5: 46327 | AF5: 46357 | AH5: 45962 | AI5: 45992 | AJ5: 46023 | AK5: 46054 | AL5: 46082 | AM5: 46113 | AN5: 46143 | AO5: 46174 | AP5: 46204 | AQ5: 46235 | AR5: 46266 | AS5: 46296 | AT5: 46327 | AU5: 46357
B7: Revenue | C7: ='Co. 3 eComm Sales'!T62-'Co. 3 eComm Sales'!T60+250 -> 361 | D7: =C7*1.15+100 -> 515.15 | E7: =D7*1.15+100 -> 692.4225 | H7: -0.3 | J7: Revenue | K7: =C7*(1+$H$7) -> 252.7 | L7: =D7*(1+$H$7) -> 360.605 | M7: =E7*(1+$H$7) -> 484.69575 | U7: =$K7*'2026B'!M38/'2026B'!$C38 -> 22.972727 | V7: =$K7*'2026B'!N38/'2026B'!$C38 -> 21.62139 | W7: =$K7*'2026B'!O38/'2026B'!$C38 -> 20.607888 | X7: =$K7*'2026B'!P38/'2026B'!$C38 -> 16.216043 | Y7: =$K7*'2026B'!Q38/'2026B'!$C38 -> 18.918717 | Z7: =$K7*'2026B'!R38/'2026B'!$C38 -> 16.891711 | AA7: =$K7*'2026B'!S38/'2026B'!$C38 -> 17.905214 | AB7: =$K7*'2026B'!T38/'2026B'!$C38 -> 18.243048 | ... AF7: =$K7*'2026B'!X38/'2026B'!$C38 -> 27.026738 | AH7: =S7 -> 0 | AI7: =AH7+T7 -> 0 | AJ7: =AI7+U7 -> 22.972727 | AK7: =AJ7+V7 -> 44.594118 | AL7: =AK7+W7 -> 65.202005 | AM7: =AL7+X7 -> 81.418048 | AN7: =AM7+Y7 -> 100.33676 | AO7: =AN7+Z7 -> 117.22848 | AP7: =AO7+AA7 -> 135.13369 | ... AU7: =AT7+AF7 -> 252.7
B8: Cost of Sales | C8: =-C7*(1-COGS!C36) -> -28.88 | D8: =-D7*(1-COGS!D36) -> -39.924125 | E8: =-E7*(1-COGS!E36) -> -51.931688 | J8: Cost of Sales | K8: =C8*(1+$H$7) -> -20.216 | L8: =D8*(1+$H$7) -> -27.946888 | M8: =E8*(1+$H$7) -> -36.352181 | U8: =U7*$K$8/$K$7 -> -1.8378182 | V8: =V7*$K$8/$K$7 -> -1.7297112 | W8: =W7*$K$8/$K$7 -> -1.648631 | X8: =X7*$K$8/$K$7 -> -1.2972834 | Y8: =Y7*$K$8/$K$7 -> -1.5134973 | Z8: =Z7*$K$8/$K$7 -> -1.3513369 | AA8: =AA7*$K$8/$K$7 -> -1.4324171 | AB8: =AB7*$K$8/$K$7 -> -1.4594439 | ... AF8: =AF7*$K$8/$K$7 -> -2.162139 | AH8: =S8 -> 0 | AI8: =AH8+T8 -> 0 | AJ8: =AI8+U8 -> -1.8378182 | AK8: =AJ8+V8 -> -3.5675294 | AL8: =AK8+W8 -> -5.2161604 | AM8: =AL8+X8 -> -6.5134439 | AN8: =AM8+Y8 -> -8.0269412 | AO8: =AN8+Z8 -> -9.3782781 | AP8: =AO8+AA8 -> -10.810695 | ... AU8: =AT8+AF8 -> -20.216
B10: Gross Profit I | C10: =SUM(C7:C8) -> 332.12 | D10: =SUM(D7:D8) -> 475.22587 | E10: =SUM(E7:E8) -> 640.49081 | J10: Gross Profit I | K10: =SUM(K7:K8) -> 232.484 | L10: =SUM(L7:L8) -> 332.65811 | M10: =SUM(M7:M8) -> 448.34357 | S10: =SUM(S7:S8) -> 0 | T10: =SUM(T7:T8) -> 0 | U10: =SUM(U7:U8) -> 21.134909 | V10: =SUM(V7:V8) -> 19.891679 | W10: =SUM(W7:W8) -> 18.959257 | X10: =SUM(X7:X8) -> 14.918759 | Y10: =SUM(Y7:Y8) -> 17.405219 | Z10: =SUM(Z7:Z8) -> 15.540374 | ... AF10: =SUM(AF7:AF8) -> 24.864599 | AH10: =SUM(AH7:AH8) -> 0 | AI10: =SUM(AI7:AI8) -> 0 | AJ10: =SUM(AJ7:AJ8) -> 21.134909 | AK10: =SUM(AK7:AK8) -> 41.026588 | AL10: =SUM(AL7:AL8) -> 59.985845 | AM10: =SUM(AM7:AM8) -> 74.904604 | AN10: =SUM(AN7:AN8) -> 92.309824 | AO10: =SUM(AO7:AO8) -> 107.8502 | ... AU10: =SUM(AU7:AU8) -> 232.484
B11: GP I % | C11: =C10/C$7 -> 0.92 | D11: =D10/D$7 -> 0.9225 | E11: =E10/E$7 -> 0.925 | J11: GP I % | K11: =K10/K$7 -> 0.92 | L11: =L10/L$7 -> 0.9225 | M11: =M10/M$7 -> 0.925 | S11: =S10/S$7 -> #DIV/0! | T11: =T10/T$7 -> #DIV/0! | U11: =U10/U$7 -> 0.92 | V11: =V10/V$7 -> 0.92 | W11: =W10/W$7 -> 0.92 | X11: =X10/X$7 -> 0.92 | Y11: =Y10/Y$7 -> 0.92 | Z11: =Z10/Z$7 -> 0.92 | ... AF11: =AF10/AF$7 -> 0.92 | AH11: =AH10/AH$7 -> #DIV/0! | AI11: =AI10/AI$7 -> #DIV/0! | AJ11: =AJ10/AJ$7 -> 0.92 | AK11: =AK10/AK$7 -> 0.92 | AL11: =AL10/AL$7 -> 0.92 | AM11: =AM10/AM$7 -> 0.92 | AN11: =AN10/AN$7 -> 0.92 | AO11: =AO10/AO$7 -> 0.92 | ... AU11: =AU10/AU$7 -> 0.92
B13: Shipping and distribution costs | C13: =-C7*'Other COS'!$C$37 -> -10.83 | D13: =-D7*'Other COS'!$C$37 -> -15.4545 | E13: =-E7*'Other COS'!$C$37 -> -20.772675 | J13: Shipping and distribution costs | K13: =C13*(1+$H$7) -> -7.581 | L13: =D13*(1+$H$7) -> -10.81815 | M13: =E13*(1+$H$7) -> -14.540872 | U13: =U7*$K$13/$K$7 -> -0.68918182 | V13: =V7*$K$13/$K$7 -> -0.64864171 | W13: =W7*$K$13/$K$7 -> -0.61823663 | X13: =X7*$K$13/$K$7 -> -0.48648128 | Y13: =Y7*$K$13/$K$7 -> -0.5675615 | Z13: =Z7*$K$13/$K$7 -> -0.50675134 | AA13: =AA7*$K$13/$K$7 -> -0.53715642 | AB13: =AB7*$K$13/$K$7 -> -0.54729144 | ... AF13: =AF7*$K$13/$K$7 -> -0.81080214 | AH13: =S13 -> 0 | AI13: =AH13+T13 -> 0 | AJ13: =AI13+U13 -> -0.68918182 | AK13: =AJ13+V13 -> -1.3378235 | AL13: =AK13+W13 -> -1.9560602 | AM13: =AL13+X13 -> -2.4425414 | AN13: =AM13+Y13 -> -3.0101029 | AO13: =AN13+Z13 -> -3.5168543 | AP13: =AO13+AA13 -> -4.0540107 | ... AU13: =AT13+AF13 -> -7.581
B14: Rebates | C14: 0 | D14: 0 | E14: 0 | J14: Rebates | K14: =C14*(1+$H$7) -> 0 | L14: =D14*(1+$H$7) -> 0 | M14: =E14*(1+$H$7) -> 0
B16: Gross profit II | C16: =SUM(C10,C13:C14) -> 321.29 | D16: =SUM(D10,D13:D14) -> 459.77137 | E16: =SUM(E10,E13:E14) -> 619.71814 | J16: Gross profit II | K16: =SUM(K10,K13:K14) -> 224.903 | L16: =SUM(L10,L13:L14) -> 321.83996 | M16: =SUM(M10,M13:M14) -> 433.8027 | S16: =SUM(S10,S13:S14) -> 0 | T16: =SUM(T10,T13:T14) -> 0 | U16: =SUM(U10,U13:U14) -> 20.445727 | V16: =SUM(V10,V13:V14) -> 19.243037 | W16: =SUM(W10,W13:W14) -> 18.34102 | X16: =SUM(X10,X13:X14) -> 14.432278 | Y16: =SUM(Y10,Y13:Y14) -> 16.837658 | Z16: =SUM(Z10,Z13:Z14) -> 15.033623 | ... AF16: =SUM(AF10,AF13:AF14) -> 24.053797 | AH16: =SUM(AH10,AH13:AH14) -> 0 | AI16: =SUM(AI10,AI13:AI14) -> 0 | AJ16: =SUM(AJ10,AJ13:AJ14) -> 20.445727 | AK16: =SUM(AK10,AK13:AK14) -> 39.688765 | AL16: =SUM(AL10,AL13:AL14) -> 58.029785 | AM16: =SUM(AM10,AM13:AM14) -> 72.462063 | AN16: =SUM(AN10,AN13:AN14) -> 89.299721 | AO16: =SUM(AO10,AO13:AO14) -> 104.33334 | ... AU16: =SUM(AU10,AU13:AU14) -> 224.903
B17: GP II % | C17: =C16/C$7 -> 0.89 | D17: =D16/D$7 -> 0.8925 | E17: =E16/E$7 -> 0.895 | J17: GP II % | K17: =K16/K$7 -> 0.89 | L17: =L16/L$7 -> 0.8925 | M17: =M16/M$7 -> 0.895 | S17: =S16/S$7 -> #DIV/0! | T17: =T16/T$7 -> #DIV/0! | U17: =U16/U$7 -> 0.89 | V17: =V16/V$7 -> 0.89 | W17: =W16/W$7 -> 0.89 | X17: =X16/X$7 -> 0.89 | Y17: =Y16/Y$7 -> 0.89 | Z17: =Z16/Z$7 -> 0.89 | ... AF17: =AF16/AF$7 -> 0.89 | AH17: =AH16/AH$7 -> #DIV/0! | AI17: =AI16/AI$7 -> #DIV/0! | AJ17: =AJ16/AJ$7 -> 0.89 | AK17: =AK16/AK$7 -> 0.89 | AL17: =AL16/AL$7 -> 0.89 | AM17: =AM16/AM$7 -> 0.89 | AN17: =AN16/AN$7 -> 0.89 | AO17: =AO16/AO$7 -> 0.89 | ... AU17: =AU16/AU$7 -> 0.89
B19: Advertising and Marketing | C19: =-Extra!H5/1000 -> -271.196 | D19: =C19*1.05 -> -284.7558 | E19: =D19*1.05 -> -298.99359 | J19: Advertising and Marketing | K19: =C19 -> -271.196 | L19: =D19 -> -284.7558 | M19: =E19 -> -298.99359 | U19: =$K19/12 -> -22.599667 | V19: =$K19/12 -> -22.599667 | W19: =$K19/12 -> -22.599667 | X19: =$K19/12 -> -22.599667 | Y19: =$K19/12 -> -22.599667 | Z19: =$K19/12 -> -22.599667 | AA19: =$K19/12 -> -22.599667 | AB19: =$K19/12 -> -22.599667 | ... AF19: =$K19/12 -> -22.599667 | AH19: =S19 -> 0 | AI19: =AH19+T19 -> 0 | AJ19: =AI19+U19 -> -22.599667 | AK19: =AJ19+V19 -> -45.199333 | AL19: =AK19+W19 -> -67.799 | AM19: =AL19+X19 -> -90.398667 | AN19: =AM19+Y19 -> -112.99833 | AO19: =AN19+Z19 -> -135.598 | AP19: =AO19+AA19 -> -158.19767 | ... AU19: =AT19+AF19 -> -271.196
B20: Sales and Training Expenses | C20: 0 | D20: 0 | E20: 0 | J20: Sales and Training Expenses | K20: =C20 -> 0 | L20: =D20 -> 0 | M20: =E20 -> 0
B22: Gross profit III | C22: =SUM(C16,C19:C20) -> 50.094 | D22: =SUM(D16,D19:D20) -> 175.01557 | E22: =SUM(E16,E19:E20) -> 320.72455 | J22: Gross profit III | K22: =SUM(K16,K19:K20) -> -46.293 | L22: =SUM(L16,L19:L20) -> 37.084162 | M22: =SUM(M16,M19:M20) -> 134.80911 | S22: =SUM(S16,S19:S20) -> 0 | T22: =SUM(T16,T19:T20) -> 0 | U22: =SUM(U16,U19:U20) -> -2.1539394 | V22: =SUM(V16,V19:V20) -> -3.3566292 | W22: =SUM(W16,W19:W20) -> -4.2586466 | X22: =SUM(X16,X19:X20) -> -8.1673886 | Y22: =SUM(Y16,Y19:Y20) -> -5.7620089 | Z22: =SUM(Z16,Z19:Z20) -> -7.5660437 | ... AF22: =SUM(AF16,AF19:AF20) -> 1.4541301 | AH22: =SUM(AH16,AH19:AH20) -> 0 | AI22: =SUM(AI16,AI19:AI20) -> 0 | AJ22: =SUM(AJ16,AJ19:AJ20) -> -2.1539394 | AK22: =SUM(AK16,AK19:AK20) -> -5.5105686 | AL22: =SUM(AL16,AL19:AL20) -> -9.7692152 | AM22: =SUM(AM16,AM19:AM20) -> -17.936604 | AN22: =SUM(AN16,AN19:AN20) -> -23.698613 | AO22: =SUM(AO16,AO19:AO20) -> -31.264656 | ... AU22: =SUM(AU16,AU19:AU20) -> -46.293
B23: GP III % | C23: =C22/C$7 -> 0.13876454 | D23: =D22/D$7 -> 0.33973712 | E23: =E22/E$7 -> 0.46319198 | J23: GP III % | K23: =K22/K$7 -> -0.18319351 | L23: =L22/L$7 -> 0.10283874 | M23: =M22/M$7 -> 0.2781314 | S23: =S22/S$7 -> #DIV/0! | T23: =T22/T$7 -> #DIV/0! | U23: =U22/U$7 -> -0.093760718 | V23: =V22/V$7 -> -0.15524576 | W23: =W22/W$7 -> -0.20665129 | X23: =X22/X$7 -> -0.50366102 | Y23: =Y22/Y$7 -> -0.30456659 | Z23: =Z22/Z$7 -> -0.44791458 | ... AF23: =AF22/AF$7 -> 0.05380339 | AH23: =AH22/AH$7 -> #DIV/0! | AI23: =AI22/AI$7 -> #DIV/0! | AJ23: =AJ22/AJ$7 -> -0.093760718 | AK23: =AK22/AK$7 -> -0.12357165 | AL23: =AL22/AL$7 -> -0.14982998 | AM23: =AM22/AM$7 -> -0.22030255 | AN23: =AN22/AN$7 -> -0.23619072 | AO23: =AO22/AO$7 -> -0.26669848 | ... AU23: =AU22/AU$7 -> -0.18319351
B25: Personnel Expenses | C25: 0 | D25: 0 | E25: 0 | J25: Personnel Expenses | K25: 0 | L25: 0 | M25: 0
B26: Other Admin Expenses | C26: 0 | D26: 0 | E26: 0 | J26: Other Admin Expenses | K26: =C26 -> 0 | L26: =D26 -> 0 | M26: =E26 -> 0
B28: Adjusted EBITDA | C28: =SUM(C22,C25:C26) -> 50.094 | D28: =SUM(D22,D25:D26) -> 175.01557 | E28: =SUM(E22,E25:E26) -> 320.72455 | J28: Adjusted EBITDA | K28: =SUM(K22,K25:K26) -> -46.293 | L28: =SUM(L22,L25:L26) -> 37.084162 | M28: =SUM(M22,M25:M26) -> 134.80911 | S28: =SUM(S22,S25:S26) -> 0 | T28: =SUM(T22,T25:T26) -> 0 | U28: =SUM(U22,U25:U26) -> -2.1539394 | V28: =SUM(V22,V25:V26) -> -3.3566292 | W28: =SUM(W22,W25:W26) -> -4.2586466 | X28: =SUM(X22,X25:X26) -> -8.1673886 | Y28: =SUM(Y22,Y25:Y26) -> -5.7620089 | Z28: =SUM(Z22,Z25:Z26) -> -7.5660437 | ... AF28: =SUM(AF22,AF25:AF26) -> 1.4541301 | AH28: =SUM(AH22,AH25:AH26) -> 0 | AI28: =SUM(AI22,AI25:AI26) -> 0 | AJ28: =SUM(AJ22,AJ25:AJ26) -> -2.1539394 | AK28: =SUM(AK22,AK25:AK26) -> -5.5105686 | AL28: =SUM(AL22,AL25:AL26) -> -9.7692152 | AM28: =SUM(AM22,AM25:AM26) -> -17.936604 | AN28: =SUM(AN22,AN25:AN26) -> -23.698613 | AO28: =SUM(AO22,AO25:AO26) -> -31.264656 | ... AU28: =SUM(AU22,AU25:AU26) -> -46.293
B29: Adj EBITDA % | C29: =C28/C$7 -> 0.13876454 | D29: =D28/D$7 -> 0.33973712 | E29: =E28/E$7 -> 0.46319198 | J29: Adj EBITDA % | K29: =K28/K$7 -> -0.18319351 | L29: =L28/L$7 -> 0.10283874 | M29: =M28/M$7 -> 0.2781314 | S29: =S28/S$7 -> #DIV/0! | T29: =T28/T$7 -> #DIV/0! | U29: =U28/U$7 -> -0.093760718 | V29: =V28/V$7 -> -0.15524576 | W29: =W28/W$7 -> -0.20665129 | X29: =X28/X$7 -> -0.50366102 | Y29: =Y28/Y$7 -> -0.30456659 | Z29: =Z28/Z$7 -> -0.44791458 | ... AF29: =AF28/AF$7 -> 0.05380339 | AH29: =AH28/AH$7 -> #DIV/0! | AI29: =AI28/AI$7 -> #DIV/0! | AJ29: =AJ28/AJ$7 -> -0.093760718 | AK29: =AK28/AK$7 -> -0.12357165 | AL29: =AL28/AL$7 -> -0.14982998 | AM29: =AM28/AM$7 -> -0.22030255 | AN29: =AN28/AN$7 -> -0.23619072 | AO29: =AO28/AO$7 -> -0.26669848 | ... AU29: =AU28/AU$7 -> -0.18319351
B31: Exceptionals | C31: 0 | D31: 0 | E31: 0 | J31: Exceptionals | K31: =C31 -> 0 | L31: =D31 -> 0 | M31: =E31 -> 0
B33: EBITDA | C33: =SUM(C28,C31) -> 50.094 | D33: =SUM(D28,D31) -> 175.01557 | E33: =SUM(E28,E31) -> 320.72455 | J33: EBITDA | K33: =SUM(K28,K31) -> -46.293 | L33: =SUM(L28,L31) -> 37.084162 | M33: =SUM(M28,M31) -> 134.80911 | S33: =SUM(S28,S31) -> 0 | T33: =SUM(T28,T31) -> 0 | U33: =SUM(U28,U31) -> -2.1539394 | V33: =SUM(V28,V31) -> -3.3566292 | W33: =SUM(W28,W31) -> -4.2586466 | X33: =SUM(X28,X31) -> -8.1673886 | Y33: =SUM(Y28,Y31) -> -5.7620089 | Z33: =SUM(Z28,Z31) -> -7.5660437 | ... AF33: =SUM(AF28,AF31) -> 1.4541301 | AH33: =SUM(AH28,AH31) -> 0 | AI33: =SUM(AI28,AI31) -> 0 | AJ33: =SUM(AJ28,AJ31) -> -2.1539394 | AK33: =SUM(AK28,AK31) -> -5.5105686 | AL33: =SUM(AL28,AL31) -> -9.7692152 | AM33: =SUM(AM28,AM31) -> -17.936604 | AN33: =SUM(AN28,AN31) -> -23.698613 | AO33: =SUM(AO28,AO31) -> -31.264656 | ... AU33: =SUM(AU28,AU31) -> -46.293
B34: EBITDA % | C34: =C33/C$7 -> 0.13876454 | D34: =D33/D$7 -> 0.33973712 | E34: =E33/E$7 -> 0.46319198 | J34: EBITDA % | K34: =K33/K$7 -> -0.18319351 | L34: =L33/L$7 -> 0.10283874 | M34: =M33/M$7 -> 0.2781314 | S34: =S33/S$7 -> #DIV/0! | T34: =T33/T$7 -> #DIV/0! | U34: =U33/U$7 -> -0.093760718 | V34: =V33/V$7 -> -0.15524576 | W34: =W33/W$7 -> -0.20665129 | X34: =X33/X$7 -> -0.50366102 | Y34: =Y33/Y$7 -> -0.30456659 | Z34: =Z33/Z$7 -> -0.44791458 | ... AF34: =AF33/AF$7 -> 0.05380339 | AH34: =AH33/AH$7 -> #DIV/0! | AI34: =AI33/AI$7 -> #DIV/0! | AJ34: =AJ33/AJ$7 -> -0.093760718 | AK34: =AK33/AK$7 -> -0.12357165 | AL34: =AL33/AL$7 -> -0.14982998 | AM34: =AM33/AM$7 -> -0.22030255 | AN34: =AN33/AN$7 -> -0.23619072 | AO34: =AO33/AO$7 -> -0.26669848 | ... AU34: =AU33/AU$7 -> -0.18319351
B37: Risk Amount | C37: =C19*1/12 -> -22.599667 | F37: 1 month spend | J37: Risk Amount | K37: =K19*1/12 -> -22.599667 | N37: 1 month spend
B44: Workings

Sheet 6.2 eComm Growth US
S3: Monthly | T3: Monthly | U3: Monthly | V3: Monthly | W3: Monthly | X3: Monthly | Y3: Monthly | Z3: Monthly | AA3: Monthly | AB3: Monthly | AC3: Monthly | AD3: Monthly | AE3: Monthly | AF3: Monthly | AH3: To date | AI3: To date | AJ3: To date | AK3: To date | AL3: To date | AM3: To date | AN3: To date | AO3: To date | AP3: To date | AQ3: To date | AR3: To date | AS3: To date | AT3: To date | AU3: To date
S4: =MONTH(S5)&RIGHT(YEAR(S5), 2) -> 1125 | T4: =MONTH(T5)&RIGHT(YEAR(T5), 2) -> 1225 | U4: =MONTH(U5)&RIGHT(YEAR(U5), 2) -> 126 | V4: =MONTH(V5)&RIGHT(YEAR(V5), 2) -> 226 | W4: =MONTH(W5)&RIGHT(YEAR(W5), 2) -> 326 | X4: =MONTH(X5)&RIGHT(YEAR(X5), 2) -> 426 | Y4: =MONTH(Y5)&RIGHT(YEAR(Y5), 2) -> 526 | Z4: =MONTH(Z5)&RIGHT(YEAR(Z5), 2) -> 626 | ... AF4: =MONTH(AF5)&RIGHT(YEAR(AF5), 2) -> 1226 | AH4: =MONTH(AH5)&RIGHT(YEAR(AH5), 2) -> 1125 | AI4: =MONTH(AI5)&RIGHT(YEAR(AI5), 2) -> 1225 | AJ4: =MONTH(AJ5)&RIGHT(YEAR(AJ5), 2) -> 126 | AK4: =MONTH(AK5)&RIGHT(YEAR(AK5), 2) -> 226 | AL4: =MONTH(AL5)&RIGHT(YEAR(AL5), 2) -> 326 | AM4: =MONTH(AM5)&RIGHT(YEAR(AM5), 2) -> 426 | AN4: =MONTH(AN5)&RIGHT(YEAR(AN5), 2) -> 526 | AO4: =MONTH(AO5)&RIGHT(YEAR(AO5), 2) -> 626 | ... AU4: =MONTH(AU5)&RIGHT(YEAR(AU5), 2) -> 1226
C5: 2026 | D5: 2027 | E5: 2028 | H5: Risk Factor | K5: 2026 | L5: 2027 | M5: 2028 | S5: 45962 | T5: 45992 | U5: 46023 | V5: 46054 | W5: 46082 | X5: 46113 | Y5: 46143 | Z5: 46174 | AA5: 46204 | AB5: 46235 | AC5: 46266 | AD5: 46296 | AE5: 46327 | AF5: 46357 | AH5: 45962 | AI5: 45992 | AJ5: 46023 | AK5: 46054 | AL5: 46082 | AM5: 46113 | AN5: 46143 | AO5: 46174 | AP5: 46204 | AQ5: 46235 | AR5: 46266 | AS5: 46296 | AT5: 46327 | AU5: 46357
B7: Revenue | C7: ='Co. 3 eComm Sales'!T30-'Co. 3 eComm Sales'!T28+100 -> 171 | D7: =C7*1.15+100 -> 296.65 | E7: =D7*1.15+100 -> 441.1475 | H7: -0.3 | J7: Revenue | K7: =C7*(1+$H$7) -> 119.7 | L7: =D7*(1+$H$7) -> 207.655 | M7: =E7*(1+$H$7) -> 308.80325 | U7: =$K7*'2026B'!M39/'2026B'!$C39 -> 9.1396552 | V7: =$K7*'2026B'!N39/'2026B'!$C39 -> 9.1396552 | W7: =$K7*'2026B'!O39/'2026B'!$C39 -> 10.024138 | X7: =$K7*'2026B'!P39/'2026B'!$C39 -> 9.4344828 | Y7: =$K7*'2026B'!Q39/'2026B'!$C39 -> 10.024138 | Z7: =$K7*'2026B'!R39/'2026B'!$C39 -> 9.7293103 | AA7: =$K7*'2026B'!S39/'2026B'!$C39 -> 10.024138 | AB7: =$K7*'2026B'!T39/'2026B'!$C39 -> 9.1396552 | ... AF7: =$K7*'2026B'!X39/'2026B'!$C39 -> 11.793103 | AH7: =S7 -> 0 | AI7: =AH7+T7 -> 0 | AJ7: =AI7+U7 -> 9.1396552 | AK7: =AJ7+V7 -> 18.27931 | AL7: =AK7+W7 -> 28.303448 | AM7: =AL7+X7 -> 37.737931 | AN7: =AM7+Y7 -> 47.762069 | AO7: =AN7+Z7 -> 57.491379 | AP7: =AO7+AA7 -> 67.515517 | ... AU7: =AT7+AF7 -> 119.7
B8: Cost of Sales | C8: =-C7*(1-COGS!C37) -> -13.68 | D8: =-D7*(1-COGS!D37) -> -22.990375 | E8: =-E7*(1-COGS!E37) -> -33.086063 | J8: Cost of Sales | K8: =C8*(1+$H$7) -> -9.576 | L8: =D8*(1+$H$7) -> -16.093263 | M8: =E8*(1+$H$7) -> -23.160244 | U8: =U7*$K$8/$K$7 -> -0.73117241 | V8: =V7*$K$8/$K$7 -> -0.73117241 | W8: =W7*$K$8/$K$7 -> -0.80193103 | X8: =X7*$K$8/$K$7 -> -0.75475862 | Y8: =Y7*$K$8/$K$7 -> -0.80193103 | Z8: =Z7*$K$8/$K$7 -> -0.77834483 | AA8: =AA7*$K$8/$K$7 -> -0.80193103 | AB8: =AB7*$K$8/$K$7 -> -0.73117241 | ... AF8: =AF7*$K$8/$K$7 -> -0.94344828 | AH8: =S8 -> 0 | AI8: =AH8+T8 -> 0 | AJ8: =AI8+U8 -> -0.73117241 | AK8: =AJ8+V8 -> -1.4623448 | AL8: =AK8+W8 -> -2.2642759 | AM8: =AL8+X8 -> -3.0190345 | AN8: =AM8+Y8 -> -3.8209655 | AO8: =AN8+Z8 -> -4.5993103 | AP8: =AO8+AA8 -> -5.4012414 | ... AU8: =AT8+AF8 -> -9.576
B10: Gross Profit I | C10: =SUM(C7:C8) -> 157.32 | D10: =SUM(D7:D8) -> 273.65962 | E10: =SUM(E7:E8) -> 408.06144 | J10: Gross Profit I | K10: =SUM(K7:K8) -> 110.124 | L10: =SUM(L7:L8) -> 191.56174 | M10: =SUM(M7:M8) -> 285.64301 | S10: =SUM(S7:S8) -> 0 | T10: =SUM(T7:T8) -> 0 | U10: =SUM(U7:U8) -> 8.4084828 | V10: =SUM(V7:V8) -> 8.4084828 | W10: =SUM(W7:W8) -> 9.2222069 | X10: =SUM(X7:X8) -> 8.6797241 | Y10: =SUM(Y7:Y8) -> 9.2222069 | Z10: =SUM(Z7:Z8) -> 8.9509655 | ... AF10: =SUM(AF7:AF8) -> 10.849655 | AH10: =SUM(AH7:AH8) -> 0 | AI10: =SUM(AI7:AI8) -> 0 | AJ10: =SUM(AJ7:AJ8) -> 8.4084828 | AK10: =SUM(AK7:AK8) -> 16.816966 | AL10: =SUM(AL7:AL8) -> 26.039172 | AM10: =SUM(AM7:AM8) -> 34.718897 | AN10: =SUM(AN7:AN8) -> 43.941103 | AO10: =SUM(AO7:AO8) -> 52.892069 | ... AU10: =SUM(AU7:AU8) -> 110.124
B11: GP I % | C11: =C10/C$7 -> 0.92 | D11: =D10/D$7 -> 0.9225 | E11: =E10/E$7 -> 0.925 | J11: GP I % | K11: =K10/K$7 -> 0.92 | L11: =L10/L$7 -> 0.9225 | M11: =M10/M$7 -> 0.925 | S11: =S10/S$7 -> #DIV/0! | T11: =T10/T$7 -> #DIV/0! | U11: =U10/U$7 -> 0.92 | V11: =V10/V$7 -> 0.92 | W11: =W10/W$7 -> 0.92 | X11: =X10/X$7 -> 0.92 | Y11: =Y10/Y$7 -> 0.92 | Z11: =Z10/Z$7 -> 0.92 | ... AF11: =AF10/AF$7 -> 0.92 | AH11: =AH10/AH$7 -> #DIV/0! | AI11: =AI10/AI$7 -> #DIV/0! | AJ11: =AJ10/AJ$7 -> 0.92 | AK11: =AK10/AK$7 -> 0.92 | AL11: =AL10/AL$7 -> 0.92 | AM11: =AM10/AM$7 -> 0.92 | AN11: =AN10/AN$7 -> 0.92 | AO11: =AO10/AO$7 -> 0.92 | ... AU11: =AU10/AU$7 -> 0.92
B13: Shipping and distribution costs | C13: =-C7*'Other COS'!$C$38 -> -6.84 | D13: =-D7*'Other COS'!$C$38 -> -11.866 | E13: =-E7*'Other COS'!$C$38 -> -17.6459 | J13: Shipping and distribution costs | K13: =C13*(1+$H$7) -> -4.788 | L13: =D13*(1+$H$7) -> -8.3062 | M13: =E13*(1+$H$7) -> -12.35213 | U13: =U7*$K$13/$K$7 -> -0.36558621 | V13: =V7*$K$13/$K$7 -> -0.36558621 | W13: =W7*$K$13/$K$7 -> -0.40096552 | X13: =X7*$K$13/$K$7 -> -0.37737931 | Y13: =Y7*$K$13/$K$7 -> -0.40096552 | Z13: =Z7*$K$13/$K$7 -> -0.38917241 | AA13: =AA7*$K$13/$K$7 -> -0.40096552 | AB13: =AB7*$K$13/$K$7 -> -0.36558621 | ... AF13: =AF7*$K$13/$K$7 -> -0.47172414 | AH13: =S13 -> 0 | AI13: =AH13+T13 -> 0 | AJ13: =AI13+U13 -> -0.36558621 | AK13: =AJ13+V13 -> -0.73117241 | AL13: =AK13+W13 -> -1.1321379 | AM13: =AL13+X13 -> -1.5095172 | AN13: =AM13+Y13 -> -1.9104828 | AO13: =AN13+Z13 -> -2.2996552 | AP13: =AO13+AA13 -> -2.7006207 | ... AU13: =AT13+AF13 -> -4.788
B14: Rebates | C14: 0 | D14: 0 | E14: 0 | J14: Rebates | K14: =C14*(1+$H$7) -> 0 | L14: =D14*(1+$H$7) -> 0 | M14: =E14*(1+$H$7) -> 0
B16: Gross profit II | C16: =SUM(C10,C13:C14) -> 150.48 | D16: =SUM(D10,D13:D14) -> 261.79362 | E16: =SUM(E10,E13:E14) -> 390.41554 | J16: Gross profit II | K16: =SUM(K10,K13:K14) -> 105.336 | L16: =SUM(L10,L13:L14) -> 183.25554 | M16: =SUM(M10,M13:M14) -> 273.29088 | S16: =SUM(S10,S13:S14) -> 0 | T16: =SUM(T10,T13:T14) -> 0 | U16: =SUM(U10,U13:U14) -> 8.0428966 | V16: =SUM(V10,V13:V14) -> 8.0428966 | W16: =SUM(W10,W13:W14) -> 8.8212414 | X16: =SUM(X10,X13:X14) -> 8.3023448 | Y16: =SUM(Y10,Y13:Y14) -> 8.8212414 | Z16: =SUM(Z10,Z13:Z14) -> 8.5617931 | ... AF16: =SUM(AF10,AF13:AF14) -> 10.377931 | AH16: =SUM(AH10,AH13:AH14) -> 0 | AI16: =SUM(AI10,AI13:AI14) -> 0 | AJ16: =SUM(AJ10,AJ13:AJ14) -> 8.0428966 | AK16: =SUM(AK10,AK13:AK14) -> 16.085793 | AL16: =SUM(AL10,AL13:AL14) -> 24.907034 | AM16: =SUM(AM10,AM13:AM14) -> 33.209379 | AN16: =SUM(AN10,AN13:AN14) -> 42.030621 | AO16: =SUM(AO10,AO13:AO14) -> 50.592414 | ... AU16: =SUM(AU10,AU13:AU14) -> 105.336
B17: GP II % | C17: =C16/C$7 -> 0.88 | D17: =D16/D$7 -> 0.8825 | E17: =E16/E$7 -> 0.885 | J17: GP II % | K17: =K16/K$7 -> 0.88 | L17: =L16/L$7 -> 0.8825 | M17: =M16/M$7 -> 0.885 | S17: =S16/S$7 -> #DIV/0! | T17: =T16/T$7 -> #DIV/0! | U17: =U16/U$7 -> 0.88 | V17: =V16/V$7 -> 0.88 | W17: =W16/W$7 -> 0.88 | X17: =X16/X$7 -> 0.88 | Y17: =Y16/Y$7 -> 0.88 | Z17: =Z16/Z$7 -> 0.88 | ... AF17: =AF16/AF$7 -> 0.88 | AH17: =AH16/AH$7 -> #DIV/0! | AI17: =AI16/AI$7 -> #DIV/0! | AJ17: =AJ16/AJ$7 -> 0.88 | AK17: =AK16/AK$7 -> 0.88 | AL17: =AL16/AL$7 -> 0.88 | AM17: =AM16/AM$7 -> 0.88 | AN17: =AN16/AN$7 -> 0.88 | AO17: =AO16/AO$7 -> 0.88 | ... AU17: =AU16/AU$7 -> 0.88
B19: Advertising and Marketing | C19: =-Extra!L5/1000 -> -113.28 | D19: =C19*1.05 -> -118.944 | E19: =D19*1.05 -> -124.8912 | J19: Advertising and Marketing | K19: =C19 -> -113.28 | L19: =D19 -> -118.944 | M19: =E19 -> -124.8912 | U19: =$K19/12 -> -9.44 | V19: =$K19/12 -> -9.44 | W19: =$K19/12 -> -9.44 | X19: =$K19/12 -> -9.44 | Y19: =$K19/12 -> -9.44 | Z19: =$K19/12 -> -9.44 | AA19: =$K19/12 -> -9.44 | AB19: =$K19/12 -> -9.44 | ... AF19: =$K19/12 -> -9.44 | AH19: =S19 -> 0 | AI19: =AH19+T19 -> 0 | AJ19: =AI19+U19 -> -9.44 | AK19: =AJ19+V19 -> -18.88 | AL19: =AK19+W19 -> -28.32 | AM19: =AL19+X19 -> -37.76 | AN19: =AM19+Y19 -> -47.2 | AO19: =AN19+Z19 -> -56.64 | AP19: =AO19+AA19 -> -66.08 | ... AU19: =AT19+AF19 -> -113.28
B20: Sales and Training Expenses | C20: 0 | D20: 0 | E20: 0 | J20: Sales and Training Expenses | K20: =C20 -> 0 | L20: =D20 -> 0 | M20: =E20 -> 0
B22: Gross profit III | C22: =SUM(C16,C19:C20) -> 37.2 | D22: =SUM(D16,D19:D20) -> 142.84962 | E22: =SUM(E16,E19:E20) -> 265.52434 | J22: Gross profit III | K22: =SUM(K16,K19:K20) -> -7.944 | L22: =SUM(L16,L19:L20) -> 64.311537 | M22: =SUM(M16,M19:M20) -> 148.39968 | S22: =SUM(S16,S19:S20) -> 0 | T22: =SUM(T16,T19:T20) -> 0 | U22: =SUM(U16,U19:U20) -> -1.3971034 | V22: =SUM(V16,V19:V20) -> -1.3971034 | W22: =SUM(W16,W19:W20) -> -0.61875862 | X22: =SUM(X16,X19:X20) -> -1.1376552 | Y22: =SUM(Y16,Y19:Y20) -> -0.61875862 | Z22: =SUM(Z16,Z19:Z20) -> -0.8782069 | ... AF22: =SUM(AF16,AF19:AF20) -> 0.93793103 | AH22: =SUM(AH16,AH19:AH20) -> 0 | AI22: =SUM(AI16,AI19:AI20) -> 0 | AJ22: =SUM(AJ16,AJ19:AJ20) -> -1.3971034 | AK22: =SUM(AK16,AK19:AK20) -> -2.7942069 | AL22: =SUM(AL16,AL19:AL20) -> -3.4129655 | AM22: =SUM(AM16,AM19:AM20) -> -4.5506207 | AN22: =SUM(AN16,AN19:AN20) -> -5.1693793 | AO22: =SUM(AO16,AO19:AO20) -> -6.0475862 | ... AU22: =SUM(AU16,AU19:AU20) -> -7.944
B23: GP III % | C23: =C22/C$7 -> 0.21754386 | D23: =D22/D$7 -> 0.48154264 | E23: =E22/E$7 -> 0.60189469 | J23: GP III % | K23: =K22/K$7 -> -0.066365915 | L23: =L22/L$7 -> 0.30970378 | M23: =M22/M$7 -> 0.48056384 | S23: =S22/S$7 -> #DIV/0! | T23: =T22/T$7 -> #DIV/0! | U23: =U22/U$7 -> -0.15286172 | V23: =V22/V$7 -> -0.15286172 | W23: =W22/W$7 -> -0.061726866 | X23: =X22/X$7 -> -0.1205848 | Y23: =Y22/Y$7 -> -0.061726866 | Z23: =Z22/Z$7 -> -0.090264044 | ... AF23: =AF22/AF$7 -> 0.079532164 | AH23: =AH22/AH$7 -> #DIV/0! | AI23: =AI22/AI$7 -> #DIV/0! | AJ23: =AJ22/AJ$7 -> -0.15286172 | AK23: =AK22/AK$7 -> -0.15286172 | AL23: =AL22/AL$7 -> -0.1205848 | AM23: =AM22/AM$7 -> -0.1205848 | AN23: =AN22/AN$7 -> -0.1082319 | AO23: =AO22/AO$7 -> -0.10519118 | ... AU23: =AU22/AU$7 -> -0.066365915
B25: Personnel Expenses | C25: 0 | D25: 0 | E25: 0 | J25: Personnel Expenses | K25: 0 | L25: 0 | M25: 0
B26: Other Admin Expenses | C26: 0 | D26: 0 | E26: 0 | J26: Other Admin Expenses | K26: =C26 -> 0 | L26: =D26 -> 0 | M26: =E26 -> 0
B28: Adjusted EBITDA | C28: =SUM(C22,C25:C26) -> 37.2 | D28: =SUM(D22,D25:D26) -> 142.84962 | E28: =SUM(E22,E25:E26) -> 265.52434 | J28: Adjusted EBITDA | K28: =SUM(K22,K25:K26) -> -7.944 | L28: =SUM(L22,L25:L26) -> 64.311537 | M28: =SUM(M22,M25:M26) -> 148.39968 | S28: =SUM(S22,S25:S26) -> 0 | T28: =SUM(T22,T25:T26) -> 0 | U28: =SUM(U22,U25:U26) -> -1.3971034 | V28: =SUM(V22,V25:V26) -> -1.3971034 | W28: =SUM(W22,W25:W26) -> -0.61875862 | X28: =SUM(X22,X25:X26) -> -1.1376552 | Y28: =SUM(Y22,Y25:Y26) -> -0.61875862 | Z28: =SUM(Z22,Z25:Z26) -> -0.8782069 | ... AF28: =SUM(AF22,AF25:AF26) -> 0.93793103 | AH28: =SUM(AH22,AH25:AH26) -> 0 | AI28: =SUM(AI22,AI25:AI26) -> 0 | AJ28: =SUM(AJ22,AJ25:AJ26) -> -1.3971034 | AK28: =SUM(AK22,AK25:AK26) -> -2.7942069 | AL28: =SUM(AL22,AL25:AL26) -> -3.4129655 | AM28: =SUM(AM22,AM25:AM26) -> -4.5506207 | AN28: =SUM(AN22,AN25:AN26) -> -5.1693793 | AO28: =SUM(AO22,AO25:AO26) -> -6.0475862 | ... AU28: =SUM(AU22,AU25:AU26) -> -7.944
B29: Adj EBITDA % | C29: =C28/C$7 -> 0.21754386 | D29: =D28/D$7 -> 0.48154264 | E29: =E28/E$7 -> 0.60189469 | J29: Adj EBITDA % | K29: =K28/K$7 -> -0.066365915 | L29: =L28/L$7 -> 0.30970378 | M29: =M28/M$7 -> 0.48056384 | S29: =S28/S$7 -> #DIV/0! | T29: =T28/T$7 -> #DIV/0! | U29: =U28/U$7 -> -0.15286172 | V29: =V28/V$7 -> -0.15286172 | W29: =W28/W$7 -> -0.061726866 | X29: =X28/X$7 -> -0.1205848 | Y29: =Y28/Y$7 -> -0.061726866 | Z29: =Z28/Z$7 -> -0.090264044 | ... AF29: =AF28/AF$7 -> 0.079532164 | AH29: =AH28/AH$7 -> #DIV/0! | AI29: =AI28/AI$7 -> #DIV/0! | AJ29: =AJ28/AJ$7 -> -0.15286172 | AK29: =AK28/AK$7 -> -0.15286172 | AL29: =AL28/AL$7 -> -0.1205848 | AM29: =AM28/AM$7 -> -0.1205848 | AN29: =AN28/AN$7 -> -0.1082319 | AO29: =AO28/AO$7 -> -0.10519118 | ... AU29: =AU28/AU$7 -> -0.066365915
B31: Exceptionals | C31: 0 | D31: 0 | E31: 0 | J31: Exceptionals | K31: =C31 -> 0 | L31: =D31 -> 0 | M31: =E31 -> 0
B33: EBITDA | C33: =SUM(C28,C31) -> 37.2 | D33: =SUM(D28,D31) -> 142.84962 | E33: =SUM(E28,E31) -> 265.52434 | J33: EBITDA | K33: =SUM(K28,K31) -> -7.944 | L33: =SUM(L28,L31) -> 64.311537 | M33: =SUM(M28,M31) -> 148.39968 | S33: =SUM(S28,S31) -> 0 | T33: =SUM(T28,T31) -> 0 | U33: =SUM(U28,U31) -> -1.3971034 | V33: =SUM(V28,V31) -> -1.3971034 | W33: =SUM(W28,W31) -> -0.61875862 | X33: =SUM(X28,X31) -> -1.1376552 | Y33: =SUM(Y28,Y31) -> -0.61875862 | Z33: =SUM(Z28,Z31) -> -0.8782069 | ... AF33: =SUM(AF28,AF31) -> 0.93793103 | AH33: =SUM(AH28,AH31) -> 0 | AI33: =SUM(AI28,AI31) -> 0 | AJ33: =SUM(AJ28,AJ31) -> -1.3971034 | AK33: =SUM(AK28,AK31) -> -2.7942069 | AL33: =SUM(AL28,AL31) -> -3.4129655 | AM33: =SUM(AM28,AM31) -> -4.5506207 | AN33: =SUM(AN28,AN31) -> -5.1693793 | AO33: =SUM(AO28,AO31) -> -6.0475862 | ... AU33: =SUM(AU28,AU31) -> -7.944
B34: EBITDA % | C34: =C33/C$7 -> 0.21754386 | D34: =D33/D$7 -> 0.48154264 | E34: =E33/E$7 -> 0.60189469 | J34: EBITDA % | K34: =K33/K$7 -> -0.066365915 | L34: =L33/L$7 -> 0.30970378 | M34: =M33/M$7 -> 0.48056384 | S34: =S33/S$7 -> #DIV/0! | T34: =T33/T$7 -> #DIV/0! | U34: =U33/U$7 -> -0.15286172 | V34: =V33/V$7 -> -0.15286172 | W34: =W33/W$7 -> -0.061726866 | X34: =X33/X$7 -> -0.1205848 | Y34: =Y33/Y$7 -> -0.061726866 | Z34: =Z33/Z$7 -> -0.090264044 | ... AF34: =AF33/AF$7 -> 0.079532164 | AH34: =AH33/AH$7 -> #DIV/0! | AI34: =AI33/AI$7 -> #DIV/0! | AJ34: =AJ33/AJ$7 -> -0.15286172 | AK34: =AK33/AK$7 -> -0.15286172 | AL34: =AL33/AL$7 -> -0.1205848 | AM34: =AM33/AM$7 -> -0.1205848 | AN34: =AN33/AN$7 -> -0.1082319 | AO34: =AO33/AO$7 -> -0.10519118 | ... AU34: =AU33/AU$7 -> -0.066365915
B37: Risk Amount | C37: =C19*1/12 -> -9.44 | F37: 1 month spend | J37: Risk Amount | K37: =K19*1/12 -> -9.44 | N37: 1 month spend
B44: Workings

Sheet 7.1 Cambrium NPD
S3: Monthly | T3: Monthly | U3: Monthly | V3: Monthly | W3: Monthly | X3: Monthly | Y3: Monthly | Z3: Monthly | AA3: Monthly | AB3: Monthly | AC3: Monthly | AD3: Monthly | AE3: Monthly | AF3: Monthly | AH3: To date | AI3: To date | AJ3: To date | AK3: To date | AL3: To date | AM3: To date | AN3: To date | AO3: To date | AP3: To date | AQ3: To date | AR3: To date | AS3: To date | AT3: To date | AU3: To date
S4: =MONTH(S5)&RIGHT(YEAR(S5), 2) -> 1125 | T4: =MONTH(T5)&RIGHT(YEAR(T5), 2) -> 1225 | U4: =MONTH(U5)&RIGHT(YEAR(U5), 2) -> 126 | V4: =MONTH(V5)&RIGHT(YEAR(V5), 2) -> 226 | W4: =MONTH(W5)&RIGHT(YEAR(W5), 2) -> 326 | X4: =MONTH(X5)&RIGHT(YEAR(X5), 2) -> 426 | Y4: =MONTH(Y5)&RIGHT(YEAR(Y5), 2) -> 526 | Z4: =MONTH(Z5)&RIGHT(YEAR(Z5), 2) -> 626 | ... AF4: =MONTH(AF5)&RIGHT(YEAR(AF5), 2) -> 1226 | AH4: =MONTH(AH5)&RIGHT(YEAR(AH5), 2) -> 1125 | AI4: =MONTH(AI5)&RIGHT(YEAR(AI5), 2) -> 1225 | AJ4: =MONTH(AJ5)&RIGHT(YEAR(AJ5), 2) -> 126 | AK4: =MONTH(AK5)&RIGHT(YEAR(AK5), 2) -> 226 | AL4: =MONTH(AL5)&RIGHT(YEAR(AL5), 2) -> 326 | AM4: =MONTH(AM5)&RIGHT(YEAR(AM5), 2) -> 426 | AN4: =MONTH(AN5)&RIGHT(YEAR(AN5), 2) -> 526 | AO4: =MONTH(AO5)&RIGHT(YEAR(AO5), 2) -> 626 | ... AU4: =MONTH(AU5)&RIGHT(YEAR(AU5), 2) -> 1226
C5: 2026 | D5: 2027 | E5: 2028 | H5: Risk Factor | K5: 2026 | L5: 2027 | M5: 2028 | S5: 45962 | T5: 45992 | U5: 46023 | V5: 46054 | W5: 46082 | X5: 46113 | Y5: 46143 | Z5: 46174 | AA5: 46204 | AB5: 46235 | AC5: 46266 | AD5: 46296 | AE5: 46327 | AF5: 46357 | AH5: 45962 | AI5: 45992 | AJ5: 46023 | AK5: 46054 | AL5: 46082 | AM5: 46113 | AN5: 46143 | AO5: 46174 | AP5: 46204 | AQ5: 46235 | AR5: 46266 | AS5: 46296 | AT5: 46327 | AU5: 46357
B7: Revenue | C7: =C46+'3YP'!E45*C47 -> 205.88997 | D7: =D46+'3YP'!F45*D47 -> 786.88666 | E7: =E46+'3YP'!G45*E47 -> 1080.1748 | H7: -0.25 | J7: Revenue | K7: =C7*(1+$H$7) -> 154.41748 | L7: =D7*(1+$H$7) -> 590.165 | M7: =E7*(1+$H$7) -> 810.13109 | AD7: =$K7*50% -> 77.208739 | AE7: =$K7*30% -> 46.325244 | AF7: =$K7*20% -> 30.883496 | AH7: =S7 -> 0 | AI7: =AH7+T7 -> 0 | AJ7: =AI7+U7 -> 0 | AK7: =AJ7+V7 -> 0 | AL7: =AK7+W7 -> 0 | AM7: =AL7+X7 -> 0 | AN7: =AM7+Y7 -> 0 | AO7: =AN7+Z7 -> 0 | AP7: =AO7+AA7 -> 0 | ... AU7: =AT7+AF7 -> 154.41748
B8: Cost of Sales | C8: =-C7*(1-'3YP'!E51) -> -38.866542 | D8: =-D7*(1-'3YP'!F51) -> -146.50066 | E8: =-E7*(1-'3YP'!G51) -> -206.11109 | J8: Cost of Sales | K8: =C8*(1+$H$7) -> -29.149907 | L8: =D8*(1+$H$7) -> -109.8755 | M8: =E8*(1+$H$7) -> -154.58331 | AD8: =AD7*$K$8/$K$7 -> -14.574953 | AE8: =AE7*$K$8/$K$7 -> -8.744972 | AF8: =AF7*$K$8/$K$7 -> -5.8299814 | AH8: =S8 -> 0 | AI8: =AH8+T8 -> 0 | AJ8: =AI8+U8 -> 0 | AK8: =AJ8+V8 -> 0 | AL8: =AK8+W8 -> 0 | AM8: =AL8+X8 -> 0 | AN8: =AM8+Y8 -> 0 | AO8: =AN8+Z8 -> 0 | AP8: =AO8+AA8 -> 0 | ... AU8: =AT8+AF8 -> -29.149907
B10: Gross Profit I | C10: =SUM(C7:C8) -> 167.02343 | D10: =SUM(D7:D8) -> 640.386 | E10: =SUM(E7:E8) -> 874.0637 | J10: Gross Profit I | K10: =SUM(K7:K8) -> 125.26757 | L10: =SUM(L7:L8) -> 480.2895 | M10: =SUM(M7:M8) -> 655.54778 | S10: =SUM(S7:S8) -> 0 | T10: =SUM(T7:T8) -> 0 | U10: =SUM(U7:U8) -> 0 | V10: =SUM(V7:V8) -> 0 | W10: =SUM(W7:W8) -> 0 | X10: =SUM(X7:X8) -> 0 | Y10: =SUM(Y7:Y8) -> 0 | Z10: =SUM(Z7:Z8) -> 0 | ... AF10: =SUM(AF7:AF8) -> 25.053514 | AH10: =SUM(AH7:AH8) -> 0 | AI10: =SUM(AI7:AI8) -> 0 | AJ10: =SUM(AJ7:AJ8) -> 0 | AK10: =SUM(AK7:AK8) -> 0 | AL10: =SUM(AL7:AL8) -> 0 | AM10: =SUM(AM7:AM8) -> 0 | AN10: =SUM(AN7:AN8) -> 0 | AO10: =SUM(AO7:AO8) -> 0 | ... AU10: =SUM(AU7:AU8) -> 125.26757
B11: GP I % | C11: =C10/C$7 -> 0.81122664 | D11: =D10/D$7 -> 0.81382241 | E11: =E10/E$7 -> 0.80918728 | J11: GP I % | K11: =K10/K$7 -> 0.81122664 | L11: =L10/L$7 -> 0.81382241 | M11: =M10/M$7 -> 0.80918728 | S11: =S10/S$7 -> #DIV/0! | T11: =T10/T$7 -> #DIV/0! | U11: =U10/U$7 -> #DIV/0! | V11: =V10/V$7 -> #DIV/0! | W11: =W10/W$7 -> #DIV/0! | X11: =X10/X$7 -> #DIV/0! | Y11: =Y10/Y$7 -> #DIV/0! | Z11: =Z10/Z$7 -> #DIV/0! | ... AF11: =AF10/AF$7 -> 0.81122664 | AH11: =AH10/AH$7 -> #DIV/0! | AI11: =AI10/AI$7 -> #DIV/0! | AJ11: =AJ10/AJ$7 -> #DIV/0! | AK11: =AK10/AK$7 -> #DIV/0! | AL11: =AL10/AL$7 -> #DIV/0! | AM11: =AM10/AM$7 -> #DIV/0! | AN11: =AN10/AN$7 -> #DIV/0! | AO11: =AO10/AO$7 -> #DIV/0! | ... AU11: =AU10/AU$7 -> 0.81122664
B13: Shipping and distribution costs | C13: =C7*'3YP'!E53/'3YP'!E$47 -> -4.0492247 | D13: =D7*'3YP'!F53/'3YP'!F$47 -> -16.199876 | E13: =E7*'3YP'!G53/'3YP'!G$47 -> -21.870409 | J13: Shipping and distribution costs | K13: =C13*(1+$H$7) -> -3.0369185 | L13: =D13*(1+$H$7) -> -12.149907 | M13: =E13*(1+$H$7) -> -16.402807 | AD13: =AD7*$K$13/$K$7 -> -1.5184593 | AE13: =AE7*$K$13/$K$7 -> -0.91107555 | AF13: =AF7*$K$13/$K$7 -> -0.6073837 | AH13: =S13 -> 0 | AI13: =AH13+T13 -> 0 | AJ13: =AI13+U13 -> 0 | AK13: =AJ13+V13 -> 0 | AL13: =AK13+W13 -> 0 | AM13: =AL13+X13 -> 0 | AN13: =AM13+Y13 -> 0 | AO13: =AN13+Z13 -> 0 | AP13: =AO13+AA13 -> 0 | ... AU13: =AT13+AF13 -> -3.0369185
B14: Rebates | C14: =C7*'3YP'!E54/'3YP'!E$47 -> -2.7140906 | D14: =D7*'3YP'!F54/'3YP'!F$47 -> -10.644484 | E14: =E7*'3YP'!G54/'3YP'!G$47 -> -13.840309 | J14: Rebates | K14: =C14*(1+$H$7) -> -2.035568 | L14: =D14*(1+$H$7) -> -7.9833633 | M14: =E14*(1+$H$7) -> -10.380232
B16: Gross profit II | C16: =SUM(C10,C13:C14) -> 160.26011 | D16: =SUM(D10,D13:D14) -> 613.54164 | E16: =SUM(E10,E13:E14) -> 838.35298 | J16: Gross profit II | K16: =SUM(K10,K13:K14) -> 120.19509 | L16: =SUM(L10,L13:L14) -> 460.15623 | M16: =SUM(M10,M13:M14) -> 628.76474 | S16: =SUM(S10,S13:S14) -> 0 | T16: =SUM(T10,T13:T14) -> 0 | U16: =SUM(U10,U13:U14) -> 0 | V16: =SUM(V10,V13:V14) -> 0 | W16: =SUM(W10,W13:W14) -> 0 | X16: =SUM(X10,X13:X14) -> 0 | Y16: =SUM(Y10,Y13:Y14) -> 0 | Z16: =SUM(Z10,Z13:Z14) -> 0 | ... AF16: =SUM(AF10,AF13:AF14) -> 24.446131 | AH16: =SUM(AH10,AH13:AH14) -> 0 | AI16: =SUM(AI10,AI13:AI14) -> 0 | AJ16: =SUM(AJ10,AJ13:AJ14) -> 0 | AK16: =SUM(AK10,AK13:AK14) -> 0 | AL16: =SUM(AL10,AL13:AL14) -> 0 | AM16: =SUM(AM10,AM13:AM14) -> 0 | AN16: =SUM(AN10,AN13:AN14) -> 0 | AO16: =SUM(AO10,AO13:AO14) -> 0 | ... AU16: =SUM(AU10,AU13:AU14) -> 122.23065
B17: GP II % | C17: =C16/C$7 -> 0.77837746 | D17: =D16/D$7 -> 0.77970776 | E17: =E16/E$7 -> 0.77612715 | J17: GP II % | K17: =K16/K$7 -> 0.77837746 | L17: =L16/L$7 -> 0.77970776 | M17: =M16/M$7 -> 0.77612715 | S17: =S16/S$7 -> #DIV/0! | T17: =T16/T$7 -> #DIV/0! | U17: =U16/U$7 -> #DIV/0! | V17: =V16/V$7 -> #DIV/0! | W17: =W16/W$7 -> #DIV/0! | X17: =X16/X$7 -> #DIV/0! | Y17: =Y16/Y$7 -> #DIV/0! | Z17: =Z16/Z$7 -> #DIV/0! | ... AF17: =AF16/AF$7 -> 0.7915597 | AH17: =AH16/AH$7 -> #DIV/0! | AI17: =AI16/AI$7 -> #DIV/0! | AJ17: =AJ16/AJ$7 -> #DIV/0! | AK17: =AK16/AK$7 -> #DIV/0! | AL17: =AL16/AL$7 -> #DIV/0! | AM17: =AM16/AM$7 -> #DIV/0! | AN17: =AN16/AN$7 -> #DIV/0! | AO17: =AO16/AO$7 -> #DIV/0! | ... AU17: =AU16/AU$7 -> 0.7915597
B19: Advertising and Marketing | C19: -50 | D19: -300 | E19: =E49 -> 0 | J19: Advertising and Marketing | K19: =C19 -> -50 | L19: =D19*0.8 -> -240 | M19: =E19 -> 0 | AD19: =K19 -> -50 | AH19: =S19 -> 0 | AI19: =AH19+T19 -> 0 | AJ19: =AI19+U19 -> 0 | AK19: =AJ19+V19 -> 0 | AL19: =AK19+W19 -> 0 | AM19: =AL19+X19 -> 0 | AN19: =AM19+Y19 -> 0 | AO19: =AN19+Z19 -> 0 | AP19: =AO19+AA19 -> 0 | ... AU19: =AT19+AF19 -> -50
B20: Sales and Training Expenses | C20: -30 | D20: -200 | E20: 0 | J20: Sales and Training Expenses | K20: =C20 -> -30 | L20: =D20*0.8 -> -160 | M20: =E20 -> 0 | AD20: =K20 -> -30
B22: Gross profit III | C22: =SUM(C16,C19:C20) -> 80.260114 | D22: =SUM(D16,D19:D20) -> 113.54164 | E22: =SUM(E16,E19:E20) -> 838.35298 | J22: Gross profit III | K22: =SUM(K16,K19:K20) -> 40.195085 | L22: =SUM(L16,L19:L20) -> 60.156228 | M22: =SUM(M16,M19:M20) -> 628.76474 | S22: =SUM(S16,S19:S20) -> 0 | T22: =SUM(T16,T19:T20) -> 0 | U22: =SUM(U16,U19:U20) -> 0 | V22: =SUM(V16,V19:V20) -> 0 | W22: =SUM(W16,W19:W20) -> 0 | X22: =SUM(X16,X19:X20) -> 0 | Y22: =SUM(Y16,Y19:Y20) -> 0 | Z22: =SUM(Z16,Z19:Z20) -> 0 | ... AF22: =SUM(AF16,AF19:AF20) -> 24.446131 | AH22: =SUM(AH16,AH19:AH20) -> 0 | AI22: =SUM(AI16,AI19:AI20) -> 0 | AJ22: =SUM(AJ16,AJ19:AJ20) -> 0 | AK22: =SUM(AK16,AK19:AK20) -> 0 | AL22: =SUM(AL16,AL19:AL20) -> 0 | AM22: =SUM(AM16,AM19:AM20) -> 0 | AN22: =SUM(AN16,AN19:AN20) -> 0 | AO22: =SUM(AO16,AO19:AO20) -> 0 | ... AU22: =SUM(AU16,AU19:AU20) -> 72.230653
B23: GP III % | C23: =C22/C$7 -> 0.38982041 | D23: =D22/D$7 -> 0.14429224 | E23: =E22/E$7 -> 0.77612715 | J23: GP III % | K23: =K22/K$7 -> 0.2603014 | L23: =L22/L$7 -> 0.1019312 | M23: =M22/M$7 -> 0.77612715 | S23: =S22/S$7 -> #DIV/0! | T23: =T22/T$7 -> #DIV/0! | U23: =U22/U$7 -> #DIV/0! | V23: =V22/V$7 -> #DIV/0! | W23: =W22/W$7 -> #DIV/0! | X23: =X22/X$7 -> #DIV/0! | Y23: =Y22/Y$7 -> #DIV/0! | Z23: =Z22/Z$7 -> #DIV/0! | ... AF23: =AF22/AF$7 -> 0.7915597 | AH23: =AH22/AH$7 -> #DIV/0! | AI23: =AI22/AI$7 -> #DIV/0! | AJ23: =AJ22/AJ$7 -> #DIV/0! | AK23: =AK22/AK$7 -> #DIV/0! | AL23: =AL22/AL$7 -> #DIV/0! | AM23: =AM22/AM$7 -> #DIV/0! | AN23: =AN22/AN$7 -> #DIV/0! | AO23: =AO22/AO$7 -> #DIV/0! | ... AU23: =AU22/AU$7 -> 0.46776216
B25: Personnel Expenses | C25: =-C7*5% -> -10.294499 | D25: =-D7*5% -> -39.344333 | E25: =-E7*5% -> -54.008739 | J25: Personnel Expenses | K25: =-K7*5% -> -7.7208739 | L25: =-L7*5% -> -29.50825 | M25: =-M7*5% -> -40.506555 | AD25: =AD7*$K$25/$K$7 -> -3.860437 | AE25: =AE7*$K$25/$K$7 -> -2.3162622 | AF25: =AF7*$K$25/$K$7 -> -1.5441748
B26: Other Admin Expenses | C26: -10 | D26: -12 | E26: -15 | J26: Other Admin Expenses | K26: =C26 -> -10 | L26: =D26 -> -12 | M26: =E26 -> -15 | AD26: =AD7*$K$26/$K$7 -> -5 | AE26: =AE7*$K$26/$K$7 -> -3 | AF26: =AF7*$K$26/$K$7 -> -2
B28: Adjusted EBITDA | C28: =SUM(C22,C25:C26) -> 59.965615 | D28: =SUM(D22,D25:D26) -> 62.197304 | E28: =SUM(E22,E25:E26) -> 769.34424 | J28: Adjusted EBITDA | K28: =SUM(K22,K25:K26) -> 22.474211 | L28: =SUM(L22,L25:L26) -> 18.647978 | M28: =SUM(M22,M25:M26) -> 573.25818 | S28: =SUM(S22,S25:S26) -> 0 | T28: =SUM(T22,T25:T26) -> 0 | U28: =SUM(U22,U25:U26) -> 0 | V28: =SUM(V22,V25:V26) -> 0 | W28: =SUM(W22,W25:W26) -> 0 | X28: =SUM(X22,X25:X26) -> 0 | Y28: =SUM(Y22,Y25:Y26) -> 0 | Z28: =SUM(Z22,Z25:Z26) -> 0 | ... AF28: =SUM(AF22,AF25:AF26) -> 20.901956 | AH28: =SUM(AH22,AH25:AH26) -> 0 | AI28: =SUM(AI22,AI25:AI26) -> 0 | AJ28: =SUM(AJ22,AJ25:AJ26) -> 0 | AK28: =SUM(AK22,AK25:AK26) -> 0 | AL28: =SUM(AL22,AL25:AL26) -> 0 | AM28: =SUM(AM22,AM25:AM26) -> 0 | AN28: =SUM(AN22,AN25:AN26) -> 0 | AO28: =SUM(AO22,AO25:AO26) -> 0 | ... AU28: =SUM(AU22,AU25:AU26) -> 72.230653
B29: Adj EBITDA % | C29: =C28/C$7 -> 0.29125078 | D29: =D28/D$7 -> 0.079042265 | E29: =E28/E$7 -> 0.71224051 | J29: Adj EBITDA % | K29: =K28/K$7 -> 0.14554189 | L29: =L28/L$7 -> 0.031597906 | M29: =M28/M$7 -> 0.70761163 | S29: =S28/S$7 -> #DIV/0! | T29: =T28/T$7 -> #DIV/0! | U29: =U28/U$7 -> #DIV/0! | V29: =V28/V$7 -> #DIV/0! | W29: =W28/W$7 -> #DIV/0! | X29: =X28/X$7 -> #DIV/0! | Y29: =Y28/Y$7 -> #DIV/0! | Z29: =Z28/Z$7 -> #DIV/0! | ... AF29: =AF28/AF$7 -> 0.67680019 | AH29: =AH28/AH$7 -> #DIV/0! | AI29: =AI28/AI$7 -> #DIV/0! | AJ29: =AJ28/AJ$7 -> #DIV/0! | AK29: =AK28/AK$7 -> #DIV/0! | AL29: =AL28/AL$7 -> #DIV/0! | AM29: =AM28/AM$7 -> #DIV/0! | AN29: =AN28/AN$7 -> #DIV/0! | AO29: =AO28/AO$7 -> #DIV/0! | ... AU29: =AU28/AU$7 -> 0.46776216
B31: Exceptionals | C31: -300 | D31: -150 | E31: 0 | J31: Exceptionals | K31: =C31 -> -300 | L31: =D31 -> -150 | M31: =E31 -> 0 | U31: -200 | Z31: -50 | AE31: -50
B33: EBITDA | C33: =SUM(C28,C31) -> -240.03438 | D33: =SUM(D28,D31) -> -87.802696 | E33: =SUM(E28,E31) -> 769.34424 | J33: EBITDA | K33: =SUM(K28,K31) -> -277.52579 | L33: =SUM(L28,L31) -> -131.35202 | M33: =SUM(M28,M31) -> 573.25818 | S33: =SUM(S28,S31) -> 0 | T33: =SUM(T28,T31) -> 0 | U33: =SUM(U28,U31) -> -200 | V33: =SUM(V28,V31) -> 0 | W33: =SUM(W28,W31) -> 0 | X33: =SUM(X28,X31) -> 0 | Y33: =SUM(Y28,Y31) -> 0 | Z33: =SUM(Z28,Z31) -> -50 | ... AF33: =SUM(AF28,AF31) -> 20.901956 | AH33: =SUM(AH28,AH31) -> 0 | AI33: =SUM(AI28,AI31) -> 0 | AJ33: =SUM(AJ28,AJ31) -> 0 | AK33: =SUM(AK28,AK31) -> 0 | AL33: =SUM(AL28,AL31) -> 0 | AM33: =SUM(AM28,AM31) -> 0 | AN33: =SUM(AN28,AN31) -> 0 | AO33: =SUM(AO28,AO31) -> 0 | ... AU33: =SUM(AU28,AU31) -> 72.230653
B34: EBITDA % | C34: =C33/C$7 -> -1.1658382 | D34: =D33/D$7 -> -0.11158239 | E34: =E33/E$7 -> 0.71224051 | J34: EBITDA % | K34: =K33/K$7 -> -1.7972434 | L34: =L33/L$7 -> -0.2225683 | M34: =M33/M$7 -> 0.70761163 | S34: =S33/S$7 -> #DIV/0! | T34: =T33/T$7 -> #DIV/0! | U34: =U33/U$7 -> #DIV/0! | V34: =V33/V$7 -> #DIV/0! | W34: =W33/W$7 -> #DIV/0! | X34: =X33/X$7 -> #DIV/0! | Y34: =Y33/Y$7 -> #DIV/0! | Z34: =Z33/Z$7 -> #DIV/0! | ... AF34: =AF33/AF$7 -> 0.67680019 | AH34: =AH33/AH$7 -> #DIV/0! | AI34: =AI33/AI$7 -> #DIV/0! | AJ34: =AJ33/AJ$7 -> #DIV/0! | AK34: =AK33/AK$7 -> #DIV/0! | AL34: =AL33/AL$7 -> #DIV/0! | AM34: =AM33/AM$7 -> #DIV/0! | AN34: =AN33/AN$7 -> #DIV/0! | AO34: =AO33/AO$7 -> #DIV/0! | ... AU34: =AU33/AU$7 -> 0.46776216
B37: Risk Amount | C37: =C31 -> -300 | F37: Full Cambrium cost | J37: Risk Amount | K37: =K31 -> -300 | N37: Full event cost
B44: Workings
B46: Growth Sales
B47: Existing growth % | C47: 0.015 | D47: 0.05 | E47: 0.06
B49: Advertising and Marketing
B50: Sales and Training Expenses
B52: Other Admin Expenses
B54: Exceptionals

Sheet 7.2 Social Media_Mkting
